Workbook

Sheet sales report - general
A1: Project | B1: Total Units | C1: # Units CPCV | D1: % Sold | E1: # Blocked | F1: # Reserved | G1: Inventory balance | H1: Total revenue (from CPCV units) | I1: Predicted Income | J1: Average price per unit (of the CPCV units) | K1: €/m² SOLD/CPCV | L1: €/m² Blocked | M1: €/m² Reserved | N1: BP €/M² | O1: Conclusion | P1: Sales targets for 2025 | Q1: CPCV Signed in 2025 | R1: % of year goals | S1: CPCV in present month | T1: November Goals | U1: % of month goals | V1: Volume per month | W1: Avg p/ unit | X1: AVG P/Unit
A2: Panorama | B2: ='PANORAMA (SETUBAL)'!G93 -> 77 | C2: ='PANORAMA (SETUBAL)'!C82 -> 76 | D2: =C2/B2 -> 0.98701299 | E2: ='PANORAMA (SETUBAL)'!C83 -> 0 | F2: ='PANORAMA (SETUBAL)'!C85 -> 1 | G2: ='PANORAMA (SETUBAL)'!C84 -> 0 | H2: ='PANORAMA (SETUBAL)'!D82 -> 23838560 | I2: ='PANORAMA (SETUBAL)'!D86 -> 24458560 | J2: ='PANORAMA (SETUBAL)'!G103 -> 313665.26 | K2: ='PANORAMA (SETUBAL)'!G97 -> 3224.9653 | L2: ='PANORAMA (SETUBAL)'!E83 -> #DIV/0! | M2: ='PANORAMA (SETUBAL)'!E85 -> 3445.727 | N2: 2700 | O2: 1Q 2025 | P2: 12 | Q2: ='PANORAMA (SETUBAL)'!H85 -> 11 | R2: =Q2/P2 -> 0.91666667 | S2: =COUNTIFS('PANORAMA (SETUBAL)'!AC2:AC78,">="&EOMONTH(TODAY(),-1)+1,'PANORAMA (SETUBAL)'!AC2:AC78,"<"&EOMONTH(TODAY(),0)+1) -> 0 | T2: 0 | U2: =S2/T2 -> #DIV/0! | V2: =SUMIFS('PANORAMA (SETUBAL)'!R2:R78,'PANORAMA (SETUBAL)'!AC2:AC78,">="&EOMONTH(TODAY(),-1)+1,'PANORAMA (SETUBAL)'!AC2:AC78,"<"&EOMONTH(TODAY(),0)+1,'PANORAMA (SETUBAL)'!Q2:Q78,'PANORAMA (SETUBAL)'!Q2) -> 0 | W2: =V2/S2 -> #DIV/0! | X2: =V2/S2 -> #DIV/0!
A3: Verde Vale V1 | B3: ='VERDE VALE H1 (MAIA)'!C73 -> 64 | C3: ='VERDE VALE H1 (MAIA)'!C69 -> 64 | D3: =C3/B3 -> 1 | E3: ='VERDE VALE H1 (MAIA)'!C70 -> 0 | F3: ='VERDE VALE H1 (MAIA)'!C72 -> 0 | G3: ='VERDE VALE H1 (MAIA)'!C71 -> 0 | H3: ='VERDE VALE H1 (MAIA)'!D69 -> 19176340 | I3: ='VERDE VALE H1 (MAIA)'!D73 -> 19176340 | J3: ='VERDE VALE H1 (MAIA)'!H90 -> 299630.31 | K3: ='VERDE VALE H1 (MAIA)'!E69 -> 2803.7765 | L3: ='VERDE VALE H1 (MAIA)'!E70 -> #DIV/0! | M3: ='VERDE VALE H1 (MAIA)'!E72 -> #DIV/0! | N3: 2550 | O3: 4Q 2025 | P3: 1 | Q3: ='VERDE VALE H1 (MAIA)'!H72 -> 1 | R3: =Q3/P3 -> 1 | S3: =COUNTIFS('VERDE VALE H1 (MAIA)'!AB2:AB65,">="&EOMONTH(TODAY(),-1)+1,'VERDE VALE H1 (MAIA)'!AB2:AB65,"<"&EOMONTH(TODAY(),0)+1) -> 0 | T3: 0 | U3: =S3/T3 -> #DIV/0! | V3: =SUMIFS('VERDE VALE H1 (MAIA)'!R2:R65,'VERDE VALE H1 (MAIA)'!AB2:AB65,">="&EOMONTH(TODAY(),-1)+1,'VERDE VALE H1 (MAIA)'!AB2:AB65,"<"&EOMONTH(TODAY(),0)+1,'VERDE VALE H1 (MAIA)'!J2:J65,'VERDE VALE H1 (MAIA)'!J3) -> 0 | X3: =V3/S3 -> #DIV/0!
A4: Verde ValeV2 & V3 | B4: ='VERDE VALE H3 A&B (MAIA)'!C65 -> 56 | C4: ='VERDE VALE H3 A&B (MAIA)'!C61 -> 56 | D4: =C4/B4 -> 1 | E4: ='VERDE VALE H3 A&B (MAIA)'!C62 -> 0 | F4: ='VERDE VALE H3 A&B (MAIA)'!C64 -> 0 | G4: ='VERDE VALE H3 A&B (MAIA)'!C63 -> 0 | H4: ='VERDE VALE H3 A&B (MAIA)'!D61 -> 20851972 | I4: ='VERDE VALE H3 A&B (MAIA)'!D65 -> 20851972 | J4: ='VERDE VALE H3 A&B (MAIA)'!G82 -> 372356.64 | K4: ='VERDE VALE H3 A&B (MAIA)'!E61 -> 3268.6119 | L4: ='VERDE VALE H3 A&B (MAIA)'!E62 -> #DIV/0! | M4: ='VERDE VALE H3 A&B (MAIA)'!E64 -> #DIV/0! | N4: 2550 | O4: 4Q 2025 | P4: 6 | Q4: ='VERDE VALE H3 A&B (MAIA)'!H62 -> 6 | R4: =Q4/P4 -> 1 | S4: =COUNTIFS('VERDE VALE H3 A&B (MAIA)'!AC2:AC57,">="&EOMONTH(TODAY(),-1)+1,'VERDE VALE H3 A&B (MAIA)'!AC2:AC57,"<"&EOMONTH(TODAY(),0)+1) -> 0 | T4: 0 | U4: =S4/T4 -> #DIV/0! | V4: =SUMIFS('VERDE VALE H3 A&B (MAIA)'!S2:S57,'VERDE VALE H3 A&B (MAIA)'!AC2:AC57,">="&EOMONTH(TODAY(),-1)+1,'VERDE VALE H3 A&B (MAIA)'!AC2:AC57,"<"&EOMONTH(TODAY(),0)+1,'VERDE VALE H3 A&B (MAIA)'!Q2:Q57,'VERDE VALE H3 A&B (MAIA)'!Q55) -> 0 | X4: =V4/S4 -> #DIV/0!
A5: Verde Vale V4 | B5: ='VERDE VALE H2 (MAIA)'!C63 -> 54 | C5: ='VERDE VALE H2 (MAIA)'!C59 -> 53 | D5: =C5/B5 -> 0.98148148 | E5: ='VERDE VALE H2 (MAIA)'!C60 -> 0 | F5: ='VERDE VALE H2 (MAIA)'!C62 -> 0 | G5: ='VERDE VALE H2 (MAIA)'!C61 -> 1 | H5: ='VERDE VALE H2 (MAIA)'!D59 -> 19448392 | I5: ='VERDE VALE H2 (MAIA)'!D63 -> 20197192 | J5: ='VERDE VALE H2 (MAIA)'!G80 -> 366950.79 | K5: ='VERDE VALE H2 (MAIA)'!E59 -> 3282.6941 | L5: ='VERDE VALE H2 (MAIA)'!E60 -> #DIV/0! | M5: ='VERDE VALE H2 (MAIA)'!E62 -> #DIV/0! | N5: 2550 | O5: 3Q 2026 | P5: 6 | Q5: ='VERDE VALE H2 (MAIA)'!H60 -> 7 | R5: =Q5/P5 -> 1.1666667 | S5: =COUNTIFS('VERDE VALE H2 (MAIA)'!AB2:AB55,">="&EOMONTH(TODAY(),-1)+1,'VERDE VALE H2 (MAIA)'!AB2:AB55,"<"&EOMONTH(TODAY(),0)+1) -> 0 | T5: 0 | U5: =S5/T5 -> #DIV/0! | V5: =SUMIFS('VERDE VALE H2 (MAIA)'!R2:R55,'VERDE VALE H2 (MAIA)'!AB2:AB55,">="&EOMONTH(TODAY(),-1)+1,'VERDE VALE H2 (MAIA)'!AB2:AB55,"<"&EOMONTH(TODAY(),0)+1,'VERDE VALE H2 (MAIA)'!J2:J55,'VERDE VALE H2 (MAIA)'!J50) -> 0 | X5: =V5/S5 -> #DIV/0!
A6: Verde ValeV5 & V6 | B6: ='VERDE VALE H4 A&B (MAIA)'!C91 -> 80 | C6: ='VERDE VALE H4 A&B (MAIA)'!C87 -> 76 | D6: =C6/B6 -> 0.95 | E6: ='VERDE VALE H4 A&B (MAIA)'!C88 -> 0 | F6: ='VERDE VALE H4 A&B (MAIA)'!C90 -> 1 | G6: ='VERDE VALE H4 A&B (MAIA)'!C89 -> 3 | H6: ='VERDE VALE H4 A&B (MAIA)'!D87 -> 29531403 | I6: ='VERDE VALE H4 A&B (MAIA)'!D91 -> 32747403 | J6: ='VERDE VALE H4 A&B (MAIA)'!H108 -> 388571.09 | K6: ='VERDE VALE H4 A&B (MAIA)'!E87 -> 3550.7315 | L6: ='VERDE VALE H4 A&B (MAIA)'!E88 -> #DIV/0! | M6: ='VERDE VALE H4 A&B (MAIA)'!E90 -> 4027.9016 | N6: 2550 | O6: 3Q 2026 | P6: 40 | Q6: ='VERDE VALE H4 A&B (MAIA)'!H88 -> 40 | R6: =Q6/P6 -> 1 | S6: =COUNTIFS('VERDE VALE H4 A&B (MAIA)'!AC4:AC83,">="&EOMONTH(TODAY(),-1)+1,'VERDE VALE H4 A&B (MAIA)'!AC4:AC83,"<"&EOMONTH(TODAY(),0)+1) -> 0 | T6: 1 | U6: =S6/T6 -> 0 | V6: {=SUMIFS('VERDE VALE H4 A&B (MAIA)'!S4:S83,'VERDE VALE H4 A&B (MAIA)'!AC4:AC83,">="&EOMONTH(TODAY(),-1)+1,'VERDE VALE H4 A&B (MAIA)'!AC4:AC83,"<"&EOMONTH(TODAY(),0)+1,'VERDE VALE H4 A&B (MAIA)'!K4:K83,'VERDE VALE H4 A&B (MAIA)'!A87:B87)} -> 0 | W6: 0 | X6: =V6/S6 -> #DIV/0!
A7: Sal D'Ouro Ocean (8) | B7: ='SAL D''OURO OCEAN (8)'!C40 -> 31 | C7: ='SAL D''OURO OCEAN (8)'!C36 -> 31 | D7: =C7/B7 -> 1 | E7: ='SAL D''OURO OCEAN (8)'!C37 -> 0 | F7: ='SAL D''OURO OCEAN (8)'!C39 -> 0 | G7: ='SAL D''OURO OCEAN (8)'!C38 -> 0 | H7: ='SAL D''OURO OCEAN (8)'!D36 -> 15514480 | I7: ='SAL D''OURO OCEAN (8)'!D40 -> 15514480 | J7: ='SAL D''OURO OCEAN (8)'!G57 -> 500467.1 | K7: ='SAL D''OURO OCEAN (8)'!E36 -> 4449.2006 | L7: ='SAL D''OURO OCEAN (8)'!E37 -> #DIV/0! | M7: ='SAL D''OURO OCEAN (8)'!E39 -> #DIV/0! | N7: 3600 | O7: 1Q 2025 | P7: 6 | Q7: ='SAL D''OURO OCEAN (8)'!H39 -> 6 | R7: =Q7/P7 -> 1 | S7: =COUNTIFS('SAL D''OURO OCEAN (8)'!W2:W32,">="&EOMONTH(TODAY(),-1)+1,'SAL D''OURO OCEAN (8)'!W2:W32,"<"&EOMONTH(TODAY(),0)+1) -> 0 | T7: 0 | U7: =S7/T7 -> #DIV/0! | V7: {=SUMIFS('SAL D''OURO OCEAN (8)'!N2:N32,'SAL D''OURO OCEAN (8)'!W2:W32,">="&EOMONTH(TODAY(),-1)+1,'SAL D''OURO OCEAN (8)'!W2:W32,"<"&EOMONTH(TODAY(),0)+1,'SAL D''OURO OCEAN (8)'!K2:K32,'SAL D''OURO OCEAN (8)'!A36:B36)} -> 0 | W7: 0 | X7: =V7/S7 -> #DIV/0!
A8: Sal D'Ouro Park (12.2) | B8: ='SAL D''OURO PARK (12,2)'!C46 -> 37 | C8: ='SAL D''OURO PARK (12,2)'!C42 -> 35 | D8: =C8/B8 -> 0.94594595 | E8: ='SAL D''OURO PARK (12,2)'!C43 -> 0 | F8: ='SAL D''OURO PARK (12,2)'!C45 -> 1 | G8: ='SAL D''OURO PARK (12,2)'!C44 -> 1 | H8: ='SAL D''OURO PARK (12,2)'!D42 -> 14869817 | I8: ='SAL D''OURO PARK (12,2)'!D46 -> 15705673 | J8: ='SAL D''OURO PARK (12,2)'!G63 -> 424851.91 | K8: ='SAL D''OURO PARK (12,2)'!E42 -> 4320.9015 | L8: ='SAL D''OURO PARK (12,2)'!E43 -> #DIV/0! | M8: ='SAL D''OURO PARK (12,2)'!E45 -> 4212.5698 | N8: 3600 | O8: 1Q 2026 | P8: 13 | Q8: ='SAL D''OURO PARK (12,2)'!H44 -> 11 | R8: =Q8/P8 -> 0.84615385 | S8: =COUNTIFS('SAL D''OURO PARK (12,2)'!AA2:AA38,">="&EOMONTH(TODAY(),-1)+1,'SAL D''OURO PARK (12,2)'!AA2:AA38,"<"&EOMONTH(TODAY(),0)+1) -> 0 | T8: 0 | U8: =S8/T8 -> #DIV/0! | V8: {=SUMIFS('SAL D''OURO PARK (12,2)'!P2:P38,'SAL D''OURO PARK (12,2)'!AA2:AA38,">="&EOMONTH(TODAY(),-1)+1,'SAL D''OURO PARK (12,2)'!AA2:AA38,"<"&EOMONTH(TODAY(),0)+1,'SAL D''OURO PARK (12,2)'!M2:M38,'SAL D''OURO PARK (12,2)'!A42:B42)} -> 0 | W8: 0 | X8: =V8/S8 -> #DIV/0!
A9: Sal D'Ouro Reserve (6) | B9: ='SAL D''OURO RESERVE (6)'!C34 -> 25 | C9: ='SAL D''OURO RESERVE (6)'!C30 -> 18 | D9: =C9/B9 -> 0.72 | E9: ='SAL D''OURO RESERVE (6)'!C31 -> 0 | F9: ='SAL D''OURO RESERVE (6)'!C33 -> 0 | G9: ='SAL D''OURO RESERVE (6)'!C32 -> 7 | H9: ='SAL D''OURO RESERVE (6)'!D30 -> 10808865 | I9: ='SAL D''OURO RESERVE (6)'!D34 -> 14672865 | J9: ='SAL D''OURO RESERVE (6)'!F51 -> 600492.5 | K9: ='SAL D''OURO RESERVE (6)'!F45 -> 5120.561 | L9: ='SAL D''OURO RESERVE (6)'!E31 -> #DIV/0! | M9: ='SAL D''OURO RESERVE (6)'!E33 -> #DIV/0! | N9: 3600 | O9: 3Q 2026 | P9: 9 | Q9: ='SAL D''OURO RESERVE (6)'!H31 -> 4 | R9: =Q9/P9 -> 0.44444444 | S9: =COUNTIFS('SAL D''OURO RESERVE (6)'!Z2:Z26,">="&EOMONTH(TODAY(),-1)+1,'SAL D''OURO RESERVE (6)'!Z2:Z26,"<"&EOMONTH(TODAY(),0)+1) -> 0 | T9: 0 | U9: =S9/T9 -> #DIV/0! | V9: {=SUMIFS('SAL D''OURO RESERVE (6)'!P2:P26,'SAL D''OURO RESERVE (6)'!Z2:Z26,">="&EOMONTH(TODAY(),-1)+1,'SAL D''OURO RESERVE (6)'!Z2:Z26,"<"&EOMONTH(TODAY(),0)+1,'SAL D''OURO RESERVE (6)'!M2:M26,'SAL D''OURO RESERVE (6)'!A30:B30)} -> 0 | W9: 0 | X9: =V9/S9 -> #DIV/0!
A10: Sal D'Ouro Horizon (9) | B10: ='SAL D''OURO HORIZON (9)'!C55 -> 46 | C10: ='SAL D''OURO HORIZON (9)'!C51 -> 38 | D10: =C10/B10 -> 0.82608696 | E10: ='SAL D''OURO HORIZON (9)'!C52 -> 0 | F10: ='SAL D''OURO HORIZON (9)'!C54 -> 1 | G10: ='SAL D''OURO HORIZON (9)'!C53 -> 7 | H10: ='SAL D''OURO HORIZON (9)'!D51 -> 17073910 | I10: ='SAL D''OURO HORIZON (9)'!D55 -> 23374930 | J10: ='SAL D''OURO HORIZON (9)'!G72 -> 449313.42 | K10: ='SAL D''OURO HORIZON (9)'!E51 -> 4414.9338 | L10: ='SAL D''OURO HORIZON (9)'!E52 -> #DIV/0! | M10: ='SAL D''OURO HORIZON (9)'!E54 -> 3867.9536 | N10: 3600 | O10: 4Q 2026 | P10: 12 | Q10: ='SAL D''OURO HORIZON (9)'!H52 -> 9 | R10: =Q10/P10 -> 0.75 | S10: =COUNTIFS('SAL D''OURO HORIZON (9)'!AA2:AA47,">="&EOMONTH(TODAY(),-1)+1,'SAL D''OURO HORIZON (9)'!AA2:AA47,"<"&EOMONTH(TODAY(),0)+1) -> 1 | T10: 0 | U10: =S10/T10 -> #DIV/0! | V10: {=SUMIFS('SAL D''OURO HORIZON (9)'!Q2:Q47,'SAL D''OURO HORIZON (9)'!AA2:AA47,">="&EOMONTH(TODAY(),-1)+1,'SAL D''OURO HORIZON (9)'!AA2:AA47,"<"&EOMONTH(TODAY(),0)+1,'SAL D''OURO HORIZON (9)'!P2:P47,'SAL D''OURO HORIZON (9)'!A51:B51)} -> 868800 | W10: 0 | X10: =V10/S10 -> 868800
A11: Sal D'Ouro Coast (10) | B11: ='SAL D''OURO COAST (10)'!C71 -> 62 | C11: ='SAL D''OURO COAST (10)'!C67 -> 56 | D11: =C11/B11 -> 0.90322581 | E11: ='SAL D''OURO COAST (10)'!C68 -> 0 | F11: ='SAL D''OURO COAST (10)'!C70 -> 0 | G11: ='SAL D''OURO COAST (10)'!C69 -> 6 | H11: ='SAL D''OURO COAST (10)'!D67 -> 28253280 | I11: ='SAL D''OURO COAST (10)'!D71 -> 32501280 | J11: ='SAL D''OURO COAST (10)'!H88 -> 504522.86 | K11: ='SAL D''OURO COAST (10)'!E67 -> 4540.1533 | L11: ='SAL D''OURO COAST (10)'!E68 -> #DIV/0! | M11: ='SAL D''OURO COAST (10)'!E70 -> #DIV/0! | N11: 3600 | O11: 4Q 2026 | P11: 20 | Q11: ='SAL D''OURO COAST (10)'!H68 -> 40 | R11: =Q11/P11 -> 2 | S11: =COUNTIFS('SAL D''OURO COAST (10)'!Y2:Y63,">="&EOMONTH(TODAY(),-1)+1,'SAL D''OURO COAST (10)'!Y2:Y63,"<"&EOMONTH(TODAY(),0)+1) -> 0 | T11: 0 | U11: =S11/T11 -> #DIV/0! | V11: {=SUMIFS('SAL D''OURO COAST (10)'!P2:P63,'SAL D''OURO COAST (10)'!Y2:Y63,">="&EOMONTH(TODAY(),-1)+1,'SAL D''OURO COAST (10)'!Y2:Y63,"<"&EOMONTH(TODAY(),0)+1,'SAL D''OURO COAST (10)'!O2:O63,'SAL D''OURO COAST (10)'!A67:B67)} -> 0 | W11: 0 | X11: =V11/S11 -> #DIV/0!
A12: Sal D'Ouro Pearl (17.2) | B12: ='SAL D''OURO 17.2'!C33 -> 24 | C12: ='SAL D''OURO 17.2'!C29 -> 0 | D12: =C12/B12 -> 0 | E12: ='SAL D''OURO 17.2'!C30 -> 0 | F12: ='SAL D''OURO 17.2'!C32 -> 0 | G12: ='SAL D''OURO 17.2'!C31 -> 24 | H12: ='SAL D''OURO 17.2'!D29 -> 0 | I12: ='SAL D''OURO 17.2'!D33 -> 18288000 | J12: ='SAL D''OURO 17.2'!H50 -> #DIV/0! | K12: ='SAL D''OURO 17.2'!E29 -> #DIV/0! | L12: ='SAL D''OURO 17.2'!E30 -> #DIV/0! | M12: ='SAL D''OURO 17.2'!E32 -> #DIV/0! | N12: 3600 | O12: 1Q 2027 | P12: 0 | Q12: ='SAL D''OURO 17.2'!H30 -> 0 | R12: =Q12/P12 -> #DIV/0! | S12: =COUNTIFS('SAL D''OURO 17.2'!Y2:Y25,">="&EOMONTH(TODAY(),-1)+1,'SAL D''OURO 17.2'!Y2:Y25,"<"&EOMONTH(TODAY(),0)+1) -> 0 | T12: 0 | U12: =S12/T12 -> #DIV/0! | V12: {=SUMIFS('SAL D''OURO 17.2'!P2:P25,'SAL D''OURO 17.2'!Y2:Y25,">="&EOMONTH(TODAY(),-1)+1,'SAL D''OURO 17.2'!Y2:Y25,"<"&EOMONTH(TODAY(),0)+1,'SAL D''OURO 17.2'!O2:O25,'SAL D''OURO 17.2'!A29:B29)} -> 0 | W12: 0 | X12: =V12/S12 -> #DIV/0!
A13: Eleven | B13: 95 | C13: ='ELEVEN (CITY HALL)'!C101 -> 93 | D13: =C13/B13 -> 0.97894737 | E13: ='ELEVEN (CITY HALL)'!C102 -> 0 | F13: ='ELEVEN (CITY HALL)'!C104 -> 1 | G13: ='ELEVEN (CITY HALL)'!C103 -> 1 | H13: ='ELEVEN (CITY HALL)'!D101 -> 30009215 | I13: ='ELEVEN (CITY HALL)'!D105 -> 31310015 | J13: ='ELEVEN (CITY HALL)'!J130 -> 345214.77 | K13: ='ELEVEN (CITY HALL)'!E109 -> 3504.6472 | L13: ='ELEVEN (CITY HALL)'!E102 -> #DIV/0! | M13: ='ELEVEN (CITY HALL)'!E104 -> 3645.0512 | N13: 3200 | O13: 1Q 2025 | P13: 14 | Q13: ='ELEVEN (CITY HALL)'!H103 -> 10 | R13: =Q13/P13 -> 0.71428571 | S13: =COUNTIFS('ELEVEN (CITY HALL)'!AB2:AB96,">="&EOMONTH(TODAY(),-1)+1,'ELEVEN (CITY HALL)'!AB2:AB96,"<"&EOMONTH(TODAY(),0)+1) -> 0 | T13: 0 | U13: =S13/T13 -> #DIV/0! | V13: {=SUMIFS('ELEVEN (CITY HALL)'!R2:R96,'ELEVEN (CITY HALL)'!AB2:AB96,">="&EOMONTH(TODAY(),-1)+1,'ELEVEN (CITY HALL)'!AB2:AB96,"<"&EOMONTH(TODAY(),0)+1,'ELEVEN (CITY HALL)'!Q2:Q96,'ELEVEN (CITY HALL)'!A101:B101)} -> 0 | W13: 0 | X13: =V13/S13 -> #DIV/0!
A14: Urban Infante 10B | B14: 65 | C14: ='URBAN INFANTE 10B'!C69 -> 65 | D14: =C14/B14 -> 1 | E14: ='URBAN INFANTE 10B'!C70 -> 0 | F14: ='URBAN INFANTE 10B'!C70 -> 0 | G14: ='URBAN INFANTE 10B'!C71 -> 0 | H14: ='URBAN INFANTE 10B'!D69 -> 14358915 | I14: ='URBAN INFANTE 10B'!D72 -> 14358915 | J14: ='URBAN INFANTE 10B'!H86 -> 220906.38 | K14: ='URBAN INFANTE 10B'!E69 -> 2544.7551 | L14: ='URBAN INFANTE 10B'!E70 -> #DIV/0! | M14: ='URBAN INFANTE 10B'!E70 -> #DIV/0! | N14: 2000 | O14: 2Q 2024 | P14: 0 | Q14: =S14 -> 0 | R14: =Q14/P14 -> #DIV/0! | S14: =COUNTIFS('URBAN INFANTE 10B'!P2:P66,">="&EOMONTH(TODAY(),-1)+1,'URBAN INFANTE 10B'!P2:P66,"<"&EOMONTH(TODAY(),0)+1) -> 0 | T14: 0 | U14: =S14/T14 -> #DIV/0! | V14: - | X14: =V14/S14 -> #VALUE!
A15: Urban Infante 10A | B15: ='URBAN INFANTE 10 A'!C58 -> 48 | C15: ='URBAN INFANTE 10 A'!C54 -> 48 | D15: =C15/B15 -> 1 | E15: ='URBAN INFANTE 10 A'!C55 -> 0 | F15: ='URBAN INFANTE 10 A'!C57 -> 0 | G15: ='URBAN INFANTE 10 A'!C56 -> 0 | H15: ='URBAN INFANTE 10 A'!D54 -> 14545595 | I15: ='URBAN INFANTE 10 A'!D58 -> 14545595 | J15: ='URBAN INFANTE 10 A'!H75 -> 303033.23 | K15: ='URBAN INFANTE 10 A'!E54 -> 2592.3719 | L15: ='URBAN INFANTE 10 A'!E55 -> #DIV/0! | M15: ='URBAN INFANTE 10 A'!E57 -> #DIV/0! | N15: 2000 | O15: 1Q 2025 | P15: 0 | Q15: 0 | R15: =Q15/P15 -> #DIV/0! | S15: =COUNTIFS(Table4[Date of CPCV],">="&EOMONTH(TODAY(),-1)+1,Table4[Date of CPCV],"<"&EOMONTH(TODAY(),0)+1) -> 0 | T15: 0 | U15: =S15/T15 -> #DIV/0! | V15: {=SUMIFS(Table4[Closing Price],Table4[Date of CPCV],">="&EOMONTH(TODAY(),-1)+1,Table4[Date of CPCV],"<"&EOMONTH(TODAY(),0)+1,Table4[Status],'URBAN INFANTE 10 A'!A54:B54)} -> 0 | W15: 0 | X15: =V15/S15 -> #DIV/0!
A16: Parkview 5 | B16: 39 | C16: ='PARKVIEW 5'!C44 -> 39 | D16: =C16/B16 -> 1 | E16: ='PARKVIEW 5'!C45 -> 0 | F16: ='PARKVIEW 5'!C47 -> 0 | G16: ='PARKVIEW 5'!C46 -> 0 | H16: ='PARKVIEW 5'!D44 -> 11771318 | I16: ='PARKVIEW 5'!D48 -> 0 | J16: ='PARKVIEW 5'!E65 -> 301828.68 | K16: ='PARKVIEW 5'!E59 -> 3160.8543 | L16: ='PARKVIEW 5'!E45 -> #DIV/0! | M16: ='PARKVIEW 5'!E47 -> #DIV/0! | N16: 2250 | O16: 3Q 2026 | P16: 25 | Q16: ='PARKVIEW 5'!H45 -> 27 | R16: =Q16/P16 -> 1.08 | S16: =COUNTIFS('PARKVIEW 5'!AD2:AD40,">="&EOMONTH(TODAY(),-1)+1,'PARKVIEW 5'!AD2:AD40,"<"&EOMONTH(TODAY(),0)+1) -> 0 | T16: 1 | U16: =S16/T16 -> 0 | V16: {=SUMIFS('PARKVIEW 5'!N2:N40,'PARKVIEW 5'!AD2:AD40,">="&EOMONTH(TODAY(),-1)+1,'PARKVIEW 5'!AD2:AD40,"<"&EOMONTH(TODAY(),0)+1,'PARKVIEW 5'!M2:M40,'PARKVIEW 5'!A44:B44)} -> 0 | W16: 0 | X16: =V16/S16 -> #DIV/0!
A17: Red Clip | B17: ='RED CLIP'!C39 -> 30 | C17: ='RED CLIP'!C35 -> 0 | D17: ='RED CLIP'!H39 -> 0 | E17: ='RED CLIP'!C36 -> 3 | F17: ='RED CLIP'!C38 -> 0 | G17: ='RED CLIP'!C37 -> 27 | H17: ='RED CLIP'!D35 -> 0 | I17: ='RED CLIP'!D39 -> 17673600 | J17: ='RED CLIP'!G56 -> #DIV/0! | K17: ='RED CLIP'!G50 -> #DIV/0! | L17: ='RED CLIP'!G51 -> 6688.77 | M17: ='RED CLIP'!G53 -> #DIV/0! | N17: 5215 | O17: 3Q 2027 | P17: 18 | Q17: ='RED CLIP'!H35 -> 0 | R17: =Q17/P17 -> 0 | S17: =COUNTIFS('RED CLIP'!X2:X31,">="&EOMONTH(TODAY(),-1)+1,'RED CLIP'!X2:X31,"<"&EOMONTH(TODAY(),0)+1) -> 0 | T17: 1 | U17: =S17/T17 -> 0 | V17: {=SUMIFS('RED CLIP'!P2:P31,'RED CLIP'!X2:X31,">="&EOMONTH(TODAY(),-1)+1,'RED CLIP'!X2:X31,"<"&EOMONTH(TODAY(),0)+1,'RED CLIP'!O2:O31,'RED CLIP'!A35:B35)} -> 0 | W17: 0 | X17: =V17/S17 -> #DIV/0!
A18: Setubal Sea View | B18: ='SETUBAL SEA VIEW'!C80 -> 71 | C18: ='SETUBAL SEA VIEW'!C76 -> 0 | D18: =C18/B18 -> 0 | E18: ='SETUBAL SEA VIEW'!C77 -> 0 | F18: ='SETUBAL SEA VIEW'!C79 -> 0 | G18: ='SETUBAL SEA VIEW'!C78 -> 71 | H18: ='SETUBAL SEA VIEW'!D76 -> 0 | I18: ='SETUBAL SEA VIEW'!D80 -> 36566400 | J18: ='SETUBAL SEA VIEW'!H90 -> #DIV/0! | K18: ='SETUBAL SEA VIEW'!E76 -> #DIV/0! | L18: ='SETUBAL SEA VIEW'!E77 -> #DIV/0! | M18: ='SETUBAL SEA VIEW'!E79 -> #DIV/0! | N18: 4850 | O18: 1Q 2028 | P18: 35 | Q18: ='SETUBAL SEA VIEW'!H76 -> 0 | R18: =Q18/P18 -> 0 | T18: 7
A19: Coimbra plot 8 & 9 | B19: ='CELAS PARQUE 9 & 8'!C37 -> 28 | C19: ='CELAS PARQUE 9 & 8'!C33 -> 0 | D19: ='CELAS PARQUE 9 & 8'!H37 -> 0 | E19: ='CELAS PARQUE 9 & 8'!C34 -> 0 | F19: ='CELAS PARQUE 9 & 8'!C36 -> 0 | G19: ='CELAS PARQUE 9 & 8'!C35 -> 28 | H19: ='CELAS PARQUE 9 & 8'!D33 -> 0 | I19: ='CELAS PARQUE 9 & 8'!D37 -> 12687360 | J19: ='CELAS PARQUE 9 & 8'!E54 -> #DIV/0! | K19: ='CELAS PARQUE 9 & 8'!E33 -> #DIV/0! | L19: ='CELAS PARQUE 9 & 8'!E34 -> #DIV/0! | M19: ='CELAS PARQUE 9 & 8'!E36 -> #DIV/0! | N19: 3800 | O19: 1Q 2028 | P19: 45 | Q19: 0 | R19: =Q19/P19 -> 0 | T19: 7
B23: =SUM(B2:B16)-B12 -> 779 | C23: =SUM(C2:C16) -> 748 | D23: =C23/B23 -> 0.96020539 | E23: =SUM(E2:E16) -> 0 | F23: =SUM(F2:F16) -> 5 | G23: =SUM(G2:G11,G13:G16) -> 26 | P23: =SUM(P2:P16) -> 164 | Q23: =SUM(Q2:Q17) -> 172 | R23: =Q23/P23 -> 1.0487805 | S23: =SUM(S2:S17) -> 1 | T23: =SUM(T2:T16) -> 2 | U23: =S23/T23 -> 0.5 | V23: =SUM(V2:V17) -> 868800 | X23: =V23/S23 -> 868800
B24: TOTAL PROJECTS | C24: TOTAL SOLD | D24: % sold ongoing proj. | E24: TOTAL BLOCKED | F24: TOTAL RESERVED | G24: TOTAL AVAILABLE | P24: Goals 2025 | Q24: TOTAL YEAR | S24: TOTAL MONTH | T24: TOTAL GOALS | U24: % Goals | V24: TOTAL VOLUME MONTH | X24: Overall Average
A27: CPCV 2025 | P27: Top month
B28: January | C28: February | D28: March | E28: April | F28: May | G28: June | H28: July | I28: August | J28: September | K28: October | L28: November | M28: December | N28: TOTAL 2025 | P28: Month | Q28: # | R28: %
A29: Panorama | B29: ='PANORAMA (SETUBAL)'!J93 -> 2 | C29: ='PANORAMA (SETUBAL)'!K93 -> 2 | D29: ='PANORAMA (SETUBAL)'!L93 -> 1 | E29: ='PANORAMA (SETUBAL)'!M93 -> 0 | F29: ='PANORAMA (SETUBAL)'!N93 -> 3 | G29: ='PANORAMA (SETUBAL)'!O93 -> 1 | H29: 0 | I29: ='PANORAMA (SETUBAL)'!Q93 -> 1 | J29: ='PANORAMA (SETUBAL)'!R93 -> 0 | K29: ='PANORAMA (SETUBAL)'!S93 -> 1 | L29: ='PANORAMA (SETUBAL)'!T93 -> 0 | M29: ='PANORAMA (SETUBAL)'!U93 -> 0 | N29: =SUM(A29:L29) -> 11 | P29: Jan | Q29: =B46 -> 21 | R29: =Q29/SUM($Q$29:$Q$40) -> 0.12138728
A30: Verde Vale V1 | B30: ='VERDE VALE H1 (MAIA)'!J80 -> 0 | C30: ='VERDE VALE H1 (MAIA)'!K80 -> 1 | D30: ='VERDE VALE H1 (MAIA)'!L80 -> 0 | E30: ='VERDE VALE H1 (MAIA)'!M80 -> 0 | F30: ='VERDE VALE H1 (MAIA)'!N80 -> 0 | G30: ='VERDE VALE H1 (MAIA)'!O80 -> 0 | H30: ='VERDE VALE H1 (MAIA)'!P80 -> 0 | I30: ='VERDE VALE H1 (MAIA)'!Q80 -> 0 | ... M30: ='VERDE VALE H1 (MAIA)'!U80 -> 0 | N30: =SUM(A30:L30) -> 1 | P30: Feb | Q30: =C46 -> 9 | R30: =Q30/SUM($Q$29:$Q$40) -> 0.052023121
A31: Verde ValeV2 & V3 | B31: ='VERDE VALE H3 A&B (MAIA)'!J68 -> 2 | C31: ='VERDE VALE H3 A&B (MAIA)'!K68 -> 1 | D31: ='VERDE VALE H3 A&B (MAIA)'!L68 -> 2 | E31: ='VERDE VALE H3 A&B (MAIA)'!M68 -> 1 | F31: ='VERDE VALE H3 A&B (MAIA)'!N68 -> 0 | G31: ='VERDE VALE H3 A&B (MAIA)'!O68 -> 0 | H31: ='VERDE VALE H3 A&B (MAIA)'!P68 -> 0 | I31: ='VERDE VALE H3 A&B (MAIA)'!Q68 -> 0 | ... M31: ='VERDE VALE H3 A&B (MAIA)'!U68 -> 0 | N31: =SUM(A31:L31) -> 6 | P31: March | Q31: =D46 -> 23 | R31: =Q31/SUM($Q$29:$Q$40) -> 0.13294798
A32: Verde Vale V4 | B32: ='VERDE VALE H2 (MAIA)'!J64 -> 0 | C32: ='VERDE VALE H2 (MAIA)'!K64 -> 0 | D32: ='VERDE VALE H2 (MAIA)'!L64 -> 2 | E32: ='VERDE VALE H2 (MAIA)'!M64 -> 0 | F32: ='VERDE VALE H2 (MAIA)'!N64 -> 0 | G32: ='VERDE VALE H2 (MAIA)'!O64 -> 0 | H32: ='VERDE VALE H2 (MAIA)'!P64 -> 0 | I32: ='VERDE VALE H2 (MAIA)'!Q64 -> 2 | ... M32: ='VERDE VALE H2 (MAIA)'!U64 -> 0 | N32: =SUM(A32:L32) -> 7 | P32: Apr | Q32: =E46 -> 22 | R32: =Q32/SUM($Q$29:$Q$40) -> 0.12716763
A33: Verde ValeV5 & V6 | B33: ='VERDE VALE H4 A&B (MAIA)'!J92 -> 4 | C33: ='VERDE VALE H4 A&B (MAIA)'!K92 -> 0 | D33: ='VERDE VALE H4 A&B (MAIA)'!L92 -> 5 | E33: ='VERDE VALE H4 A&B (MAIA)'!M92 -> 8 | F33: ='VERDE VALE H4 A&B (MAIA)'!N92 -> 8 | G33: ='VERDE VALE H4 A&B (MAIA)'!O92 -> 1 | H33: ='VERDE VALE H4 A&B (MAIA)'!P92 -> 4 | I33: ='VERDE VALE H4 A&B (MAIA)'!Q92 -> 1 | ... M33: ='VERDE VALE H4 A&B (MAIA)'!U92 -> 0 | N33: =SUM(A33:L33) -> 40 | P33: May | Q33: =F46 -> 18 | R33: =Q33/SUM($Q$29:$Q$40) -> 0.10404624
A34: Sal D'Ouro Ocean (8) | B34: ='SAL D''OURO OCEAN (8)'!J46 -> 1 | C34: ='SAL D''OURO OCEAN (8)'!K46 -> 0 | D34: ='SAL D''OURO OCEAN (8)'!L46 -> 2 | E34: ='SAL D''OURO OCEAN (8)'!M46 -> 2 | F34: ='SAL D''OURO OCEAN (8)'!N46 -> 1 | G34: ='SAL D''OURO OCEAN (8)'!O46 -> 0 | H34: ='SAL D''OURO OCEAN (8)'!P46 -> 0 | I34: ='SAL D''OURO OCEAN (8)'!Q46 -> 0 | ... M34: ='SAL D''OURO OCEAN (8)'!U46 -> 0 | N34: =SUM(A34:L34) -> 6 | P34: June | Q34: =G46 -> 16 | R34: =Q34/SUM($Q$29:$Q$40) -> 0.092485549
A35: Sal D'Ouro Park (12.2) | B35: ='SAL D''OURO PARK (12,2)'!J52 -> 0 | C35: ='SAL D''OURO PARK (12,2)'!K52 -> 0 | D35: ='SAL D''OURO PARK (12,2)'!L52 -> 1 | E35: ='SAL D''OURO PARK (12,2)'!M52 -> 1 | F35: ='SAL D''OURO PARK (12,2)'!N52 -> 1 | G35: ='SAL D''OURO PARK (12,2)'!O52 -> 2 | H35: ='SAL D''OURO PARK (12,2)'!P52 -> 2 | I35: ='SAL D''OURO PARK (12,2)'!Q52 -> 2 | ... M35: ='SAL D''OURO PARK (12,2)'!U52 -> 0 | N35: =SUM(A35:L35) -> 11 | P35: July | Q35: =H46 -> 18 | R35: =Q35/SUM($Q$29:$Q$40) -> 0.10404624
A36: Sal D'Ouro Reserve (6) | B36: ='SAL D''OURO RESERVE (6)'!J34 -> 0 | C36: ='SAL D''OURO RESERVE (6)'!K34 -> 0 | D36: ='SAL D''OURO RESERVE (6)'!L34 -> 1 | E36: ='SAL D''OURO RESERVE (6)'!M34 -> 1 | F36: ='SAL D''OURO RESERVE (6)'!N34 -> 0 | G36: ='SAL D''OURO RESERVE (6)'!O34 -> 0 | H36: ='SAL D''OURO RESERVE (6)'!P34 -> 0 | I36: ='SAL D''OURO RESERVE (6)'!R34 -> 0 | J36: ='SAL D''OURO RESERVE (6)'!S34 -> 2 | K36: ='SAL D''OURO RESERVE (6)'!T34 -> 0 | L36: ='SAL D''OURO RESERVE (6)'!V34 -> 0 | M36: ='SAL D''OURO RESERVE (6)'!W34 -> 0 | N36: =SUM(A36:L36) -> 4 | P36: Aug | Q36: =I46 -> 9 | R36: =Q36/SUM($Q$29:$Q$40) -> 0.052023121
A37: Sal D'Ouro Horizon (9) | B37: ='SAL D''OURO HORIZON (9)'!J55 -> 1 | C37: ='SAL D''OURO HORIZON (9)'!K55 -> 0 | D37: ='SAL D''OURO HORIZON (9)'!L55 -> 1 | E37: ='SAL D''OURO HORIZON (9)'!M55 -> 0 | F37: ='SAL D''OURO HORIZON (9)'!N55 -> 0 | G37: ='SAL D''OURO HORIZON (9)'!O55 -> 2 | H37: ='SAL D''OURO HORIZON (9)'!P55 -> 1 | I37: ='SAL D''OURO HORIZON (9)'!Q55 -> 0 | J37: ='SAL D''OURO HORIZON (9)'!S55 -> 1 | K37: ='SAL D''OURO HORIZON (9)'!T55 -> 0 | L37: ='SAL D''OURO HORIZON (9)'!U55 -> 2 | M37: ='SAL D''OURO HORIZON (9)'!V55 -> 1 | N37: =SUM(A37:L37) -> 8 | P37: Sept. | Q37: =J46 -> 14 | R37: =Q37/SUM($Q$29:$Q$40) -> 0.080924855
A38: Sal D'Ouro Coast (10) | B38: ='SAL D''OURO COAST (10)'!J72 -> 1 | C38: ='SAL D''OURO COAST (10)'!K72 -> 2 | D38: ='SAL D''OURO COAST (10)'!L72 -> 2 | E38: ='SAL D''OURO COAST (10)'!M72 -> 2 | F38: ='SAL D''OURO COAST (10)'!N72 -> 4 | G38: ='SAL D''OURO COAST (10)'!O72 -> 7 | H38: ='SAL D''OURO COAST (10)'!P72 -> 7 | I38: ='SAL D''OURO COAST (10)'!Q72 -> 3 | ... M38: ='SAL D''OURO COAST (10)'!U72 -> 0 | N38: =SUM(A38:L38) -> 40 | P38: Oct | Q38: =K46 -> 12 | R38: =Q38/SUM($Q$29:$Q$40) -> 0.069364162
A39: Sal D'Ouro Pearl (17.2) | N39: =SUM(A39:L39) -> 0 | P39: Nov | Q39: =L46 -> 10 | R39: =Q39/SUM($Q$29:$Q$40) -> 0.057803468
A40: Eleven | B40: ='ELEVEN (CITY HALL)'!L108 -> 6 | C40: ='ELEVEN (CITY HALL)'!M108 -> 1 | D40: ='ELEVEN (CITY HALL)'!N108 -> 1 | E40: ='ELEVEN (CITY HALL)'!O108 -> 0 | F40: ='ELEVEN (CITY HALL)'!P108 -> 1 | G40: ='ELEVEN (CITY HALL)'!Q108 -> 1 | H40: ='ELEVEN (CITY HALL)'!R108 -> 0 | I40: ='ELEVEN (CITY HALL)'!S108 -> 0 | ... M40: ='ELEVEN (CITY HALL)'!W108 -> 0 | N40: =SUM(A40:L40) -> 10 | P40: Decem. | Q40: =M46 -> 1 | R40: =Q40/SUM($Q$29:$Q$40) -> 0.0057803468
A41: Urban Infante 10B | B41: 1 | N41: =SUM(A41:L41) -> 1
A42: Urban Infante 10A | N42: =SUM(A42:L42) -> 0
A43: Parkview 5 | B43: ='PARKVIEW 5'!G55 -> 3 | C43: ='PARKVIEW 5'!H55 -> 2 | D43: ='PARKVIEW 5'!I55 -> 5 | E43: ='PARKVIEW 5'!J55 -> 7 | F43: ='PARKVIEW 5'!K55 -> 0 | G43: ='PARKVIEW 5'!L55 -> 2 | H43: ='PARKVIEW 5'!M55 -> 4 | I43: ='PARKVIEW 5'!N55 -> 0 | ... M43: ='PARKVIEW 5'!R55 -> 0 | N43: =SUM(A43:L43) -> 27
A44: Red Clip | B44: ='RED CLIP'!J37 -> 0 | C44: ='RED CLIP'!K37 -> 0 | D44: ='RED CLIP'!L37 -> 0 | E44: ='RED CLIP'!M37 -> 0 | F44: ='RED CLIP'!O37 -> 0 | G44: ='RED CLIP'!P37 -> 0 | H44: ='RED CLIP'!Q37 -> 0 | I44: ='RED CLIP'!R37 -> 0 | J44: ='RED CLIP'!S37 -> 0 | K44: ='RED CLIP'!T37 -> 0 | L44: ='RED CLIP'!U37 -> 0 | M44: ='RED CLIP'!V37 -> 0 | N44: =SUM(A44:L44) -> 0
A46: TOTAL P/ MONTH | B46: =SUM(B29:B44) -> 21 | C46: =SUM(C29:C44) -> 9 | D46: =SUM(D29:D44) -> 23 | E46: =SUM(E29:E44) -> 22 | F46: =SUM(F29:F44) -> 18 | G46: =SUM(G29:G44) -> 16 | H46: =SUM(H29:H44) -> 18 | I46: =SUM(I29:I44) -> 9 | ... N46: =SUM(N29:N44) -> 172
A50: Brokers | K50: Top Broker
B51: GlobalKey | C51: Tranquildiscovery | D51: Empril | E51: ChaveNova | F51: JLL | G51: Réplica | H51: Venda Directa | K51: Broker | L51: # | M51: %
A52: Panorama | B52: ='PANORAMA (SETUBAL)'!K99 -> 12 | C52: ='PANORAMA (SETUBAL)'!K100 -> 7 | D52: - | E52: - | F52: ='PANORAMA (SETUBAL)'!K98 -> 51 | G52: - | H52: ='PANORAMA (SETUBAL)'!K101 -> 6 | K52: GlobalKey | L52: =B68 -> 233 | M52: =L52/(SUM($L$52:$L$58)) -> 0.43068392
A53: Verde Vale V1 | B53: ='VERDE VALE H1 (MAIA)'!K85 -> 43 | C53: ='VERDE VALE H1 (MAIA)'!K87 -> 10 | D53: - | E53: ='VERDE VALE H1 (MAIA)'!K86 -> 11 | F53: - | G53: - | H53: - | K53: Tranquildiscovery | L53: =C68 -> 76 | M53: =L53/(SUM($L$52:$L$58)) -> 0.14048059
A54: Verde ValeV2 & V3 | B54: ='VERDE VALE H3 A&B (MAIA)'!K73 -> 38 | C54: ='VERDE VALE H3 A&B (MAIA)'!K75 -> 5 | D54: - | E54: ='VERDE VALE H3 A&B (MAIA)'!K74 -> 13 | F54: - | G54: - | H54: - | K54: Empril | L54: =D68 -> 105 | M54: =L54/(SUM($L$52:$L$58)) -> 0.19408503
A55: Verde Vale V4 | B55: ='VERDE VALE H2 (MAIA)'!K69 -> 25 | C55: ='VERDE VALE H2 (MAIA)'!K71 -> 0 | D55: - | E55: ='VERDE VALE H2 (MAIA)'!K70 -> 28 | F55: - | G55: - | H55: - | K55: ChaveNova | L55: =E68 -> 52 | M55: =L55/(SUM($L$52:$L$58)) -> 0.096118299
A56: Verde ValeV5 & V6 | B56: ='VERDE VALE H4 A&B (MAIA)'!K97 -> 0 | C56: ='VERDE VALE H4 A&B (MAIA)'!K99 -> 0 | D56: - | E56: ='VERDE VALE H4 A&B (MAIA)'!K98 -> 0 | F56: - | G56: - | H56: - | K56: JLL | L56: =F68 -> 64 | M56: =L56/(SUM($L$52:$L$58)) -> 0.11829945
A57: Sal D'Ouro Ocean (8) | B57: ='SAL D''OURO OCEAN (8)'!K51 -> 15 | C57: ='SAL D''OURO OCEAN (8)'!K53+'SAL D''OURO OCEAN (8)'!K54 -> 11 | D57: - | E57: - | F57: ='SAL D''OURO OCEAN (8)'!K55 -> 0 | G57: ='SAL D''OURO OCEAN (8)'!K52 -> 5 | H57: - | K57: Réplica | L57: =G68 -> 5 | M57: =L57/(SUM($L$52:$L$58)) -> 0.0092421442
A58: Sal D'Ouro Park (12.2) | B58: ='SAL D''OURO PARK (12,2)'!K57 -> 24 | C58: ='SAL D''OURO PARK (12,2)'!K58 -> 6 | D58: - | E58: - | F58: ='SAL D''OURO PARK (12,2)'!K60 -> 2 | G58: - | H58: - | K58: Venda Directa | L58: =H68 -> 6 | M58: =L58/(SUM($L$52:$L$58)) -> 0.011090573
A59: Sal D'Ouro Reserve (6) | B59: ='SAL D''OURO RESERVE (6)'!K40 -> 9 | C59: ='SAL D''OURO RESERVE (6)'!K41 -> 3 | D59: - | E59: - | F59: ='SAL D''OURO RESERVE (6)'!K42 -> 4 | G59: - | H59: -
A60: Sal D'Ouro Horizon (9) | B60: ='SAL D''OURO HORIZON (9)'!K61 -> 0 | C60: ='SAL D''OURO HORIZON (9)'!K62 -> 0 | D60: - | E60: - | F60: ='SAL D''OURO HORIZON (9)'!L63 -> 3 | G60: - | H60: -
A61: Sal D'Ouro Coast (10) | B61: ='SAL D''OURO COAST (10)'!K78 -> 0 | C61: ='SAL D''OURO COAST (10)'!K79 -> 0 | D61: - | E61: - | F61: ='SAL D''OURO COAST (10)'!L80 -> 4 | G61: - | H61: -
A62: Sal D'Ouro Pearl (17.2) | B62: ='SAL D''OURO 17.2'!K42 -> 0 | C62: ='SAL D''OURO 17.2'!K43 -> 0 | D62: - | E62: - | F62: ='SAL D''OURO COAST (10)'!K80 -> 0 | G62: - | H62: -
A63: Eleven | B63: ='ELEVEN (CITY HALL)'!M114 -> 44 | C63: ='ELEVEN (CITY HALL)'!M115 -> 32 | D63: ='ELEVEN (CITY HALL)'!M116 -> 17 | E63: - | F63: - | G63: - | H63: -
A64: Urban Infante 10B | B64: ='URBAN INFANTE 10B'!K73 -> 13 | C64: ='URBAN INFANTE 10B'!K74 -> 0 | D64: ='URBAN INFANTE 10B'!K75 -> 52 | E64: - | F64: - | G64: - | H64: -
A65: Urban Infante 10A | B65: ='URBAN INFANTE 10 A'!K65 -> 10 | C65: ='URBAN INFANTE 10 A'!K66 -> 2 | D65: ='URBAN INFANTE 10 A'!K67 -> 36 | E65: - | F65: - | G65: - | H65: -
A66: Parkview 5 | B66: ='PARKVIEW 5'!H64 -> 0 | C66: ='PARKVIEW 5'!H64 -> 0 | D66: - | E66: ='PARKVIEW 5'!H63 -> 0 | F66: - | G66: - | H66: -
A68: TOTAL | B68: =SUM(B52:B66) -> 233 | C68: =SUM(C52:C66) -> 76 | D68: =SUM(D52:D66) -> 105 | E68: =SUM(E52:E66) -> 52 | F68: =SUM(F52:F66) -> 64 | G68: =SUM(G52:G66) -> 5 | H68: =SUM(H52:H66) -> 6
A71: Nationalities
B72: Portugal | C72: Israel | D72: Brazil | E72: China | F72: France | G72: Spain | H72: Finland | I72: Leban | J72: Iran | K72: United Kingdom | L72: USA | M72: Belgium | N72: Italy | O72: Nepal | P72: Morroco | Q72: Korea | R72: Mozambique | S72: Canada | T72: Poland | U72: Angola | V72: Ukraine | W72: Venezuela | X72: Total | Y72: % Portuguese | Z72: # foreigners
A73: Panorama | B73: ='PANORAMA (SETUBAL)'!P98 -> 34 | C73: ='PANORAMA (SETUBAL)'!P99 -> 18 | D73: ='PANORAMA (SETUBAL)'!P108 -> 6 | E73: - | F73: ='PANORAMA (SETUBAL)'!P100 -> 1 | G73: - | H73: ='PANORAMA (SETUBAL)'!P101 -> 1 | I73: ='PANORAMA (SETUBAL)'!P102 -> 1 | J73: ='PANORAMA (SETUBAL)'!P103 -> 1 | K73: ='PANORAMA (SETUBAL)'!P104 -> 3 | L73: ='PANORAMA (SETUBAL)'!P105 -> 3 | M73: ='PANORAMA (SETUBAL)'!P106 -> 2 | N73: ='PANORAMA (SETUBAL)'!P107 -> 1 | O73: - | P73: - | Q73: - | R73: - | S73: - | T73: ='PANORAMA (SETUBAL)'!P109 -> 2 | U73: ='PANORAMA (SETUBAL)'!P110 -> 1 | W73: - | X73: =SUM(B73:W73) -> 74 | Y73: =B73/X73 -> 0.45945946 | Z73: =SUM(C73:W73) -> 40
A74: Verde Vale V1 | B74: ='VERDE VALE H1 (MAIA)'!P85 -> 50 | C74: ='VERDE VALE H1 (MAIA)'!P86 -> 11 | D74: ='VERDE VALE H1 (MAIA)'!L123 -> 0 | E74: ='VERDE VALE H1 (MAIA)'!P88 -> 2 | F74: - | G74: - | H74: - | I74: - | J74: - | K74: - | L74: - | M74: - | N74: - | O74: - | P74: - | Q74: - | R74: - | S74: - | T74: - | U74: ='VERDE VALE H1 (MAIA)'!P87 -> 1 | W74: - | X74: =SUM(B74:W74) -> 64 | Y74: =B74/X74 -> 0.78125 | Z74: =SUM(C74:W74) -> 14
A75: Verde ValeV2 & V3 | B75: ='VERDE VALE H3 A&B (MAIA)'!P73 -> 49 | C75: ='VERDE VALE H3 A&B (MAIA)'!P74 -> 2 | D75: ='VERDE VALE H3 A&B (MAIA)'!P76 -> 1 | E75: - | F75: - | G75: - | H75: - | I75: - | J75: - | K75: - | L75: - | M75: - | N75: - | O75: - | P75: - | Q75: - | R75: - | S75: - | T75: - | U75: - | W75: ='VERDE VALE H3 A&B (MAIA)'!P75 -> 1 | X75: =SUM(B75:W75) -> 53 | Y75: =B75/X75 -> 0.9245283 | Z75: =SUM(C75:W75) -> 4
A76: Verde Vale V4 | B76: ='VERDE VALE H2 (MAIA)'!P69 -> 50 | C76: ='VERDE VALE H2 (MAIA)'!P70 -> 0 | D76: ='VERDE VALE H2 (MAIA)'!P71 -> 1 | E76: - | F76: - | G76: - | H76: - | I76: - | J76: - | K76: - | L76: - | M76: - | N76: - | O76: - | P76: - | Q76: - | R76: - | S76: - | T76: - | U76: - | W76: - | X76: =SUM(B76:W76) -> 51 | Y76: =B76/X76 -> 0.98039216 | Z76: =SUM(C76:W76) -> 1
A77: Verde ValeV5 & V6 | B77: ='VERDE VALE H4 A&B (MAIA)'!P97 -> 58 | C77: ='VERDE VALE H4 A&B (MAIA)'!P98 -> 5 | D77: ='VERDE VALE H4 A&B (MAIA)'!P99 -> 4 | E77: - | F77: - | G77: - | H77: - | I77: - | J77: - | K77: - | L77: - | M77: - | N77: - | O77: - | P77: - | Q77: - | R77: - | S77: - | T77: - | U77: - | W77: - | X77: =SUM(B77:W77) -> 67 | Y77: =B77/X77 -> 0.86567164 | Z77: =SUM(C77:W77) -> 9
A78: Sal D'Ouro Ocean (8) | B78: ='SAL D''OURO OCEAN (8)'!P51 -> 13 | C78: ='SAL D''OURO OCEAN (8)'!P52 -> 12 | D78: ='SAL D''OURO OCEAN (8)'!P53 -> 1 | E78: - | F78: - | G78: ='SAL D''OURO OCEAN (8)'!P54 -> 3 | H78: - | I78: - | J78: - | K78: - | L78: - | M78: - | N78: - | O78: - | P78: ='SAL D''OURO OCEAN (8)'!P55 -> 1 | Q78: - | R78: - | S78: - | T78: - | U78: - | W78: - | X78: =SUM(B78:W78) -> 30 | Y78: =B78/X78 -> 0.43333333 | Z78: =SUM(C78:W78) -> 17
A79: Sal D'Ouro Park (12.2) | B79: ='SAL D''OURO PARK (12,2)'!P57 -> 14 | C79: ='SAL D''OURO PARK (12,2)'!P58 -> 9 | D79: ='SAL D''OURO PARK (12,2)'!P59 -> 6 | E79: ='SAL D''OURO PARK (12,2)'!P63 -> 1 | F79: - | G79: ='SAL D''OURO PARK (12,2)'!P60 -> 1 | H79: - | I79: - | J79: - | K79: - | L79: - | M79: - | N79: - | O79: ='SAL D''OURO PARK (12,2)'!P62 -> 1 | P79: ='SAL D''OURO PARK (12,2)'!P61 -> 1 | Q79: - | R79: - | S79: - | T79: - | U79: - | W79: - | X79: =SUM(B79:W79) -> 33 | Y79: =B79/X79 -> 0.42424242 | Z79: =SUM(C79:W79) -> 19
A80: Sal D'Ouro Reserve (6) | B80: ='SAL D''OURO RESERVE (6)'!P40 -> 6 | C80: ='SAL D''OURO RESERVE (6)'!P41 -> 3 | D80: ='SAL D''OURO RESERVE (6)'!P42 -> 4 | E80: - | F80: - | G80: - | H80: - | I80: - | J80: - | K80: - | L80: ='SAL D''OURO RESERVE (6)'!P43 -> 4 | M80: - | N80: - | O80: - | P80: - | Q80: - | R80: - | S80: - | T80: - | U80: - | W80: - | X80: =SUM(B80:W80) -> 17 | Y80: =B80/X80 -> 0.35294118 | Z80: =SUM(C80:W80) -> 11
A81: Sal D'Ouro Horizon (9) | B81: ='SAL D''OURO HORIZON (9)'!Q61 -> 23 | C81: ='SAL D''OURO HORIZON (9)'!Q62 -> 3 | D81: - | E81: - | F81: - | G81: - | H81: - | I81: - | J81: - | K81: - | L81: - | M81: - | N81: - | O81: - | P81: - | Q81: - | R81: - | S81: - | T81: - | U81: - | W81: - | X81: =SUM(B81:W81) -> 26 | Y81: =B81/X81 -> 0.88461538 | Z81: =SUM(C81:W81) -> 3
A82: Sal D'Ouro Coast (10) | B82: ='SAL D''OURO COAST (10)'!P78 -> 24 | C82: ='SAL D''OURO COAST (10)'!P79 -> 5 | D82: - | E82: - | F82: - | G82: - | H82: - | I82: - | J82: - | K82: - | L82: - | M82: - | N82: - | O82: - | P82: - | Q82: - | R82: - | S82: - | T82: - | U82: - | W82: - | X82: =SUM(B82:W82) -> 29 | Y82: =B82/X82 -> 0.82758621 | Z82: =SUM(C82:W82) -> 5
A83: Sal D'Ouro Pearl (17.2) | B83: ='SAL D''OURO 17.2'!P42 -> 0 | C83: ='SAL D''OURO 17.2'!P43 -> 0 | D83: - | E83: - | F83: - | G83: - | H83: - | I83: - | J83: - | K83: - | L83: - | M83: - | N83: - | O83: - | P83: - | Q83: - | R83: - | S83: - | T83: - | U83: - | W83: - | X83: =SUM(B83:W83) -> 0 | Y83: =B83/X83 -> #DIV/0! | Z83: =SUM(C83:W83) -> 0
A84: Eleven | B84: ='ELEVEN (CITY HALL)'!R114 -> 50 | C84: ='ELEVEN (CITY HALL)'!R115 -> 20 | D84: ='ELEVEN (CITY HALL)'!R116 -> 6 | E84: - | F84: ='ELEVEN (CITY HALL)'!R122 -> 0 | G84: - | H84: - | I84: - | J84: - | K84: - | L84: ='ELEVEN (CITY HALL)'!R117 -> 5 | M84: - | N84: ='ELEVEN (CITY HALL)'!R123 -> 1 | O84: - | P84: ='ELEVEN (CITY HALL)'!R118 -> 1 | Q84: ='ELEVEN (CITY HALL)'!R124 -> 1 | R84: ='ELEVEN (CITY HALL)'!R119 -> 1 | S84: ='ELEVEN (CITY HALL)'!R121 -> 1 | T84: - | U84: ='ELEVEN (CITY HALL)'!R120 -> 1 | W84: ='ELEVEN (CITY HALL)'!R125 -> 3 | X84: =SUM(B84:W84) -> 90 | Y84: =B84/X84 -> 0.55555556 | Z84: =SUM(C84:W84) -> 40
A85: Urban Infante 10B | B85: ='URBAN INFANTE 10B'!P73 -> 57 | C85: - | D85: ='URBAN INFANTE 10B'!P74 -> 4 | E85: ='URBAN INFANTE 10B'!P75 -> 2 | F85: ='URBAN INFANTE 10B'!P77 -> 1 | G85: - | H85: - | I85: - | J85: - | K85: - | L85: - | M85: - | N85: - | O85: - | P85: - | Q85: ='URBAN INFANTE 10B'!P76 -> 1 | R85: - | S85: - | T85: - | U85: - | W85: - | X85: =SUM(B85:W85) -> 65 | Y85: =B85/X85 -> 0.87692308 | Z85: =SUM(C85:W85) -> 8
A86: Urban Infante 10A | B86: ='URBAN INFANTE 10 A'!P65 -> 43 | C86: ='URBAN INFANTE 10 A'!P66 -> 0 | D86: ='URBAN INFANTE 10 A'!P67 -> 2 | E86: - | F86: - | G86: - | H86: - | I86: - | J86: - | K86: - | L86: ='URBAN INFANTE 10 A'!P68 -> 1 | M86: - | N86: ='URBAN INFANTE 10 A'!P70 -> 1 | O86: - | P86: - | Q86: - | R86: - | S86: - | T86: - | U86: - | W86: ='URBAN INFANTE 10 A'!P69 -> 1 | X86: =SUM(B86:W86) -> 48 | Y86: =B86/X86 -> 0.89583333 | Z86: =SUM(C86:W86) -> 5
A87: Parkview 5 | B87: ='PARKVIEW 5'!M62 -> 21 | C87: ='PARKVIEW 5'!M63 -> 0 | D87: - | E87: - | F87: - | G87: - | H87: - | I87: - | J87: - | K87: - | L87: - | M87: - | N87: - | O87: - | P87: - | Q87: - | R87: - | S87: - | T87: - | U87: ='PARKVIEW 5'!M67 -> 1 | W87: - | X87: =SUM(B87:W87) -> 22 | Y87: =B87/X87 -> 0.95454545 | Z87: =SUM(C87:W87) -> 1
A89: TOTAL P/ MONTH | B89: =SUM(B73:B87) -> 492 | C89: =SUM(C73:C87) -> 88 | D89: =SUM(D73:D87) -> 35 | E89: =SUM(E73:E87) -> 5 | F89: =SUM(F73:F87) -> 2 | G89: =SUM(G73:G87) -> 4 | H89: =SUM(H73:H87) -> 1 | I89: =SUM(I73:I87) -> 1 | ... U89: =SUM(U73:U87) -> 4 | W89: =SUM(W73:W87) -> 5
A91: Nationalities
A92: Country | B92: # | C92: %
A93: Portugal | B93: =B89 -> 492 | C93: =B93/(SUM($B$93:$B$113)) -> 0.73542601
A94: Israel | B94: =C89 -> 88 | C94: =B94/(SUM($B$93:$B$113)) -> 0.13153961
A95: Brazil | B95: =D89 -> 35 | C95: =B95/(SUM($B$93:$B$113)) -> 0.052316891
A96: Venezuela | B96: =W89 -> 5 | C96: =B96/(SUM($B$93:$B$113)) -> 0.0074738416
A97: USA | B97: =L89 -> 13 | C97: =B97/(SUM($B$93:$B$113)) -> 0.019431988
A98: China | B98: =E89 -> 5 | C98: =B98/(SUM($B$93:$B$113)) -> 0.0074738416
A99: France | B99: =F89 -> 2 | C99: =B99/(SUM($B$93:$B$113)) -> 0.0029895366
A100: Spain | B100: =G89 -> 4 | C100: =B100/(SUM($B$93:$B$113)) -> 0.0059790732
A101: Morroco | B101: =P89 -> 3 | C101: =B101/(SUM($B$93:$B$113)) -> 0.0044843049
A102: Italy | B102: =N89 -> 3 | C102: =B102/(SUM($B$93:$B$113)) -> 0.0044843049
A103: Angola | B103: =U89 -> 4 | C103: =B103/(SUM($B$93:$B$113)) -> 0.0059790732
A104: United Kingdom | B104: =K89 -> 3 | C104: =B104/(SUM($B$93:$B$113)) -> 0.0044843049
A105: Belgium | B105: =M89 -> 2 | C105: =B105/(SUM($B$93:$B$113)) -> 0.0029895366
A106: Poland | B106: =T89 -> 2 | C106: =B106/(SUM($B$93:$B$113)) -> 0.0029895366
A107: Korea | B107: =Q89 -> 2 | C107: =B107/(SUM($B$93:$B$113)) -> 0.0029895366
A108: Finland | B108: =H89 -> 1 | C108: =B108/(SUM($B$93:$B$113)) -> 0.0014947683
A109: Leban | B109: =I89 -> 1 | C109: =B109/(SUM($B$93:$B$113)) -> 0.0014947683
A110: Iran | B110: =J89 -> 1 | C110: =B110/(SUM($B$93:$B$113)) -> 0.0014947683
A111: Nepal | B111: =O89 -> 1 | C111: =B111/(SUM($B$93:$B$113)) -> 0.0014947683
A112: Mozambique | B112: =R89 -> 1 | C112: =B112/(SUM($B$93:$B$113)) -> 0.0014947683
A113: Canada | B113: =S89 -> 1 | C113: =B113/(SUM($B$93:$B$113)) -> 0.0014947683

Sheet VERDE VALE H1 (MAIA)
A1: Unit | B1: Fraction | C1: Layout | D1: Floor | E1: Directions | F1: Main area | G1: Balcony | H1: Terrace | I1: Saleable Area | J1: Status | K1: Parking 1 | L1: Parking 2 | M1: Parking 3 | N1: Parking 4 | O1: Storage | P1: Signed | Q1: Payment | R1: Closing Price | S1: Min. Price | T1: Asking Price UPDATE 20/04 | V1: % Discount | W1: €/m² sold | X1: €/m² min. price | Y1: €/m² asking price | Z1: On hold | AA1: Date of Reservation | AB1: Date of CPCV | AC1: CPCV Value | AD1: 1st down payment | AE1: Date 1st down pmt. | AF1: 2nd down payment | AG1: Date 2nd down pmt. | AH1: Deed | AI1: Brokers company | AJ1: Broker Name | AK1: % Commission | AL1: PO done? | AM1: Invoice received? | AN1: Invoice Paid? | AO1: Client | AP1: Client Nationality | AQ1: Birth Date | AR1: Age | AS1: Investor / Final Client | AT1: Email | AU1: Phone | AV1: Cancelled? | AW1: Why Cancelled? | AX1: Business Plan Price | AY1: €/m² Business Plan | AZ1: RESALE
A2: 1 | B2: A | C2: T3 | D2: 1 | E2: Nort/East | F2: 109.21 | G2: 24.622 | I2: =F2+0.3*G2 -> 116.5966 | J2: CPCV | K2: menos 1 (1 place) | R2: 369600 | S2: =0.96*T2 -> 369600 | T2: 385000 | V2: =S2/T2-1 -> -0.04 | W2: =R2/I2 -> 3169.9038 | X2: =S2/I2 -> 3169.9038 | Y2: =T2/I2 -> 3301.9831 | AB2: 45701 | AC2: =5000+68920 -> 73920 | AH2: 295680 | AI2: ChaveNova | AO2: Tiago Senra Monteiro Fonseca & Joana Alexandra Ferreira da Rosa | AP2: Portugal | AT2: tiagosenra@live.com.pt | AU2: 912870265 | AX2: =AY2*I2 -> 318308.72 | AY2: 2730
A3: 2 | B3: B | C3: T2 | D3: 1 | E3: East | F3: 83.411 | G3: 22.855 | I3: =F3+0.3*G3 -> 90.2675 | J3: CPCV | K3: menos 2 (1 place) | P3: YES | Q3: YES | R3: 235000 | S3: 235000 | T3: 246750 | W3: =R3/I3 -> 2603.3733 | X3: =T3/I3 -> 2733.542 | AA3: 44897 | AB3: 45343 | AC3: 47000 | AH3: 188000 | AI3: GlobalKey | AJ3: Rute | AO3: BRENNO S.A (Carlos Jorge Coelho de Lemos ) | AP3: Portugal | AV3: Yes | AX3: =AY3*I3 -> 246430.27 | AY3: 2730
A4: 3 | B4: C | C4: T2 | D4: 1 | E4: East | F4: 83.411 | G4: 22.855 | I4: =F4+0.3*G4 -> 90.2675 | J4: CPCV | K4: menos 1 (1 place) | P4: YES | Q4: YES | R4: 235000 | S4: 235000 | T4: 246750 | W4: =R4/I4 -> 2603.3733 | X4: =T4/I4 -> 2733.542 | AA4: 44897 | AB4: 45343 | AC4: 47000 | AH4: 188000 | AI4: GlobalKey | AJ4: Rute | AO4: BRENNO S.A (Carlos Jorge Coelho de Lemos ) | AP4: Portugal | AV4: Yes | AX4: =AY4*I4 -> 246430.27 | AY4: 2730
A5: 4 | B5: D | C5: T1 | D5: 1 | E5: East | F5: 64.431 | G5: 18.389 | I5: =F5+0.3*G5 -> 69.9477 | J5: CPCV | K5: menos 2 ( 1 place) | P5: YES | Q5: YES | R5: 212000 | S5: 208000 | T5: 212000 | V5: =100%-(T5/S5) -> -0.019230769 | W5: =R5/I5 -> 3030.8359 | X5: =S5/I5 -> 2973.6503 | Y5: =T5/I5 -> 3030.8359 | AA5: 45189 | AB5: 45316 | AC5: 41800 | AD5: 31800 | AE5: =365+AB5 -> 45681 | AH5: 138400 | AI5: ChaveNova | AL5: YES | AM5: YES | AO5: Iolanda Teresa Ribeiro Ferreira Teixeira & Manuel de Sousa Teixeira | AP5: Portugal | AT5: iolandatteixeira@gmail.com | AU5: 913923366 | AX5: =AY5*I5 -> 190957.22 | AY5: 2730
A6: 5 | B6: E | C6: T2 | D6: 1 | E6: North/West | F6: 86.69 | G6: 62.113 | I6: =F6+0.3*G6 -> 105.3239 | J6: CPCV | K6: menos 2 (1 place) | P6: YES | Q6: YES | R6: 311000 | S6: 310800 | T6: 317000 | V6: =100%-(T6/S6) -> -0.01994852 | W6: =R6/I6 -> 2952.7961 | X6: =S6/I6 -> 2950.8972 | Y6: =T6/I6 -> 3009.7632 | AA6: 45189 | AB6: 45313 | AC6: 62200 | AH6: 248800 | AI6: GlobalKey | AL6: YES | AO6: Maria da Conceição Azevedo Moreira Dias | AP6: Portugal | AT6: florindam453@gmail.com | AU6: 916662498 | AX6: =AY6*I6 -> 287534.25 | AY6: 2730
A7: 6 | B7: F | C7: T1 | D7: 1 | E7: West | F7: 62.317 | G7: 45.787 | I7: =F7+0.3*G7 -> 76.0531 | J7: CPCV | K7: menos 1 (1 place) | P7: YES | Q7: YES | R7: 194000 | S7: 194000 | T7: 203700 | W7: =R7/I7 -> 2550.8493 | X7: =T7/I7 -> 2678.3918 | AA7: 44889 | AB7: 45359 | AC7: 38800 | AH7: 155200 | AI7: GlobalKey | AJ7: Francisco | AO7: Carlos Filipe Gil Daniel & Ana Maria Daniel Filipe | AP7: Portugal | AT7: cfgd.gildaniel@hotmail.com | AU7: 963810100 | AX7: =AY7*I7 -> 207624.96 | AY7: 2730
A8: 7 | B8: G | C8: T2 | D8: 1 | E8: West | F8: 84.579 | G8: 60.765 | I8: =F8+0.3*G8 -> 102.8085 | J8: CPCV | K8: menos 1 (1 place) | P8: YES | Q8: YES | R8: 283240 | S8: =T8-(T8*V8) -> 283240 | T8: 292000 | V8: 0.03 | W8: =R8/I8 -> 2755.0251 | X8: 77 | AA8: 44987 | AB8: 45317 | AC8: 42486 | AD8: 14162 | AE8: =365+AB8 -> 45682 | AH8: 226592 | AI8: GlobalKey | AJ8: Rute | AL8: YES | AO8: João Rafael Gonçalves Novo | AP8: Portugal | AT8: joaorgnovo@gmail.com | AU8: 913121776 | AX8: =AY8*I8 -> 280667.2 | AY8: 2730
A9: 8 | B9: H | C9: T2 | D9: 1 | E9: West | F9: 84.579 | G9: 60.765 | I9: =F9+0.3*G9 -> 102.8085 | J9: CPCV | K9: menos 1 (1 place) | P9: YES | Q9: YES | R9: 280330 | S9: =T9-(T9*V9) -> 280330 | T9: 289000 | V9: 0.03 | W9: =R9/I9 -> 2726.7201 | X9: =S9/I9 -> 2726.7201 | AA9: 44964 | AB9: 45315 | AC9: 56066 | AH9: 224264 | AI9: GlobalKey | AJ9: Paulo Pinto | AL9: YES | AO9: João Miguel Correia da Silva Carreira Almeida | AP9: Portugal | AT9: joao.miguel.carreira.almeida@gmail.com | AU9: 969522828 | AX9: =AY9*I9 -> 280667.2 | AY9: 2730
A10: 9 | B10: I | C10: T1 | D10: 1 | E10: West | F10: 62.317 | G10: 45.787 | I10: =F10+0.3*G10 -> 76.0531 | J10: CPCV | K10: menos 2 ( 1 place) | P10: YES | Q10: YES | R10: 190000 | S10: 190000 | T10: 199500 | W10: =R10/I10 -> 2498.2545 | X10: =T10/I10 -> 2623.1672 | AA10: 44876 | AB10: 45323 | AC10: 38000 | AH10: 152000 | AI10: GlobalKey | AJ10: Rute | AL10: YES | AO10: FÓRMULA FIDEDIGNA Sérgio Manuel Ferreira Vieira | AP10: Portugal | AT10: sergioomfvieira@gmail.com | AU10: 934208586 | AX10: =AY10*I10 -> 207624.96 | AY10: 2730 | AZ10: 250000
A11: 10 | B11: J | C11: T2 | D11: 1 | E11: South/West | F11: 86.69 | G11: 62.113 | I11: =F11+0.3*G11 -> 105.3239 | J11: CPCV | K11: menos 2 (1 place) | P11: YES | Q11: YES | R11: 304320 | S11: =0.96*T11 -> 304320 | T11: 317000 | V11: =S11/T11-1 -> -0.04 | W11: =R11/I11 -> 2889.3727 | X11: =S11/I11 -> 2889.3727 | Y11: =T11/I11 -> 3009.7632 | AB11: 45441 | AC11: 30432 | AD11: 30432 | AE11: 45688 | AH11: 243456 | AI11: GlobalKey | AJ11: José Gonçalves | AO11: BQUARTO Unipessoal | AP11: Portugal | AT11: acosta2001@sapo.pt | AU11: 932837723 | AX11: =AY11*I11 -> 287534.25 | AY11: 2730
A12: 11 | B12: K | C12: T3 | D12: 2 | E12: Nort/East | F12: 116.492 | G12: 47.337 | I12: =F12+0.3*G12 -> 130.6931 | J12: CPCV | K12: menos 1 (2 places) | P12: YES | Q12: YES | R12: 384000 | S12: =0.96*T12 -> 384000 | T12: 400000 | V12: =S12/T12-1 -> -0.04 | W12: =R12/I12 -> 2938.1811 | X12: =S12/I12 -> 2938.1811 | Y12: =T12/I12 -> 3060.6053 | AB12: 45460 | AC12: 38400 | AH12: 345600 | AI12: GlobalKey | AJ12: José Gonçalves | AO12: Maria João Bravo Lopes | AP12: Portugal | AX12: =AY12*I12 -> 356792.16 | AY12: 2730
A13: 12 | B13: L | C13: T2 | D13: 2 | E13: East | F13: 84 | G13: 28.107 | I13: =F13+0.3*G13 -> 92.4321 | J13: CPCV | K13: menos 1 (1 place) | P13: YES | Q13: YES | R13: 259960 | S13: =T13-(T13*V13) -> 259960 | T13: 268000 | V13: 0.03 | W13: =R13/I13 -> 2812.4429 | X13: =S13/I13 -> 2812.4429 | AA13: 45005 | AB13: 45321 | AC13: 51992 | AH13: 207968 | AI13: GlobalKey | AJ13: Francisco Simões | AL13: YES | AO13: Vítor Manuel Pereira Martins | AP13: Portugal | AT13: victormanuelpmartins@gmail.com | AU13: 968915158 | AX13: =AY13*I13 -> 252339.63 | AY13: 2730
A14: 13 | B14: M | C14: T2 | D14: 2 | E14: East | F14: 84 | G14: 28.107 | I14: =F14+0.3*G14 -> 92.4321 | J14: CPCV | K14: menos 2 (1 place) | P14: YES | Q14: YES | R14: 247500 | S14: 247500 | T14: 259875 | W14: =R14/I14 -> 2677.6412 | X14: =T14/I14 -> 2811.5233 | AA14: 44879 | AB14: 45345 | AC14: 49500 | AH14: 198000 | AI14: GlobalKey | AJ14: Paulo Pinto | AO14: Hugo Feliciano de Sousa Gonçalves + Mónica Pinto + Nuno Lameiras + Andreia Oliveira | AP14: Portugal | AT14: feliciano03@me.com | AU14: 965486041 | AX14: =AY14*I14 -> 252339.63 | AY14: 2730
A15: 14 | B15: N | C15: T3 | D15: 2 | E15: South/East | F15: 116.495 | G15: 47.337 | I15: =F15+0.3*G15 -> 130.6961 | J15: CPCV | K15: menos 2 (2 spots) | P15: YES | Q15: YES | R15: 340000 | S15: 340000 | T15: 357000 | W15: =R15/I15 -> 2601.4548 | X15: =T15/I15 -> 2731.5276 | AA15: 44892 | AB15: 45321 | AC15: 68000 | AH15: 272000 | AI15: GlobalKey | AJ15: Rute | AL15: YES | AO15: Cristina Serra & Vítor Mota | AP15: Portugal | AT15: serra.cmm@gmail.com | AU15: 913322001 | AX15: =AY15*I15 -> 356800.35 | AY15: 2730
A16: 15 | B16: O | C16: T2 | D16: 2 | E16: North/West | F16: 86.61 | G16: 54.763 | I16: =F16+0.3*G16 -> 103.0389 | J16: CPCV | K16: menos 2 (1 place) | P16: YES | Q16: YES | R16: 274000 | S16: 274000 | T16: 287700 | W16: =R16/I16 -> 2659.1899 | X16: =T16/I16 -> 2792.1494 | AA16: 44907 | AB16: 45320 | AC16: 54800 | AH16: 219200 | AI16: GlobalKey | AJ16: Rute | AL16: YES | AO16: João Pedro Ramos Pereira da Silva | AP16: Portugal | AT16: joaopsilva1995@gmail.com | AU16: 918603930 | AX16: =AY16*I16 -> 281296.2 | AY16: 2730
A17: 16 | B17: P | C17: T1 | D17: 2 | E17: West | F17: 62.317 | G17: 25.147 | I17: =F17+0.3*G17 -> 69.8611 | J17: CPCV | K17: menos 2 ( 1 place) | P17: YES | Q17: YES | R17: 189000 | S17: 189000 | T17: 198450 | W17: =R17/I17 -> 2705.3682 | X17: =T17/I17 -> 2840.6366 | AA17: 44876 | AB17: 45323 | AC17: 37800 | AH17: 151200 | AI17: GlobalKey | AJ17: Rute | AL17: YES | AO17: Marco Elton Veloso Carvalheira & Vera Lucia Borges dos Santos | AP17: Portugal | AT17: sergiomfvieira@gmail.com | AU17: 934208586 | AX17: =AY17*I17 -> 190720.8 | AY17: 2730
A18: 17 | B18: Q | C18: T2 | D18: 2 | E18: West | F18: 84.579 | G18: 33.245 | I18: =F18+0.3*G18 -> 94.5525 | J18: CPCV | K18: menos 1 (1 place) | P18: YES | Q18: YES | R18: 269660 | S18: =T18-(T18*V18) -> 269660 | T18: 278000 | V18: 0.03 | W18: =R18/I18 -> 2851.9606 | X18: =T18/I18 -> 2940.1655 | AA18: 44881 | AB18: 45330 | AC18: 53932 | AH18: 215728 | AI18: GlobalKey | AJ18: Rute | AL18: YES | AO18: Ana Paula Lourido Machado | AP18: Portugal | AT18: anapaulalourido@gmail.com | AU18: 966124767 | AX18: =AY18*I18 -> 258128.32 | AY18: 2730
A19: 18 | B19: R | C19: T2 | D19: 2 | E19: West | F19: 84.579 | G19: 33.245 | I19: =F19+0.3*G19 -> 94.5525 | J19: CPCV | K19: menos 1 (1 place) | P19: YES | Q19: YES | R19: 255000 | S19: 255000 | T19: 267750 | W19: =R19/I19 -> 2696.9144 | X19: =T19/I19 -> 2831.7601 | AA19: 44900 | AB19: 45324 | AC19: 61000 | AH19: 194000 | AI19: ChaveNova | AL19: YES | AM19: YES | AO19: Maria Virgínia Ferreira de Sousa | AP19: Portugal | AT19: gigi.203@hotmail.com | AU19: 910764191 | AX19: =AY19*I19 -> 258128.32 | AY19: 2730
A20: 19 | B20: S | C20: T1 | D20: 2 | E20: West | F20: 62.317 | G20: 25.147 | I20: =F20+0.3*G20 -> 69.8611 | J20: CPCV | K20: menos 2 (1 place) | P20: YES | Q20: YES | R20: 185000 | S20: 185000 | T20: 194250 | W20: =R20/I20 -> 2648.1118 | X20: =T20/I20 -> 2780.5173 | AA20: 44907 | AB20: 45324 | AC20: 47000 | AH20: 138000 | AI20: ChaveNova | AL20: YES | AM20: YES | AO20: JOSE FERNANDO CARREIRA BERNARDINO | AP20: Portugal | AT20: jose.f.bernardino@hotmail.com | AU20: 917340566 | AX20: =AY20*I20 -> 190720.8 | AY20: 2730
A21: 20 | B21: T | C21: T2 | D21: 2 | E21: South/West | F21: 86.61 | G21: 54.763 | I21: =F21+0.3*G21 -> 103.0389 | J21: CPCV | K21: menos 1 (1 place) | P21: YES | Q21: YES | R21: 270000 | S21: 270000 | T21: 283500 | W21: =R21/I21 -> 2620.3696 | X21: =T21/I21 -> 2751.3881 | AA21: 44879 | AB21: 45345 | AC21: 54000 | AH21: 216000 | AI21: GlobalKey | AJ21: Paulo Pinto | AO21: Hugo Feliciano de Sousa Gonçalves + Mónica Pinto + Nuno Lameiras + Andreia Oliveira | AP21: Portugal | AT21: feliciano03@me.com | AU21: 965486041 | AX21: =AY21*I21 -> 281296.2 | AY21: 2730 | AZ21: 350000
A22: 21 | B22: U | C22: T3 | D22: 3 | E22: Nort/East | F22: 116.492 | G22: 21.416 | I22: =F22+0.3*G22 -> 122.9168 | J22: CPCV | K22: menos 1 ( 2 places) | R22: =0.95*T22 -> 373350 | S22: =0.96*T22 -> 377280 | T22: 393000 | V22: =R22/T22-1 -> -0.05 | W22: =R22/I22 -> 3037.4204 | X22: =S22/I22 -> 3069.3933 | Y22: =T22/I22 -> 3197.2847 | AB22: 45568 | AC22: =5000+32335 -> 37335 | AD22: 18667.5 | AH22: 317347.5 | AI22: GlobalKey | AJ22: Jose Gonçalves | AO22: Liu Yingxue & Li Jun | AP22: China | AT22: lidia_love@163.com | AU22: 968242946 | AX22: =AY22*I22 -> 335562.86 | AY22: 2730
A23: 22 | B23: V | C23: T1 | D23: 3 | E23: East | F23: 59.669 | G23: 5.785 | I23: =F23+0.3*G23 -> 61.4045 | J23: CPCV | K23: menos 2 ( 1 place) | P23: YES | Q23: YES | R23: 176000 | S23: 176000 | T23: 176000 | W23: =R23/I23 -> 2866.2394 | X23: =S23/I23 -> 2866.2394 | AA23: 44991 | AB23: 45356 | AC23: 35200 | AH23: 140800 | AI23: GlobalKey | AJ23: Francisco Simões | AO23: André Dias Lopes | AP23: Portugal | AT23: hugo.mesquita1@gmail.com | AU23: 968083749 | AX23: =AY23*I23 -> 167634.29 | AY23: 2730
A24: 23 | B24: W | C24: T3 | D24: 3 | E24: East/West | F24: 131.804 | G24: 43 | I24: =F24+0.3*G24 -> 144.704 | J24: CPCV | K24: menos 1 ( 2 places) | P24: YES | Q24: YES | R24: 388000 | S24: =T24-(T24*V24) -> 388000 | T24: 400000 | V24: 0.03 | W24: =R24/I24 -> 2681.3357 | X24: =S24/I24 -> 2681.3357 | AA24: 44980 | AB24: 45378 | AC24: =20%*R24 -> 77600 | AH24: =R24-AC24 -> 310400 | AI24: GlobalKey | AJ24: Francisco Simões | AO24: Ana Isabel Teixeira de Jesus da Silva | AP24: Portugal | AT24: anasilva0883@gmail.com | AU24: 916367853 | AX24: =AY24*I24 -> 395041.92 | AY24: 2730
A25: 24 | B25: X | C25: T3 | D25: 3 | E25: East/West | F25: 131.804 | G25: 43 | I25: =F25+0.3*G25 -> 144.704 | J25: CPCV | K25: menos 1 ( 2 places) | P25: YES | Q25: YES | R25: 372000 | S25: 372000 | T25: 390600 | W25: =R25/I25 -> 2570.7651 | X25: =T25/I25 -> 2699.3034 | AA25: 44877 | AB25: 45342 | AC25: 74400 | AH25: 297600 | AI25: GlobalKey | AJ25: Francisco Simões | AL25: YES | AO25: José António Luzano de Quadros Flores & Cândida Quadros | AP25: Portugal | AT25: joseluzano@yahoo.com | AU25: 919818660 | AX25: =AY25*I25 -> 395041.92 | AY25: 2730
A26: 25 | B26: Y | C26: T1 | D26: 3 | E26: East | F26: 59.669 | G26: 5.785 | I26: =F26+0.3*G26 -> 61.4045 | J26: CPCV | K26: menos 2 ( 1 place) | P26: YES | Q26: YES | R26: 167500 | S26: 167500 | T26: 175875 | W26: =R26/I26 -> 2727.8131 | X26: =T26/I26 -> 2864.2038 | AA26: 44881 | AB26: 45316 | AC26: 43500 | AH26: 124000 | AI26: ChaveNova | AL26: YES | AM26: YES | AO26: EPOPEIA FRONDOSA (company) | AP26: Portugal | AT26: finogueira@live.com.pt | AU26: 933255320 | AX26: =AY26*I26 -> 167634.29 | AY26: 2730
A27: 26 | B27: Z | C27: T3 | D27: 3 | E27: South/East | F27: 116.492 | G27: 16 | I27: =F27+0.3*G27 -> 121.292 | J27: CPCV | K27: menos 2 (2 spots) | P27: YES | Q27: YES | R27: 369000 | S27: 376500 | T27: 384000 | V27: =100%-(T27/S27) -> -0.019920319 | W27: =R27/I27 -> 3042.2452 | X27: =S27/I27 -> 3104.0794 | Y27: =T27/I27 -> 3165.9137 | AB27: 45342 | AC27: 60000 | AD27: 13800 | AE27: 45351 | AH27: 295200 | AI27: ChaveNova | AO27: Diogo da Cunha Rego | AP27: Portugal | AT27: diogo_rego89@hotmail.com | AU27: 915094942 | AX27: =AY27*I27 -> 331127.16 | AY27: 2730
A28: 27 | B28: AA | C28: T2 | D28: 3 | E28: North/West | F28: 86.61 | G28: =34.052+14.95 -> 49.002 | I28: =F28+0.3*G28 -> 101.3106 | J28: CPCV | K28: menos 1 (1 place) | P28: YES | Q28: YES | R28: 269000 | S28: 269000 | T28: 282450 | W28: =R28/I28 -> 2655.2009 | X28: =T28/I28 -> 2787.961 | AA28: 44890 | AB28: 45331 | AC28: 53800 | AH28: 215200 | AI28: GlobalKey | AJ28: Francisco | AL28: YES | AO28: Ana Margarida Gonçalves Dias da Silva & José Gonçalves da Silva | AP28: Portugal | AT28: amargaridagds@gmail.com | AU28: 914461887 | AX28: =AY28*I28 -> 276577.94 | AY28: 2730
A29: 28 | B29: AB | C29: T1 | D29: 3 | E29: West | F29: 63.221 | G29: 25.147 | I29: =F29+0.3*G29 -> 70.7651 | J29: CPCV | K29: menos 2 ( 1 place) | P29: YES | Q29: YES | R29: 194000 | S29: 194000 | T29: 203700 | W29: =R29/I29 -> 2741.4644 | X29: =T29/I29 -> 2878.5376 | AA29: 44880 | AB29: 45324 | AC29: 38800 | AH29: 155200 | AI29: GlobalKey | AJ29: Paulo Pinto | AL29: YES | AO29: Narciso Jorge Gomes da Silva Magalhães | AP29: Portugal | AT29: jorge.magalhaes1967@gmail.com | AU29: 919992138 | AX29: =AY29*I29 -> 193188.72 | AY29: 2730
A30: 29 | B30: AC | C30: T1 | D30: 3 | E30: West | F30: 63.221 | G30: 25.147 | I30: =F30+0.3*G30 -> 70.7651 | J30: CPCV | K30: menos 2 ( 1 place) | P30: YES | Q30: YES | R30: 199820 | S30: =T30-(T30*V30) -> 199820 | T30: 206000 | V30: 0.03 | W30: =R30/I30 -> 2823.7083 | X30: =T30/I30 -> 2911.0395 | AA30: 44953 | AB30: 45324 | AC30: 39364 | AH30: 159856 | AI30: GlobalKey | AJ30: Francisco Simões | AL30: YES | AO30: Sandra Mota Lda | AP30: Portugal | AT30: odracir.seravat@gmail.com | AU30: 963871036 | AX30: =AY30*I30 -> 193188.72 | AY30: 2730
A31: 30 | B31: AD | C31: T2 | D31: 3 | E31: South/West | F31: 86.61 | G31: 52.568 | I31: =F31+0.3*G31 -> 102.3804 | J31: CPCV | K31: menos 1 (1 place) | P31: YES | Q31: YES | R31: 280000 | S31: 280000 | T31: 294000 | W31: =R31/I31 -> 2734.8985 | X31: =T31/I31 -> 2871.6434 | AA31: 44914 | AB31: 45343 | AC31: 56000 | AH31: 224000 | AI31: Tranquildiscovery | AK31: 0.04 | AO31: GAL SHWEBISH | AP31: Israel | AT31: galshvebish@gmail.com | AU31: - | AX31: =AY31*I31 -> 279498.49 | AY31: 2730
A32: 31 | B32: AE | C32: T3 | D32: 4 | E32: Nort/East | F32: 116.492 | G32: 21.416 | I32: =F32+0.3*G32 -> 122.9168 | J32: CPCV | K32: menos 2 (2 spots) | P32: YES | Q32: YES | R32: 383000 | S32: =0.96*T32 -> 382080 | T32: 398000 | V32: =S32/T32-1 -> -0.04 | W32: =R32/I32 -> 3115.9288 | X32: =S32/I32 -> 3108.4441 | Y32: =T32/I32 -> 3237.9626 | AB32: 45425 | AC32: 38300 | AH32: 344700 | AI32: GlobalKey | AO32: Vitor Daniel da Silva Pinto & Fernanda Maia da Silva | AP32: Portugal | AT32: vitorpinto0778@gmail.com | AU32: 914966220 | AX32: =AY32*I32 -> 335562.86 | AY32: 2730
A33: 32 | B33: AF | C33: T1 | D33: 4 | E33: East | F33: 59.669 | G33: 5.785 | I33: =F33+0.3*G33 -> 61.4045 | J33: CPCV | K33: menos 2 ( 1 place) | P33: YES | Q33: YES | R33: 170000 | S33: 170000 | T33: 178500 | W33: =R33/I33 -> 2768.5267 | X33: =T33/I33 -> 2906.9531 | AA33: 44882 | AB33: 45316 | AC33: 44000 | AH33: 126000 | AI33: ChaveNova | AL33: YES | AM33: YES | AO33: Wisenas Lda | AP33: Portugal | AT33: rogeriopinhosilva@gmail.com | AU33: 966501924 | AX33: =AY33*I33 -> 167634.29 | AY33: 2730
A34: 33 | B34: AG | C34: T3 | D34: 4 | E34: East/West | F34: 131.804 | G34: 43 | I34: =F34+0.3*G34 -> 144.704 | J34: CPCV | K34: menos 2 (2 spots) | P34: YES | Q34: YES | R34: 393820 | S34: =T34-(T34*V34) -> 393820 | T34: 406000 | V34: 0.03 | W34: =R34/I34 -> 2721.5557 | X34: =S34/I34 -> 2721.5557 | AA34: 44979 | AB34: 45378 | AC34: =20%*R34 -> 78764 | AH34: =80%*R34 -> 315056 | AI34: GlobalKey | AJ34: Francisco Simões | AO34: André Nuno Pereira Emiliano | AP34: Portugal | AT34: andre@dangels.pt | AU34: 914618925 | AX34: =AY34*I34 -> 395041.92 | AY34: 2730
A35: 34 | B35: AH | C35: T3 | D35: 4 | E35: East/West | F35: 131.804 | G35: 43 | I35: =F35+0.3*G35 -> 144.704 | J35: CPCV | K35: menos 1 ( 2 places) | P35: YES | Q35: YES | R35: 377000 | S35: 377000 | T35: 395850 | W35: =R35/I35 -> 2605.3184 | X35: =T35/I35 -> 2735.5844 | AA35: 44902 | AB35: 45343 | AC35: 75400 | AH35: 301600 | AI35: Tranquildiscovery | AK35: 0.04 | AO35: Eden Brizel | AP35: Israel | AT35: edenbrizel@gmail.com | AX35: =AY35*I35 -> 395041.92 | AY35: 2730
A36: 35 | B36: AI | C36: T1 | D36: 4 | E36: East | F36: 59.669 | G36: 5.785 | I36: =F36+0.3*G36 -> 61.4045 | J36: CPCV | K36: menos 2 ( 1 place) | P36: YES | Q36: YES | R36: 178480 | S36: =T36-(T36*V36) -> 178480 | T36: 184000 | V36: 0.03 | W36: =R36/I36 -> 2906.6274 | X36: =T36/I36 -> 2996.5231 | AA36: 44946 | AB36: 45343 | AC36: 35969 | AH36: 142784 | AI36: GlobalKey | AJ36: Francisco Simões | AO36: Maria Adélia Coelho de Sá | AP36: Portugal | AT36: suportejs34@gmail.com | AU36: 967429350 | AX36: =AY36*I36 -> 167634.29 | AY36: 2730
A37: 36 | B37: AJ | C37: T3 | D37: 4 | E37: South/East | F37: 116.492 | G37: 16 | I37: =F37+0.3*G37 -> 121.292 | J37: CPCV | K37: menos 2 (2 spots) | P37: YES | Q37: YES | R37: =0.96*T37 -> 375360 | S37: 383250 | T37: 391000 | V37: =100%-(T37/S37) -> -0.020221787 | W37: =R37/I37 -> 3094.6806 | X37: =S37/I37 -> 3159.7302 | Y37: =T37/I37 -> 3223.6256 | AB37: 45343 | AC37: 75072 | AH37: 300288 | AI37: ChaveNova | AO37: Eugénia Margarida Machado Martins Ferreira & João Manuel de Carvalho Santos | AP37: Portugal | AX37: =AY37*I37 -> 331127.16 | AY37: 2730
A38: 37 | B38: AK | C38: T2 | D38: 4 | E38: North/West | F38: 86.61 | G38: =34.052+14.95 -> 49.002 | I38: =F38+0.3*G38 -> 101.3106 | J38: CPCV | K38: menos 1 (1 place) | P38: YES | Q38: YES | R38: 274000 | S38: 274000 | T38: 287700 | W38: =R38/I38 -> 2704.5541 | X38: =T38/I38 -> 2839.7818 | AA38: 44941 | AB38: 45342 | AC38: 54800 | AH38: 219200 | AI38: Tranquildiscovery | AK38: 0.04 | AO38: Yekutiel Zafari | AP38: Israel | AX38: =AY38*I38 -> 276577.94 | AY38: 2730
A39: 38 | B39: AL | C39: T1 | D39: 4 | E39: West | F39: 63.221 | G39: 25.147 | I39: =F39+0.3*G39 -> 70.7651 | J39: CPCV | K39: menos 2 ( 1 place) | P39: YES | Q39: YES | R39: 187750 | S39: 196500 | T39: 206325 | W39: =R39/I39 -> 2653.144 | X39: =S39/I39 -> 2776.7925 | Y39: =T39/I39 -> 2915.6321 | AA39: 45182 | AB39: 45345 | AC39: 18775 | AH39: 168975 | AI39: GlobalKey | AK39: 0 | AO39: Adriana Pereira | AP39: Israel | AX39: =AY39*I39 -> 193188.72 | AY39: 2730
A40: 39 | B40: AM | C40: T1 | D40: 4 | E40: West | F40: 63.221 | G40: 25.147 | I40: =F40+0.3*G40 -> 70.7651 | J40: CPCV | K40: menos 1 (1 place) | P40: YES | Q40: YES | R40: 192500 | S40: 192500 | T40: 202125 | W40: =R40/I40 -> 2720.2675 | X40: =T40/I40 -> 2856.2809 | AA40: 44879 | AB40: 45345 | AC40: 38500 | AH40: 154000 | AI40: GlobalKey | AJ40: Paulo Pinto | AO40: Hugo Feliciano de Sousa Gonçalves + Mónica Pinto + Nuno Lameiras + Andreia Oliveira | AP40: Portugal | AX40: =AY40*I40 -> 193188.72 | AY40: 2730 | AZ40: 240000
A41: 40 | B41: AN | C41: T2 | D41: 4 | E41: South/West | F41: 86.61 | G41: 52.568 | I41: =F41+0.3*G41 -> 102.3804 | J41: CPCV | K41: menos 1 (1 place) | P41: YES | Q41: YES | R41: 285000 | S41: 285000 | T41: 299250 | W41: =R41/I41 -> 2783.7359 | X41: =T41/I41 -> 2922.9227 | AA41: 44951 | AB41: 45342 | AC41: 57000 | AH41: 228000 | AI41: Tranquildiscovery | AK41: 0.04 | AO41: Yaron Levy | AP41: Israel | AX41: =AY41*I41 -> 279498.49 | AY41: 2730
A42: 41 | B42: AO | C42: T3 | D42: 5 | E42: Nort/East | F42: 116.492 | G42: 21.416 | I42: =F42+0.3*G42 -> 122.9168 | J42: CPCV | K42: menos 1 ( 2 places) | R42: 393000 | S42: =0.96*T42 -> 386880 | T42: 403000 | V42: =S42/T42-1 -> -0.04 | W42: =R42/I42 -> 3197.2847 | X42: =S42/I42 -> 3147.4949 | Y42: =T42/I42 -> 3278.6405 | AA42: 45540 | AB42: 45596 | AC42: =20%*R42 -> 78600 | AH42: =80%*R42 -> 314400 | AI42: GlobalKey | AO42: Vitor Manuel Mendes da Costa & Madalena Cristina Marques Dias da Silva Mendes da Costa | AP42: Portugal | AT42: vitormendescosta@hotmail.com | AU42: 919361698 | AX42: =AY42*I42 -> 335562.86 | AY42: 2730
A43: 42 | B43: AP | C43: T1 | D43: 5 | E43: East | F43: 59.669 | G43: 5.785 | I43: =F43+0.3*G43 -> 61.4045 | J43: CPCV | K43: menos 2 ( 1 place) | P43: YES | Q43: YES | R43: 181390 | S43: =T43-(T43*V43) -> 181390 | T43: 187000 | V43: 0.03 | W43: =R43/I43 -> 2954.018 | X43: =S43/I43 -> 2954.018 | AA43: 44953 | AB43: 45324 | AC43: 36278 | AH43: 145112 | AI43: GlobalKey | AJ43: Francisco Simões | AL43: YES | AO43: Ricardo Jorge Silva Tavares & Sandra Borges | AP43: Portugal | AT43: odracir.seravat@gmial.com | AU43: 963871036 | AX43: =AY43*I43 -> 167634.29 | AY43: 2730
A44: 43 | B44: AQ | C44: T3 | D44: 5 | E44: East/West | F44: 131.804 | G44: 43 | I44: =F44+0.3*G44 -> 144.704 | J44: CPCV | K44: menos 2 (2 spots) | P44: YES | Q44: YES | R44: 398670 | S44: =T44-(T44*V44) -> 398670 | T44: 411000 | V44: 0.03 | W44: =R44/I44 -> 2755.0724 | X44: =S44/I44 -> 2755.0724 | AA44: 44970 | AB44: 45322 | AC44: 79734 | AH44: 318936 | AI44: GlobalKey | AJ44: Rute | AL44: YES | AO44: Nuno André Teixeira Silva Oliveira | AP44: Portugal | AT44: nuno@alfacomer.pt | AU44: 965094440 | AX44: =AY44*I44 -> 395041.92 | AY44: 2730
A45: 44 | B45: AR | C45: T3 | D45: 5 | E45: East/West | F45: 131.804 | G45: 43 | I45: =F45+0.3*G45 -> 144.704 | J45: CPCV | K45: menos 1 ( 2 places) | P45: YES | Q45: YES | R45: 348680 | S45: 382000 | T45: 401100 | W45: =R45/I45 -> 2409.6086 | X45: =S45/I45 -> 2639.8717 | Y45: =-(100%-(R45/S45)) -> -0.087225131 | AA45: 45054 | AB45: 45343 | AC45: 34868 | AH45: 313812 | AI45: Tranquildiscovery | AK45: 0 | AO45: Achyia Josef Wadmani | AP45: Israel | AT45: achiya@tagaurbanic.com | AU45: -526709105 | AX45: =AY45*I45 -> 395041.92 | AY45: 2730 | AZ45: 460420
A46: 45 | B46: AS | C46: T1 | D46: 5 | E46: East | F46: 59.669 | G46: 5.785 | I46: =F46+0.3*G46 -> 61.4045 | J46: CPCV | K46: menos 1 (1 place) | P46: YES | Q46: YES | R46: 172500 | S46: 172500 | T46: 181125 | W46: =R46/I46 -> 2809.2404 | X46: =T46/I46 -> 2949.7024 | AA46: 44889 | AB46: 45341 | AC46: 34500 | AH46: 138000 | AI46: GlobalKey | AJ46: Rute | AL46: YES | AO46: Estratégianédita LDA | AP46: Portugal | AT46: freitas.diogo@gmail.com | AU46: 968964123 | AX46: =AY46*I46 -> 167634.29 | AY46: 2730
A47: 46 | B47: AT | C47: T3 | D47: 5 | E47: South/East | F47: 116.492 | G47: 16 | I47: =F47+0.3*G47 -> 121.292 | J47: CPCV | K47: menos 2 (2 spots) | P47: YES | Q47: YES | R47: 358900 | S47: =T47-(T47*V47) -> 358900 | T47: 370000 | V47: 0.03 | W47: =R47/I47 -> 2958.975 | X47: =T47/I47 -> 3050.4897 | AA47: 44935 | AB47: 45324 | AC47: 71780 | AH47: 287120 | AI47: GlobalKey | AJ47: Rute | AK47: 4 | AL47: YES | AO47: Paula Cristina Vieira Gonçalves | AP47: Portugal | AT47: paulacvg@gmail.com | AU47: 910117524 | AX47: =AY47*I47 -> 331127.16 | AY47: 2730
A48: 47 | B48: AU | C48: T2 | D48: 5 | E48: North/West | F48: 86.61 | G48: =34.052+14.95 -> 49.002 | I48: =F48+0.3*G48 -> 101.3106 | J48: CPCV | K48: menos 1 (1 place) | P48: YES | Q48: YES | R48: 279000 | S48: 279000 | T48: 292950 | W48: =R48/I48 -> 2753.9073 | X48: =T48/I48 -> 2891.6027 | AA48: 44941 | AB48: 45343 | AC48: 55800 | AH48: 223200 | AI48: Tranquildiscovery | AK48: 0.04 | AO48: Asaf Sabag | AP48: Israel | AT48: assafs@ein.gedi.co.il | AU48: 972523525907 | AX48: =AY48*I48 -> 276577.94 | AY48: 2730
A49: 48 | B49: AV | C49: T1 | D49: 5 | E49: West | F49: 63.221 | G49: 25.147 | I49: =F49+0.3*G49 -> 70.7651 | J49: CPCV | K49: menos 2 ( 1 place) | P49: YES | Q49: YES | R49: 199000 | S49: 199000 | T49: 208950 | W49: =R49/I49 -> 2812.1207 | X49: =T49/I49 -> 2952.7267 | AA49: 44879 | AB49: 45324 | AC49: 39800 | AH49: 159200 | AI49: GlobalKey | AJ49: Paulo Pinto | AL49: YES | AO49: Jorge Manuel de Sequeira e Costa | AP49: Portugal | AT49: sequeira.js@mail.telepac.pt | AU49: 968077175 | AX49: =AY49*I49 -> 193188.72 | AY49: 2730
A50: 49 | B50: AW | C50: T1 | D50: 5 | E50: West | F50: 63.221 | G50: 25.147 | I50: =F50+0.3*G50 -> 70.7651 | J50: CPCV | K50: menos 1 (1 place) | P50: YES | Q50: YES | R50: 204670 | S50: =T50-(T50*V50) -> 204670 | T50: 211000 | V50: 0.03 | W50: =R50/I50 -> 2892.2449 | X50: =S50/I50 -> 2892.2449 | AA50: 44970 | AB50: 45356 | AC50: 40934 | AH50: 163736 | AI50: GlobalKey | AJ50: Francisco Simões | AO50: Gonçalo Santos Oliveira | AP50: Portugal | AT50: hugo.mesquita1@gmail.com | AU50: 968083749 | AX50: =AY50*I50 -> 193188.72 | AY50: 2730
A51: 50 | B51: AX | C51: T2 | D51: 5 | E51: South/West | F51: 86.61 | G51: 52.568 | I51: =F51+0.3*G51 -> 102.3804 | J51: CPCV | K51: menos 1 (1 place) | P51: YES | Q51: YES | R51: 290000 | S51: 290000 | T51: 304500 | W51: =R51/I51 -> 2832.5734 | X51: =T51/I51 -> 2974.2021 | AA51: 44909 | AB51: 45331 | AC51: 58000 | AH51: 232000 | AI51: Tranquildiscovery | AK51: 0.04 | AO51: Duti Litvak | AP51: Israel | AT51: litvakd@netvusuib.net.il | AX51: =AY51*I51 -> 279498.49 | AY51: 2730
A52: 51 | B52: AY | C52: T3 | D52: 6 | E52: Nort/East | F52: 116.492 | G52: 21.416 | I52: =F52+0.3*G52 -> 122.9168 | J52: CPCV | K52: menos 1 ( 2 places) | P52: YES | Q52: YES | R52: 393600 | S52: =0.96*T52 -> 393600 | T52: 410000 | V52: =S52/T52-1 -> -0.04 | W52: =R52/I52 -> 3202.166 | X52: =S52/I52 -> 3202.166 | Y52: =T52/I52 -> 3335.5896 | AB52: 45454 | AC52: 39360 | AD52: 19680 | AE52: 45565 | AF52: 19680 | AG52: 45657 | AH52: 314880 | AI52: ChaveNova | AO52: Lisa Yang Liu & Mali Weng | AP52: China | AX52: =AY52*I52 -> 335562.86 | AY52: 2730
A53: 52 | B53: AZ | C53: T1 | D53: 6 | E53: East | F53: 59.669 | G53: 5.785 | I53: =F53+0.3*G53 -> 61.4045 | J53: CPCV | K53: menos 2 ( 1 place) | P53: YES | Q53: YES | R53: 175000 | S53: 175000 | T53: 183750 | W53: =R53/I53 -> 2849.954 | X53: =T53/I53 -> 2992.4517 | AA53: 44908 | AB53: 45352 | AC53: 35000 | AH53: 140000 | AI53: GlobalKey | AJ53: Francisco | AO53: Sandra Marisa Rodrigues Mota Oliveira | AP53: Portugal | AT53: sandra.mota.oliveira-5310p@adv.oa.pt | AU53: 968837313 | AX53: =AY53*I53 -> 167634.29 | AY53: 2730
A54: 53 | B54: BA | C54: T3 | D54: 6 | E54: East/West | F54: 131.804 | G54: 43 | I54: =F54+0.3*G54 -> 144.704 | J54: CPCV | K54: menos 2 (2 spots) | P54: YES | Q54: YES | R54: 385000 | S54: 385000 | T54: 404250 | W54: =R54/I54 -> 2660.6037 | X54: =T54/I54 -> 2793.6339 | AA54: 44904 | AB54: 45385 | AC54: 38250 | AD54: 38250 | AE54: =90+AB54 -> 45475 | AH54: 308000 | AI54: GlobalKey | AJ54: Francisco | AO54: Pedro Nuno Maia Carvalho / Raquel Rodrigues Duarte Carvalho | AP54: Portugal | AT54: pedro.maia.carvalho@gmail.com | AU54: 969525321 | AX54: =AY54*I54 -> 395041.92 | AY54: 2730
A55: 54 | B55: BB | C55: T3 | D55: 6 | E55: East/West | F55: 131.804 | G55: 43 | I55: =F55+0.3*G55 -> 144.704 | J55: CPCV | K55: menos 2 (2 spots) | P55: YES | Q55: YES | R55: 353500 | S55: 387000 | T55: 406350 | V55: =S55/T55-1 -> -0.047619048 | W55: =R55/I55 -> 2442.918 | X55: =S55/I55 -> 2674.425 | Y55: =-(100%-(R55/S55)) -> -0.086563307 | AB55: 45471 | AC55: 35350 | AH55: 318150 | AI55: Tranquildiscovery | AO55: Ariel Chilkiyahu | AP55: Israel | AT55: ariel@tagaurbanic.com | AU55: -52199068 | AX55: =AY55*I55 -> 395041.92 | AY55: 2730 | AZ55: 480000
A56: 55 | B56: BC | C56: T1 | D56: 6 | E56: East | F56: 59.669 | G56: 5.785 | I56: =F56+0.3*G56 -> 61.4045 | J56: CPCV | K56: menos 1 (1 place) | P56: YES | Q56: YES | R56: 175000 | S56: 175000 | T56: 183750 | W56: =R56/I56 -> 2849.954 | X56: =T56/I56 -> 2992.4517 | AA56: 44889 | AB56: 45341 | AC56: 35000 | AH56: 140000 | AI56: GlobalKey | AJ56: Rute | AL56: YES | AO56: Estratégianédita LDA | AP56: Portugal | AT56: freitas.diogo@gmail.com | AU56: 968964123 | AX56: =AY56*I56 -> 167634.29 | AY56: 2730
A57: 56 | B57: BD | C57: T3 | D57: 6 | E57: South/East | F57: 116.492 | G57: 16 | I57: =F57+0.3*G57 -> 121.292 | J57: CPCV | K57: menos 2 (2 spots) | P57: YES | Q57: YES | R57: 393600 | S57: =0.96*T57 -> 393600 | T57: 410000 | V57: =S57/T57-1 -> -0.04 | W57: =R57/I57 -> 3245.0615 | X57: =S57/I57 -> 3245.0615 | AB57: 45405 | AC57: =20%*R57 -> 78720 | AH57: =80%*R57 -> 314880 | AI57: GlobalKey | AJ57: Jose Gonçalves | AO57: Álvaro Fernando Pinho da Costa | AP57: Portugal | AX57: =AY57*I57 -> 331127.16 | AY57: 2730
A58: 57 | B58: BE | C58: T2 | D58: 6 | E58: North/West | F58: 86.61 | G58: =34.052+14.95 -> 49.002 | I58: =F58+0.3*G58 -> 101.3106 | J58: CPCV | K58: menos 1 (1 place) | P58: YES | Q58: YES | R58: 258440 | S58: 284000 | T58: 298200 | W58: =R58/I58 -> 2550.967 | X58: =S58/I58 -> 2803.2605 | Y58: =T58/I58 -> 2943.4235 | AA58: 45108 | AB58: 45343 | AC58: 25844 | AH58: 232596 | AI58: Tranquildiscovery | AK58: 0 | AO58: Zohar Gafni | AP58: Israel | AX58: =AY58*I58 -> 276577.94 | AY58: 2730 | AZ58: 380000
A59: 58 | B59: BF | C59: T1 | D59: 6 | E59: West | F59: 63.221 | G59: 25.147 | I59: =F59+0.3*G59 -> 70.7651 | J59: CPCV | K59: menos 2 ( 1 place) | P59: YES | Q59: YES | R59: 211460 | S59: =T59-(T59*V59) -> 211460 | T59: 218000 | V59: 0.03 | W59: =R59/I59 -> 2988.1962 | X59: =S59/I59 -> 2988.1962 | AA59: 44988 | AB59: 45376 | AC59: =20%*R59 -> 42292 | AH59: =80%*R59 -> 169168 | AI59: GlobalKey | AJ59: Francisco Simões | AO59: José Pedro Duarte da Costa | AP59: Angola | AT59: josepedrodcosta@gmail.com | AU59: 934207731/+244-928059008 | AX59: =AY59*I59 -> 193188.72 | AY59: 2730
A60: 59 | B60: BG | C60: T1 | D60: 6 | E60: West | F60: 63.221 | G60: 25.147 | I60: =F60+0.3*G60 -> 70.7651 | J60: CPCV | K60: menos 1 (place) | P60: YES | Q60: YES | R60: 197500 | S60: 197500 | T60: 207375 | W60: =R60/I60 -> 2790.9238 | X60: =T60/I60 -> 2930.47 | AA60: 44897 | AB60: 45343 | AC60: 39500 | AH60: 158000 | AI60: GlobalKey | AJ60: Rute | AO60: BRENNO S.A (Carlos Jorge Coelho de Lemos ) | AP60: Portugal | AX60: =AY60*I60 -> 193188.72 | AY60: 2730
A61: 60 | B61: BH | C61: T2 | D61: 6 | E61: South/West | F61: 86.61 | G61: 52.568 | I61: =F61+0.3*G61 -> 102.3804 | J61: CPCV | K61: menos 1 (1 place) | P61: YES | Q61: YES | R61: 295000 | S61: 295000 | T61: 309750 | W61: =R61/I61 -> 2881.4109 | X61: =T61/I61 -> 3025.4814 | AA61: 44914 | AB61: 45345 | AC61: 59000 | AH61: 236000 | AI61: Tranquildiscovery | AK61: 0.04 | AO61: YOAV LERNER | AP61: Israel | AX61: =AY61*I61 -> 279498.49 | AY61: 2730 | AZ61: 360000
A62: 61 | B62: BI | C62: T5 | D62: 7 | E62: East/North/West | F62: 216.31 | G62: 127.727 | I62: =F62+0.3*G62 -> 254.6281 | J62: CPCV | K62: menos 2 (box + 2 places) | P62: YES | Q62: YES | R62: 786240 | S62: =0.96*T62 -> 786240 | T62: 819000 | V62: =S62/T62-1 -> -0.04 | W62: =R62/I62 -> 3087.7975 | X62: =S62/I62 -> 3087.7975 | Y62: =T62/I62 -> 3216.4557 | AB62: 45485 | AC62: 78624 | AD62: 39312 | AE62: 45627 | AF62: 39312 | AG62: 45839 | AH62: 628992 | AI62: ChaveNova | AO62: Mário Jorge Torres Pereira da Silva & Marta Maria RAMOS Silva da Cruz Barbosa | AP62: Portugal | AT62: mariojorgesilva1967@gmail.com | AU62: 935074005 | AX62: =AY62*I62 -> 695134.71 | AY62: 2730
A63: 62 | B63: BJ | C63: T4 | D63: 7 | E63: East/West | F63: 180.204 | G63: 49 | I63: =F63+0.3*G63 -> 194.904 | J63: CPCV | K63: menos 1 (box + 1 place) | P63: YES | Q63: YES | R63: 612000 | S63: 612000 | T63: 624000 | V63: =100%-(T63/S63) -> -0.019607843 | W63: =R63/I63 -> 3140.0074 | X63: =S63/I63 -> 3140.0074 | Y63: =T63/I63 -> 3201.5762 | AA63: 45188 | AB63: 45313 | AC63: 122400 | AH63: 489600 | AI63: GlobalKey | AL63: YES | AO63: Florinda Maria Dias Mouta | AP63: Portugal | AT63: florindam543@gmail.com | AU63: 916662498 | AX63: =AY63*I63 -> 532087.92 | AY63: 2730
A64: 63 | B64: BK | C64: T4 | D64: 7 | E64: East/West | F64: 180.204 | G64: 49 | I64: =F64+0.3*G64 -> 194.904 | J64: CPCV | K64: menos 1 (box + 1 place) | P64: YES | Q64: YES | R64: 530000 | S64: 530000 | T64: 556500 | W64: =R64/I64 -> 2719.2874 | X64: =T64/I64 -> 2855.2518 | AA64: 44881 | AB64: 45317 | AC64: 116000 | AH64: 414000 | AI64: ChaveNova | AL64: YES | AM64: YES | AO64: André João Martins Santos Ferreira & Rita Cortez | AP64: Portugal | AT64: andre.ferreira@aboutpublicity.com | AU64: 964291841 | AX64: =AY64*I64 -> 532087.92 | AY64: 2730
A65: 64 | B65: BL | C65: T5 | D65: 7 | E65: East/South/West | F65: 216.31 | G65: 127.727 | I65: =F65+0.3*G65 -> 254.6281 | J65: CPCV | K65: menos 2 (box + 2 places) | P65: YES | Q65: YES | R65: 690000 | S65: 690000 | T65: 724500 | W65: =R65/I65 -> 2709.8345 | X65: =T65/I65 -> 2845.3262 | AA65: 44907 | AB65: 45324 | AC65: 138000 | AH65: 552000 | AI65: GlobalKey | AJ65: Francisco | AL65: YES | AO65: José Miguel Coelho Antunes & Maria Ramos | AP65: Portugal | AT65: miguel.antunes1970@gmial.com | AU65: 919534783 | AX65: =AY65*I65 -> 695134.71 | AY65: 2730
F66: =SUM(F2:F65) -> 6131.03 | I66: =SUM(I2:I65) -> 6822.2609 | S66: =SUM(S2:S65) -> 19285550
C68: # | D68: € | E68: €/m² | G68: SOLD IN
A69: CPCV | C69: =COUNTIF(J2:J65,A69) -> 64 | D69: =SUMIF(J2:J65,A69,R2:R65) -> 19176340 | E69: =AVERAGEIF(J2:J65,A69,W2:W65) -> 2803.7765 | G69: 2022 | H69: =COUNTIFS(AA2:AA65,">="&DATE(2022,1,1),AA2:AA65,"<="&DATE(2022,12,31)) -> 30
A70: BLOCKED | C70: =COUNTIF(J2:J65,A70) -> 0 | D70: =SUMIF(J2:J65,A70,S2:S65) -> 0 | E70: =AVERAGEIF(J2:J65,A70,X2:X65) -> #DIV/0! | G70: 2023 | H70: =COUNTIFS(AA2:AA65,">="&DATE(2023,1,1),AA2:AA65,"<="&DATE(2023,12,31)) -> 22
A71: AVAILABLE | C71: =COUNTIF(J2:J65,"") -> 0 | D71: =SUMIF(J2:J65,"",S2:S65) -> 0 | E71: =AVERAGEIF(J2:J65,"",X2:X65) -> #DIV/0! | G71: 2024 | H71: =C69-(H69+H70) -> 12
A72: RESERVED | C72: =COUNTIF(J2:J65,A72) -> 0 | D72: =SUMIF(J2:J65,A72,R2:R65) -> 0 | E72: =AVERAGEIF(J2:J65,A72,W2:W65) -> #DIV/0! | G72: 2025 | H72: =COUNTIFS(AB2:AB65,">="&DATE(2025,1,1),AB2:AB65,"<="&DATE(2025,12,31)) -> 1
A73: TOTAL | C73: =SUBTOTAL(9,C69:C72) -> 64 | D73: =SUBTOTAL(9,D69:D72) -> 19176340 | E73: =D73/I66 -> 2810.8482 | G73: Percentage Sold | H73: =(C72+C69)/C73 -> 1
J74: CPCV 2024
A75: # | C75: T1 | D75: T2 | E75: T3 | F75: T4 | G75: T5 | H75: Total | J75: January | K75: February | L75: March | M75: April | N75: May | O75: June | P75: July | Q75: August | R75: September | S75: October | T75: November | U75: December
A76: CPCV | C76: =COUNTIFS(J2:J65,A76,C2:C65,C75) -> 21 | D76: =COUNTIFS(J2:J65,A76,C2:C65,D75) -> 20 | E76: =COUNTIFS(J2:J65,A76,C2:C65,E75) -> 19 | F76: =COUNTIFS(J2:J65,A76,C2:C65,F75) -> 2 | G76: =COUNTIFS(J2:J65,A76,C2:C65,G75) -> 2 | H76: =SUM(C76:G76) -> 64 | J76: =COUNTIFS(AB2:AB65,">="&DATE(2024,1,1),AB2:AB65,"<="&DATE(2024,1,31)) -> 12 | K76: =COUNTIFS(AB2:AB65,">="&DATE(2024,2,1),AB2:AB65,"<="&DATE(2024,2,29)) -> 34 | L76: =COUNTIFS(AB2:AB65,">="&DATE(2024,3,1),AB2:AB65,"<="&DATE(2024,3,31)) -> 7 | M76: =COUNTIFS(AB2:AB65,">="&DATE(2024,4,1),AB2:AB65,"<="&DATE(2024,4,31)) -> 2 | N76: =COUNTIFS(AB2:AB65,">="&DATE(2024,5,1),AB2:AB65,"<="&DATE(2024,5,31)) -> 2 | O76: =COUNTIFS(AB2:AB65,">="&DATE(2024,6,1),AB2:AB65,"<="&DATE(2024,6,31)) -> 3 | P76: =COUNTIFS(AB2:AB65,">="&DATE(2024,7,1),AB2:AB65,"<="&DATE(2024,7,31)) -> 1 | Q76: =COUNTIFS(AB2:AB65,">="&DATE(2024,8,1),AB2:AB65,"<="&DATE(2024,8,31)) -> 0 | R76: =COUNTIFS(AB2:AB65,">="&DATE(2024,9,1),AB2:AB65,"<="&DATE(2024,9,31)) -> 0 | S76: =COUNTIFS(AB2:AB65,">="&DATE(2024,10,1),AB2:AB65,"<="&DATE(2024,10,31)) -> 2 | T76: =COUNTIFS(AB2:AB65,">="&DATE(2024,11,1),AB2:AB65,"<="&DATE(2024,11,31)) -> 0 | U76: =COUNTIFS(AB2:AB65,">="&DATE(2024,12,1),AB2:AB65,"<="&DATE(2024,12,31)) -> 0
A77: BLOCKED | C77: =COUNTIFS(J2:J65,A77,C2:C65,C75) -> 0 | D77: =COUNTIFS(J2:J61,A77,C2:C61,D75) -> 0 | E77: =COUNTIFS(J2:J65,A77,C2:C65,E75) -> 0 | F77: =COUNTIFS(J2:J65,A77,C2:C65,F75) -> 0 | G77: =COUNTIFS(J2:J65,A77,C2:C65,G75) -> 0 | H77: =SUM(C77:G77) -> 0
A78: AVAILABLE | C78: =COUNTIFS(J2:J65,"",C2:C65,C75) -> 0 | D78: =COUNTIFS(J2:J65,"",C2:C65,D75) -> 0 | E78: =COUNTIFS(J2:J65,"",C2:C65,E75) -> 0 | F78: =COUNTIFS(J2:J65,"",C2:C65,F75) -> 0 | G78: =COUNTIFS(J2:J65,"",C2:C65,G75) -> 0 | H78: =SUM(C78:G78) -> 0 | J78: CPCV 2025
A79: RESERVED | C79: =COUNTIFS(J2:J65,A79,C2:C65,C75) -> 0 | D79: =COUNTIFS(J2:J65,A79,C2:C65,D75) -> 0 | E79: =COUNTIFS(J2:J65,A79,C2:C65,E75) -> 0 | F79: =COUNTIFS(J2:J65,A79,C2:C65,F75) -> 0 | G79: =COUNTIFS(J2:J65,A79,C2:C65,G75) -> 0 | H79: =SUM(C79:G79) -> 0 | J79: January | K79: February | L79: March | M79: April | N79: May | O79: June | P79: July | Q79: August | R79: September | S79: October | T79: November | U79: December
A80: Total | C80: =SUM(C76:C79) -> 21 | D80: =SUM(D76:D79) -> 20 | E80: =SUM(E76:E79) -> 19 | F80: =SUM(F76:F79) -> 2 | G80: =SUM(G76:G79) -> 2 | H80: =SUM(H76:H79) -> 64 | J80: =COUNTIFS(AB2:AB65,">="&DATE(2025,1,1),AB2:AB65,"<="&DATE(2025,1,31)) -> 0 | K80: =COUNTIFS(AB2:AB65,">="&DATE(2025,2,1),AB2:AB65,"<="&DATE(2025,2,28)) -> 1 | L80: =COUNTIFS(AB6:AB69,">="&DATE(2025,3,1),AB6:AB69,"<="&DATE(2025,3,31)) -> 0 | M80: =COUNTIFS(AB6:AB69,">="&DATE(2025,4,1),AB6:AB69,"<="&DATE(2025,4,30)) -> 0 | N80: =COUNTIFS(AB6:AB69,">="&DATE(2025,5,1),AB6:AB69,"<="&DATE(2025,5,31)) -> 0 | O80: =COUNTIFS(AB6:AB69,">="&DATE(2025,6,1),AB6:AB69,"<="&DATE(2025,6,30)) -> 0 | P80: =COUNTIFS(AB6:AB69,">="&DATE(2025,7,1),AB6:AB69,"<="&DATE(2025,7,31)) -> 0 | Q80: =COUNTIFS(AB6:AB69,">="&DATE(2025,8,1),AB6:AB69,"<="&DATE(2025,8,31)) -> 0 | R80: =COUNTIFS(AB6:AB69,">="&DATE(2025,9,1),AB6:AB69,"<="&DATE(2025,9,30)) -> 0 | S80: =COUNTIFS(AB6:AB69,">="&DATE(2025,10,1),AB6:AB69,"<="&DATE(2025,10,31)) -> 0 | T80: =COUNTIFS(AB6:AB69,">="&DATE(2025,11,1),AB6:AB69,"<="&DATE(2025,11,30)) -> 0 | U80: =COUNTIFS(AB6:AB69,">="&DATE(2025,12,1),AB6:AB69,"<="&DATE(2025,12,31)) -> 0
A83: Average €/m² | C83: T1 | D83: T2 | E83: T3 | F83: T4 | G83: T5 | H83: Total | J83: Brokers | O83: Nationalities
A84: CPCV | C84: =AVERAGEIFS(W2:W65,J2:J65,A84,C2:C65,C83) -> 2789.8982 | D84: =AVERAGEIFS(W2:W65,J2:J65,A84,C2:C65,D83) -> 2737.3214 | E84: =AVERAGEIFS(W2:W65,J2:J65,A84,C2:C65,E83) -> 2865.8147 | F84: =AVERAGEIFS(W2:W65,J2:J65,A84,C2:C65,F83) -> 2929.6474 | G84: =AVERAGEIFS(W2:W65,J2:J65,A84,C2:C65,G83) -> 2898.816 | H84: =AVERAGEIF(J2:J65,A84,W2:W65) -> 2803.7765 | K84: Overall | L84: 2024 | M84: % | P84: Overall | Q84: 2024 | R84: %
A85: BLOCKED | C85: =AVERAGEIFS(X2:X65,J2:J65,A85,C2:C65,C83) -> #DIV/0! | D85: =AVERAGEIFS(X2:X65,J2:J65,A85,C2:C65,D83) -> #DIV/0! | E85: =AVERAGEIFS(X2:X65,J2:J65,A85,C2:C65,E83) -> #DIV/0! | F85: =AVERAGEIFS(X2:X65,J2:J65,A85,C2:C65,F83) -> #DIV/0! | G85: =AVERAGEIFS(X2:X65,J2:J65,A85,C2:C65,G83) -> #DIV/0! | H85: =AVERAGEIF(J2:J65,A85,X2:X65) -> #DIV/0! | J85: GLOBALKEY | K85: =COUNTIFS(J2:J65,J3,AI2:AI65,J85) -> 43 | L85: =COUNTIFS(AB2:AB65,">="&DATE(2024,1,1),AB2:AB65,"<="&DATE(2024,12,31),AI2:AI65,J85) -> 43 | M85: =K85/(+K85+K86+K87) -> 0.671875 | O85: Portugal | P85: =COUNTIFS($J$2:$J$65,$J$3,$AP$2:$AP$65,O85) -> 50 | Q85: =COUNTIFS(AB2:AB65,">="&DATE(2024,1,1),AB2:AB65,"<="&DATE(2024,12,31),$AP$2:$AP$65,O85) -> 49 | R85: =P85/(+P85+P86+P87) -> 0.80645161
A86: AVAILABLE | C86: =AVERAGEIFS(X2:X65,J2:J65,"",C2:C65,C83) -> #DIV/0! | D86: =AVERAGEIFS(X2:X65,J2:J65,"",C2:C65,D83) -> #DIV/0! | E86: =AVERAGEIFS(X2:X65,J2:J65,"",C2:C65,E83) -> #DIV/0! | F86: =AVERAGEIFS(X2:X65,J2:J65,"",C2:C65,F83) -> #DIV/0! | G86: =AVERAGEIFS(X2:X65,J2:J65,"",C2:C65,G83) -> #DIV/0! | H86: =AVERAGEIF(J2:J65,"",X2:X65) -> #DIV/0! | J86: CHAVENOVA | K86: =COUNTIFS(J2:J65,J3,AI2:AI65,J86) -> 11 | L86: =COUNTIFS(AB2:AB65,">="&DATE(2024,1,1),AB2:AB65,"<="&DATE(2024,12,31),AI2:AI65,J86) -> 10 | M86: =K86/(+K85+K86+K87) -> 0.171875 | O86: Israel | P86: =COUNTIFS($J$2:$J$65,$J$3,$AP$2:$AP$65,O86) -> 11 | Q86: =COUNTIFS(AB2:AB65,">="&DATE(2024,1,1),AB2:AB65,"<="&DATE(2024,12,31),$AP$2:$AP$65,O86) -> 11 | R86: =P86/(+P85+P86+P87) -> 0.17741935
A87: RESERVED | C87: =AVERAGEIFS(W2:W65,J2:J65,A87,C2:C65,C83) -> #DIV/0! | D87: =AVERAGEIFS(W2:W65,J2:J65,A87,C2:C65,D83) -> #DIV/0! | E87: =AVERAGEIFS(W2:W65,J2:J65,A87,C2:C65,E83) -> #DIV/0! | F87: =AVERAGEIFS(W2:W65,J2:J65,A87,C2:C65,F83) -> #DIV/0! | G87: =AVERAGEIFS(W2:W65,J2:J65,A87,C2:C65,G83) -> #DIV/0! | H87: =AVERAGEIF(J2:J65,A87,W2:W65) -> #DIV/0! | J87: TRANQUILDISCOVERY | K87: =COUNTIFS(J2:J65,J3,AI2:AI65,J87) -> 10 | L87: =COUNTIFS(AB2:AB65,">="&DATE(2024,1,1),AB2:AB65,"<="&DATE(2024,12,31),AI2:AI65,J87) -> 10 | M87: =K87/(+K85+K86+K87) -> 0.15625 | O87: Angola | P87: =COUNTIFS($J$2:$J$65,$J$3,$AP$2:$AP$65,O87) -> 1 | Q87: =COUNTIFS(AB2:AB65,">="&DATE(2024,1,1),AB2:AB65,"<="&DATE(2024,12,31),$AP$2:$AP$65,O87) -> 1 | R87: =P87/(+P85+P86+P87) -> 0.016129032
O88: China | P88: =COUNTIFS($J$2:$J$65,$J$3,$AP$2:$AP$65,O88) -> 2 | Q88: =COUNTIFS(AB3:AB66,">="&DATE(2024,1,1),AB3:AB66,"<="&DATE(2024,12,31),$AP$2:$AP$65,O88) -> 2 | R88: =P88/(+P86+P87+P88) -> 0.14285714
A89: Average €/unit | C89: T1 | D89: T2 | E89: T3 | F89: T4 | G89: T5 | H89: Total
A90: CPCV | C90: =AVERAGEIFS(R2:R65,J2:J65,A90,C2:C65,C89) -> 188217.62 | D90: =AVERAGEIFS(R2:R65,J2:J65,A90,C2:C65,D89) -> 272772.5 | E90: =AVERAGEIFS(R2:R65,J2:J65,A90,C2:C65,E89) -> 376320 | F90: =AVERAGEIFS(R2:R65,J2:J65,A90,C2:C65,F89) -> 571000 | G90: =AVERAGEIFS(R2:R65,J2:J65,A90,C2:C65,G89) -> 738120 | H90: =AVERAGEIF(J2:J65,A90,R2:R65) -> 299630.31
A91: BLOCKED | C91: =AVERAGEIFS(T2:T65,J2:J65,A91,C2:C65,C89) -> #DIV/0! | D91: =AVERAGEIFS(T2:T65,J2:J65,A91,C2:C65,D89) -> #DIV/0! | E91: =AVERAGEIFS(T2:T65,J2:J65,A91,C2:C65,E89) -> #DIV/0! | F91: =AVERAGEIFS(T2:T65,J2:J65,A91,C2:C65,F89) -> #DIV/0! | G91: =AVERAGEIFS(T2:T65,J2:J65,A91,C2:C65,G89) -> #DIV/0! | H91: =AVERAGEIF(J2:J65,A91,R2:R65) -> #DIV/0!
A92: AVAILABLE | C92: =AVERAGEIFS(T2:T65,J2:J65,"",C2:C65,C89) -> #DIV/0! | D92: =AVERAGEIFS(T2:T65,J2:J65,"",C2:C65,D89) -> #DIV/0! | E92: =AVERAGEIFS(S2:S65,J2:J65,"",C2:C65,E89) -> #DIV/0! | F92: =AVERAGEIFS(T2:T65,J2:J65,"",C2:C65,F89) -> #DIV/0! | G92: =AVERAGEIFS(T2:T65,J2:J65,"",C2:C65,G89) -> #DIV/0! | H92: =AVERAGEIF(J2:J65,"",T2:T65) -> #DIV/0!
A93: RESERVED | C93: =AVERAGEIFS(R2:R65,J2:J65,A93,C2:C65,C89) -> #DIV/0! | D93: =AVERAGEIFS(R2:R65,J2:J65,A93,C2:C65,D89) -> #DIV/0! | E93: =AVERAGEIFS(R2:R65,J2:J65,A93,C2:C65,E89) -> #DIV/0! | F93: =AVERAGEIFS(R2:R65,J2:J65,A93,C2:C65,F89) -> #DIV/0! | G93: =AVERAGEIFS(R2:R65,J2:J65,A93,C2:C65,G89) -> #DIV/0! | H93: =AVERAGEIF(J2:J65,A93,R2:R65) -> #DIV/0!
A95: Average size m² | C95: T1 | D95: T2 | E95: T3 | F95: T4 | G95: T5 | H95: Total
A96: CPCV | C96: =AVERAGEIFS(I2:I65,C2:C65,C95,J2:J65,A96) -> 67.577757 | D96: =AVERAGEIFS(I2:I65,C2:C65,D95,J2:J65,A96) -> 99.58054 | E96: =AVERAGEIFS(I2:I65,C2:C65,E95,J2:J65,A96) -> 132.23437 | F96: =AVERAGEIFS(I2:I65,C2:C65,F95,J2:J65,A96) -> 194.904 | G96: =AVERAGEIFS(I2:I65,C2:C65,G95,J2:J65,A96) -> 254.6281 | H96: =AVERAGEIF(J2:J65,A96,I2:I65) -> 106.59783
A97: BLOCKED | C97: =AVERAGEIFS(I2:I65,C2:C65,C95,J2:J65,A97) -> #DIV/0! | D97: =AVERAGEIFS(I2:I65,C2:C65,D95,J2:J65,A97) -> #DIV/0! | E97: =AVERAGEIFS(I2:I65,C2:C65,E95,J2:J65,A97) -> #DIV/0! | F97: =AVERAGEIFS(I2:I65,C2:C65,F95,J2:J65,A97) -> #DIV/0! | G97: =AVERAGEIFS(I2:I65,C2:C65,G95,J2:J65,A97) -> #DIV/0! | H97: =AVERAGEIF(J2:J65,A97,I2:I65) -> #DIV/0!
A98: AVAILABLE | C98: =AVERAGEIFS(I2:I65,C2:C65,C95,J2:J65,"") -> #DIV/0! | D98: =AVERAGEIFS(I2:I65,C2:C65,D95,J2:J65,"") -> #DIV/0! | E98: =AVERAGEIFS(I2:I65,C2:C65,E95,J2:J65,"") -> #DIV/0! | F98: =AVERAGEIFS(I2:I65,C2:C65,F95,J2:J65,"") -> #DIV/0! | G98: =AVERAGEIFS(I2:I65,C2:C65,G95,J2:J65,"") -> #DIV/0! | H98: =AVERAGEIF(J2:J65,"",I2:I65) -> #DIV/0!
A99: RESERVED | C99: =AVERAGEIFS(I2:I65,C2:C65,C95,J2:J65,A99) -> #DIV/0! | D99: =AVERAGEIFS(I2:I65,C2:C65,D95,J2:J65,A99) -> #DIV/0! | E99: =AVERAGEIFS(I2:I65,C2:C65,E95,J2:J65,A99) -> #DIV/0! | F99: =AVERAGEIFS(I2:I65,C2:C65,F95,J2:J65,A99) -> #DIV/0! | G99: =AVERAGEIFS(I2:I65,C2:C65,G95,J2:J65,A99) -> #DIV/0! | H99: =AVERAGEIF(J2:J65,A99,I2:I65) -> #DIV/0!
C101: =1.5*C99 -> #DIV/0! | D101: =1.5*D99 -> #DIV/0! | E101: =1.5*E99 -> #DIV/0! | F101: =1.5*F99 -> #DIV/0! | G101: =1.5*G99 -> #DIV/0!

Sheet VERDE VALE H3 A&B (MAIA)
A1: Unit | B1: Building | C1: Fraction | D1: Layout | E1: Floor | F1: Directions | G1: Main area | H1: Balcony | I1: Patio | J1: Terrace | K1: Saleable Area | L1: Parking 1 | M1: Parking 2 | N1: Parking 3 | O1: Parking 4 | P1: Storage | Q1: Status | R1: Paid? | S1: Closing Price | T1: first Price 1/02 | U1: Second price 15/02 | V1: Min. Price | W1: Asking Price 1/03 | X1: % Discount | Y1: €/m² sold | Z1: €/m² min. price | AA1: €/m² asking price | AB1: Date of Reservation | AC1: Date of CPCV | AD1: CPCV Value | AE1: 1st down payment | AF1: Date 1st down pmt. | AG1: 2nd down payment | AH1: Date 2nd down pmt. | AI1: Deed | AJ1: Brokers company | AK1: Broker Name | AL1: % Commission | AM1: Invoice sent? | AN1: Invoice Paid? | AO1: Client | AP1: Client Nationality | AQ1: Birth Date | AR1: Age | AS1: Investor / Final Client | AT1: Email | AU1: Phone | AV1: Cancelled? | AW1: Why Cancelled? | AX1: Business Plan Price | AY1: €/m² Business Plan | AZ1: Resale
A2: 1 | B2: H3A | C2: A | D2: T4 | E2: 1 | F2: N/E/W | G2: 161.3 | I2: =14.5+67.1 -> 81.6 | K2: =G2+0.2*H2+0.2*I2+0.2*J2 -> 177.62 | L2: 3 | P2: 1 | Q2: CPCV | S2: 539520 | T2: 562000 | U2: 562000 | V2: =0.96*W2 -> 539520 | W2: 562000 | X2: =1-(S2/W2) -> 0.04 | Y2: =S2/K2 -> 3037.4958 | Z2: =V2/K2 -> 3037.4958 | AA2: =W2/K2 -> 3164.0581 | AC2: 45768 | AD2: =10%*S2 -> 53952 | AE2: =10%*S2 -> 53952 | AI2: =80%*S2 -> 431616 | AJ2: GlobalKey | AO2: Pedro Saul Ferreira dos Santos | AP2: Portugal | AX2: =AY2*K2 -> 484902.6 | AY2: 2730
A3: 2 | B3: H3A | C3: B | D3: T2 | E3: 1 | F3: E | G3: 85 | I3: 28.4 | K3: =G3+0.2*H3+0.2*I3+0.2*J3 -> 90.68 | L3: 1 | P3: - | Q3: CPCV | R3: YES | S3: 281280 | T3: 265000 | U3: 276000 | V3: =0.96*W3 -> 281280 | W3: 293000 | X3: =1-(S3/W3) -> 0.04 | Y3: =S3/K3 -> 3101.8968 | Z3: =V3/K3 -> 3101.8968 | AA3: =W3/K3 -> 3231.1425 | AB3: 45447 | AC3: 45471 | AD3: 56256 | AI3: 225024 | AJ3: GlobalKey | AK3: Ignas Bobinas | AM3: YES | AO3: Sandra Marisa Rodrigues Mota Oliveira | AP3: Portugal | AT3: sandra.mota.oliveira-5310p@adv.oa.pt | AU3: 968837313 | AX3: =AY3*K3 -> 247556.4 | AY3: 2730
A4: 3 | B4: H3A | C4: C | D4: T1 | E4: 1 | F4: W | G4: 62.4 | I4: 46.8 | K4: =G4+0.2*H4+0.2*I4+0.2*J4 -> 71.76 | L4: 1 | P4: - | Q4: CPCV | R4: YES | S4: 204480 | T4: 213000 | U4: 213000 | V4: =0.96*W4 -> 204480 | W4: 213000 | X4: =1-(S4/W4) -> 0.04 | Y4: =S4/K4 -> 2849.4983 | Z4: =V4/K4 -> 2849.4983 | AA4: =W4/K4 -> 2968.2274 | AC4: 45365 | AD4: 40896 | AI4: 163584 | AJ4: ChaveNova | AO4: nÚMEROS100ACENTO | AP4: Portugal | AT4: jcastrogreat@gmail.com | AU4: 968032204 | AX4: =AY4*K4 -> 195904.8 | AY4: 2730
A5: 4 | B5: H3A | C5: D | D5: T2 | E5: 1 | F5: W | G5: 85.9 | I5: 62.5 | K5: =G5+0.2*H5+0.2*I5+0.2*J5 -> 98.4 | L5: 1 | P5: - | Q5: CPCV | S5: 270720 | T5: 271000 | U5: 282000 | V5: =0.96*W5 -> 270720 | W5: 282000 | X5: =1-(S5/W5) -> 0.04 | Y5: =S5/K5 -> 2751.2195 | Z5: =V5/K5 -> 2751.2195 | AA5: =W5/K5 -> 2865.8537 | AB5: 45351 | AC5: 45358 | AD5: =20%*S5 -> 54144 | AI5: =S5-AD5 -> 216576 | AJ5: ChaveNova | AO5: Sofia Maria dos Santos Andrade Ferreira | AP5: Portugal | AT5: ferreira.andrade.sofia@gmail.com | AU5: 919920672 | AX5: =AY5*K5 -> 268632 | AY5: 2730
A6: 5 | B6: H3A | C6: E | D6: T4 | E6: 2 | F6: N/E/W | G6: 164.9 | H6: 98.4 | K6: =G6+0.2*H6+0.2*I6+0.2*J6 -> 184.58 | L6: 3 | P6: 1 | Q6: CPCV | S6: 593000 | T6: 593000 | U6: 593000 | V6: =0.96*W6 -> 569280 | W6: 593000 | X6: =1-(S6/W6) -> 0 | Y6: =S6/K6 -> 3212.6991 | Z6: =V6/K6 -> 3084.1911 | AA6: =W6/K6 -> 3212.6991 | AB6: 45440 | AC6: 45672 | AD6: =5000+113600 -> 118600 | AI6: 474400 | AJ6: GlobalKey | AO6: Jóni Nunes | AP6: Portugal | AT6: joninunesortopedia@gmail.com | AU6: 919525513 | AX6: =AY6*K6 -> 503903.4 | AY6: 2730
A7: 6 | B7: H3A | C7: F | D7: T3 | E7: 2 | F7: S/E | G7: 116.3 | H7: 53.1 | K7: =G7+0.2*H7+0.2*I7+0.2*J7 -> 126.92 | L7: 2 | P7: 1 | Q7: CPCV | S7: 393600 | T7: 372000 | U7: 387000 | V7: =0.96*W7 -> 393600 | W7: 410000 | X7: =1-(S7/W7) -> 0.04 | Y7: =S7/K7 -> 3101.1661 | Z7: =V7/K7 -> 3101.1661 | AA7: =W7/K7 -> 3230.3813 | AC7: 45572 | AD7: 78720 | AI7: 314880 | AJ7: Chavenova | AO7: Ricardo André Gomes da Silva & Maria Graciete da Silva | AP7: Portugal | AT7: - | AU7: 96897230431 | AX7: =AY7*K7 -> 346491.6 | AY7: 2730
A8: 7 | B8: H3A | C8: G | D8: T1 | E8: 2 | F8: N/W | G8: 62.5 | H8: 26 | K8: =G8+0.2*H8+0.2*I8+0.2*J8 -> 67.7 | L8: 1 | P8: - | Q8: CPCV | R8: YES | S8: 199680 | T8: 208000 | U8: 208000 | V8: =0.96*W8 -> 199680 | W8: 208000 | X8: =1-(S8/W8) -> 0.04 | Y8: =S8/K8 -> 2949.483 | Z8: =V8/K8 -> 2949.483 | AA8: =W8/K8 -> 3072.3781 | AC8: 45387 | AD8: 39936 | AI8: 159744 | AJ8: Tranquildiscovery | AK8: Pedro | AO8: Hélder Domingos Fernandes Martins | AP8: Portugal | AT8: hmartins1958@gmail.com | AU8: 917321296 | AX8: =AY8*K8 -> 184821 | AY8: 2730
A9: 8 | B9: H3A | C9: H | D9: T2 | E9: 2 | F9: S/W | G9: 85.6 | H9: 54.9 | K9: =G9+0.2*H9+0.2*I9+0.2*J9 -> 96.58 | L9: 1 | P9: - | Q9: CPCV | S9: 320000 | T9: 302000 | U9: 314000 | V9: =0.96*W9 -> 319680 | W9: 333000 | X9: =1-(S9/W9) -> 0.039039039 | Y9: =S9/K9 -> 3313.3154 | Z9: =V9/K9 -> 3310.0021 | AA9: =W9/K9 -> 3447.9188 | AB9: 45391 | AC9: 45561 | AD9: =20%*S9 -> 64000 | AI9: =80%*S9 -> 256000 | AJ9: GlobalKey | AO9: LOARD, UNIPESSOAL LDA. | AP9: Portugal | AT9: loard.lda@gmail.com | AU9: 913005306 | AX9: =AY9*K9 -> 263663.4 | AY9: 2730
A10: 9 | B10: H3A | C10: I | D10: T3 | E10: 3 | F10: N/E | G10: 116.3 | H10: 21.2 | K10: =G10+0.3*H10+0.2*I10+0.2*J10 -> 122.66 | L10: 2 | Q10: CPCV | S10: 385920 | T10: 379000 | U10: 379000 | V10: =0.96*W10 -> 385920 | W10: 402000 | X10: =1-(S10/W10) -> 0.04 | Y10: =S10/K10 -> 3146.2579 | Z10: =V10/K10 -> 3146.2579 | AA10: =W10/K10 -> 3277.352 | AC10: 45596 | AD10: =10%*S10 -> 38592 | AI10: =90%*S10 -> 347328 | AJ10: GlobalKey | AO10: DUPLA AMBIÇÃO - Meidaçao imobilairia | AP10: Portugal | AT10: paula.truck@gmail.com | AU10: 939947609 | AX10: =AY10*K10 -> 334861.8 | AY10: 2730
A11: 10 | B11: H3A | C11: J | D11: T3 | E11: 3 | F11: S/E | G11: 116.2 | H11: 16.6 | K11: =G11+0.3*H11+0.2*I11+0.2*J11 -> 121.18 | L11: 2 | P11: 1 | Q11: CPCV | S11: 405000 | T11: 382000 | U11: 382000 | V11: =0.96*W11 -> 388800 | W11: 405000 | X11: =1-(S11/W11) -> 0 | Y11: =S11/K11 -> 3342.1357 | Z11: =V11/K11 -> 3208.4502 | AA11: =W11/K11 -> 3342.1357 | AC11: 45631 | AD11: =5000+35500 -> 40500 | AI11: 364500 | AJ11: GlobalKey | AO11: António Ramos de Carvalho Júnior & Tamille Lima Gonçalves | AP11: Portugal | AU11: 913993043 | AX11: =AY11*K11 -> 330821.4 | AY11: 2730
A12: 11 | B12: H3A | C12: K | D12: T2 | E12: 3 | F12: N/W | G12: 86.5 | H12: 55 | K12: =G12+0.2*H12+0.2*I12+0.2*J12 -> 97.5 | L12: 1 | P12: - | Q12: CPCV | S12: 321600 | T12: 304000 | U12: 316000 | V12: =0.96*W12 -> 321600 | W12: 335000 | X12: =1-(S12/W12) -> 0.04 | Y12: =S12/K12 -> 3298.4615 | Z12: =V12/K12 -> 3298.4615 | AA12: =W12/K12 -> 3435.8974 | AC12: 45504 | AD12: 64320 | AI12: 257280 | AJ12: GlobalKey | AO12: David Beijoco & Daniela Cabanelos | AP12: Portugal | AT12: davidbeijoco@bastarda.pt | AU12: 916676729 | AX12: =AY12*K12 -> 266175 | AY12: 2730
A13: 12 | B13: H3A | C13: L | D13: T1 | E13: 3 | F13: W | G13: 62.4 | H13: 25.2 | K13: =G13+0.2*H13+0.2*I13+0.2*J13 -> 67.44 | L13: 1 | P13: - | Q13: CPCV | R13: YES | S13: 204480 | T13: 213000 | U13: 213000 | V13: =0.96*W13 -> 204480 | W13: 213000 | X13: =1-(S13/W13) -> 0.04 | Y13: =S13/K13 -> 3032.0285 | Z13: =V13/K13 -> 3032.0285 | AA13: =W13/K13 -> 3158.363 | AC13: 45365 | AD13: =20%*S13 -> 40896 | AI13: =80%*S13 -> 163584 | AJ13: ChaveNova | AO13: Décimas Ancestrais & Epopeia Frondosa | AP13: Portugal | AX13: =AY13*K13 -> 184111.2 | AY13: 2730
A14: 13 | B14: H3A | C14: M | D14: T2 | E14: 3 | F14: S/W | G14: 85.6 | H14: 52.8 | K14: =G14+0.2*H14+0.2*I14+0.2*J14 -> 96.16 | L14: 1 | P14: 1 | Q14: CPCV | S14: 324480 | T14: 307000 | U14: 319000 | V14: =0.96*W14 -> 324480 | W14: 338000 | X14: =1-(S14/W14) -> 0.04 | Y14: =S14/K14 -> 3374.376 | Z14: =V14/K14 -> 3374.376 | AA14: =W14/K14 -> 3514.975 | AB14: 45467 | AC14: 45541 | AD14: 64896 | AI14: 259584 | AJ14: GlobalKey | AO14: Fábio Rui Ludovino Seixas & Joana Pires Martins | AP14: Portugal | AX14: =AY14*K14 -> 262516.8 | AY14: 2730
A15: 14 | B15: H3A | C15: N | D15: T3 | E15: 4 | F15: N/E | G15: 116.3 | H15: 21.2 | K15: =G15+0.3*H15+0.2*I15+0.2*J15 -> 122.66 | L15: 2 | Q15: CPCV | S15: 391680 | T15: 384000 | U15: 384000 | V15: =0.96*W15 -> 391680 | W15: 408000 | X15: =1-(S15/W15) -> 0.04 | Y15: =S15/K15 -> 3193.217 | Z15: =V15/K15 -> 3193.217 | AA15: =W15/K15 -> 3326.2677 | AB15: 45688 | AC15: 45714 | AD15: =5000+34168 -> 39168 | AE15: 39168 | AF15: =30+AC15 -> 45744 | AI15: 313344 | AJ15: GlobalKey | AO15: Miguel António Pereira de Medeiros | AP15: Portugal | AT15: medeirosmig@gmail.com | AU15: 930498457 | AX15: =AY15*K15 -> 334861.8 | AY15: 2730
A16: 15 | B16: H3A | C16: O | D16: T3 | E16: 4 | F16: S/E | G16: 116.2 | H16: 16.6 | K16: =G16+0.3*H16+0.2*I16+0.2*J16 -> 121.18 | L16: 2 | P16: 1 | Q16: CPCV | S16: 410000 | T16: 387000 | U16: 387000 | V16: =0.96*W16 -> 393600 | W16: 410000 | X16: =1-(S16/W16) -> 0 | Y16: =S16/K16 -> 3383.3966 | Z16: =V16/K16 -> 3248.0607 | AA16: =W16/K16 -> 3383.3966 | AC16: 45686 | AD16: 82000 | AI16: 328000 | AJ16: ChaveNova | AO16: Oleg Mikhailov | AP16: Russia | AU16: 913924704 | AX16: =AY16*K16 -> 330821.4 | AY16: 2730
A17: 16 | B17: H3A | C17: P | D17: T2 | E17: 4 | F17: N/W | G17: 86.5 | H17: 55 | K17: =G17+0.2*H17+0.2*I17+0.2*J17 -> 97.5 | L17: 1 | P17: - | Q17: CPCV | R17: YES | S17: 308160 | T17: 309000 | U17: 321000 | V17: =0.96*W17 -> 308160 | W17: 321000 | X17: =1-(S17/W17) -> 0.04 | Y17: =S17/K17 -> 3160.6154 | Z17: =V17/K17 -> 3160.6154 | AA17: =W17/K17 -> 3292.3077 | AC17: 45369 | AD17: =56632+5000 -> 61632 | AI17: 246528 | AJ17: GlobalKey | AO17: Pedro Miguel Barbos da Costa | AP17: Portugal | AT17: pedro.barbosa.rh@hotmail.com | AU17: 932110134 | AX17: =AY17*K17 -> 266175 | AY17: 2730 | AZ17: 378000
A18: 17 | B18: H3A | C18: Q | D18: T1 | E18: 4 | F18: W | G18: 62.4 | H18: 25.2 | K18: =G18+0.2*H18+0.2*I18+0.2*J18 -> 67.44 | L18: 1 | P18: - | Q18: CPCV | R18: YES | S18: 236160 | T18: 218000 | U18: 236000 | V18: 236000 | W18: 246000 | X18: =1-(S18/W18) -> 0.04 | Y18: =S18/K18 -> 3501.7794 | Z18: =V18/K18 -> 3499.4069 | AA18: =W18/K18 -> 3647.6868 | AB18: 45352 | AC18: 45369 | AD18: =5000+42232 -> 47232 | AI18: 188928 | AJ18: GlobalKey | AO18: HORA EXTRA CLUB UNIPESSOAL | AP18: Portugal | AT18: horaextra.club@gmail.com | AU18: 914400000 | AX18: =AY18*K18 -> 184111.2 | AY18: 2730
A19: 18 | B19: H3A | C19: R | D19: T2 | E19: 4 | F19: S/W | G19: 85.6 | H19: 52.8 | K19: =G19+0.2*H19+0.2*I19+0.2*J19 -> 96.16 | L19: 1 | P19: 1 | Q19: CPCV | S19: 331200 | T19: 312000 | U19: 325000 | V19: =0.96*W19 -> 331200 | W19: 345000 | X19: =1-(S19/W19) -> 0.04 | Y19: =S19/K19 -> 3444.2596 | Z19: =V19/K19 -> 3444.2596 | AA19: =W19/K19 -> 3587.7704 | AC19: 45583 | AD19: 66240 | AI19: 264960 | AJ19: GlobalKey | AO19: Maria Madalena de Azevedo Sousa | AP19: Portugal | AT19: mariamadalenasousa@gmail.com | AU19: 917833757 | AX19: =AY19*K19 -> 262516.8 | AY19: 2730
A20: 19 | B20: H3A | C20: S | D20: T3 | E20: 5 | F20: N/E | G20: 116.3 | H20: 21.2 | K20: =G20+0.3*H20+0.2*I20+0.2*J20 -> 122.66 | L20: 2 | Q20: CPCV | S20: 396480 | T20: 389000 | U20: 389000 | V20: =0.96*W20 -> 396480 | W20: 413000 | X20: =1-(S20/W20) -> 0.04 | Y20: =S20/K20 -> 3232.3496 | Z20: =V20/K20 -> 3232.3496 | AA20: =W20/K20 -> 3367.0308 | AC20: 45742 | AD20: =20%*S20 -> 79296 | AI20: =80%*S20 -> 317184 | AJ20: GlobalKey | AO20: Serguei Popov | AP20: Russia | AX20: =AY20*K20 -> 334861.8 | AY20: 2730
A21: 20 | B21: H3A | C21: T | D21: T3 | E21: 5 | F21: S/E | G21: 116.2 | H21: 16.6 | K21: =G21+0.3*H21+0.2*I21+0.2*J21 -> 121.18 | L21: 2 | P21: 1 | Q21: CPCV | S21: 398400 | T21: 392000 | U21: 392000 | V21: =0.96*W21 -> 398400 | W21: 415000 | X21: =1-(S21/W21) -> 0.04 | Y21: =S21/K21 -> 3287.6712 | Z21: =V21/K21 -> 3287.6712 | AA21: =W21/K21 -> 3424.6575 | AC21: 45646 | AD21: 39840 | AE21: 39840 | AF21: =AC21+185 -> 45831 | AI21: 318720 | AJ21: ChaveNova | AO21: Tiago Miguel Ferreira Cardoso | AP21: Portugal | AT21: tiagomfcardoso@gmail.com | AU21: 914585868 | AX21: =AY21*K21 -> 330821.4 | AY21: 2730
A22: 21 | B22: H3A | C22: U | D22: T2 | E22: 5 | F22: N/W | G22: 86.5 | H22: 55 | K22: =G22+0.2*H22+0.2*I22+0.2*J22 -> 97.5 | L22: 1 | P22: - | Q22: CPCV | R22: YES | S22: 301440 | T22: 314000 | U22: 314000 | V22: =0.96*W22 -> 301440 | W22: 314000 | X22: =1-(S22/W22) -> 0.04 | Y22: =S22/K22 -> 3091.6923 | Z22: =V22/K22 -> 3091.6923 | AA22: =W22/K22 -> 3220.5128 | AC22: 45379 | AD22: 60288 | AI22: 241152 | AJ22: GlobalKey | AO22: HB Design | AP22: Portugal | AT22: hb@hbdesignbrands.com | AU22: 917427956 | AX22: =AY22*K22 -> 266175 | AY22: 2730
A23: 22 | B23: H3A | C23: V | D23: T1 | E23: 5 | F23: W | G23: 62.4 | H23: 25.2 | K23: =G23+0.2*H23+0.2*I23+0.2*J23 -> 67.44 | L23: 1 | P23: - | Q23: CPCV | R23: YES | S23: 215040 | T23: 224000 | U23: 224000 | V23: =0.96*W23 -> 215040 | W23: 224000 | X23: =1-(S23/W23) -> 0.04 | Y23: =S23/K23 -> 3188.6121 | Z23: =V23/K23 -> 3188.6121 | AA23: =W23/K23 -> 3321.4709 | AC23: 45365 | AD23: 43008 | AI23: 172032 | AJ23: ChaveNova | AO23: nÚMEROS100ACENTO | AP23: Portugal | AT23: jcastrogreat@gmail.com | AU23: 968032204 | AX23: =AY23*K23 -> 184111.2 | AY23: 2730
A24: 23 | B24: H3A | C24: W | D24: T2 | E24: 5 | F24: S/W | G24: 85.6 | H24: 52.8 | K24: =G24+0.2*H24+0.2*I24+0.2*J24 -> 96.16 | L24: 1 | P24: 1 | Q24: CPCV | R24: YES | S24: 336000 | T24: 317000 | U24: 330000 | V24: =0.96*W24 -> 336000 | W24: 350000 | X24: =1-(S24/W24) -> 0.04 | Y24: =S24/K24 -> 3494.1764 | Z24: =V24/K24 -> 3494.1764 | AA24: =W24/K24 -> 3639.7671 | AC24: 45439 | AD24: 67200 | AI24: 268800 | AJ24: ChaveNova | AO24: José Maria Duarte Vieira Lobo de Albuquerque & Bianca Couto da Silva Oliveira | AX24: =AY24*K24 -> 262516.8 | AY24: 2730
A25: 24 | B25: H3A | C25: X | D25: T3 | E25: 6 | F25: N/E | G25: 116.3 | H25: 21.2 | K25: =G25+0.3*H25+0.2*I25+0.2*J25 -> 122.66 | L25: 2 | P25: 1 | Q25: CPCV | S25: 401280 | T25: 394000 | U25: 394000 | V25: =0.96*W25 -> 401280 | W25: 418000 | X25: =1-(S25/W25) -> 0.04 | Y25: =S25/K25 -> 3271.4821 | Z25: =V25/K25 -> 3271.4821 | AA25: =W25/K25 -> 3407.7939 | AB25: 45496 | AC25: 45498 | AD25: 40128 | AI25: 361152 | AJ25: GlobalKey | AO25: Vítor Valente . Projectos e Empreendimentos LDA | AP25: Portugal | AT25: paula.romao.prof@gmail.com | AU25: 962058589 | AX25: =AY25*K25 -> 334861.8 | AY25: 2730
A26: 25 | B26: H3A | C26: Y | D26: T3 | E26: 6 | F26: S/E | G26: 116.2 | H26: 16.6 | K26: =G26+0.3*H26+0.2*I26+0.2*J26 -> 121.18 | L26: 2 | P26: 1 | Q26: CPCV | S26: 404160 | T26: 397000 | U26: 397000 | V26: =0.96*W26 -> 404160 | W26: 421000 | X26: =1-(S26/W26) -> 0.04 | Y26: =S26/K26 -> 3335.2038 | Z26: =V26/K26 -> 3335.2038 | AA26: =W26/K26 -> 3474.1707 | AC26: 45421 | AD26: =20%*S26 -> 80832 | AI26: =80%*S26 -> 323328 | AJ26: GlobalKey | AO26: Maria Luísa Ferreira Campos | AP26: Portugal | AT26: luisacampos@hotmail.com | AU26: 918584205 | AX26: =AY26*K26 -> 330821.4 | AY26: 2730
A27: 26 | B27: H3A | C27: Z | D27: T2 | E27: 6 | F27: N/W | G27: 86.5 | H27: 55 | K27: =G27+0.2*H27+0.2*I27+0.2*J27 -> 97.5 | L27: 1 | P27: - | Q27: CPCV | R27: YES | S27: 306240 | T27: 319000 | U27: 319000 | V27: =0.96*W27 -> 306240 | W27: 319000 | X27: =1-(S27/W27) -> 0.04 | Y27: =S27/K27 -> 3140.9231 | Z27: =V27/K27 -> 3140.9231 | AA27: =W27/K27 -> 3271.7949 | AC27: 45379 | AD27: 61248 | AI27: 244992 | AJ27: GlobalKey | AO27: HB Design | AP27: Portugal | AT27: - | AU27: 917427956 | AX27: =AY27*K27 -> 266175 | AY27: 2730
A28: 27 | B28: H3A | C28: AA | D28: T1 | E28: 6 | F28: W | G28: 62.4 | H28: 25.2 | K28: =G28+0.2*H28+0.2*I28+0.2*J28 -> 67.44 | L28: 1 | P28: - | Q28: CPCV | S28: 242880 | T28: 229000 | U28: 243000 | V28: =0.96*W28 -> 242880 | W28: 253000 | X28: =1-(S28/W28) -> 0.04 | Y28: =S28/K28 -> 3601.4235 | Z28: =V28/K28 -> 3601.4235 | AA28: =W28/K28 -> 3751.4828 | AB28: 45352 | AC28: 45369 | AD28: =5000+43576 -> 48576 | AI28: 194304 | AJ28: GlobalKey | AO28: HORA EXTRA CLUB UNIPESSOAL | AP28: Portugal | AT28: horaextra.club@gmail.com | AU28: 914400000 | AX28: =AY28*K28 -> 184111.2 | AY28: 2730
A29: 28 | B29: H3A | C29: AB | D29: T2 | E29: 6 | F29: S/W | G29: 85.6 | H29: 52.8 | K29: =G29+0.2*H29+0.2*I29+0.2*J29 -> 96.16 | L29: 1 | P29: 1 | Q29: CPCV | S29: 340800 | T29: 322000 | U29: 335000 | V29: =0.96*W29 -> 340800 | W29: 355000 | X29: =1-(S29/W29) -> 0.04 | Y29: =S29/K29 -> 3544.0932 | Z29: =V29/K29 -> 3544.0932 | AA29: =W29/K29 -> 3691.7637 | AC29: 45449 | AD29: 68160 | AI29: 272640 | AJ29: GlobalKey | AO29: Maria José Teixeira Passos Moura | AP29: Portugal | AT29: mjtpmoura@gmail.com | AU29: 962639135 | AX29: =AY29*K29 -> 262516.8 | AY29: 2730
A30: 29 | B30: H3A | C30: AC | D30: T4 | E30: 7 | F30: N/E/W | G30: 173 | J30: 110.8 | K30: =G30+0.2*H30+0.2*I30+0.3*J30 -> 206.24 | L30: (Box2+1)=3 | Q30: CPCV | S30: 658560 | T30: 686000 | U30: 686000 | V30: =0.96*W30 -> 658560 | W30: 686000 | X30: =1-(S30/W30) -> 0.04 | Y30: =S30/K30 -> 3193.173 | Z30: =V30/K30 -> 3193.173 | AA30: =W30/K30 -> 3326.2219 | AC30: 45496 | AD30: 136712 | AI30: 526848 | AJ30: GlobalKey | AO30: Luís Manuel Duarte Azevedo / Maria Alina Alves de Almeida Azevedo | AP30: Portugal | AT30: idazevedo@imda.pt | AU30: 933338099 | AX30: =AY30*K30 -> 563035.2 | AY30: 2730
A31: 30 | B31: H3A | C31: AD | D31: T4 | E31: 7 | F31: S/E/W | G31: 173 | J31: 110.8 | K31: =G31+0.2*H31+0.2*I31+0.3*J31 -> 206.24 | L31: (Box2+1)=3 | Q31: CPCV | R31: YES | S31: 658560 | T31: 686000 | U31: 686000 | V31: =0.96*W31 -> 658560 | W31: 686000 | X31: =1-(S31/W31) -> 0.04 | Y31: =S31/K31 -> 3193.173 | Z31: =V31/K31 -> 3193.173 | AA31: =W31/K31 -> 3326.2219 | AC31: 45370 | AD31: =126712+5000 -> 131712 | AI31: 526848 | AJ31: GlobalKey | AO31: Joaquim Fernando Pereira Carvalho | AP31: Portugal | AT31: carvalho1951@gmail.com | AU31: 917219495 | AX31: =AY31*K31 -> 563035.2 | AY31: 2730
A32: 31 | B32: H3B | C32: AE | D32: T2 | E32: 1 | F32: N/E/W | G32: 100.4 | I32: =9.7+34.1 -> 43.8 | K32: =G32+0.2*H32+0.2*I32+0.2*J32 -> 109.16 | L32: 1 | P32: - | Q32: CPCV | S32: 324480 | T32: 307000 | U32: 319000 | V32: =0.96*W32 -> 324480 | W32: 338000 | X32: =1-(S32/W32) -> 0.04 | Y32: =S32/K32 -> 2972.5174 | Z32: =V32/K32 -> 2972.5174 | AA32: =W32/K32 -> 3096.3723 | AB32: 45409 | AC32: 45471 | AD32: 64896 | AI32: 259584 | AJ32: GlobalKey | AO32: Casa Meneses - Sociedade de empreendimentos turísticos LDA | AP32: Portugal | AT32: andremeneses@selectadivison.pt | AU32: 913006949 | AX32: =AY32*K32 -> 298006.8 | AY32: 2730
A33: 32 | B33: H3B | C33: AF | D33: T2 | E33: 1 | F33: E | G33: 90.9 | I33: 28.4 | K33: =G33+0.2*H33+0.2*I33+0.2*J33 -> 96.58 | L33: 1 | P33: - | Q33: CPCV | S33: 281280 | T33: 265000 | U33: 276000 | V33: =0.96*W33 -> 281280 | W33: 293000 | X33: =1-(S33/W33) -> 0.04 | Y33: =S33/K33 -> 2912.4042 | Z33: =V33/K33 -> 2912.4042 | AA33: =W33/K33 -> 3033.7544 | AC33: 45471 | AD33: 56256 | AI33: 225024 | AJ33: GlobalKey | AO33: Casa Agrícola Meneses LDA | AP33: Portugal | AX33: =AY33*K33 -> 263663.4 | AY33: 2730
A34: 33 | B34: H3B | C34: AG | D34: T2 | E34: 1 | F34: W | G34: 84.4 | I34: 60.2 | K34: =G34+0.2*H34+0.2*I34+0.2*J34 -> 96.44 | L34: 1 | P34: - | Q34: CPCV | S34: 275520 | T34: 276000 | U34: 287000 | V34: =0.96*W34 -> 275520 | W34: 287000 | X34: =1-(S34/W34) -> 0.04 | Y34: =S34/K34 -> 2856.9058 | Z34: =V34/K34 -> 2856.9058 | AA34: =W34/K34 -> 2975.9436 | AB34: 45350 | AC34: 45376 | AD34: 55104 | AI34: 220416 | AJ34: GlobalKey | AO34: Vítor Valente . Projectos e Empreendimentos LDA | AP34: Portugal | AT34: mouravalente@gmail.com | AU34: 963023090 | AX34: =AY34*K34 -> 263281.2 | AY34: 2730
A35: 34 | B35: H3B | C35: AH | D35: T2 | E35: 1 | F35: W | G35: 85.9 | I35: 62.5 | K35: =G35+0.2*H35+0.2*I35+0.2*J35 -> 98.4 | L35: 1 | P35: - | Q35: CPCV | S35: 289000 | T35: 278000 | U35: 289000 | V35: =0.96*W35 -> 294720 | W35: 307000 | X35: =1-(S35/W35) -> 0.058631922 | Y35: =S35/K35 -> 2936.9919 | Z35: =V35/K35 -> 2995.122 | AA35: =W35/K35 -> 3119.9187 | AB35: 45370 | AC35: 45378 | AD35: =20%*S35 -> 57800 | AI35: =80%*S35 -> 231200 | AJ35: Chavenova | AO35: Pinto Ferreira ORL, Lda | AP35: Portugal | AU35: 919734623 | AX35: =AY35*K35 -> 268632 | AY35: 2730
A36: 35 | B36: H3B | C36: AI | D36: T2 | E36: 2 | F36: N/E/W | G36: 103.8 | H36: 74.3 | K36: =G36+0.2*H36+0.2*I36+0.2*J36 -> 118.66 | L36: 1 | P36: - | Q36: CPCV | S36: 368640 | T36: 348000 | U36: 362000 | V36: =0.96*W36 -> 368640 | W36: 384000 | X36: =1-(S36/W36) -> 0.04 | Y36: =S36/K36 -> 3106.6914 | Z36: =V36/K36 -> 3106.6914 | AA36: =W36/K36 -> 3236.1369 | AB36: 45478 | AC36: 45504 | AD36: 73728 | AI36: 294912 | AJ36: GlobalKey | AO36: Ana Paula Conceição Alves & ANTÓNIO Júlio Pereira Mendes | AP36: Portugal | AT36: paula.truck@gmail.com | AU36: 939947609 | AX36: =AY36*K36 -> 323941.8 | AY36: 2730
A37: 36 | B37: H3B | C37: AJ | D37: T3 | E37: 2 | F37: S/E | G37: 116.1 | H37: 53.2 | K37: =G37+0.2*H37+0.2*I37+0.2*J37 -> 126.74 | L37: 2 | P37: 1 | Q37: CPCV | S37: 400000 | T37: 392000 | U37: 392000 | V37: =0.96*W37 -> 399360 | W37: 416000 | X37: 0 | Y37: =S37/K37 -> 3156.0675 | Z37: =V37/K37 -> 3151.0178 | AA37: =W37/K37 -> 3282.3102 | AB37: 45701 | AC37: 45744 | AD37: =5000+75000 -> 80000 | AI37: 320000 | AJ37: GlobalKey | AO37: Diogo Figueiredo Moniz de Figueiredo Costa | AP37: Portugal | AT37: diogofmfc90@gmail.com | AU37: 917368073 | AX37: =AY37*K37 -> 346000.2 | AY37: 2730
A38: 37 | B38: H3B | C38: AK | D38: T2 | E38: 2 | F38: W | G38: 84.6 | H38: 32.3 | K38: =G38+0.2*H38+0.2*I38+0.2*J38 -> 91.06 | L38: 1 | P38: - | Q38: CPCV | S38: 335040 | T38: 304000 | U38: 329000 | V38: =0.96*W38 -> 335040 | W38: 349000 | X38: =1-(S38/W38) -> 0.04 | Y38: =S38/K38 -> 3679.3323 | Z38: =V38/K38 -> 3679.3323 | AA38: =W38/K38 -> 3832.6378 | AB38: 45546 | AC38: 45559 | AD38: 67008 | AI38: 268032 | AJ38: GlobalKey | AO38: Maria do Céu e aSousa de Oliveira Maia | AP38: Portugal | AT38: maiaceu1@gmail.com | AU38: 919692924 | AX38: =AY38*K38 -> 248593.8 | AY38: 2730
A39: 38 | B39: H3B | C39: AL | D39: T2 | E39: 2 | F39: S/W | G39: 85.8 | H39: 54.7 | K39: =G39+0.2*H39+0.2*I39+0.2*J39 -> 96.74 | L39: 1 | P39: - | Q39: CPCV | S39: 312000 | T39: 312000 | U39: 325000 | V39: =0.96*W39 -> 312000 | W39: 325000 | X39: =1-(S39/W39) -> 0.04 | Y39: =S39/K39 -> 3225.1395 | Z39: =V39/K39 -> 3225.1395 | AA39: =W39/K39 -> 3359.5204 | AB39: 45340 | AC39: 45373 | AD39: 62400 | AI39: 249600 | AJ39: GlobalKey | AO39: Ricardo Jorge Loureiro da Silva Unipessoal & Tiago André Duarte Barata Santos Gomes | AP39: Portugal | AT39: ricardojls@hotmail.com | AU39: 919180952 | AX39: =AY39*K39 -> 264100.2 | AY39: 2730 | AZ39: 355000
A40: 39 | B40: H3B | C40: AM | D40: T4 | E40: 3 | F40: N/E/W | G40: 155.9 | H40: 83.4 | K40: =G40+0.2*H40+0.2*I40+0.2*J40 -> 172.58 | L40: (Box2+1)=3 | Q40: CPCV | S40: 569280 | T40: 593000 | U40: 593000 | V40: =0.96*W40 -> 569280 | W40: 593000 | X40: =1-(S40/W40) -> 0.04 | Y40: =S40/K40 -> 3298.6441 | Z40: =V40/K40 -> 3298.6441 | AA40: =W40/K40 -> 3436.0876 | AB40: 45540 | AC40: 45555 | AD40: 113856 | AI40: 455424 | AJ40: GlobalKey | AO40: Rui Miguel Nogueira da Silva e Sousa | AP40: Portugal | AT40: ruisousa_7@hotmail.com | AU40: 919480502 | AX40: =AY40*K40 -> 471143.4 | AY40: 2730
A41: 40 | B41: H3B | C41: AN | D41: T3 | E41: 3 | F41: S/E | G41: 116 | H41: 16.6 | K41: =G41+0.3*H41+0.2*I41+0.2*J41 -> 120.98 | L41: 2 | P41: 1 | Q41: CPCV | S41: 392350 | T41: 389000 | U41: 389000 | V41: =0.96*W41 -> 396480 | W41: 413000 | X41: =1-(S41/W41) -> 0.05 | Y41: =S41/K41 -> 3243.098 | Z41: =V41/K41 -> 3277.2359 | AA41: =W41/K41 -> 3413.7874 | AC41: 45625 | AD41: 78470 | AI41: 313880 | AJ41: GlobalKey | AO41: Rui de Lemos Monteiro | AP41: Portugal | AU41: 917225875 | AX41: =AY41*K41 -> 330275.4 | AY41: 2730
A42: 41 | B42: H3B | C42: AO | D42: T1 | E42: 3 | F42: W | G42: 63.4 | H42: 25.1 | K42: =G42+0.2*H42+0.2*I42+0.2*J42 -> 68.42 | L42: 1 | P42: - | Q42: CPCV | S42: 238080 | T42: 234000 | U42: 248000 | V42: =0.96*W42 -> 238080 | W42: 248000 | X42: =1-(S42/W42) -> 0.04 | Y42: =S42/K42 -> 3479.6843 | Z42: =V42/K42 -> 3479.6843 | AA42: =W42/K42 -> 3624.6711 | AB42: 45349 | AC42: 45385 | AD42: =20%*V42 -> 47616 | AI42: =80%*V42 -> 190464 | AJ42: GlobalKey | AO42: Fercobar - Sociedade Imobiliária Lda | AP42: Portugal | AT42: hsilva@ferbar.com | AU42: 229438100 | AX42: =AY42*K42 -> 186786.6 | AY42: 2730
A43: 42 | B43: H3B | C43: AP | D43: T2 | E43: 3 | F43: S/W | G43: 86.6 | H43: 52.7 | K43: =G43+0.2*H43+0.2*I43+0.2*J43 -> 97.14 | L43: 1 | P43: 1 | Q43: CPCV | S43: 355200 | T43: 335000 | U43: 349000 | V43: =0.96*W43 -> 355200 | W43: 370000 | X43: =1-(S43/W43) -> 0.04 | Y43: =S43/K43 -> 3656.5781 | Z43: =V43/K43 -> 3656.5781 | AA43: =W43/K43 -> 3808.9356 | AB43: 45441 | AC43: 45441 | AD43: 71040 | AI43: 284160 | AJ43: Chavenova | AO43: Mafalda Pires Leão Martins Cardoso & Fernando Valter da Silva Cardoso e Luís Maria Pires Leão Martins Cardoso | AP43: Portugal | AU43: 919106928 | AX43: =AY43*K43 -> 265192.2 | AY43: 2730
A44: 43 | B44: H3B | C44: AQ | D44: T4 | E44: 4 | F44: N/E/W | G44: 155.9 | H44: 83.4 | K44: =G44+0.2*H44+0.2*I44+0.2*J44 -> 172.58 | L44: (Box2+1)=3 | Q44: CPCV | S44: 574080 | T44: 598000 | U44: 598000 | V44: =0.96*W44 -> 574080 | W44: 598000 | X44: =1-(S44/W44) -> 0.04 | Y44: =S44/K44 -> 3326.4573 | Z44: =V44/K44 -> 3326.4573 | AA44: =W44/K44 -> 3465.0597 | AC44: 45516 | AD44: =5000+81112 -> 86112 | AI44: 487968 | AJ44: Globalkey | AO44: Fernando Joaquim da Silva Bispo & Paula Araújo e Melo | AP44: Portugal | AT44: fsbispo@hotmail.com | AU44: 938015022 | AX44: =AY44*K44 -> 471143.4 | AY44: 2730
A45: 44 | B45: H3B | C45: AR | D45: T3 | E45: 4 | F45: S/E | G45: 116 | H45: 16.6 | K45: =G45+0.3*H45+0.2*I45+0.2*J45 -> 120.98 | L45: 2 | P45: 1 | Q45: CPCV | S45: 401280 | T45: 394000 | U45: 394000 | V45: =0.96*W45 -> 401280 | W45: 418000 | X45: =1-(S45/W45) -> 0.04 | Y45: =S45/K45 -> 3316.9119 | Z45: =V45/K45 -> 3316.9119 | AA45: =W45/K45 -> 3455.1165 | AC45: 45574 | AD45: =5000+75256 -> 80256 | AI45: 321024 | AJ45: Globalkey | AK45: José G. | AO45: Pragmatic Scale Lda. | AP45: Portugal | AT45: sara_silvago@hotmail.com | AU45: 966902483 | AX45: =AY45*K45 -> 330275.4 | AY45: 2730
A46: 45 | B46: H3B | C46: AS | D46: T1 | E46: 4 | F46: W | G46: 63.4 | H46: 25.1 | K46: =G46+0.2*H46+0.2*I46+0.2*J46 -> 68.42 | L46: 1 | P46: - | Q46: CPCV | S46: 248000 | T46: 239000 | U46: 254000 | V46: =0.96*W46 -> 243840 | W46: 254000 | X46: =1-(S46/W46) -> 0.023622047 | Y46: =S46/K46 -> 3624.6711 | Z46: =V46/K46 -> 3563.8702 | AA46: =W46/K46 -> 3712.3648 | AB46: 45349 | AC46: 45512 | AD46: 49600 | AI46: 198400 | AJ46: Tranquildiscovery | AK46: Matan | AO46: Osnat Zeiman & Elimelech Zeiman | AP46: Israel | AT46: ziman1964@gmail.com | AU46: 972508801816 | AX46: =AY46*K46 -> 186786.6 | AY46: 2730
A47: 46 | B47: H3B | C47: AT | D47: T2 | E47: 4 | F47: S/W | G47: 86.6 | H47: 52.7 | K47: =G47+0.2*H47+0.2*I47+0.2*J47 -> 97.14 | L47: 1 | P47: 1 | Q47: CPCV | S47: 332000 | T47: 345000 | U47: 345000 | V47: =0.96*W47 -> 331200 | W47: 345000 | X47: =1-(S47/W47) -> 0.037681159 | Y47: =S47/K47 -> 3417.7476 | Z47: =V47/K47 -> 3409.512 | AA47: =W47/K47 -> 3551.575 | AC47: 45456 | AD47: 66400 | AI47: 265600 | AJ47: Tranquildiscovery | AK47: Tzafrir | AO47: Israel Barda & Shay Adar | AP47: Israel | AT47: linecomn@gmail.com | AU47: 972509009099 | AX47: =AY47*K47 -> 265192.2 | AY47: 2730
A48: 47 | B48: H3B | C48: AU | D48: T4 | E48: 5 | F48: N/E/W | G48: 155.9 | H48: 83.4 | K48: =G48+0.2*H48+0.2*I48+0.2*J48 -> 172.58 | L48: (Box2+1)=3 | Q48: CPCV | S48: 578880 | T48: 603000 | U48: 603000 | V48: =0.96*W48 -> 578880 | W48: 603000 | X48: =1-(S48/W48) -> 0.04 | Y48: =S48/K48 -> 3354.2705 | Z48: =V48/K48 -> 3354.2705 | AA48: =W48/K48 -> 3494.0318 | AB48: 45470 | AC48: 45526 | AD48: =20%*S48 -> 115776 | AI48: =80%*S48 -> 463104 | AJ48: Chavenova | AO48: Igor Ferreira Quinan & Cidália de Fátima Ribeiro Peixoto | AP48: Brazil | AT48: igorquinan@gmail.com | AU48: 867967280 | AX48: =AY48*K48 -> 471143.4 | AY48: 2730
A49: 48 | B49: H3B | C49: AV | D49: T3 | E49: 5 | F49: S/E | G49: 116 | H49: 16.6 | K49: =G49+0.3*H49+0.2*I49+0.2*J49 -> 120.98 | L49: 2 | P49: 1 | Q49: CPCV | S49: 406000 | T49: 399000 | U49: 399000 | V49: =0.96*W49 -> 406080 | W49: 423000 | X49: =1-(S49/W49) -> 0.040189125 | Y49: =S49/K49 -> 3355.9266 | Z49: =V49/K49 -> 3356.5879 | AA49: =W49/K49 -> 3496.4457 | AC49: 45439 | AD49: 81200 | AI49: 324800 | AJ49: GlobalKey | AO49: José Paulo Esteves da Cunha | AP49: Portugal | AX49: =AY49*K49 -> 330275.4 | AY49: 2730
A50: 49 | B50: H3B | C50: AW | D50: T1 | E50: 5 | F50: W | G50: 63.4 | H50: 25.1 | K50: =G50+0.2*H50+0.2*I50+0.2*J50 -> 68.42 | L50: 1 | P50: - | Q50: CPCV | S50: 248640 | T50: 244000 | U50: 259000 | V50: =0.96*W50 -> 248640 | W50: 259000 | X50: =1-(S50/W50) -> 0.04 | Y50: =S50/K50 -> 3634.0251 | Z50: =V50/K50 -> 3634.0251 | AA50: =W50/K50 -> 3785.4429 | AB50: 45349 | AC50: 45385 | AD50: =20%*V50 -> 49728 | AI50: =80%*V50 -> 198912 | AJ50: GlobalKey | AO50: Fercobar - Sociedade Imobiliária Lda | AP50: Portugal | AX50: =AY50*K50 -> 186786.6 | AY50: 2730
A51: 50 | B51: H3B | C51: AX | D51: T2 | E51: 5 | F51: S/W | G51: 86.6 | H51: 52.7 | K51: =G51+0.2*H51+0.2*I51+0.2*J51 -> 97.14 | L51: 1 | P51: 1 | Q51: CPCV | S51: 376320 | T51: 355000 | U51: 369000 | V51: =0.96*W51 -> 376320 | W51: 392000 | X51: =1-(S51/W51) -> 0.04 | Y51: =S51/K51 -> 3873.9963 | Z51: =V51/K51 -> 3873.9963 | AA51: =W51/K51 -> 4035.4128 | AB51: 45509 | AC51: 45531 | AD51: 75264 | AI51: 301056 | AJ51: GlobalKey | AO51: Maria Campos Maia | AP51: Portugal | AT51: emiliamaria@gmail.com | AU51: 963458001 | AX51: =AY51*K51 -> 265192.2 | AY51: 2730
A52: 51 | B52: H3B | C52: AY | D52: T4 | E52: 6 | F52: N/E/W | G52: 155.9 | H52: 83.4 | K52: =G52+0.2*H52+0.2*I52+0.2*J52 -> 172.58 | L52: (Box2+1)=3 | Q52: CPCV | S52: 583680 | T52: 608000 | U52: 608000 | V52: =0.96*W52 -> 583680 | W52: 608000 | X52: =1-(S52/W52) -> 0.04 | Y52: =S52/K52 -> 3382.0837 | Z52: =V52/K52 -> 3382.0837 | AA52: =W52/K52 -> 3523.0038 | AC52: 45425 | AD52: =20%*S52 -> 116736 | AI52: =80%*S52 -> 466944 | AJ52: GlobalKey | AO52: Paralelus 2000 LDA | AP52: Portugal | AX52: =AY52*K52 -> 471143.4 | AY52: 2730
A53: 52 | B53: H3B | C53: AZ | D53: T3 | E53: 6 | F53: S/E | G53: 116 | H53: 16.6 | K53: =G53+0.3*H53+0.2*I53+0.2*J53 -> 120.98 | L53: 2 | P53: 1 | Q53: CPCV | S53: 406600 | T53: 404000 | U53: 404000 | V53: =0.96*W53 -> 410880 | W53: 428000 | X53: =1-(S53/W53) -> 0.05 | Y53: =S53/K53 -> 3360.8861 | Z53: =V53/K53 -> 3396.2638 | AA53: =W53/K53 -> 3537.7748 | AB53: 45497 | AC53: 45625 | AD53: =20%*S53 -> 81320 | AI53: =80%*S53 -> 325280 | AJ53: GlobalKey | AO53: Rui de Lemos Monteiro | AP53: Portugal | AU53: 917225875 | AX53: =AY53*K53 -> 330275.4 | AY53: 2730
A54: 53 | B54: H3B | C54: BA | D54: T1 | E54: 6 | F54: W | G54: 63.4 | H54: 25.1 | K54: =G54+0.2*H54+0.2*I54+0.2*J54 -> 68.42 | L54: 1 | P54: - | Q54: CPCV | R54: YES | S54: 240000 | T54: 250000 | U54: 250000 | V54: =0.96*W54 -> 240000 | W54: 250000 | X54: =1-(S54/W54) -> 0.04 | Y54: =S54/K54 -> 3507.7463 | Z54: =V54/K54 -> 3507.7463 | AA54: =W54/K54 -> 3653.9024 | AC54: 45385 | AD54: =20%*S54 -> 48000 | AI54: =80%*S54 -> 192000 | AJ54: Chavenova | AO54: António Sá da Cunha | AP54: Venezuela | AU54: 962011245 | AX54: =AY54*K54 -> 186786.6 | AY54: 2730
A55: 54 | B55: H3B | C55: BB | D55: T2 | E55: 6 | F55: S/W | G55: 86.6 | H55: 52.7 | K55: =G55+0.2*H55+0.2*I55+0.2*J55 -> 97.14 | L55: 1 | P55: 1 | Q55: CPCV | S55: 280486 | T55: 365000 | U55: 380000 | V55: =0.96*W55 -> 364800 | W55: 380000 | X55: =1-(S55/W55) -> 0.26187895 | Y55: =S55/K55 -> 2887.4408 | Z55: =V55/K55 -> 3755.4046 | AA55: =W55/K55 -> 3911.8798 | AB55: 45349 | AC55: 45481 | AD55: =10%*S55 -> 28048.6 | AI55: =90%*S55 -> 252437.4 | AJ55: Tranquildiscovery | AK55: Tzafrir | AO55: Catarina Gonçalves Barrias | AP55: Portugal | AT55: catarina.barrias@outlook.com | AU55: 915273173 | AX55: =AY55*K55 -> 265192.2 | AY55: 2730 | AZ55: 369500
A56: 55 | B56: H3B | C56: BC | D56: T3 | E56: 7 | F56: N/E/W | G56: 133.7 | J56: 98.2 | K56: =G56+0.3*H56+0.2*I56+0.3*J56 -> 163.16 | L56: (Box2+1)=3 | Q56: CPCV | R56: YES | S56: =0.91*V56 -> 489216 | T56: 560000 | U56: 560000 | V56: =0.96*W56 -> 537600 | W56: 560000 | X56: =1-(S56/W56) -> 0.1264 | Y56: =S56/K56 -> 2998.382 | Z56: =V56/K56 -> 3294.9252 | AA56: =W56/K56 -> 3432.2138 | AC56: 45387 | AD56: 48921.6 | AI56: 440294.4 | AJ56: Tranquildiscovery | AO56: Paulo Martins & Pedro Martins | AP56: Portugal | AT56: paulo.sousa.martins93@gmail.com | AU56: 914561545 | AX56: =AY56*K56 -> 445426.8 | AY56: 2730
A57: 56 | B57: H3B | C57: BD | D57: T4 | E57: 7 | F57: S/E/W | G57: 173 | J57: 110.7 | K57: =G57+0.2*H57+0.2*I57+0.3*J57 -> 206.21 | L57: (Box2+1)=3 | Q57: CPCV | S57: 765120 | T57: 738000 | U57: 738000 | V57: =0.96*W57 -> 765120 | W57: 797000 | X57: =1-(S57/W57) -> 0.04 | Y57: =S57/K57 -> 3710.3923 | Z57: =V57/K57 -> 3710.3923 | AA57: =W57/K57 -> 3864.992 | AB57: 45432 | AC57: 45505 | AD57: =10%*S57 -> 76512 | AE57: =10%*S57 -> 76512 | AF57: 45550 | AI57: =80%*S57 -> 612096 | AJ57: Chavenova | AO57: Medipere - Mediação de Seguros | AP57: Portugal | AU57: 918705711 | AX57: =AY57*K57 -> 562953.3 | AY57: 2730
G58: =SUM(G2:G57) -> 5784.1 | K58: =SUM(K2:K57) -> 6386.11 | V58: =SUM(V2:V57) -> 20936480 | W58: =SUM(W2:W57) -> 21809000
C60: # | D60: € | E60: €/m² | G60: RESERVATION SIGNED IN
A61: CPCV | C61: =COUNTIF(Q2:Q57,A61) -> 56 | D61: =SUMIF(Q2:Q57,A61,S2:S57) -> 20851972 | E61: =AVERAGEIF(Q2:Q57,A61,Y2:Y57) -> 3268.6119 | G61: 2024 | H61: =COUNTIFS(AC2:AC57,">="&DATE(2024,1,1),AC2:AC57,"<="&DATE(2024,12,31)) -> 50
A62: BLOCKED | C62: =COUNTIF(Q2:Q57,A62) -> 0 | D62: =SUMIF(Q2:Q57,A62,V2:V57) -> 0 | E62: =AVERAGEIF(Q2:Q57,A62,Z2:Z57) -> #DIV/0! | G62: 2025 | H62: =COUNTIFS(AC2:AC57,">="&DATE(2025,1,1),AC2:AC57,"<="&DATE(2025,12,31)) -> 6 | J62: CPCV 2024
A63: AVAILABLE | C63: =COUNTIF(Q2:Q57,"") -> 0 | D63: =SUMIF(Q2:Q57,"",V2:V57) -> 0 | E63: =AVERAGEIF(Q2:Q57,"",Z2:Z57) -> #DIV/0! | G63: 2026 | H63: =COUNTIFS(AC2:AC57,">="&DATE(2026,1,1),AC2:AC57,"<="&DATE(2026,12,31)) -> 0 | J63: January | K63: February | L63: March | M63: April | N63: May | O63: June | P63: July | Q63: August | R63: September | S63: October | T63: November | U63: December
A64: RESERVED | C64: =COUNTIF(Q2:Q57,A64) -> 0 | D64: =SUMIF(Q2:Q57,A64,S2:S57) -> 0 | E64: =AVERAGEIF(Q2:Q57,A64,Y2:Y57) -> #DIV/0! | J64: =COUNTIFS(AC2:AC57,">="&DATE(2024,1,1),AC2:AC57,"<="&DATE(2024,1,31)) -> 0 | K64: =COUNTIFS(AC2:AC57,">="&DATE(2024,2,1),AC2:AC57,"<="&DATE(2024,2,31)) -> 0 | L64: =COUNTIFS(AC2:AC57,">="&DATE(2024,3,1),AC2:AC57,"<="&DATE(2024,3,31)) -> 13 | M64: =COUNTIFS(AC2:AC57,">="&DATE(2024,4,1),AC2:AC57,"<="&DATE(2024,4,31)) -> 5 | N64: =COUNTIFS(AC2:AC57,">="&DATE(2024,5,1),AC2:AC57,"<="&DATE(2024,5,31)) -> 5 | O64: =COUNTIFS(AC2:AC57,">="&DATE(2024,6,1),AC2:AC57,"<="&DATE(2024,6,31)) -> 5 | P64: =COUNTIFS(AC2:AC57,">="&DATE(2024,7,1),AC2:AC57,"<="&DATE(2024,7,31)) -> 5 | Q64: =COUNTIFS(AC2:AC57,">="&DATE(2024,8,1),AC2:AC57,"<="&DATE(2024,8,31)) -> 5 | R64: =COUNTIFS(AC2:AC57,">="&DATE(2024,9,1),AC2:AC57,"<="&DATE(2024,9,31)) -> 4 | S64: =COUNTIFS(AC2:AC57,">="&DATE(2024,10,1),AC2:AC57,"<="&DATE(2024,10,31)) -> 4 | T64: =COUNTIFS(AC2:AC57,">="&DATE(2024,11,1),AC2:AC57,"<="&DATE(2024,11,31)) -> 2 | U64: =COUNTIFS(AC2:AC57,">="&DATE(2024,12,1),AC2:AC57,"<="&DATE(2024,12,31)) -> 2
A65: TOTAL | C65: =SUBTOTAL(9,C61:C64) -> 56 | D65: =SUBTOTAL(9,D61:D64) -> 20851972 | E65: =D65/K58 -> 3265.2071 | G65: Percentage Sold | H65: =C61/C65 -> 1
J66: CPCV 2025
A67: # | C67: T1 | D67: T2 | E67: T3 | F67: T4 | G67: Total | J67: January | K67: February | L67: March | M67: April | N67: May | O67: June | P67: July | Q67: August | R67: September | S67: October | T67: November | U67: December
A68: CPCV | C68: =COUNTIFS($D$2:$D$57,C67,$Q$2:$Q$57,$A$68) -> 10 | D68: =COUNTIFS($D$2:$D$57,D67,$Q$2:$Q$57,$A$68) -> 22 | E68: =COUNTIFS($D$2:$D$57,E67,$Q$2:$Q$57,$A$68) -> 15 | F68: =COUNTIFS($D$2:$D$57,F67,$Q$2:$Q$57,$A$68) -> 9 | G68: =SUM(C68:F68) -> 56 | J68: =COUNTIFS(AC2:AC57,">="&DATE(2025,1,1),AC2:AC57,"<="&DATE(2025,1,31)) -> 2 | K68: =COUNTIFS(AC2:AC57,">="&DATE(2025,2,1),AC2:AC57,"<="&DATE(2025,2,28)) -> 1 | L68: =COUNTIFS(AC2:AC57,">="&DATE(2025,3,1),AC2:AC57,"<="&DATE(2025,3,31)) -> 2 | M68: =COUNTIFS(AC2:AC57,">="&DATE(2025,4,1),AC2:AC57,"<="&DATE(2025,4,30)) -> 1 | N68: =COUNTIFS(AC2:AC57,">="&DATE(2025,5,1),AC2:AC57,"<="&DATE(2025,5,31)) -> 0 | O68: =COUNTIFS(AC2:AC57,">="&DATE(2025,6,1),AC2:AC57,"<="&DATE(2025,6,30)) -> 0 | P68: =COUNTIFS(AC2:AC57,">="&DATE(2025,7,1),AC2:AC57,"<="&DATE(2025,7,31)) -> 0 | Q68: =COUNTIFS(AC2:AC57,">="&DATE(2025,8,1),AC2:AC57,"<="&DATE(2025,8,31)) -> 0 | R68: =COUNTIFS(AC2:AC57,">="&DATE(2025,9,1),AC2:AC57,"<="&DATE(2025,9,30)) -> 0 | S68: =COUNTIFS(AC2:AC57,">="&DATE(2025,10,1),AC2:AC57,"<="&DATE(2025,10,31)) -> 0 | T68: =COUNTIFS(AC2:AC57,">="&DATE(2025,11,1),AC2:AC57,"<="&DATE(2025,11,30)) -> 0 | U68: =COUNTIFS(AC2:AC57,">="&DATE(2025,12,1),AC2:AC57,"<="&DATE(2025,12,31)) -> 0
A69: BLOCKED | C69: =COUNTIFS($D$2:$D$57,C67,$Q$2:$Q$57,$A$69) -> 0 | D69: =COUNTIFS($D$2:$D$57,D67,$Q$2:$Q$57,$A$69) -> 0 | E69: =COUNTIFS($D$2:$D$57,E67,$Q$2:$Q$57,$A$69) -> 0 | F69: =COUNTIFS($D$2:$D$57,F67,$Q$2:$Q$57,$A$69) -> 0 | G69: =SUM(C69:F69) -> 0
A70: AVAILABLE | C70: =COUNTIFS($D$2:$D$57,C67,$Q$2:$Q$57,"") -> 0 | D70: =COUNTIFS($D$2:$D$57,D67,$Q$2:$Q$57,"") -> 0 | E70: =COUNTIFS($D$2:$D$57,E67,$Q$2:$Q$57,"") -> 0 | F70: =COUNTIFS($D$2:$D$57,F67,$Q$2:$Q$57,"") -> 0 | G70: =SUM(C70:F70) -> 0
A71: RESERVED | C71: =COUNTIFS($D$2:$D$57,C67,$Q$2:$Q$57,A71) -> 0 | D71: =COUNTIFS($D$2:$D$57,D67,$Q$2:$Q$57,A71) -> 0 | E71: =COUNTIFS($D$2:$D$57,E67,$Q$2:$Q$57,A71) -> 0 | F71: =COUNTIFS($D$2:$D$57,F67,$Q$2:$Q$57,A71) -> 0 | G71: =SUM(C71:F71) -> 0 | J71: Brokers | O71: Nationalities
A72: Total | C72: =SUM(C68:C71) -> 10 | D72: =SUM(D68:D71) -> 22 | E72: =SUM(E68:E71) -> 15 | F72: =SUM(F68:F71) -> 9 | G72: =SUM(G68:G71) -> 56 | K72: Overall | L72: 2024 | M72: % | P72: Overall | Q72: 2024 | R72: %
J73: GLOBALKEY | K73: =COUNTIFS(Q2:Q57,Q39,AJ2:AJ57,J73) -> 38 | L73: =COUNTIFS(AC2:AC57,">="&DATE(2024,1,1),AC2:AC57,"<="&DATE(2024,12,31),AJ2:AJ57,J73) -> 33 | M73: =K73/(+K73+K74+K75) -> 0.67857143 | O73: Portugal | P73: =COUNTIFS($Q$2:$Q$57,$Q$56,$AP$2:$AP$57,O73) -> 49 | Q73: =COUNTIFS(AC2:AC57,">="&DATE(2024,1,1),AC2:AC57,"<="&DATE(2024,12,31),$AP$2:$AP$57,O73) -> 45 | R73: =P73/(+P73+P74+P75+P76) -> 0.9245283
J74: CHAVENOVA | K74: =COUNTIFS(Q2:Q57,Q39,AJ2:AJ57,J74) -> 13 | L74: =COUNTIFS(AC2:AC57,">="&DATE(2024,1,1),AC2:AC57,"<="&DATE(2024,12,31),AJ2:AJ57,J74) -> 12 | M74: =K74/(+K73+K74+K75) -> 0.23214286 | O74: Israel | P74: =COUNTIFS($Q$2:$Q$57,$Q$56,$AP$2:$AP$57,O74) -> 2 | Q74: =COUNTIFS(AC3:AC58,">="&DATE(2024,1,1),AC3:AC58,"<="&DATE(2024,12,31),$AP$2:$AP$57,O74) -> 2 | R74: =P74/(+P73+P74+P75+P76) -> 0.037735849
A75: Average €/m² | C75: T1 | D75: T2 | E75: T3 | F75: T4 | G75: Total | J75: TRANQUILDISCOVERY | K75: =COUNTIFS(Q2:Q57,Q39,AJ2:AJ57,J75) -> 5 | L75: =COUNTIFS(AC2:AC57,">="&DATE(2024,1,1),AC2:AC57,"<="&DATE(2024,12,31),AJ2:AJ57,J75) -> 5 | M75: =K75/(+K73+K74+K75) -> 0.089285714 | O75: Venezuela | P75: =COUNTIFS($Q$2:$Q$57,$Q$56,$AP$2:$AP$57,O75) -> 1 | Q75: =COUNTIFS(AC4:AC59,">="&DATE(2024,1,1),AC4:AC59,"<="&DATE(2024,12,31),$AP$2:$AP$57,O75) -> 1 | R75: =P75/(+P73+P74+P75+P76) -> 0.018867925
A76: CPCV | C76: =AVERAGEIFS($Y$2:$Y$57,$Q$2:$Q$57,$A$76,$D$2:$D$57,C75) -> 3336.8952 | D76: =AVERAGEIFS($Y$2:$Y$57,$Q$2:$Q$57,$A$76,$D$2:$D$57,D75) -> 3238.217 | E76: =AVERAGEIFS($Y$2:$Y$57,$Q$2:$Q$57,$A$76,$D$2:$D$57,E75) -> 3248.2768 | F76: =AVERAGEIFS($Y$2:$Y$57,$Q$2:$Q$57,$A$76,$D$2:$D$57,F75) -> 3300.9321 | G76: =AVERAGEIF($P$2:$P$57,A76,$Y$2:$Y$57) -> #DIV/0! | O76: Brazil | P76: =COUNTIFS($Q$2:$Q$57,Q46,$AP$2:$AP$57,O76) -> 1 | Q76: =COUNTIFS(AC5:AC60,">="&DATE(2024,1,1),AC5:AC60,"<="&DATE(2024,12,31),$AP$2:$AP$57,O76) -> 1 | R76: =P76/(SUM(P73:P76)) -> 0.018867925
A77: BLOCKED | C77: =AVERAGEIFS($Z$2:$Z$57,$Q$2:$Q$57,$A$77,$D$2:$D$57,C75) -> #DIV/0! | D77: =AVERAGEIFS($Z$2:$Z$57,$Q$2:$Q$57,$A$77,$D$2:$D$57,D75) -> #DIV/0! | E77: =AVERAGEIFS($Z$2:$Z$57,$Q$2:$Q$57,$A$77,$D$2:$D$57,E75) -> #DIV/0! | F77: =AVERAGEIFS($Z$2:$Z$57,$Q$2:$Q$57,$A$77,$D$2:$D$57,F75) -> #DIV/0! | G77: =AVERAGEIF($Q$2:$Q$57,A77,$Z$2:$Z$57) -> #DIV/0!
A78: AVAILABLE | C78: =AVERAGEIFS($Z$2:$Z$57,$Q$2:$Q$57,"",$D$2:$D$57,C75) -> #DIV/0! | D78: =AVERAGEIFS($Z$2:$Z$57,$Q$2:$Q$57,"",$D$2:$D$57,D75) -> #DIV/0! | E78: =AVERAGEIFS($Z$2:$Z$57,$Q$2:$Q$57,"",$D$2:$D$57,E75) -> #DIV/0! | F78: =AVERAGEIFS($Z$2:$Z$57,$Q$2:$Q$57,"",$D$2:$D$57,F75) -> #DIV/0! | G78: =AVERAGEIF($Q$2:$Q$57,"",$Z$2:$Z$57) -> #DIV/0!
A79: RESERVED | C79: =AVERAGEIFS($Z$2:$Z$57,$Q$2:$Q$57,$A$79,$D$2:$D$57,C75) -> #DIV/0! | D79: =AVERAGEIFS($Z$2:$Z$57,$Q$2:$Q$57,$A$79,$D$2:$D$57,D75) -> #DIV/0! | E79: =AVERAGEIFS($Z$2:$Z$57,$Q$2:$Q$57,$A$79,$D$2:$D$57,E75) -> #DIV/0! | F79: =AVERAGEIFS($Z$2:$Z$57,$Q$2:$Q$57,$A$79,$D$2:$D$57,F75) -> #DIV/0! | G79: =AVERAGEIF($Q$2:$Q$57,A79,$Z$2:$Z$57) -> #DIV/0!
A81: Average €/unit | C81: T1 | D81: T2 | E81: T3 | F81: T4 | G81: Total
A82: CPCV | C82: =AVERAGEIFS($S$2:$S$57,$Q$2:$Q$57,$A$82,$D$2:$D$57,C81) -> 227744 | D82: =AVERAGEIFS($S$2:$S$57,$Q$2:$Q$57,$A$82,$D$2:$D$57,D81) -> 316903.91 | E82: =AVERAGEIFS($S$2:$S$57,$Q$2:$Q$57,$A$82,$D$2:$D$57,E81) -> 405464.4 | F82: =AVERAGEIFS($S$2:$S$57,$Q$2:$Q$57,$A$82,$D$2:$D$57,F81) -> 613408.89 | G82: =AVERAGEIF(Q2:Q57,A82,S2:S57) -> 372356.64
A83: BLOCKED | C83: =AVERAGEIFS($V$2:$V$57,$Q$2:$Q$57,$A$83,$D$2:$D$57,C81) -> #DIV/0! | D83: =AVERAGEIFS($V$2:$V$57,$Q$2:$Q$57,$A$83,$D$2:$D$57,D81) -> #DIV/0! | E83: =AVERAGEIFS($V$2:$V$57,$Q$2:$Q$57,$A$83,$D$2:$D$57,E81) -> #DIV/0! | F83: =AVERAGEIFS($V$2:$V$57,$Q$2:$Q$57,$A$83,$D$2:$D$57,F81) -> #DIV/0! | G83: =AVERAGEIF(Q2:Q57,A83,V2:V57) -> #DIV/0!
A84: AVAILABLE | C84: =AVERAGEIFS($V$2:$V$57,$Q$2:$Q$57,"",$D$2:$D$57,C81) -> #DIV/0! | D84: =AVERAGEIFS($V$2:$V$57,$Q$2:$Q$57,"",$D$2:$D$57,D81) -> #DIV/0! | E84: =AVERAGEIFS($V$2:$V$57,$Q$2:$Q$57,"",$D$2:$D$57,E81) -> #DIV/0! | F84: =AVERAGEIFS($V$2:$V$57,$Q$2:$Q$57,"",$D$2:$D$57,F81) -> #DIV/0! | G84: =AVERAGEIF(Q2:Q57,"",V2:V57) -> #DIV/0!
A85: RESERVED | C85: =AVERAGEIFS($V$2:$V$57,$Q$2:$Q$57,$A$85,$D$2:$D$57,C81) -> #DIV/0! | D85: =AVERAGEIFS($V$2:$V$57,$Q$2:$Q$57,$A$85,$D$2:$D$57,D81) -> #DIV/0! | E85: =AVERAGEIFS($V$2:$V$57,$Q$2:$Q$57,$A$85,$D$2:$D$57,E81) -> #DIV/0! | F85: =AVERAGEIFS($V$2:$V$57,$Q$2:$Q$57,$A$85,$D$2:$D$57,F81) -> #DIV/0! | G85: =AVERAGEIF(Q2:Q57,A85,V2:V57) -> #DIV/0!
A87: Average size m² | C87: T1 | D87: T2 | E87: T3 | F87: T4 | G87: Total
A88: CPCV | C88: =AVERAGEIFS($K$2:$K$57,$Q$2:$Q$57,$A$88,$D$2:$D$57,C87) -> 68.29 | D88: =AVERAGEIFS($K$2:$K$57,$Q$2:$Q$57,$A$88,$D$2:$D$57,D87) -> 97.995455 | E88: =AVERAGEIFS($K$2:$K$57,$Q$2:$Q$57,$A$88,$D$2:$D$57,E87) -> 125.07333 | F88: =AVERAGEIFS($K$2:$K$57,$Q$2:$Q$57,$A$88,$D$2:$D$57,F87) -> 185.69 | G88: =AVERAGEIF(Q2:Q57,A88,K2:K57) -> 114.03768
A89: BLOCKED | C89: =AVERAGEIFS($K$2:$K$57,$Q$2:$Q$57,$A$89,$D$2:$D$57,C87) -> #DIV/0! | D89: =AVERAGEIFS($K$2:$K$57,$Q$2:$Q$57,$A$89,$D$2:$D$57,D87) -> #DIV/0! | E89: =AVERAGEIFS($K$2:$K$57,$Q$2:$Q$57,$A$89,$D$2:$D$57,E87) -> #DIV/0! | F89: =AVERAGEIFS($K$2:$K$57,$Q$2:$Q$57,$A$89,$D$2:$D$57,F87) -> #DIV/0! | G89: =AVERAGEIF(Q2:Q57,A89,K2:K57) -> #DIV/0!
A90: AVAILABLE | C90: =AVERAGEIFS($K$2:$K$57,$Q$2:$Q$57,"",$D$2:$D$57,C87) -> #DIV/0! | D90: =AVERAGEIFS($K$2:$K$57,$Q$2:$Q$57,"",$D$2:$D$57,D87) -> #DIV/0! | E90: =AVERAGEIFS($K$2:$K$57,$Q$2:$Q$57,"",$D$2:$D$57,E87) -> #DIV/0! | F90: =AVERAGEIFS($K$2:$K$57,$Q$2:$Q$57,"",$D$2:$D$57,F87) -> #DIV/0! | G90: =AVERAGEIF(Q2:Q57,"",K2:K57) -> #DIV/0!
A91: RESERVED | C91: =AVERAGEIFS($K$2:$K$57,$Q$2:$Q$57,$A$91,$D$2:$D$57,C87) -> #DIV/0! | D91: =AVERAGEIFS($K$2:$K$57,$Q$2:$Q$57,$A$91,$D$2:$D$57,D87) -> #DIV/0! | E91: =AVERAGEIFS($K$2:$K$57,$Q$2:$Q$57,$A$91,$D$2:$D$57,E87) -> #DIV/0! | F91: =AVERAGEIFS($K$2:$K$57,$Q$2:$Q$57,$A$91,$D$2:$D$57,F87) -> #DIV/0! | G91: =AVERAGEIF(Q2:Q57,A91,K2:K57) -> #DIV/0!

Sheet VERDE VALE H2 (MAIA)
A1: Unit | B1: Fraction | C1: Layout | D1: Floor | E1: Directions | F1: Main area | G1: Balcony | H1: Terrace | I1: Saleable Area | J1: Status | K1: Parking 1 | L1: Parking Floor | M1: Parking 3 | N1: Parking 4 | O1: Storage | P1: Signed | Q1: Payment | R1: Closing Price | S1: Min. Price | T1: Asking Price | U1: Old Price | V1: % Discount | W1: €/m² sold | X1: €/m² min. price | Y1: €/m² asking price | Z1: On hold | AA1: Date of Reservation | AB1: Date of CPCV | AC1: CPCV Value | AD1: 1st down payment | AE1: Date 1st down pmt. | AF1: 2nd down payment | AG1: Date 2nd down pmt. | AH1: Deed | AI1: Brokers company | AJ1: Broker Name | AK1: % Commission | AL1: PO done? | AM1: Invoice received? | AN1: Invoice Paid? | AO1: Client | AP1: Client Nationality | AQ1: Birth Date | AR1: Age | AS1: Investor / Final Client | AT1: Email | AU1: Phone | AV1: Cancelled? | AW1: Why Cancelled? | AX1: Business Plan Price | AY1: €/m² Business Plan | AZ1: Resale
A2: 1 | B2: A | C2: T1 | D2: 1 | E2: E | F2: 64.6 | H2: 19.4 | I2: =F2+0.3*G2+0.3*H2 -> 70.42 | J2: CPCV | K2: 1 spot | L2: in -1 | R2: 227520 | S2: =0.96*T2 -> 227520 | T2: 237000 | V2: =S2/T2-1 -> -0.04 | W2: =R2/I2 -> 3230.9003 | X2: =S2/I2 -> 3230.9003 | Y2: =T2/I2 -> 3365.5212 | AA2: 45486 | AB2: 45510 | AC2: =20%*R2+5000 -> 50504 | AH2: =80%*R2-5000 -> 177016 | AI2: Chavenova | AO2: Abreu dos Santos Alonso e Sónia Maria Barbosa da Silva Carvalhido | AP2: Portugal | AT2: abreualonso1964@gmail.com | AU2: 919459875 | AX2: =AY2*I2 -> 192246.6 | AY2: 2730
A3: 2 | B3: B | C3: T1 | D3: 1 | E3: E | F3: 60.9 | H3: 19.2 | I3: =F3+0.3*G3+0.3*H3 -> 66.66 | J3: CPCV | K3: 1 spot | L3: in -2 | R3: 218400 | S3: =0.96*T3 -> 218400 | T3: 227500 | V3: =S3/T3-1 -> -0.04 | W3: =R3/I3 -> 3276.3276 | X3: =S3/I3 -> 3276.3276 | Y3: =T3/I3 -> 3412.8413 | AA3: 45486 | AB3: 45540 | AC3: =20%*R3 -> 43680 | AH3: =80%*R3 -> 174720 | AI3: GlobalKey | AO3: Helio Ribeiro | AP3: Portugal | AT3: heliofiliperibeiro@gmail.com | AU3: 937288304 | AX3: =AY3*I3 -> 181981.8 | AY3: 2730
A4: 3 | B4: C | C4: T1 | D4: 1 | E4: E | F4: 60.9 | H4: 19.2 | I4: =F4+0.3*G4+0.3*H4 -> 66.66 | J4: CPCV | K4: 1 spot | L4: in -2 | R4: 222950 | S4: =0.96*T4 -> 218400 | T4: 227500 | V4: =S4/T4-1 -> -0.04 | W4: =R4/I4 -> 3344.5845 | X4: =S4/I4 -> 3276.3276 | Y4: =T4/I4 -> 3412.8413 | AA4: 45486 | AB4: 45502 | AC4: =20%*R4 -> 44590 | AH4: =80%*R4 -> 178360 | AI4: GlobalKey | AO4: Anabela Afonso | AP4: Portugal | AT4: anabelaafonso74@gmail.com | AU4: 919029145 | AX4: =AY4*I4 -> 181981.8 | AY4: 2730
A5: 4 | B5: D | C5: T3 | D5: 1 | E5: S/E | F5: 109.7 | H5: 25.2 | I5: =F5+0.3*G5+0.3*H5 -> 117.26 | J5: CPCV | K5: 1 spot | L5: in -1 | R5: 367000 | S5: =0.96*T5 -> 355200 | T5: 370000 | U5: 355000 | V5: =S5/T5-1 -> -0.04 | W5: =R5/I5 -> 3129.797 | X5: =S5/I5 -> 3029.166 | Y5: =T5/I5 -> 3155.3812 | AA5: 45706 | AB5: 45744 | AC5: =5000+68400 -> 73400 | AH5: =80%*R5 -> 293600 | AI5: GlobalKey | AO5: Maria Augusta Gonçalves Fernandes Fugas | AP5: Portugal | AT5: - | AU5: 934601193 | AX5: =AY5*I5 -> 320119.8 | AY5: 2730
A6: 5 | B6: E | C6: T2 | D6: 1 | E6: N/W | F6: 87.3 | H6: 62.7 | I6: =F6+0.3*G6+0.2*H6 -> 99.84 | J6: CPCV | K6: 1 spot | L6: in -1 | R6: 293000 | S6: =0.96*T6 -> 290880 | T6: 303000 | V6: =S6/T6-1 -> -0.04 | W6: =R6/I6 -> 2934.6955 | X6: =S6/I6 -> 2913.4615 | Y6: =T6/I6 -> 3034.8558 | AB6: 45523 | AC6: 29300 | AD6: 29300 | AH6: =80%*R6 -> 234400 | AI6: GlobalKey | AO6: Bruno Miguel Fortunato Charters & Catarina Carvalho | AP6: Portugal | AT6: brunocharters@outlook.com | AU6: 916169468 | AX6: =AY6*I6 -> 272563.2 | AY6: 2730
A7: 6 | B7: F | C7: T1 | D7: 1 | E7: W | F7: 62.3 | H7: 46.2 | I7: =F7+0.3*G7+0.2*H7 -> 71.54 | J7: CPCV | K7: 1 spot | L7: in -2 | R7: 237120 | S7: =0.96*T7 -> 237120 | T7: 247000 | V7: =S7/T7-1 -> -0.04 | W7: =R7/I7 -> 3314.5094 | X7: =S7/I7 -> 3314.5094 | Y7: =T7/I7 -> 3452.6139 | AA7: 45486 | AB7: 45525 | AC7: =20%*R7 -> 47424 | AH7: =80%*R7 -> 189696 | AI7: GlobalKey | AO7: Rita Ramalho Da Silva Quadros | AP7: Portugal | AT7: qrita1@hotmail.com | AU7: 914052730 | AX7: =AY7*I7 -> 195304.2 | AY7: 2730
A8: 7 | B8: G | C8: T1 | D8: 1 | E8: W | F8: 62.4 | H8: 47 | I8: =F8+0.3*G8+0.2*H8 -> 71.8 | J8: CPCV | K8: 1 spot | L8: in -2 | R8: 235000 | S8: =0.96*T8 -> 237120 | T8: 247000 | V8: =S8/T8-1 -> -0.04 | W8: =R8/I8 -> 3272.9805 | X8: =S8/I8 -> 3302.507 | Y8: =T8/I8 -> 3440.1114 | AA8: 45486 | AB8: 45502 | AC8: =20%*R8 -> 47000 | AH8: =80%*R8 -> 188000 | AI8: GlobalKey | AO8: Sandra Marisa Rodrigues Mota Oliveira | AP8: Portugal | AT8: sandra.mota.oliveira-55130p@adv.oa.pt | AU8: 968837313 | AX8: =AY8*I8 -> 196014 | AY8: 2730
A9: 8 | B9: H | C9: T1 | D9: 1 | E9: W | F9: 62.4 | H9: 47 | I9: =F9+0.3*G9+0.2*H9 -> 71.8 | J9: CPCV | K9: 1 spot | L9: in -2 | R9: 237120 | S9: =0.96*T9 -> 237120 | T9: 247000 | V9: =S9/T9-1 -> -0.04 | W9: =R9/I9 -> 3302.507 | X9: =S9/I9 -> 3302.507 | Y9: =T9/I9 -> 3440.1114 | AA9: 45486 | AB9: 45504 | AC9: =20%*R9+5000 -> 52424 | AH9: =80%*R9-5000 -> 184696 | AI9: Chavenova | AO9: Carlos Manuel Lopes Varanda | AP9: Portugal | AT9: carloslopesvaranda@hotmail.com | AU9: 919008365 | AX9: =AY9*I9 -> 196014 | AY9: 2730
A10: 9 | B10: I | C10: T1 | D10: 1 | E10: W | F10: 62.3 | H10: 46.2 | I10: =F10+0.3*G10+0.2*H10 -> 71.54 | J10: CPCV | K10: 1 spot | L10: in -2 | R10: 247000 | S10: =0.96*T10 -> 237120 | T10: 247000 | V10: =S10/T10-1 -> -0.04 | W10: =R10/I10 -> 3452.6139 | X10: =S10/I10 -> 3314.5094 | Y10: =T10/I10 -> 3452.6139 | AA10: 45486 | AB10: 45526 | AC10: =20%*R10 -> 49400 | AH10: =80%*R10 -> 197600 | AI10: GlobalKey | AO10: Monteiro & Goulart | AP10: Portugal | AT10: andre.b.goulart@gmail.com | AU10: 969020736 | AX10: =AY10*I10 -> 195304.2 | AY10: 2730
A11: 10 | B11: J | C11: T2 | D11: 1 | E11: S/W | F11: 87.3 | H11: 62.7 | I11: =F11+0.3*G11+0.2*H11 -> 99.84 | J11: CPCV | K11: 1 spot | L11: in -2 | R11: 299520 | S11: =0.96*T11 -> 299520 | T11: 312000 | V11: =S11/T11-1 -> -0.04 | W11: =R11/I11 -> 3000 | X11: =S11/I11 -> 3000 | Y11: =T11/I11 -> 3125 | AB11: 45532 | AC11: =20%*R11 -> 59904 | AH11: =80%*R11 -> 239616 | AI11: Chavenova | AO11: Joaquim Maia de Sousa, Lda | AP11: Portugal | AT11: joaquimmaiasousa@sapo.pt | AU11: 965592217 | AX11: =AY11*I11 -> 272563.2 | AY11: 2730
A12: 11 | B12: K | C12: T3 | D12: 2 | E12: N/E | F12: 116.6 | G12: 47.5 | I12: =F12+0.3*G12+0.3*H12 -> 130.85 | J12: CPCV | K12: 2 spots (in front of each other) Opposite side (no alternative) | L12: in -2 | R12: 360000 | S12: =0.96*T12 -> 360000 | T12: 375000 | V12: =S12/T12-1 -> -0.04 | W12: =R12/I12 -> 2751.2419 | X12: =S12/I12 -> 2751.2419 | Y12: =T12/I12 -> 2865.877 | AA12: 45486 | AB12: 45498 | AC12: =5000+31000 -> 36000 | AH12: 324000 | AI12: GlobalKey | AO12: Paulo Alexandre Oliveira Marques | AP12: Portugal | AT12: p-oliveira-m@hotmail.com | AU12: 938610917 | AX12: =AY12*I12 -> 357220.5 | AY12: 2730
A13: 12 | B13: L | C13: T3 | D13: 2 | E13: E/W | F13: 135.2 | G13: =36+20 -> 56 | I13: =F13+0.3*G13+0.3*H13 -> 152 | J13: CPCV | K13: 2 spots (side by side) | L13: in -1 | R13: 469440 | S13: =0.96*T13 -> 451200 | T13: 470000 | V13: =S13/T13-1 -> -0.04 | W13: =R13/I13 -> 3088.4211 | X13: =S13/I13 -> 2968.4211 | Y13: =T13/I13 -> 3092.1053 | AA13: 45486 | AB13: 45506 | AC13: 46944 | AH13: 422496 | AI13: Chavenova | AO13: Ana Sofia Pais Carvalho Bessa | AP13: Portugal | AT13: sofia.bessamail@gmail.com | AU13: 912442781 | AX13: =AY13*I13 -> 414960 | AY13: 2730
A14: 13 | B14: M | C14: T3 | D14: 2 | E14: E/W | F14: 135.2 | G14: =36+20 -> 56 | I14: =F14+0.3*G14+0.3*H14 -> 152 | J14: CPCV | K14: 2 spots (side by side) | L14: in -1 | R14: 455000 | S14: =0.96*T14 -> 451200 | T14: 470000 | V14: =S14/T14-1 -> -0.04 | W14: =R14/I14 -> 2993.4211 | X14: =S14/I14 -> 2968.4211 | Y14: =T14/I14 -> 3092.1053 | AA14: 45486 | AB14: 45504 | AC14: =20%*R14 -> 91000 | AH14: =80%*R14 -> 364000 | AI14: GlobalKey | AO14: Pedro Acário Freitas Teixeira | AP14: Portugal | AT14: pedrotet18@gmail.com | AU14: 917974305 | AX14: =AY14*I14 -> 414960 | AY14: 2730
A15: 14 | B15: N | C15: T3 | D15: 2 | E15: S/E | F15: 116.6 | G15: 47.5 | I15: =F15+0.3*G15+0.3*H15 -> 130.85 | J15: CPCV | K15: 2 spots (in front of each other) | L15: in -1 | R15: 384000 | S15: =0.96*T15 -> 384000 | T15: 400000 | V15: =S15/T15-1 -> -0.04 | W15: =R15/I15 -> 2934.658 | X15: =S15/I15 -> 2934.658 | Y15: =T15/I15 -> 3056.9354 | AA15: 45486 | AB15: 45498 | AC15: =10%*R15 -> 38400 | AH15: =90%*R15 -> 345600 | AI15: GlobalKey | AO15: Tiago Francisco Garção Gil | AP15: Portugal | AT15: tiagofranciscogil93@hotmail.com | AU15: 912395347 | AX15: =AY15*I15 -> 357220.5 | AY15: 2730
A16: 15 | B16: O | C16: T2 | D16: 2 | E16: N/W | F16: 86.7 | G16: 60.3 | I16: =F16+0.2*G16+0.3*H16 -> 98.76 | J16: CPCV | K16: 1 spot | L16: in -2 | R16: 329280 | S16: =0.96*T16 -> 329280 | T16: 343000 | U16: 317000 | V16: =S16/T16-1 -> -0.04 | W16: =R16/I16 -> 3334.1434 | X16: =S16/I16 -> 3334.1434 | Y16: =T16/I16 -> 3473.066 | AA16: 45684 | AB16: 45730 | AC16: =20%*S16 -> 65856 | AH16: =80%*S16 -> 263424 | AI16: Chavenova | AO16: Beatriz Mesquita de Oliveira | AP16: Portugal | AT16: mesquitab1308@gmail.com | AU16: 916467866 | AX16: =AY16*I16 -> 269614.8 | AY16: 2730
A17: 16 | B17: P | C17: T1 | D17: 2 | E17: W | F17: 63.4 | G17: 25.1 | I17: =F17+0.3*G17+0.3*H17 -> 70.93 | J17: CPCV | K17: 1 spot | L17: in -1 | R17: 244800 | S17: =0.96*T17 -> 244800 | T17: 255000 | V17: =S17/T17-1 -> -0.04 | W17: =R17/I17 -> 3451.29 | X17: =S17/I17 -> 3451.29 | Y17: =T17/I17 -> 3595.0938 | AA17: 45486 | AB17: 45518 | AC17: =20%*R17+5000 -> 53960 | AH17: =80%*R17-5000 -> 190840 | AI17: Chavenova | AO17: Francisco Fonseca Barros | AP17: Portugal | AT17: franciscofbarros@gmail.com | AU17: 966064060 | AX17: =AY17*I17 -> 193638.9 | AY17: 2730
A18: 17 | B18: Q | C18: T1 | D18: 2 | E18: W | F18: 63.4 | G18: 25.1 | I18: =F18+0.3*G18+0.3*H18 -> 70.93 | J18: CPCV | K18: 1 spot | L18: in -2 | R18: 244800 | S18: =0.96*T18 -> 244800 | T18: 255000 | V18: =S18/T18-1 -> -0.04 | W18: =R18/I18 -> 3451.29 | X18: =S18/I18 -> 3451.29 | Y18: =T18/I18 -> 3595.0938 | AA18: 45486 | AB18: 45504 | AC18: =20%*R18 -> 48960 | AH18: 195840 | AI18: Chavenova | AO18: Cosme Augusto da Costa Azevedo | AP18: Portugal | AT18: - | AU18: 934773419 | AX18: =AY18*I18 -> 193638.9 | AY18: 2730
A19: 18 | B19: R | C19: T2 | D19: 2 | E19: S/W | F19: 86.7 | G19: 60.3 | I19: =F19+0.2*G19+0.3*H19 -> 98.76 | J19: CPCV | K19: 1 spot | L19: in -2 | R19: 313920 | S19: =0.96*T19 -> 313920 | T19: 327000 | V19: =S19/T19-1 -> -0.04 | W19: =R19/I19 -> 3178.6148 | X19: =S19/I19 -> 3178.6148 | Y19: =T19/I19 -> 3311.0571 | AA19: 45486 | AB19: 45511 | AC19: =20%*R19 -> 62784 | AH19: =80%*R19 -> 251136 | AI19: GlobalKey | AO19: EDU4BUSINESS promoção imoviliária | AP19: Portugal | AT19: jardinssaguaviva@sapo.pt | AU19: 965387997 | AX19: =AY19*I19 -> 269614.8 | AY19: 2730
A20: 19 | B20: S | C20: T3 | D20: 3 | E20: N/E | F20: 116.6 | G20: 21.1 | I20: =F20+0.3*G20+0.3*H20 -> 122.93 | J20: CPCV | K20: 2 spots (in front of each other) | L20: in -2 | R20: 374400 | S20: =0.96*T20 -> 374400 | T20: 390000 | U20: 375000 | V20: =S20/T20-1 -> -0.04 | W20: =R20/I20 -> 3045.6357 | X20: =S20/I20 -> 3045.6357 | Y20: =T20/I20 -> 3172.5372 | AA20: 45593 | AB20: 45607 | AC20: =20%*R20 -> 74880 | AH20: =80%*R20 -> 299520 | AI20: Chavenova | AO20: Joaquim Ricardo de Jesus da Veiga | AP20: Portugal | AT20: joaquim.veiga@gmail.com | AU20: 963662946 | AX20: =AY20*I20 -> 335598.9 | AY20: 2730
A21: 20 | B21: T | C21: T3 | D21: 3 | E21: E/W | F21: 134.6 | G21: =7.6+24.6 -> 32.2 | I21: =F21+0.3*G21+0.3*H21 -> 144.26 | J21: CPCV | K21: 2 spots (in front of each other) | L21: in -2 | R21: 464640 | S21: =0.96*T21 -> 464640 | T21: 484000 | U21: 465000 | V21: =S21/T21-1 -> -0.04 | W21: =R21/I21 -> 3220.8512 | X21: =S21/I21 -> 3220.8512 | Y21: =T21/I21 -> 3355.0534 | AB21: 45603 | AC21: =20%*R21 -> 92928 | AH21: =80%*R21 -> 371712 | AI21: Chavenova | AO21: DIVERSTOCK INVESTMENTS SA | AP21: Portugal | AT21: jose.meneses@diverstock.com | AU21: 917520252 | AX21: =AY21*I21 -> 393829.8 | AY21: 2730
A22: 21 | B22: U | C22: T3 | D22: 3 | E22: E/W | F22: 134.6 | G22: =7.6+24.6 -> 32.2 | I22: =F22+0.3*G22+0.3*H22 -> 144.26 | J22: CPCV | K22: 2 spots (in front of each other) | L22: in -2 | R22: 446000 | S22: =0.96*T22 -> 446400 | T22: 465000 | V22: =S22/T22-1 -> -0.04 | W22: =R22/I22 -> 3091.6401 | X22: =S22/I22 -> 3094.4129 | Y22: =T22/I22 -> 3223.3467 | AA22: 45486 | AB22: 45510 | AC22: 47500 | AH22: 398900 | AI22: GlobalKey | AO22: Diogo Silva de Magalhaes | AP22: Portugal | AT22: ds.magalhaes99@gmail.com | AU22: 915051579 | AX22: =AY22*I22 -> 393829.8 | AY22: 2730 | AZ22: 450000
A23: 22 | B23: V | C23: T3 | D23: 3 | E23: S/E | F23: 116.6 | G23: 16.5 | I23: =F23+0.3*G23+0.3*H23 -> 121.55 | J23: CPCV | K23: 2 spots (in front of each other) | L23: in -1 | R23: 384000 | S23: =0.96*T23 -> 384000 | T23: 400000 | V23: =S23/T23-1 -> -0.04 | W23: =R23/I23 -> 3159.1937 | X23: =S23/I23 -> 3159.1937 | Y23: =T23/I23 -> 3290.8268 | AA23: 45486 | AB23: 45504 | AC23: =10%*R23 -> 38400 | AH23: =90%*R23 -> 345600 | AI23: Chavenova | AO23: João Rodrigues Barbosa | AP23: Portugal | AX23: =AY23*I23 -> 331831.5 | AY23: 2730
A24: 23 | B24: W | C24: T2 | D24: 3 | E24: N/W | F24: 85.8 | G24: 54.9 | I24: =F24+0.2*G24+0.3*H24 -> 96.78 | J24: CPCV | K24: 1 spot | L24: in -2 | R24: 304320 | S24: =0.96*T24 -> 304320 | T24: 317000 | V24: =S24/T24-1 -> -0.04 | W24: =R24/I24 -> 3144.4513 | X24: =S24/I24 -> 3144.4513 | Y24: =T24/I24 -> 3275.4701 | AB24: 45523 | AC24: 30432 | AD24: 30432 | AE24: 45551 | AH24: =80%*R24 -> 243456 | AI24: GlobalKey | AO24: João Areoso & Zita Cabo | AP24: Portugal | AT24: joaoaroso18@gmail.com | AU24: 914735968 | AX24: =AY24*I24 -> 264209.4 | AY24: 2730
A25: 24 | B25: X | C25: T2 | D25: 3 | E25: W | F25: 84.8 | G25: 33.2 | I25: =F25+0.2*G25+0.3*H25 -> 91.44 | J25: CPCV | K25: 1 spot | L25: in -2 | R25: 325000 | S25: =0.96*T25 -> 324480 | T25: =325000*1.04 -> 338000 | U25: 312000 | V25: =S25/T25-1 -> -0.04 | W25: =R25/I25 -> 3554.2432 | X25: =S25/I25 -> 3548.5564 | Y25: =T25/I25 -> 3696.4129 | AA25: 45573 | AB25: 45586 | AC25: =20%*R25 -> 65000 | AH25: =80%*R25 -> 260000 | AI25: GlobalKey | AO25: Lino Alfredo Rolo Duarte Alves França | AP25: Portugal | AT25: lino.franco@hotmail.com | AU25: 936708308 | AX25: =AY25*I25 -> 249631.2 | AY25: 2730
A26: 25 | B26: Y | C26: T2 | D26: 3 | E26: W | F26: 84.8 | G26: 33.2 | I26: =F26+0.2*G26+0.3*H26 -> 91.44 | J26: CPCV | K26: 1 spot | L26: in -2 | R26: 299520 | S26: =0.96*T26 -> 299520 | T26: 312000 | V26: =S26/T26-1 -> -0.04 | W26: =R26/I26 -> 3275.5906 | X26: =S26/I26 -> 3275.5906 | Y26: =T26/I26 -> 3412.0735 | AA26: 45516 | AB26: 45532 | AC26: =20%*R26 -> 59904 | AH26: =80%*R26 -> 239616 | AI26: GlobalKey | AO26: Maria Luisa Ferreira Campos | AP26: Portugal | AT26: luiscampos@hotmail.com | AU26: 918584205 | AX26: =AY26*I26 -> 249631.2 | AY26: 2730
A27: 26 | B27: Z | C27: T2 | D27: 3 | E27: S/W | F27: 85.8 | G27: 50.8 | I27: =F27+0.2*G27+0.3*H27 -> 95.96 | J27: CPCV | K27: 1 spot | L27: in -2 | R27: 313920 | S27: =0.96*T27 -> 313920 | T27: 327000 | V27: =S27/T27-1 -> -0.04 | W27: =R27/I27 -> 3271.3631 | X27: =S27/I27 -> 3271.3631 | Y27: =T27/I27 -> 3407.6699 | AA27: 45486 | AB27: 45513 | AC27: =20%*R27+5000 -> 67784 | AH27: =80%*R27-5000 -> 246136 | AI27: Chavenova | AO27: Rui Pedro Marques Quintas | AP27: Portugal | AT27: ruipquintas@gmail.com | AU27: 932680129 | AX27: =AY27*I27 -> 261970.8 | AY27: 2730
A28: 27 | B28: AA | C28: T3 | D28: 4 | E28: N/E | F28: 116.6 | G28: 21.1 | I28: =F28+0.3*G28+0.3*H28 -> 122.93 | J28: CPCV | K28: 2 spots (in front of each other) | L28: in -2 | R28: 395000 | S28: =0.96*T28 -> 379200 | T28: 395000 | U28: 380000 | V28: =S28/T28-1 -> -0.04 | W28: =R28/I28 -> 3213.2108 | X28: =S28/I28 -> 3084.6823 | Y28: =T28/I28 -> 3213.2108 | AB28: 45595 | AC28: =10%*T28 -> 39500 | AH28: =90%*T28 -> 355500 | AI28: Chavenova | AO28: Erika Priscilla Costa Gomes Monteiro | AP28: Brazil | AT28: eloyfarias@gmail.com | AU28: 967108870 | AX28: =AY28*I28 -> 335598.9 | AY28: 2730
A29: 28 | B29: AB | C29: T3 | D29: 4 | E29: E/W | F29: 134.6 | G29: =7.6+24.6 -> 32.2 | I29: =F29+0.3*G29+0.3*H29 -> 144.26 | J29: CPCV | K29: 2 spots (side by side) | L29: in -1 | R29: 469442 | S29: =0.96*T29 -> 469440 | T29: 489000 | U29: 470000 | V29: =S29/T29-1 -> -0.04 | W29: =R29/I29 -> 3254.1384 | X29: =S29/I29 -> 3254.1245 | Y29: =T29/I29 -> 3389.713 | AA29: 45903 | AB29: 45930 | AC29: =5000+88888 -> 93888 | AH29: =80%*R29 -> 375553.6 | AI29: GlobalKey | AO29: Rodrigo josé Fragoso luís & Ana Catarina Faria Pereira | AP29: Portugal | AX29: =AY29*I29 -> 393829.8 | AY29: 2730
A30: 29 | B30: AC | C30: T3 | D30: 4 | E30: E/W | F30: 134.6 | G30: =7.6+24.6 -> 32.2 | I30: =F30+0.3*G30+0.3*H30 -> 144.26 | J30: CPCV | K30: 2 spots (in front of each other) | L30: in -2 | R30: 469440 | S30: =0.96*T30 -> 469440 | T30: 489000 | U30: 470000 | V30: =S30/T30-1 -> -0.04 | W30: =R30/I30 -> 3254.1245 | X30: =S30/I30 -> 3254.1245 | Y30: =T30/I30 -> 3389.713 | AA30: 45892 | AB30: 45911 | AC30: =5000+88888 -> 93888 | AH30: 375552 | AI30: GlobalKey | AO30: RUBEN FERNANDO CAMPELO REBELO & SOFIA FERREIRA DOS SANTOS REBELO | AP30: Portugal | AX30: =AY30*I30 -> 393829.8 | AY30: 2730
A31: 30 | B31: AD | C31: T3 | D31: 4 | E31: S/E | F31: 116.6 | G31: 16.5 | I31: =F31+0.3*G31+0.3*H31 -> 121.55 | J31: CPCV | K31: 2 spots (in front of each other) | L31: in -1 | R31: 388800 | S31: =0.96*T31 -> 388800 | T31: 405000 | V31: =S31/T31-1 -> -0.04 | W31: =R31/I31 -> 3198.6837 | X31: =S31/I31 -> 3198.6837 | Y31: =T31/I31 -> 3331.9622 | AA31: 45486 | AB31: 45524 | AC31: =10%*R31 -> 38880 | AH31: =90%*R31 -> 349920 | AI31: Chavenova | AO31: Constroia Construçoes e Exploraçoes turisticas | AP31: Portugal | AT31: socimpee@gmail.com | AU31: 919865477 | AX31: =AY31*I31 -> 331831.5 | AY31: 2730
A32: 31 | B32: AE | C32: T2 | D32: 4 | E32: N/W | F32: 85.8 | G32: 54.9 | I32: =F32+0.2*G32+0.3*H32 -> 96.78 | J32: CPCV | K32: 1 spot | L32: in -1 | R32: 321600 | S32: =0.96*T32 -> 321600 | T32: 335000 | U32: 322000 | V32: =S32/T32-1 -> -0.04 | W32: =R32/I32 -> 3323.0006 | X32: =S32/I32 -> 3323.0006 | Y32: =T32/I32 -> 3461.459 | AB32: 45547 | AC32: =20%*R32 -> 64320 | AH32: =80%*R32 -> 257280 | AI32: Chavenova | AO32: Mariana Silva Pinto | AP32: Portugal | AT32: - | AU32: 913941962 | AX32: =AY32*I32 -> 264209.4 | AY32: 2730
A33: 32 | B33: AF | C33: T2 | D33: 4 | E33: W | F33: 84.8 | G33: 33.2 | I33: =F33+0.2*G33+0.3*H33 -> 91.44 | J33: CPCV | K33: 1 spot | L33: in -2 | R33: 316800 | S33: =0.96*T33 -> 316800 | T33: 330000 | U33: 317000 | V33: =S33/T33-1 -> -0.04 | W33: =R33/I33 -> 3464.5669 | X33: =S33/I33 -> 3464.5669 | Y33: =T33/I33 -> 3608.9239 | AB33: 45561 | AC33: =20%*R33 -> 63360 | AH33: =80%*R33 -> 253440 | AI33: Chavenova | AO33: VALEFERRUGEM, UNIPESSOAL, LDA | AP33: Portugal | AT33: vale380engenharia@gmail.com | AU33: 937565124 | AX33: =AY33*I33 -> 249631.2 | AY33: 2730
A34: 33 | B34: AG | C34: T2 | D34: 4 | E34: W | F34: 84.8 | G34: 33.2 | I34: =F34+0.2*G34+0.3*H34 -> 91.44 | J34: CPCV | K34: 1 spot | L34: in -2 | R34: 330000 | S34: =0.96*T34 -> 329280 | T34: 343000 | U34: 317000 | V34: =S34/T34-1 -> -0.04 | W34: =R34/I34 -> 3608.9239 | X34: =S34/I34 -> 3601.0499 | Y34: =T34/I34 -> 3751.0936 | AA34: 45563 | AB34: 45587 | AC34: =20%*R34 -> 66000 | AH34: =80%*R34 -> 264000 | AI34: GlobalKey | AO34: Search Paradise LDA. | AP34: Portugal | AT34: ajm.malheiro@gmail.com | AU34: 968489250 | AX34: =AY34*I34 -> 249631.2 | AY34: 2730
A35: 34 | B35: AH | C35: T2 | D35: 4 | E35: S/W | F35: 85.8 | G35: 50.8 | I35: =F35+0.2*G35+0.3*H35 -> 95.96 | J35: CPCV | K35: 1 spot | L35: in -2 | R35: 317760 | S35: =0.96*T35 -> 317760 | T35: 331000 | V35: =S35/T35-1 -> -0.04 | W35: =R35/I35 -> 3311.3797 | X35: =S35/I35 -> 3311.3797 | Y35: =T35/I35 -> 3449.3539 | AA35: 45486 | AB35: 45511 | AC35: =20%*R35+5000 -> 68552 | AH35: =80%*R35-5000 -> 249208 | AI35: Chavenova | AO35: Pedro Miguel Magalhães Fumega dos Santos | AP35: Portugal | AT35: pmfumega@gmail.com | AU35: 933639298 | AX35: =AY35*I35 -> 261970.8 | AY35: 2730
A36: 35 | B36: AI | C36: T3 | D36: 5 | E36: N/E | F36: 116.6 | G36: 21.1 | I36: =F36+0.3*G36+0.3*H36 -> 122.93 | J36: CPCV | K36: 2 spots (in front of each other) | L36: in -2 | R36: =0.95*T36 -> 380000 | S36: =0.96*T36 -> 384000 | T36: 400000 | U36: 385000 | V36: =S36/T36-1 -> -0.04 | W36: =R36/I36 -> 3091.1901 | X36: =S36/I36 -> 3123.729 | Y36: =T36/I36 -> 3253.8843 | AB36: 45568 | AC36: 80000 | AH36: 300000 | AI36: GlobalKey | AJ36: Ignas | AO36: David Martins | AP36: Portugal | AT36: d.matamartins@live.com | AU36: 916143034 | AX36: =AY36*I36 -> 335598.9 | AY36: 2730
A37: 36 | B37: AJ | C37: T3 | D37: 5 | E37: E/W | F37: 134.6 | G37: =7.6+24.6 -> 32.2 | I37: =F37+0.3*G37+0.3*H37 -> 144.26 | J37: CPCV | K37: 2 spots (side by side) | L37: in -1 | R37: 474240 | S37: =0.96*T37 -> 474240 | T37: 494000 | U37: 475000 | V37: =S37/T37-1 -> -0.04 | W37: =R37/I37 -> 3287.3978 | X37: =S37/I37 -> 3287.3978 | Y37: =T37/I37 -> 3424.3727 | AA37: 45891 | AB37: 45898 | AC37: =5000+89848 -> 94848 | AH37: =80%*R37 -> 379392 | AI37: GlobalKey | AO37: Bernardo Eisenlohr Barcellos & Roberta Motta de Muros | AP37: Portugal | AX37: =AY37*I37 -> 393829.8 | AY37: 2730
A38: 37 | B38: AK | C38: T3 | D38: 5 | E38: E/W | F38: 134.6 | G38: =7.6+24.6 -> 32.2 | I38: =F38+0.3*G38+0.3*H38 -> 144.26 | J38: CPCV | K38: 2 spots (side by side) | L38: in -1 | R38: 484120 | S38: =0.96*T38 -> 474240 | T38: 494000 | U38: 475000 | V38: =S38/T38-1 -> -0.04 | W38: =R38/I38 -> 3355.8852 | X38: =S38/I38 -> 3287.3978 | Y38: =T38/I38 -> 3424.3727 | AA38: 45855 | AB38: 45877 | AC38: =5000+43412 -> 48412 | AH38: 435708 | AI38: GlobalKey | AO38: Mário Rui Araújo Ribeiro & Núria Silva Jorge | AP38: Portugal | AX38: =AY38*I38 -> 393829.8 | AY38: 2730
A39: 38 | B39: AL | C39: T3 | D39: 5 | E39: S/E | F39: 116.6 | G39: 16.5 | I39: =F39+0.3*G39+0.3*H39 -> 121.55 | J39: CPCV | K39: 2 spots (in front of each other) | L39: in -1 | R39: 393600 | S39: =0.96*T39 -> 393600 | T39: 410000 | V39: =S39/T39-1 -> -0.04 | W39: =R39/I39 -> 3238.1736 | X39: =S39/I39 -> 3238.1736 | Y39: =T39/I39 -> 3373.0975 | AA39: 45486 | AB39: 45511 | AC39: =10%*R39+5000 -> 44360 | AH39: =90%*R39-5000 -> 349240 | AI39: Chavenova | AO39: Eugénis Margarida Machado Martins Ferreira & José Manuel de Carvalho Santos Ferreira | AP39: Portugal | AT39: jennymargarida@outlook.com | AU39: 938885306 | AX39: =AY39*I39 -> 331831.5 | AY39: 2730
A40: 39 | B40: AM | C40: T2 | D40: 5 | E40: N/W | F40: 85.8 | G40: 54.9 | I40: =F40+0.2*G40+0.3*H40 -> 96.78 | J40: CPCV | K40: 1 spot | L40: in -2 | R40: 313920 | S40: =0.96*T40 -> 313920 | T40: 327000 | V40: =S40/T40-1 -> -0.04 | W40: =R40/I40 -> 3243.6454 | X40: =S40/I40 -> 3243.6454 | Y40: =T40/I40 -> 3378.7973 | AB40: 45516 | AC40: =20%*R40 -> 62784 | AH40: =80%*R40 -> 251136 | AI40: Chavenova | AO40: Eduardo António Vaz Macieira | AP40: Portugal | AT40: eduardovazmacieira@gmail.com | AU40: 912168217 | AX40: =AY40*I40 -> 264209.4 | AY40: 2730
A41: 40 | B41: AN | C41: T2 | D41: 5 | E41: W | F41: 84.8 | G41: 33.2 | I41: =F41+0.2*G41+0.3*H41 -> 91.44 | J41: CPCV | K41: 1 spot | L41: in -2 | R41: 336000 | S41: =0.96*T41 -> 335040 | T41: 349000 | U41: 322000 | V41: =S41/T41-1 -> -0.04 | W41: =R41/I41 -> 3674.5407 | X41: =S41/I41 -> 3664.042 | Y41: =T41/I41 -> 3816.7104 | AA41: 45573 | AB41: 45586 | AC41: 67200 | AH41: 268800 | AI41: GlobalKey | AO41: Lino Alfredo Rolo Duarte Alves França | AP41: Portugal | AT41: lino.franco@hotmail.com | AU41: 936708308 | AX41: =AY41*I41 -> 249631.2 | AY41: 2730
A42: 41 | B42: AO | C42: T2 | D42: 5 | E42: W | F42: 84.8 | G42: 33.2 | I42: =F42+0.2*G42+0.3*H42 -> 91.44 | J42: CPCV | K42: 1 spot | L42: in -1 | R42: 338880 | S42: =0.96*T42 -> 338880 | T42: 353000 | U42: 322000 | V42: =S42/T42-1 -> -0.04 | W42: =R42/I42 -> 3706.0367 | X42: =S42/I42 -> 3706.0367 | Y42: =T42/I42 -> 3860.4549 | AA42: 45615 | AB42: 45625 | AC42: =20%*R42 -> 67776 | AH42: =80%*R42 -> 271104 | AI42: Chavenova | AO42: Catarina Best Alves Lopes | AP42: Portugal | AT42: cblopes84@gmail.com | AU42: 918689890 | AX42: =AY42*I42 -> 249631.2 | AY42: 2730
A43: 42 | B43: AP | C43: T2 | D43: 5 | E43: S/W | F43: 85.8 | G43: 50.8 | I43: =F43+0.2*G43+0.3*H43 -> 95.96 | J43: CPCV | K43: 1 spot | L43: in -2 | R43: 322560 | S43: =0.96*T43 -> 322560 | T43: 336000 | V43: =S43/T43-1 -> -0.04 | W43: =R43/I43 -> 3361.4006 | X43: =S43/I43 -> 3361.4006 | Y43: =T43/I43 -> 3501.4589 | AA43: 45492 | AB43: 45525 | AC43: =20%*R43+5000 -> 69512 | AH43: =80%*R43-5000 -> 253048 | AI43: Chavenova | AO43: INSPIREGATE Unipessoal LDA | AP43: Portugal | AT43: cmoandrade@gmail.com | AU43: 935120003 | AX43: =AY43*I43 -> 261970.8 | AY43: 2730
A44: 43 | B44: AQ | C44: T3 | D44: 6 | E44: N/E | F44: 116.6 | G44: 21.1 | I44: =F44+0.3*G44+0.3*H44 -> 122.93 | J44: CPCV | K44: 2 spots (in front of each other) | L44: in -2 | R44: 389760 | S44: =0.96*T44 -> 389760 | T44: 406000 | U44: 390000 | V44: =S44/T44-1 -> -0.04 | W44: =R44/I44 -> 3170.5849 | X44: =S44/I44 -> 3170.5849 | Y44: =T44/I44 -> 3302.6926 | AB44: 45643 | AC44: =20%*R44 -> 77952 | AH44: =80%*R44 -> 311808 | AI44: GlobalKey | AO44: Brilhantina Maria da Silva Almeida | AP44: Portugal | AT44: zimscorp.tina@hotmail.com | AU44: 967185058 | AX44: =AY44*I44 -> 335598.9 | AY44: 2730
A45: 44 | B45: AR | C45: T3 | D45: 6 | E45: E/W | F45: 134.6 | G45: =7.6+24.6 -> 32.2 | I45: =F45+0.3*G45+0.3*H45 -> 144.26 | J45: CPCV | K45: 2 spots (side by side) | L45: in -1 | R45: 479040 | S45: =0.96*T45 -> 479040 | T45: 499000 | U45: 480000 | V45: =S45/T45-1 -> -0.04 | W45: =R45/I45 -> 3320.671 | X45: =S45/I45 -> 3320.671 | Y45: =T45/I45 -> 3459.0323 | AB45: 45603 | AC45: =20%*R45 -> 95808 | AH45: =80%*R45 -> 383232 | AI45: Chavenova | AO45: DIVERSTOCK INVESTMENTS SA | AP45: Portugal | AT45: jose.meneses@diverstock.com | AU45: 917520252 | AX45: =AY45*I45 -> 393829.8 | AY45: 2730
A46: 45 | B46: AS | C46: T3 | D46: 6 | E46: E/W | F46: 134.6 | G46: =7.6+24.6 -> 32.2 | I46: =F46+0.3*G46+0.3*H46 -> 144.26 | J46: CPCV | K46: 2 spots (side by side) | L46: in -1 | R46: 460800 | S46: =0.96*T46 -> 460800 | T46: 480000 | V46: =S46/T46-1 -> -0.04 | W46: =R46/I46 -> 3194.2326 | X46: =S46/I46 -> 3194.2326 | Y46: =T46/I46 -> 3327.3257 | AA46: 45486 | AB46: 45502 | AC46: =10%*R46+5000 -> 51080 | AH46: =90%*R46-5000 -> 409720 | AI46: Chavenova | AO46: Florentino Alberto Pereira dos Santos | AP46: Portugal | AT46: florentino-a-santos@sapo.pt | AU46: 969012963 | AX46: =AY46*I46 -> 393829.8 | AY46: 2730
A47: 46 | B47: AT | C47: T3 | D47: 6 | E47: S/E | F47: 116.6 | G47: 16.5 | I47: =F47+0.3*G47+0.3*H47 -> 121.55 | J47: CPCV | K47: 2 spots (in front of each other) | L47: in -1 | R47: 398400 | S47: =0.96*T47 -> 398400 | T47: 415000 | V47: =S47/T47-1 -> -0.04 | W47: =R47/I47 -> 3277.6635 | X47: =S47/I47 -> 3277.6635 | Y47: =T47/I47 -> 3414.2328 | AA47: 45486 | AB47: 45510 | AC47: =10%*R47+5000 -> 44840 | AH47: =90%*R47-5000 -> 353560 | AI47: Chavenova | AO47: Abreu dos Santos Alonso e Sónia Maria Barbosa da Silva Carvalhido | AP47: Portugal | AT47: abreualonso1964@gmail.com | AU47: 919459875 | AX47: =AY47*I47 -> 331831.5 | AY47: 2730
A48: 47 | B48: AU | C48: T2 | D48: 6 | E48: N/W | F48: 85.8 | G48: 54.9 | I48: =F48+0.2*G48+0.3*H48 -> 96.78 | J48: CPCV | K48: 1 spot | L48: in -1 | R48: 322560 | S48: =0.96*T48 -> 322560 | T48: 336000 | V48: =S48/T48-1 -> -0.04 | W48: =R48/I48 -> 3332.92 | X48: =S48/I48 -> 3332.92 | Y48: =T48/I48 -> 3471.7917 | AB48: 45525 | AC48: =10%*R48 -> 32256 | AD48: =10%*R48 -> 32256 | AE48: =182+AB48 -> 45707 | AH48: =80%*R48 -> 258048 | AI48: Chavenova | AO48: INSPIREGATE Unipessoal LDA | AP48: Portugal | AT48: cmoandrade@gmail.com | AU48: 935120003 | AX48: =AY48*I48 -> 264209.4 | AY48: 2730
A49: 48 | B49: AV | C49: T2 | D49: 6 | E49: W | F49: 84.8 | G49: 33.2 | I49: =F49+0.2*G49+0.3*H49 -> 91.44 | J49: CPCV | K49: 1 spot | L49: in -1 | R49: 313920 | S49: =0.96*T49 -> 313920 | T49: 327000 | V49: =S49/T49-1 -> -0.04 | W49: =R49/I49 -> 3433.0709 | X49: =S49/I49 -> 3433.0709 | Y49: =T49/I49 -> 3576.1155 | AB49: 45526 | AC49: =20%*R49 -> 62784 | AH49: =80%*R49 -> 251136 | AI49: Chavenova | AO49: Hugo Tiago Ferreira Teixeira & Laure Isabelle Audrey Gisela Andrée Harivel | AP49: Portugal | AX49: =AY49*I49 -> 249631.2 | AY49: 2730
A50: 49 | B50: AW | C50: T2 | D50: 6 | E50: W | F50: 84.8 | G50: 33.2 | I50: =F50+0.2*G50+0.3*H50 -> 91.44 | J50: CPCV | K50: 1 spot | L50: in -2 | R50: 313920 | S50: =0.96*T50 -> 313920 | T50: 327000 | V50: =S50/T50-1 -> -0.04 | W50: =R50/I50 -> 3433.0709 | X50: =S50/I50 -> 3433.0709 | Y50: =T50/I50 -> 3576.1155 | AA50: 45493 | AB50: 45504 | AC50: =57784+5000 -> 62784 | AH50: =80%*R50 -> 251136 | AI50: GlobalKey | AO50: David Beijoco & Daniela Cabanelos | AP50: Portugal | AT50: davidbeijoco@bastarda.pt | AU50: 916676729 | AX50: =AY50*I50 -> 249631.2 | AY50: 2730 | AZ50: 365000
A51: 50 | B51: AX | C51: T2 | D51: 6 | E51: S/W | F51: 85.8 | G51: 50.8 | I51: =F51+0.2*G51+0.3*H51 -> 95.96 | J51: CPCV | K51: 1 spot | L51: in -2 | R51: 332160 | S51: =0.96*T51 -> 332160 | T51: 346000 | V51: =S51/T51-1 -> -0.04 | W51: =R51/I51 -> 3461.4423 | X51: =S51/I51 -> 3461.4423 | Y51: =T51/I51 -> 3605.669 | AA51: 45486 | AB51: 45535 | AC51: 66432 | AH51: 265728 | AI51: Chavenova | AO51: Maria Isabel Silva Cruz | AP51: Portugal | AT51: isabel.misc2001@gmail.com | AU51: 938835623 | AX51: =AY51*I51 -> 261970.8 | AY51: 2730
A52: 51 | B52: AY | C52: T4 | D52: 7 | E52: N/E/W | F52: 177 | H52: 110.7 | I52: =F52+0.3*G52+0.3*H52 -> 210.21 | K52: 1 box + 1 spot | L52: in -1 | S52: =0.96*T52 -> 748800 | T52: 780000 | U52: 780000 | V52: =S52/T52-1 -> -0.04 | W52: =R52/I52 -> 0 | X52: =S52/I52 -> 3562.1521 | Y52: =T52/I52 -> 3710.5751 | AC52: =20%*R52 -> 0 | AH52: =80%*R52 -> 0 | AX52: =AY52*I52 -> 573873.3 | AY52: 2730
A53: 52 | B53: AZ | C53: T4 | D53: 7 | E53: E/W | F53: 174.2 | H53: 55.9 | I53: =F53+0.3*G53+0.3*H53 -> 190.97 | J53: CPCV | K53: 1 box + 1 spot | L53: in -2 | R53: 662400 | S53: =0.96*T53 -> 662400 | T53: 690000 | U53: 690000 | V53: =S53/T53-1 -> -0.04 | W53: =R53/I53 -> 3468.6076 | X53: =S53/I53 -> 3468.6076 | Y53: =T53/I53 -> 3613.133 | AA53: 45780 | AB53: 45943 | AC53: =20%*S53 -> 132480 | AH53: =80%*S53 -> 529920 | AI53: Chavenova | AO53: Andre Eugenio Ruivo de Sousa | AX53: =AY53*I53 -> 521348.1 | AY53: 2730
A54: 53 | B54: BA | C54: T4 | D54: 7 | E54: E/W | F54: 174.2 | H54: 55.9 | I54: =F54+0.3*G54+0.3*H54 -> 190.97 | J54: CPCV | K54: 1 box + 1 spot | L54: in -2 | R54: 662400 | S54: =0.96*T54 -> 662400 | T54: 690000 | V54: =S54/T54-1 -> -0.04 | W54: =R54/I54 -> 3468.6076 | X54: =S54/I54 -> 3468.6076 | Y54: =T54/I54 -> 3613.133 | AB54: 45534 | AC54: =20%*R54 -> 132480 | AH54: =80%*R54 -> 529920 | AI54: GlobalKey | AO54: Antonio Aires Moreira Pinto Ferreira & Palmira Ferreira | AP54: Portugal | AT54: aampf@hotmail.com | AU54: 966930007 | AX54: =AY54*I54 -> 521348.1 | AY54: 2730
A55: 54 | B55: BB | C55: T4 | D55: 7 | E55: S/E/W | F55: 177 | H55: 110.7 | I55: =F55+0.3*G55+0.3*H55 -> 210.21 | J55: CPCV | K55: 1 box + 1 spot | L55: in -1 | R55: 763200 | S55: =0.96*T55 -> 763200 | T55: 795000 | U55: 795000 | V55: =S55/T55-1 -> -0.04 | W55: =R55/I55 -> 3630.6551 | X55: =S55/I55 -> 3630.6551 | Y55: =T55/I55 -> 3781.9324 | AA55: 45608 | AB55: 45574 | AC55: =20%*R55+5000 -> 157640 | AH55: =80%*R55-5000 -> 605560 | AI55: Chavenova | AO55: QXQTXU, LDA | AP55: China | AT55: nunoxu.05070@gmail.com | AU55: 967893230 | AX55: =AY55*I55 -> 573873.3 | AY55: 2730
F56: =SUM(F2:F55) -> 5600.7 | I56: =SUM(I2:I55) -> 6149.28 | S56: =SUM(S2:S55) -> 20125440
C58: # | D58: € | E58: €/m² | G58: SOLD IN | J58: CPCV 2024
A59: CPCV | C59: =COUNTIF(J2:J55,A59) -> 53 | D59: =SUMIF(J2:J55,A59,R2:R55) -> 19448392 | E59: =AVERAGEIF(J2:J55,A59,W2:W55) -> 3282.6941 | G59: 2024 | H59: =COUNTIFS(AB2:AB55,">="&DATE(2024,1,1),AB2:AB55,"<="&DATE(2024,12,31)) -> 46 | J59: January | K59: February | L59: March | M59: April | N59: May | O59: June | P59: July | Q59: August | R59: September | S59: October | T59: November | U59: December
A60: BLOCKED | C60: =COUNTIF(J2:J55,A60) -> 0 | D60: =SUMIF(J2:J55,A60,S2:S55) -> 0 | E60: =AVERAGEIF(J2:J55,A60,X2:X55) -> #DIV/0! | G60: 2025 | H60: =COUNTIFS(AA2:AA55,">="&DATE(2025,1,1),AA2:AA55,"<="&DATE(2025,12,31)) -> 7 | J60: =COUNTIFS(AB2:AB55,">="&DATE(2024,1,1),AB2:AB55,"<="&DATE(2024,1,31)) -> 0 | K60: =COUNTIFS(AB2:AB55,">="&DATE(2024,2,1),AB2:AB55,"<="&DATE(2024,2,29)) -> 0 | L60: =COUNTIFS(AB2:AB55,">="&DATE(2024,3,1),AB2:AB55,"<="&DATE(2024,3,31)) -> 0 | M60: =COUNTIFS(AB2:AB55,">="&DATE(2024,4,1),AB2:AB55,"<="&DATE(2024,4,31)) -> 0 | N60: =COUNTIFS(AB2:AB55,">="&DATE(2024,5,1),AB2:AB55,"<="&DATE(2024,5,31)) -> 0 | O60: =COUNTIFS(AB2:AB55,">="&DATE(2024,6,1),AB2:AB55,"<="&DATE(2024,6,31)) -> 0 | P60: =COUNTIFS(AB2:AB55,">="&DATE(2024,7,1),AB2:AB55,"<="&DATE(2024,7,31)) -> 10 | Q60: =COUNTIFS(AB2:AB55,">="&DATE(2024,8,1),AB2:AB55,"<="&DATE(2024,8,31)) -> 22 | R60: =COUNTIFS(AB2:AB55,">="&DATE(2024,9,1),AB2:AB55,"<="&DATE(2024,9,31)) -> 3 | S60: =COUNTIFS(AB2:AB55,">="&DATE(2024,10,1),AB2:AB55,"<="&DATE(2024,10,31)) -> 6 | T60: =COUNTIFS(AB2:AB55,">="&DATE(2024,11,1),AB2:AB55,"<="&DATE(2024,11,31)) -> 4 | U60: =COUNTIFS(AB2:AB55,">="&DATE(2024,12,1),AB2:AB55,"<="&DATE(2024,12,31)) -> 1
A61: AVAILABLE | C61: =COUNTIF(J2:J55,"") -> 1 | D61: =SUMIF(J2:J55,"",S2:S55) -> 748800 | E61: =AVERAGEIF(J2:J55,"",X2:X55) -> 3562.1521 | G61: 2026 | H61: =COUNTIFS(AA2:AA55,">="&DATE(2026,1,1),AA2:AA55,"<="&DATE(2026,12,31)) -> 0
A62: RESERVED | C62: =COUNTIF(J2:J55,A62) -> 0 | D62: =SUMIF(J2:J55,A62,R2:R55) -> 0 | E62: =AVERAGEIF(J2:J55,A62,W2:W55) -> #DIV/0! | J62: CPCV 2025
A63: TOTAL | C63: =SUBTOTAL(9,C59:C62) -> 54 | D63: =SUBTOTAL(9,D59:D62) -> 20197192 | E63: =D63/I56 -> 3284.4808 | G63: Percentage Sold | H63: =(C62+C59)/C63 -> 0.98148148 | J63: January | K63: February | L63: March | M63: April | N63: May | O63: June | P63: July | Q63: August | R63: September | S63: October | T63: November | U63: December
J64: =COUNTIFS(AB2:AB55,">="&DATE(2025,1,1),AB2:AB55,"<="&DATE(2025,1,31)) -> 0 | K64: =COUNTIFS(AB2:AB55,">="&DATE(2025,2,1),AB2:AB55,"<="&DATE(2025,2,28)) -> 0 | L64: =COUNTIFS(AB2:AB55,">="&DATE(2025,3,1),AB2:AB55,"<="&DATE(2025,3,31)) -> 2 | M64: =COUNTIFS(AB2:AB55,">="&DATE(2025,4,1),AB2:AB55,"<="&DATE(2025,4,31)) -> 0 | N64: =COUNTIFS(AB2:AB55,">="&DATE(2025,5,1),AB2:AB55,"<="&DATE(2025,5,31)) -> 0 | O64: =COUNTIFS(AB2:AB55,">="&DATE(2025,6,1),AB2:AB55,"<="&DATE(2025,6,31)) -> 0 | P64: =COUNTIFS(AB2:AB55,">="&DATE(2025,7,1),AB2:AB55,"<="&DATE(2025,7,31)) -> 0 | Q64: =COUNTIFS(AB2:AB55,">="&DATE(2025,8,1),AB2:AB55,"<="&DATE(2025,8,31)) -> 2 | R64: =COUNTIFS(AB2:AB55,">="&DATE(2025,9,1),AB2:AB55,"<="&DATE(2025,9,31)) -> 2 | S64: =COUNTIFS(AB2:AB55,">="&DATE(2025,10,1),AB2:AB55,"<="&DATE(2025,10,31)) -> 1 | T64: =COUNTIFS(AB2:AB55,">="&DATE(2025,11,1),AB2:AB55,"<="&DATE(2025,11,31)) -> 0 | U64: =COUNTIFS(AB2:AB55,">="&DATE(2025,12,1),AB2:AB55,"<="&DATE(2025,12,31)) -> 0
A65: # | C65: T1 | D65: T2 | E65: T3 | F65: T4 | G65: Total
A66: CPCV | C66: =COUNTIFS(J2:J55,A66,C2:C55,C65) -> 9 | D66: =COUNTIFS(J2:J55,A66,C2:C55,D65) -> 20 | E66: =COUNTIFS(J2:J55,A66,C2:C55,E65) -> 21 | F66: =COUNTIFS(J2:J55,A66,C2:C55,F65) -> 3 | G66: =SUM(C66:F66) -> 53
A67: BLOCKED | C67: =COUNTIFS(J2:J55,A67,C2:C55,C65) -> 0 | D67: =COUNTIFS(J2:J55,A67,C2:C55,D65) -> 0 | E67: =COUNTIFS(J2:J55,A67,C2:C55,E65) -> 0 | F67: =COUNTIFS(J2:J55,A67,C2:C55,F65) -> 0 | G67: =SUM(C67:F67) -> 0 | J67: Brokers | O67: Nationalities
A68: AVAILABLE | C68: =COUNTIFS(J2:J55,"",C2:C55,C65) -> 0 | D68: =COUNTIFS(J2:J55,"",C2:C55,D65) -> 0 | E68: =COUNTIFS(J2:J55,"",C2:C55,E65) -> 0 | F68: =COUNTIFS(J2:J55,"",C2:C55,F65) -> 1 | G68: =SUM(C68:F68) -> 1 | K68: Overall | L68: 2024 | M68: % | P68: Overall | Q68: 2024 | R68: %
A69: RESERVED | C69: =COUNTIFS(J2:J55,A69,C2:C55,C65) -> 0 | D69: =COUNTIFS(J2:J55,A69,C2:C55,D65) -> 0 | E69: =COUNTIFS(J2:J55,A69,C2:C55,E65) -> 0 | F69: =COUNTIFS(J2:J55,A69,C2:C55,F65) -> 0 | G69: =SUM(C69:F69) -> 0 | J69: GLOBALKEY | K69: =COUNTIFS(J2:J55,J4,AI2:AI55,J69) -> 25 | L69: =COUNTIFS(AB2:AB55,">="&DATE(2024,1,1),AB2:AB55,"<="&DATE(2024,12,31),AI2:AI55,J69) -> 20 | M69: =K69/(+K69+K70+K71) -> 0.47169811 | O69: Portugal | P69: =COUNTIFS($J$2:$J$55,J4,$AP$2:$AP$55,O69) -> 50 | Q69: =COUNTIFS(AB2:AB55,">="&DATE(2024,1,1),AB2:AB55,"<="&DATE(2024,12,31),$AP$2:$AP$55,O69) -> 44 | R69: =P69/(+P69+P70+P71) -> 0.98039216
A70: Total | C70: =SUM(C66:C69) -> 9 | D70: =SUM(D66:D69) -> 20 | E70: =SUM(E66:E69) -> 21 | F70: =SUM(F66:F69) -> 4 | G70: =SUM(G66:G69) -> 54 | J70: CHAVENOVA | K70: =COUNTIFS(J2:J55,J4,AI2:AI55,J70) -> 28 | L70: =COUNTIFS(AB2:AB55,">="&DATE(2024,1,1),AB2:AB55,"<="&DATE(2024,12,31),AI2:AI55,J70) -> 26 | M70: =K70/(+K69+K70+K71) -> 0.52830189 | O70: Israel | P70: =COUNTIFS($J$2:$J$55,J55,$AP$2:$AP$55,O70) -> 0 | Q70: =COUNTIFS(AB2:AB55,">="&DATE(2024,1,1),AB2:AB55,"<="&DATE(2024,12,31),$AP$2:$AP$55,O70) -> 0 | R70: =P70/(+P69+P70+P71) -> 0
J71: TRANQUILDISCOVERY | K71: =COUNTIFS(J2:J55,J4,AI2:AI55,J71) -> 0 | L71: =COUNTIFS(AB2:AB55,">="&DATE(2024,1,1),AB2:AB55,"<="&DATE(2024,12,31),AI2:AI55,J71) -> 0 | M71: =K71/(+K69+K70+K71) -> 0 | O71: Brazil | P71: =COUNTIFS($J$2:$J$55,J54,$AP$2:$AP$55,O71) -> 1 | Q71: =COUNTIFS(AB2:AB55,">="&DATE(2024,1,1),AB2:AB55,"<="&DATE(2024,12,31),$AP$2:$AP$55,O71) -> 1 | R71: =P71/(+P69+P70+P71) -> 0.019607843
O72: China | P72: =COUNTIFS($J$2:$J$55,J55,$AP$2:$AP$55,O72) -> 1 | Q72: =COUNTIFS(AB3:AB56,">="&DATE(2024,1,1),AB3:AB56,"<="&DATE(2024,12,31),$AP$2:$AP$55,O72) -> 0 | R72: =P72/(SUM(P69:P72)) -> 0.019230769
A73: Average €/m² | C73: T1 | D73: T2 | E73: T3 | F73: T4 | G73: Total
A74: CPCV | C74: =AVERAGEIFS(W2:W55,J2:J55,A74,C2:C55,C73) -> 3344.1115 | D74: =AVERAGEIFS(W2:W55,J2:J55,A74,C2:C55,D73) -> 3352.355 | E74: =AVERAGEIFS(W2:W55,J2:J55,A74,C2:C55,E73) -> 3155.7531 | F74: =AVERAGEIFS(W2:W55,J2:J55,A74,C2:C55,F73) -> 3522.6234 | G74: =AVERAGEIF(J2:J55,A74,W2:W55) -> 3282.6941
A75: BLOCKED | C75: =AVERAGEIFS(X2:X55,J2:J55,A75,C2:C55,C73) -> #DIV/0! | D75: =AVERAGEIFS(X2:X55,J2:J55,A75,C2:C55,D73) -> #DIV/0! | E75: =AVERAGEIFS(X2:X55,J2:J55,A75,C2:C55,E73) -> #DIV/0! | F75: =AVERAGEIFS(X2:X55,J2:J55,A75,C2:C55,F73) -> #DIV/0! | G75: =AVERAGEIF(J2:J55,A75,X2:X55) -> #DIV/0!
A76: AVAILABLE | C76: =AVERAGEIFS(X2:X55,J2:J55,"",C2:C55,C73) -> #DIV/0! | D76: =AVERAGEIFS(X2:X55,J2:J55,"",C2:C55,D73) -> #DIV/0! | E76: =AVERAGEIFS(X2:X55,J2:J55,"",C2:C55,E73) -> #DIV/0! | F76: =AVERAGEIFS(X2:X55,J2:J55,"",C2:C55,F73) -> 3562.1521 | G76: =AVERAGEIF(J2:J55,"",X2:X55) -> 3562.1521
A77: RESERVED | C77: =AVERAGEIFS(W2:W55,J2:J55,A77,C2:C55,C73) -> #DIV/0! | D77: =AVERAGEIFS(W2:W55,J2:J55,A77,C2:C55,D73) -> #DIV/0! | E77: =AVERAGEIFS(W2:W55,J2:J55,A77,C2:C55,E73) -> #DIV/0! | F77: =AVERAGEIFS(W2:W55,J2:J55,A77,C2:C55,F73) -> #DIV/0! | G77: =AVERAGEIF(J2:J55,A77,W2:W55) -> #DIV/0!
A79: Average €/unit | C79: T1 | D79: T2 | E79: T3 | F79: T4 | G79: Total
A80: CPCV | C80: =AVERAGEIFS(R2:R55,J2:J55,A80,C2:C55,C79) -> 234967.78 | D80: =AVERAGEIFS(R2:R55,J2:J55,A80,C2:C55,D79) -> 317928 | E80: =AVERAGEIFS(R2:R55,J2:J55,A80,C2:C55,E79) -> 423196.29 | F80: =AVERAGEIFS(R2:R55,J2:J55,A80,C2:C55,F79) -> 696000 | G80: =AVERAGEIF(J2:J55,A80,R2:R55) -> 366950.79
A81: BLOCKED | C81: =AVERAGEIFS(T2:T55,J2:J55,A81,C2:C55,C79) -> #DIV/0! | D81: =AVERAGEIFS(T2:T55,J2:J55,A81,C2:C55,D79) -> #DIV/0! | E81: =AVERAGEIFS(T2:T55,J2:J55,A81,C2:C55,E79) -> #DIV/0! | F81: =AVERAGEIFS(T2:T55,J2:J55,A81,C2:C55,F79) -> #DIV/0! | G81: =AVERAGEIF(J2:J55,A81,R2:R55) -> #DIV/0!
A82: AVAILABLE | C82: =AVERAGEIFS(S2:S55,J2:J55,"",C2:C55,C79) -> #DIV/0! | D82: =AVERAGEIFS(T2:T55,J2:J55,"",C2:C55,D79) -> #DIV/0! | E82: =AVERAGEIFS(S2:S55,J2:J55,"",C2:C55,E79) -> #DIV/0! | F82: =AVERAGEIFS(T2:T55,J2:J55,"",C2:C55,F79) -> 780000 | G82: =AVERAGEIF(J2:J55,"",S2:S55) -> 748800
A83: RESERVED | C83: =AVERAGEIFS(R2:R55,J2:J55,A83,C2:C55,C79) -> #DIV/0! | D83: =AVERAGEIFS(R2:R55,J2:J55,A83,C2:C55,D79) -> #DIV/0! | E83: =AVERAGEIFS(R2:R55,J2:J55,A83,C2:C55,E79) -> #DIV/0! | F83: =AVERAGEIFS(R2:R55,J2:J55,A83,C2:C55,F79) -> #DIV/0! | G83: =AVERAGEIF(J2:J55,A83,R2:R55) -> #DIV/0!
A85: Average size m² | C85: T1 | D85: T2 | E85: T3 | F85: T4 | G85: Total
A86: CPCV | C86: =AVERAGEIFS(I2:I55,C2:C55,C85,J2:J55,A86) -> 70.253333 | D86: =AVERAGEIFS(I2:I55,C2:C55,D85,J2:J55,A86) -> 94.984 | E86: =AVERAGEIFS(I2:I55,C2:C55,E85,J2:J55,A86) -> 134.04571 | F86: =AVERAGEIFS(I2:I55,C2:C55,F85,J2:J55,A86) -> 197.38333 | G86: =AVERAGEIF(J2:J55,A86,I2:I55) -> 112.05792
A87: BLOCKED | C87: =AVERAGEIFS(I2:I55,C2:C55,C85,J2:J55,A87) -> #DIV/0! | D87: =AVERAGEIFS(I2:I55,C2:C55,D85,J2:J55,A87) -> #DIV/0! | E87: =AVERAGEIFS(I2:I55,C2:C55,E85,J2:J55,A87) -> #DIV/0! | F87: =AVERAGEIFS(I2:I55,C2:C55,F85,J2:J55,A87) -> #DIV/0! | G87: =AVERAGEIF(J2:J55,A87,I2:I55) -> #DIV/0!
A88: AVAILABLE | C88: =AVERAGEIFS(I2:I55,C2:C55,C85,J2:J55,"") -> #DIV/0! | D88: =AVERAGEIFS(I2:I55,C2:C55,D85,J2:J55,"") -> #DIV/0! | E88: =AVERAGEIFS(I2:I55,C2:C55,E85,J2:J55,"") -> #DIV/0! | F88: =AVERAGEIFS(I2:I55,C2:C55,F85,J2:J55,"") -> 210.21 | G88: =AVERAGEIF(J2:J55,"",I2:I55) -> 210.21
A89: RESERVED | C89: =AVERAGEIFS(I2:I55,C2:C55,C85,J2:J55,A89) -> #DIV/0! | D89: =AVERAGEIFS(I2:I55,C2:C55,D85,J2:J55,A89) -> #DIV/0! | E89: =AVERAGEIFS(I2:I55,C2:C55,E85,J2:J55,A89) -> #DIV/0! | F89: =AVERAGEIFS(I2:I55,C2:C55,F85,J2:J55,A89) -> #DIV/0! | G89: =AVERAGEIF(J2:J55,A89,I2:I55) -> #DIV/0!
C91: =1.5*C89 -> #DIV/0! | D91: =1.5*D89 -> #DIV/0! | E91: =1.5*E89 -> #DIV/0! | F91: =1.5*F89 -> #DIV/0!

Sheet VERDE VALE H4 A&B (MAIA)
A1: Unit | B1: Building | C1: Fraction | D1: Layout | E1: Floor | F1: Directions | G1: Main area | H1: Balcony | I1: Terrace | J1: Saleable Area | K1: Status | L1: Parking 1 | M1: Parking Floor | N1: Storage | O1: Parking 4 | P1: Storage | Q1: Signed | R1: Payment | S1: Closing Price | T1: Min. Price | U1: Asking Price | V1: First price (27/09) | W1: % Discount | X1: €/m² sold | Y1: €/m² min. price | Z1: €/m² asking price | AA1: On hold | AB1: Date of Reservation | AC1: Date of CPCV | AD1: CPCV Value | AE1: 1st down payment | AF1: Date 1st down pmt. | AG1: 2nd down payment | AH1: Date 2nd down pmt. | AI1: Deed | AJ1: Brokers company | AK1: Broker Name | AL1: % Commission | AM1: PO done? | AN1: Invoice received? | AO1: Invoice Paid? | AP1: Client | AQ1: Client Nationality | AR1: Birth Date | AS1: Age | AT1: Investor / Final Client | AU1: Email | AV1: Phone | AW1: Cancelled? | AX1: Why Cancelled? | AY1: Business Plan Price | AZ1: €/m² Business Plan
A2: A | B2: S1 | C2: Services | G2: 225 | H2: 225 | J2: =G2+0.3*H2 -> 292.5 | L2: 4 | M2: gf | T2: =0.96*U2 -> 576000 | U2: 600000 | Z2: =U2/J2 -> 2051.2821
A3: B | B3: S1 | C3: Services | G3: =225+60.4 -> 285.4 | H3: 152.7 | J3: =G3+0.3*H3 -> 331.21 | L3: 6 | M3: gf | T3: =0.96*U3 -> 768000 | U3: 800000 | Z3: =U3/J3 -> 2415.386
A4: 1 | B4: H4A | C4: A | D4: T1 | E4: 1 | F4: E | G4: 64.6 | I4: 19.4 | J4: =G4+0.3*H4+0.3*I4 -> 70.42 | K4: CPCV | L4: 1 spot | M4: -1 | N4: No | S4: 254400 | T4: =0.96*U4 -> 254400 | U4: 265000 | W4: =S4/U4-1 -> -0.04 | X4: =S4/J4 -> 3612.6101 | Y4: =T4/J4 -> 3612.6101 | Z4: =U4/J4 -> 3763.1355 | AB4: 45839 | AC4: 45870 | AD4: =5000+45880 -> 50880 | AI4: 203520 | AJ4: Chavenova | AP4: Telmo Pereira Peixoto Correia Braga | AQ4: Portugal | AY4: =AZ4*J4 -> 192246.6 | AZ4: 2730
A5: 2 | B5: H4A | C5: B | D5: T1 | E5: 1 | F5: E | G5: 60.9 | I5: 19.2 | J5: =G5+0.3*H5+0.2*I5 -> 64.74 | K5: CPCV | L5: 1 spot | M5: -2 | N5: Yes | S5: =0.96*U5 -> 244800 | T5: =0.96*U5 -> 244800 | U5: 255000 | W5: =S5/U5-1 -> -0.04 | X5: =S5/J5 -> 3781.279 | Y5: =T5/J5 -> 3781.279 | Z5: =U5/J5 -> 3938.8323 | AB5: 45563 | AC5: 45575 | AD5: =20%*S5+5000 -> 53960 | AI5: =80%*S5-5000 -> 190840 | AJ5: Chavenova | AP5: JACINTO MANUEL ARAUJO | AQ5: Portugal | AY5: =AZ5*J5 -> 176740.2 | AZ5: 2730
A6: 3 | B6: H4A | C6: C | D6: T1 | E6: 1 | F6: E | G6: 60.9 | I6: 19.2 | J6: =G6+0.3*H6+0.2*I6 -> 64.74 | K6: CPCV | L6: 1 spot | M6: -2 | N6: No | S6: 244800 | T6: =0.96*U6 -> 244800 | U6: 255000 | W6: =S6/U6-1 -> -0.04 | X6: =S6/J6 -> 3781.279 | Y6: =T6/J6 -> 3781.279 | Z6: =U6/J6 -> 3938.8323 | AB6: 45649 | AC6: 45688 | AD6: 35000 | AE6: 13960 | AI6: =80%*S6 -> 195840 | AJ6: Chavenova | AP6: Mariana Costa Marinho | AQ6: Portugal | AU6: marianacostamarinho@gmail.com | AV6: 912469329 | AY6: =AZ6*J6 -> 176740.2 | AZ6: 2730
A7: 4 | B7: H4A | C7: D | D7: T3 | E7: 1 | F7: S/E | G7: 109.7 | I7: 25.2 | J7: =G7+0.3*H7+0.3*I7 -> 117.26 | K7: CPCV | L7: 2 spots (side by side) | M7: -2 | N7: Yes | S7: 384000 | T7: =0.96*U7 -> 384000 | U7: 400000 | W7: =S7/U7-1 -> -0.04 | X7: =S7/J7 -> 3274.774 | Y7: =T7/J7 -> 3274.774 | Z7: =U7/J7 -> 3411.2229 | AB7: 45713 | AC7: 45730 | AD7: =5000+71800 -> 76800 | AI7: =80%*S7 -> 307200 | AJ7: Chavenova | AP7: Carlos Manuel Gouveia Pereira & Sandrine Figueira Pedro | AQ7: Portugal | AU7: cmgpereira@gmail.com | AV7: 935167167 | AY7: =AZ7*J7 -> 320119.8 | AZ7: 2730
A8: 5 | B8: H4A | C8: E | D8: T2 | E8: 1 | F8: N/W | G8: 87.3 | I8: 62.7 | J8: =G8+0.3*H8+0.2*I8 -> 99.84 | K8: CPCV | L8: 1 spot | M8: -1 | N8: Yes | S8: =0.96*U8 -> 297600 | T8: =0.96*U8 -> 297600 | U8: 310000 | W8: =S8/U8-1 -> -0.04 | X8: =S8/J8 -> 2980.7692 | Y8: =T8/J8 -> 2980.7692 | Z8: =U8/J8 -> 3104.9679 | AB8: 45563 | AC8: 45575 | AD8: =20%*S8 -> 59520 | AI8: =80%*S8 -> 238080 | AJ8: Chavenova | AP8: VALEFERRUGEM UNIPESSOAL LDA | AQ8: Portugal | AU8: vale380engenharia@gmail.com | AV8: 937565124 | AY8: =AZ8*J8 -> 272563.2 | AZ8: 2730
A9: 6 | B9: H4A | C9: F | D9: T1 | E9: 1 | F9: W | G9: 62.3 | I9: 46.2 | J9: =G9+0.3*H9+0.2*I9 -> 71.54 | K9: CPCV | L9: 1 spot | M9: -2 | N9: No | S9: =0.96*U9 -> 256320 | T9: =0.96*U9 -> 256320 | U9: 267000 | W9: =S9/U9-1 -> -0.04 | X9: =S9/J9 -> 3582.8907 | Y9: =T9/J9 -> 3582.8907 | Z9: =U9/J9 -> 3732.1778 | AC9: 45589 | AD9: =20%*S9 -> 51264 | AI9: =80%*S9 -> 205056 | AJ9: Globalkey | AP9: ROSEMBERG Unipessoal | AQ9: Brazil | AU9: rosembergsouza59@gmail.com | AV9: 912625055 | AY9: =AZ9*J9 -> 195304.2 | AZ9: 2730
A10: 7 | B10: H4A | C10: G | D10: T1 | E10: 1 | F10: W | G10: 62.4 | I10: 47 | J10: =G10+0.3*H10+0.2*I10 -> 71.8 | K10: CPCV | L10: 1 spot | M10: -2 | N10: No | S10: 262000 | T10: =0.96*U10 -> 256320 | U10: 267000 | W10: =S10/U10-1 -> -0.018726592 | X10: =S10/J10 -> 3649.0251 | Y10: =T10/J10 -> 3569.9164 | Z10: =U10/J10 -> 3718.663 | AB10: 45602 | AC10: 45677 | AD10: =5000+47400 -> 52400 | AI10: =80%*S10 -> 209600 | AJ10: Globalkey | AP10: Polina Arshtein | AQ10: Israel | AY10: =AZ10*J10 -> 196014 | AZ10: 2730
A11: 8 | B11: H4A | C11: H | D11: T1 | E11: 1 | F11: W | G11: 62.4 | I11: 47 | J11: =G11+0.3*H11+0.2*I11 -> 71.8 | K11: CPCV | L11: 1 spot | M11: -2 | N11: No | R11: =4%*S11 -> 10600 | S11: 265000 | T11: =0.96*U11 -> 259200 | U11: 270000 | W11: =S11/U11-1 -> -0.018518519 | X11: =S11/J11 -> 3690.8078 | Y11: =T11/J11 -> 3610.0279 | Z11: =U11/J11 -> 3760.4457 | AB11: 45706 | AC11: 45722 | AD11: =5000+48000 -> 53000 | AI11: 212000 | AJ11: Globalkey | AP11: Isabel Maria Pereira Ferreira Braga | AQ11: Brazil | AU11: bebelbraga1@sapo.pt | AV11: 961697819 | AY11: =AZ11*J11 -> 196014 | AZ11: 2730
A12: 9 | B12: H4A | C12: I | D12: T1 | E12: 1 | F12: W | G12: 62.3 | I12: 46.2 | J12: =G12+0.3*H12+0.2*I12 -> 71.54 | K12: CPCV | L12: 1 spot | M12: -1 | N12: No | S12: 270000 | T12: =0.96*U12 -> 259200 | U12: 270000 | W12: =S12/U12-1 -> 0 | X12: =S12/J12 -> 3774.1124 | Y12: =T12/J12 -> 3623.1479 | Z12: =U12/J12 -> 3774.1124 | AB12: 45563 | AC12: 45575 | AD12: =20%*S12 -> 54000 | AI12: =80%*S12 -> 216000 | AJ12: Chavenova | AP12: João Ismael Ferreira | AQ12: Portugal | AU12: joao.ismael@gmail.com | AV12: 936422183 | AY12: =AZ12*J12 -> 195304.2 | AZ12: 2730
A13: 10 | B13: H4A | C13: J | D13: T2 | E13: 1 | F13: S/W | G13: 87.3 | I13: 62.7 | J13: =G13+0.3*H13+0.2*I13 -> 99.84 | K13: CPCV | L13: 1 spot | M13: -1 | N13: Yes | S13: 319680 | T13: =0.96*U13 -> 319680 | U13: 333000 | V13: 320000 | W13: =S13/U13-1 -> -0.04 | X13: =S13/J13 -> 3201.9231 | Y13: =T13/J13 -> 3201.9231 | Z13: =U13/J13 -> 3335.3365 | AB13: 45590 | AC13: 45601 | AD13: =20%*S13 -> 63936 | AI13: =80%*S13 -> 255744 | AJ13: Globalkey | AP13: Andreia Cristina Gomes Moreira | AQ13: Portugal | AU13: andreiacgmoreira1985@gmail.com | AV13: 912373654 | AY13: =AZ13*J13 -> 272563.2 | AZ13: 2730
A14: 11 | B14: H4A | C14: K | D14: T3 | E14: 2 | F14: N/E | G14: 116.6 | H14: 47.5 | J14: =G14+0.2*H14+0.3*I14 -> 126.1 | K14: CPCV | L14: 2 spots (1 in front of other) | M14: -2 | N14: Yes | S14: 408000 | T14: =0.96*U14 -> 412800 | U14: 430000 | W14: =S14/U14-1 -> -0.051162791 | X14: =S14/J14 -> 3235.5274 | Y14: =T14/J14 -> 3273.5924 | Z14: =U14/J14 -> 3409.9921 | AB14: 45860 | AC14: 45868 | AD14: =5000+76600 -> 81600 | AI14: =80%*S14 -> 326400 | AJ14: Chavenova | AP14: Ricardo Manuel Marante de Oliveira Teixeira & Maria Rosa de Magalhães Sales Teixeira | AQ14: Portugal | AY14: =AZ14*J14 -> 344253 | AZ14: 2730
A15: 12 | B15: H4A | C15: L | D15: T3 | E15: 2 | F15: E/W | G15: 135.2 | H15: =36+20 -> 56 | J15: =G15+0.2*H15+0.3*I15 -> 146.4 | K15: CPCV | L15: 2 spots (side by side) | M15: -1 | N15: Yes | S15: 451200 | T15: =0.96*U15 -> 451200 | U15: 470000 | W15: =S15/U15-1 -> -0.04 | X15: =S15/J15 -> 3081.9672 | Y15: =T15/J15 -> 3081.9672 | Z15: =U15/J15 -> 3210.3825 | AB15: 45729 | AC15: 45764 | AD15: =5000+85240 -> 90240 | AI15: =80%*S15 -> 360960 | AJ15: Globalkey | AP15: Adriana Pires | AQ15: Portugal | AY15: =AZ15*J15 -> 399672 | AZ15: 2730
A16: 13 | B16: H4A | C16: M | D16: T3 | E16: 2 | F16: E/W | G16: 135.2 | H16: =36+20 -> 56 | J16: =G16+0.2*H16+0.3*I16 -> 146.4 | K16: CPCV | L16: 2 spots (side by side) | M16: -1 | N16: Yes | S16: 466000 | T16: =0.96*U16 -> 465600 | U16: 485000 | W16: =S16/U16-1 -> -0.039175258 | X16: =S16/J16 -> 3183.0601 | Y16: =T16/J16 -> 3180.3279 | Z16: =U16/J16 -> 3312.8415 | AB16: 45706 | AC16: 45792 | AD16: =5000+36000 -> 41000 | AE16: 20500 | AF16: =120+AC16 -> 45912 | AG16: 20500 | AH16: =120+AF16 -> 46032 | AI16: 384000 | AJ16: Globalkey | AP16: RENAN GOMES BELMONTE & GABRIELA QUELLER VALERIO | AQ16: Brazil | AU16: ric.pimenta@gmail.com | AV16: 918852877 | AY16: =AZ16*J16 -> 399672 | AZ16: 2730
A17: 14 | B17: H4A | C17: N | D17: T3 | E17: 2 | F17: S/E | G17: 116.6 | H17: 47.5 | J17: =G17+0.2*H17+0.3*I17 -> 126.1 | K17: CPCV | L17: 2 spots (side by side) | M17: -2 | N17: Yes | S17: 422400 | T17: =0.96*U17 -> 422400 | U17: 440000 | W17: =S17/U17-1 -> -0.04 | X17: =S17/J17 -> 3349.7224 | Y17: =T17/J17 -> 3349.7224 | Z17: =U17/J17 -> 3489.2942 | AB17: 45744 | AC17: 45782 | AD17: =5000+79480 -> 84480 | AI17: =80%*S17 -> 337920 | AJ17: Globalkey | AP17: Piotr Wenderski & Rochelette Dumbrique | AQ17: Polish | AY17: =AZ17*J17 -> 344253 | AZ17: 2730
A18: 15 | B18: H4A | C18: O | D18: T2 | E18: 2 | F18: N/W | G18: 86.7 | H18: 60.3 | J18: =G18+0.2*H18+0.3*I18 -> 98.76 | K18: CPCV | L18: 1 spot | M18: -1 | N18: Yes | S18: 340800 | T18: =0.96*U18 -> 340800 | U18: 355000 | V18: 335000 | W18: =S18/U18-1 -> -0.04 | X18: =S18/J18 -> 3450.7898 | Y18: =T18/J18 -> 3450.7898 | Z18: =U18/J18 -> 3594.5727 | AB18: 45742 | AC18: 45762 | AD18: =20%*S18 -> 68160 | AI18: =80%*S18 -> 272640 | AJ18: Globalkey | AP18: Beatriz Santos | AQ18: Portugal | AY18: =AZ18*J18 -> 269614.8 | AZ18: 2730
A19: 16 | B19: H4A | C19: P | D19: T1 | E19: 2 | F19: W | G19: 63.4 | H19: 25.1 | J19: =G19+0.2*H19+0.3*I19 -> 68.42 | K19: CPCV | L19: 1 spot | M19: -1 | N19: No | S19: 264000 | T19: =0.96*U19 -> 264000 | U19: 275000 | W19: =S19/U19-1 -> -0.04 | X19: =S19/J19 -> 3858.5209 | Y19: =T19/J19 -> 3858.5209 | Z19: =U19/J19 -> 4019.2926 | AB19: 45568 | AC19: 45625 | AD19: =20%*S19 -> 52800 | AI19: =80%*S19 -> 211200 | AJ19: Globalkey | AP19: Rui Santos | AQ19: Portugal | AU19: rui@oticatransmontana.pt | AV19: 273098336 | AY19: =AZ19*J19 -> 186786.6 | AZ19: 2730
A20: 17 | B20: H4A | C20: Q | D20: T1 | E20: 2 | F20: W | G20: 63.4 | H20: 25.1 | J20: =G20+0.2*H20+0.3*I20 -> 68.42 | K20: CPCV | L20: 1 spot | M20: -1 | N20: No | S20: 264000 | T20: =0.96*U20 -> 264000 | U20: 275000 | W20: =S20/U20-1 -> -0.04 | X20: =S20/J20 -> 3858.5209 | Y20: =T20/J20 -> 3858.5209 | Z20: =U20/J20 -> 4019.2926 | AC20: 45594 | AD20: =20%*S20 -> 52800 | AI20: =80%*S20 -> 211200 | AJ20: Tranquildiscovery | AP20: Sagie Arie | AQ20: Israel | AU20: sagia@davideng.co.il | AY20: =AZ20*J20 -> 186786.6 | AZ20: 2730
A21: 18 | B21: H4A | C21: R | D21: T2 | E21: 2 | F21: S/W | G21: 86.7 | H21: 60.3 | J21: =G21+0.2*H21+0.3*I21 -> 98.76 | K21: CPCV | L21: 1 spot | M21: -1 | N21: Yes | S21: =0.96*U21 -> 340800 | T21: =0.96*U21 -> 340800 | U21: 355000 | W21: =S21/U21-1 -> -0.04 | X21: =S21/J21 -> 3450.7898 | Y21: =T21/J21 -> 3450.7898 | Z21: =U21/J21 -> 3594.5727 | AB21: 45563 | AC21: 45647 | AD21: =20%*S21 -> 68160 | AI21: =80%*S21 -> 272640 | AJ21: Chavenova | AP21: Pedro Nuno Duarte Lima | AQ21: Portugal | AU21: pndlima@gmail.com | AV21: 916442592 | AY21: =AZ21*J21 -> 269614.8 | AZ21: 2730
A22: 19 | B22: H4A | C22: S | D22: T3 | E22: 3 | F22: N/E | G22: 116.6 | H22: 21.1 | J22: =G22+0.3*H22+0.3*I22 -> 122.93 | K22: CPCV | L22: 2 spots (1 in front of other) | M22: -2 | N22: Yes | S22: 417600 | T22: =0.96*U22 -> 417600 | U22: 435000 | W22: =S22/U22-1 -> -0.04 | X22: =S22/J22 -> 3397.0552 | Y22: =T22/J22 -> 3397.0552 | Z22: =U22/J22 -> 3538.5992 | AB22: 45892 | AC22: 45947 | AD22: =20%*S22 -> 83520 | AI22: =80%*S22 -> 334080 | AJ22: Globalkey | AP22: João Serrano & Daniela Serrano | AQ22: Portugal | AY22: =AZ22*J22 -> 335598.9 | AZ22: 2730
A23: 20 | B23: H4A | C23: T | D23: T3 | E23: 3 | F23: E/W | G23: 134.6 | H23: =7.6+24.6 -> 32.2 | J23: =G23+0.3*H23+0.3*I23 -> 144.26 | K23: CPCV | L23: 2 spots (side by side) | M23: -2 | N23: Yes | S23: 456000 | T23: =0.96*U23 -> 456000 | U23: 475000 | W23: =S23/U23-1 -> -0.04 | X23: =S23/J23 -> 3160.9594 | Y23: =T23/J23 -> 3160.9594 | Z23: =U23/J23 -> 3292.666 | AB23: 45747 | AC23: 45764 | AD23: =5000+86200 -> 91200 | AI23: 364800 | AJ23: Globalkey | AP23: Sergii Bondar | AQ23: Ukraine | AY23: =AZ23*J23 -> 393829.8 | AZ23: 2730
A24: 21 | B24: H4A | C24: U | D24: T3 | E24: 3 | F24: E/W | G24: 134.6 | H24: =7.6+24.6 -> 32.2 | J24: =G24+0.3*H24+0.3*I24 -> 144.26 | K24: CPCV | L24: 2 spots (side by side) | M24: -2 | N24: Yes | S24: 471000 | T24: =0.96*U24 -> 470400 | U24: 490000 | W24: =S24/U24-1 -> -0.03877551 | X24: =S24/J24 -> 3264.9383 | Y24: =T24/J24 -> 3260.7791 | Z24: =U24/J24 -> 3396.6449 | AB24: 45814 | AC24: 45863 | AD24: =5000+89200 -> 94200 | AI24: =80%*S24 -> 376800 | AJ24: Globalkey | AP24: Vania Regina Gomes Nogueira de Sousa & Marco Daniel Ribeiro Maçarico | AQ24: Portugal | AY24: =AZ24*J24 -> 393829.8 | AZ24: 2730
A25: 22 | B25: H4A | C25: V | D25: T3 | E25: 3 | F25: S/E | G25: 116.6 | H25: 16.5 | J25: =G25+0.3*H25+0.3*I25 -> 121.55 | K25: CPCV | L25: 2 spots (side by side) | M25: -2 | N25: Yes | S25: 427200 | T25: =0.96*U25 -> 436800 | U25: 455000 | W25: =S25/U25-1 -> -0.061098901 | X25: =S25/J25 -> 3514.603 | Y25: =T25/J25 -> 3593.5829 | Z25: =U25/J25 -> 3743.3155 | AB25: 45895 | AC25: 45972 | AD25: =5000+80440 -> 85440 | AI25: =80%*S25 -> 341760 | AJ25: Globalkey | AP25: Filipe Carvalho Stevens & Francisca Gonçalves Melo Rodrigues Pereira | AQ25: Portugal | AY25: =AZ25*J25 -> 331831.5 | AZ25: 2730
A26: 23 | B26: H4A | C26: W | D26: T2 | E26: 3 | F26: N/W | G26: 85.8 | H26: 54.9 | J26: =G26+0.2*H26+0.3*I26 -> 96.78 | K26: CPCV | L26: 1 spot | M26: -1 | N26: Yes | S26: 345600 | T26: =0.96*U26 -> 345600 | U26: 360000 | V26: 340000 | W26: =S26/U26-1 -> -0.04 | X26: =S26/J26 -> 3570.9857 | Y26: =T26/J26 -> 3570.9857 | Z26: =U26/J26 -> 3719.7768 | AB26: 45697 | AC26: 45750 | AD26: =20%*S26 -> 69120 | AI26: =80%*S26 -> 276480 | AJ26: Globalkey | AP26: João Morais | AQ26: Portugal | AY26: =AZ26*J26 -> 264209.4 | AZ26: 2730
A27: 24 | B27: H4A | C27: X | D27: T2 | E27: 3 | F27: W | G27: 84.8 | H27: 33.2 | J27: =G27+0.2*H27+0.3*I27 -> 91.44 | K27: CPCV | L27: 1 spot | M27: -1 | N27: No | S27: =0.96*U27 -> 316800 | T27: =0.96*U27 -> 316800 | U27: 330000 | W27: =S27/U27-1 -> -0.04 | X27: =S27/J27 -> 3464.5669 | Y27: =T27/J27 -> 3464.5669 | Z27: =U27/J27 -> 3608.9239 | AB27: 45563 | AC27: 45576 | AD27: =63360+5000 -> 68360 | AI27: =248440 -> 248440 | AJ27: Chavenova | AP27: Ana Joao Vaz Monteiro Porto Sampaio | AQ27: Portugal | AU27: anaportosampaio@gmail.com | AV27: 916632767 | AY27: =AZ27*J27 -> 249631.2 | AZ27: 2730
A28: 25 | B28: H4A | C28: Y | D28: T2 | E28: 3 | F28: W | G28: 84.8 | H28: 33.2 | J28: =G28+0.2*H28+0.3*I28 -> 91.44 | K28: CPCV | L28: 1 spot | M28: -1 | N28: No | S28: =0.96*U28 -> 336000 | T28: =0.96*U28 -> 336000 | U28: 350000 | W28: =S28/U28-1 -> -0.04 | X28: =S28/J28 -> 3674.5407 | Y28: =T28/J28 -> 3674.5407 | Z28: =U28/J28 -> 3827.6465 | AB28: 45563 | AC28: 45588 | AD28: =20%*S28 -> 67200 | AI28: =80%*S28 -> 268800 | AJ28: Chavenova | AP28: Jorge Moia | AQ28: Portugal | AU28: moiajorge@gmail.com | AV28: 966032143 | AY28: =AZ28*J28 -> 249631.2 | AZ28: 2730
A29: 26 | B29: H4A | C29: Z | D29: T2 | E29: 3 | F29: S/W | G29: 85.8 | H29: 50.8 | J29: =G29+0.2*H29+0.3*I29 -> 95.96 | K29: CPCV | L29: 1 spot | M29: -1 | N29: Yes | S29: 360000 | T29: =0.96*U29 -> 360000 | U29: 375000 | V29: 360000 | W29: =S29/U29-1 -> -0.04 | X29: =S29/J29 -> 3751.5632 | Y29: =T29/J29 -> 3751.5632 | Z29: =U29/J29 -> 3907.8783 | AB29: 45575 | AC29: 45677 | AD29: =20%*S29 -> 72000 | AI29: =80%*S29 -> 288000 | AJ29: Globalkey | AP29: Nadav Lev & Shelly Tamir Lev | AQ29: Israel | AU29: lev.nadav@gmail.com | AV29: 972542000000 | AY29: =AZ29*J29 -> 261970.8 | AZ29: 2730
A30: 27 | B30: H4A | C30: AA | D30: T3 | E30: 4 | F30: N/E | G30: 116.6 | H30: 21.1 | J30: =G30+0.3*H30+0.3*I30 -> 122.93 | K30: CPCV | L30: 2 spots (1 in front of other) | M30: -2 | N30: Yes | S30: 440000 | T30: =0.96*U30 -> 422400 | U30: 440000 | W30: =S30/U30-1 -> 0 | X30: =S30/J30 -> 3579.2728 | Y30: =T30/J30 -> 3436.1018 | Z30: =U30/J30 -> 3579.2728 | AB30: 45922 | AC30: 45987 | AD30: =20%*S30 -> 88000 | AI30: =80%*S30 -> 352000 | AJ30: Globalkey | AP30: Juliana Andrade | AQ30: Brazil | AY30: =AZ30*J30 -> 335598.9 | AZ30: 2730
A31: 28 | B31: H4A | C31: AB | D31: T3 | E31: 4 | F31: E/W | G31: 134.6 | H31: =7.6+24.6 -> 32.2 | J31: =G31+0.3*H31+0.3*I31 -> 144.26 | K31: CPCV | L31: 2 spots (side by side) | M31: -2 | N31: Yes | S31: 460800 | T31: =0.96*U31 -> 460800 | U31: 480000 | W31: =S31/U31-1 -> -0.04 | X31: =S31/J31 -> 3194.2326 | Y31: =T31/J31 -> 3194.2326 | Z31: =U31/J31 -> 3327.3257 | AB31: 45797 | AC31: 45813 | AD31: =5000+87160 -> 92160 | AI31: 368640 | AJ31: Globalkey | AP31: Daniel Rodrigues de Morais e Ana Catarina d Silva Souto | AQ31: Portugal | AY31: =AZ31*J31 -> 393829.8 | AZ31: 2730
A32: 29 | B32: H4A | C32: AC | D32: T3 | E32: 4 | F32: E/W | G32: 134.6 | H32: =7.6+24.6 -> 32.2 | J32: =G32+0.3*H32+0.3*I32 -> 144.26 | K32: CPCV | L32: 2 spots (side by side) | M32: -2 | N32: Yes | S32: 475200 | T32: =0.96*U32 -> 475200 | U32: 495000 | W32: =S32/U32-1 -> -0.04 | X32: =S32/J32 -> 3294.0524 | Y32: =T32/J32 -> 3294.0524 | Z32: =U32/J32 -> 3431.3046 | AC32: 45629 | AD32: =5000+66280+23760 -> 95040 | AI32: =80%*S32 -> 380160 | AJ32: Globalkey | AP32: Mário Rui Ascensão Dias de Lima Fontes | AQ32: Portugal | AU32: marioruifontes@gmail.com | AV32: 918420563 | AY32: =AZ32*J32 -> 393829.8 | AZ32: 2730
A33: 30 | B33: H4A | C33: AD | D33: T3 | E33: 4 | F33: S/E | G33: 116.6 | H33: 16.5 | J33: =G33+0.3*H33+0.3*I33 -> 121.55 | K33: CPCV | L33: 2 spots (side by side) | M33: -2 | N33: Yes | S33: 450000 | T33: =0.96*U33 -> 432000 | U33: 450000 | W33: =S33/U33-1 -> 0 | X33: =S33/J33 -> 3702.1802 | Y33: =T33/J33 -> 3554.093 | Z33: =U33/J33 -> 3702.1802 | AB33: 45781 | AC33: 45806 | AD33: =20%*S33 -> 90000 | AI33: =80%*S33 -> 360000 | AJ33: Globalkey | AP33: Anton Dushko & Daria Fedorenko | AQ33: Ukraine | AY33: =AZ33*J33 -> 331831.5 | AZ33: 2730
A34: 31 | B34: H4A | C34: AE | D34: T2 | E34: 4 | F34: N/W | G34: 85.8 | H34: 54.9 | J34: =G34+0.2*H34+0.3*I34 -> 96.78 | K34: CPCV | L34: 1 spot | M34: -1 | N34: Yes | S34: 338100 | T34: =0.96*U34 -> 331200 | U34: 345000 | W34: =S34/U34-1 -> -0.02 | X34: =S34/J34 -> 3493.4904 | Y34: =T34/J34 -> 3422.1947 | Z34: =U34/J34 -> 3564.7861 | AB34: 45563 | AC34: 45581 | AD34: =5000+64000 -> 69000 | AI34: 276000 | AJ34: Chavenova | AP34: Paulo Jorge Caldas Sousa | AQ34: Portugal | AU34: pjfsousaimoveis@gmail.com | AV34: 933305270 | AY34: =AZ34*J34 -> 264209.4 | AZ34: 2730
A35: 32 | B35: H4A | C35: AF | D35: T2 | E35: 4 | F35: W | G35: 84.8 | H35: 33.2 | J35: =G35+0.2*H35+0.3*I35 -> 91.44 | K35: CPCV | L35: 1 spot | M35: -1 | N35: Yes | S35: 345600 | T35: =0.96*U35 -> 345600 | U35: 360000 | V35: 335000 | W35: =S35/U35-1 -> -0.04 | X35: =S35/J35 -> 3779.5276 | Y35: =T35/J35 -> 3779.5276 | Z35: =U35/J35 -> 3937.0079 | AB35: 45757 | AC35: 45777 | AD35: =5000+64120 -> 69120 | AI35: =80%*S35 -> 276480 | AJ35: Chavenova | AP35: Jochen Frederik Hainke | AQ35: Portugal | AY35: =AZ35*J35 -> 249631.2 | AZ35: 2730
A36: 33 | B36: H4A | C36: AG | D36: T2 | E36: 4 | F36: W | G36: 84.8 | H36: 33.2 | J36: =G36+0.2*H36+0.3*I36 -> 91.44 | K36: CPCV | L36: 1 spot | M36: -2 | N36: Yes | S36: 360960 | T36: =0.96*U36 -> 360960 | U36: 376000 | V36: 355000 | W36: =S36/U36-1 -> -0.04 | X36: =S36/J36 -> 3947.5066 | Y36: =T36/J36 -> 3947.5066 | Z36: =U36/J36 -> 4111.986 | AB36: 45589 | AC36: 45615 | AD36: =20%*S36 -> 72192 | AI36: =80%*S36 -> 288768 | AJ36: Globalkey | AK36: Daniel Cruz | AP36: António José Morais Lopes Teixeira | AQ36: Portugal | AV36: 917518337 | AY36: =AZ36*J36 -> 249631.2 | AZ36: 2730
A37: 34 | B37: H4A | C37: AH | D37: T2 | E37: 4 | F37: S/W | G37: 85.8 | H37: 50.8 | J37: =G37+0.2*H37+0.3*I37 -> 95.96 | K37: CPCV | L37: 1 spot | M37: -1 | N37: Yes | S37: 371520 | T37: =0.96*U37 -> 371520 | U37: 387000 | V37: 365000 | W37: =S37/U37-1 -> -0.04 | X37: =S37/J37 -> 3871.6132 | Y37: =T37/J37 -> 3871.6132 | Z37: =U37/J37 -> 4032.9304 | AB37: 45684 | AC37: 45762 | AD37: 50000 | AE37: 24304 | AF37: 46022 | AI37: =80%*S37 -> 297216 | AJ37: Chavenova | AP37: António Sá da Cunha & Antonietta Celli Lo Monaco | AQ37: Portugal | AU37: antonio.cunha@boshrexroth.com | AV37: 962011245 | AY37: =AZ37*J37 -> 261970.8 | AZ37: 2730
A38: 35 | B38: H4A | C38: AI | D38: T3 | E38: 5 | F38: N/E | G38: 116.6 | H38: 21.1 | J38: =G38+0.3*H38+0.3*I38 -> 122.93 | K38: CPCV | L38: 2 spots (1 in front of other) | M38: -2 | N38: Yes | S38: 422400 | T38: =0.96*U38 -> 422400 | U38: 440000 | W38: =S38/U38-1 -> -0.04 | X38: =S38/J38 -> 3436.1018 | Y38: =T38/J38 -> 3436.1018 | Z38: =U38/J38 -> 3579.2728 | AB38: 45918 | AC38: 45930 | AD38: =20%*S38 -> 84480 | AI38: =80%*S38 -> 337920 | AJ38: Globalkey | AP38: António Mascarenhas | AQ38: Portugal | AU38: mascarenhas@me.com | AV38: 916506939 | AY38: =AZ38*J38 -> 335598.9 | AZ38: 2730
A39: 36 | B39: H4A | C39: AJ | D39: T3 | E39: 5 | F39: E/W | G39: 134.6 | H39: =7.6+24.6 -> 32.2 | J39: =G39+0.3*H39+0.3*I39 -> 144.26 | K39: CPCV | L39: 2 spots (side by side) | M39: -1 | N39: Yes | S39: =0.95*U39 -> 460750 | T39: =0.96*U39 -> 465600 | U39: 485000 | W39: =S39/U39-1 -> -0.05 | X39: =S39/J39 -> 3193.886 | Y39: =T39/J39 -> 3227.5059 | Z39: =U39/J39 -> 3361.9853 | AC39: 45625 | AD39: =20%*S39 -> 92150 | AI39: =80%*S39 -> 368600 | AJ39: Globalkey | AP39: Rui LemosMonteiro | AQ39: Portugal | AU39: rui.monteiro@sodecia.com | AV39: 917225875 | AY39: =AZ39*J39 -> 393829.8 | AZ39: 2730
A40: 37 | B40: H4A | C40: AK | D40: T3 | E40: 5 | F40: E/W | G40: 134.6 | H40: =7.6+24.6 -> 32.2 | J40: =G40+0.3*H40+0.3*I40 -> 144.26 | K40: CPCV | L40: 2 spots (side by side) | M40: -1 | N40: Yes | S40: 480000 | T40: =0.96*U40 -> 480000 | U40: 500000 | W40: =S40/U40-1 -> -0.04 | X40: =S40/J40 -> 3327.3257 | Y40: =T40/J40 -> 3327.3257 | Z40: =U40/J40 -> 3465.9642 | AB40: 45565 | AC40: 45644 | AD40: =20%*S40 -> 96000 | AI40: =80%*S40 -> 384000 | AJ40: Chavenova | AP40: HUGO ALEXANDRE PEREIRA MESQUITA DA SILVA | AQ40: Portugal | AU40: hugo.mesquita@gmail.com | AV40: 968083749 | AY40: =AZ40*J40 -> 393829.8 | AZ40: 2730
A41: 38 | B41: H4A | C41: AL | D41: T3 | E41: 5 | F41: S/E | G41: 116.6 | H41: 16.5 | J41: =G41+0.3*H41+0.3*I41 -> 121.55 | K41: CPCV | L41: 2 spots (side by side) | M41: -2 | N41: Yes | S41: 436800 | T41: =0.96*U41 -> 446400 | U41: 465000 | W41: =S41/U41-1 -> -0.060645161 | X41: =S41/J41 -> 3593.5829 | Y41: =T41/J41 -> 3672.5627 | Z41: =U41/J41 -> 3825.5862 | AB41: 45866 | AC41: 45945 | AD41: =5000+82360 -> 87360 | AI41: 349440 | AJ41: Globalkey | AP41: Catarina Oliveira | AQ41: Portugal | AY41: =AZ41*J41 -> 331831.5 | AZ41: 2730
A42: 39 | B42: H4A | C42: AM | D42: T2 | E42: 5 | F42: N/W | G42: 85.8 | H42: 54.9 | J42: =G42+0.2*H42+0.3*I42 -> 96.78 | K42: CPCV | L42: 1 spot | M42: -1 | N42: Yes | S42: =0.96*U42 -> 336000 | T42: =0.96*U42 -> 336000 | U42: 350000 | W42: =S42/U42-1 -> -0.04 | X42: =S42/J42 -> 3471.7917 | Y42: =T42/J42 -> 3471.7917 | Z42: =U42/J42 -> 3616.4497 | AB42: 45563 | AC42: 45583 | AD42: =20%*S42 -> 67200 | AI42: =80%*S42 -> 268800 | AJ42: Chavenova | AP42: Emanuel António Mendes de Brito | AQ42: Portugal | AU42: eambrito@gmail.com | AV42: 917199793 | AY42: =AZ42*J42 -> 264209.4 | AZ42: 2730
A43: 40 | B43: H4A | C43: AN | D43: T2 | E43: 5 | F43: W | G43: 84.8 | H43: 33.2 | J43: =G43+0.2*H43+0.3*I43 -> 91.44 | K43: CPCV | L43: 1 spot | M43: -2 | N43: Yes | S43: 351000 | T43: =0.96*U43 -> 350400 | U43: 365000 | V43: 340000 | W43: =S43/U43-1 -> -0.038356164 | X43: =S43/J43 -> 3838.5827 | Y43: =T43/J43 -> 3832.021 | Z43: =U43/J43 -> 3991.6885 | AB43: 45751 | AC43: 45785 | AD43: =5000+65200 -> 70200 | AI43: =80%*S43 -> 280800 | AJ43: Globalkey | AP43: João Paulo Barbosa Gonçalves de Bessa | AQ43: Portugal | AY43: =AZ43*J43 -> 249631.2 | AZ43: 2730
A44: 41 | B44: H4A | C44: AO | D44: T2 | E44: 5 | F44: W | G44: 84.8 | H44: 33.2 | J44: =G44+0.2*H44+0.3*I44 -> 91.44 | K44: CPCV | L44: 1 spot | M44: -1 | N44: Yes | S44: 366720 | T44: =0.96*U44 -> 366720 | U44: 382000 | V44: 360000 | W44: =S44/U44-1 -> -0.04 | X44: =S44/J44 -> 4010.4987 | Y44: =T44/J44 -> 4010.4987 | Z44: =U44/J44 -> 4177.6028 | AB44: 45579 | AC44: 45685 | AD44: =20%*S44 -> 73344 | AI44: =80%*S44 -> 293376 | AJ44: Globalkey | AP44: Clarisse Sousa and António da Silva | AQ44: Portugal | AU44: msousa.clarisse@gmail.com | AV44: 938886560 | AY44: =AZ44*J44 -> 249631.2 | AZ44: 2730
A45: 42 | B45: H4A | C45: AP | D45: T2 | E45: 5 | F45: S/W | G45: 85.8 | H45: 50.8 | J45: =G45+0.2*H45+0.3*I45 -> 95.96 | K45: CPCV | L45: 1 spot | M45: -1 | N45: Yes | S45: =0.96*U45 -> 355200 | T45: =0.96*U45 -> 355200 | U45: 370000 | W45: =S45/U45-1 -> -0.04 | X45: =S45/J45 -> 3701.5423 | Y45: =T45/J45 -> 3701.5423 | Z45: =U45/J45 -> 3855.7732 | AB45: 45563 | AC45: 45576 | AD45: =20%*S45 -> 71040 | AI45: =80%*S45 -> 284160 | AJ45: Chavenova | AP45: JORGE AUGUSTO DIAS MOUTINHO | AQ45: Portugal | AU45: jorge.moutinho@hotmail.com | AV45: 917274901 | AY45: =AZ45*J45 -> 261970.8 | AZ45: 2730
A46: 43 | B46: H4A | C46: AQ | D46: T3 | E46: 6 | F46: N/E | G46: 116.6 | H46: 21.1 | J46: =G46+0.3*H46+0.3*I46 -> 122.93 | K46: CPCV | L46: 2 spots (1 in front of other) | M46: -2 | N46: Yes | S46: 422400 | T46: =0.96*U46 -> 422400 | U46: 440000 | W46: =S46/U46-1 -> -0.04 | X46: =S46/J46 -> 3436.1018 | Y46: =T46/J46 -> 3436.1018 | Z46: =U46/J46 -> 3579.2728 | AB46: 45819 | AC46: 45847 | AD46: =5000+79480 -> 84480 | AI46: 337920 | AJ46: Globalkey | AP46: Nídia Celsa Oliveira Alves | AQ46: Portugal | AY46: =AZ46*J46 -> 335598.9 | AZ46: 2730
A47: 44 | B47: H4A | C47: AR | D47: T3 | E47: 6 | F47: E/W | G47: 134.6 | H47: =7.6+24.6 -> 32.2 | J47: =G47+0.3*H47+0.3*I47 -> 144.26 | K47: CPCV | L47: 2 spots (side by side) | M47: -1 | N47: Yes | S47: 470400 | T47: =0.96*U47 -> 470400 | U47: 490000 | W47: =S47/U47-1 -> -0.04 | X47: =S47/J47 -> 3260.7791 | Y47: =T47/J47 -> 3260.7791 | Z47: =U47/J47 -> 3396.6449 | AC47: 45755 | AD47: =20%*S47 -> 94080 | AI47: =80%*S47 -> 376320 | AJ47: Globalkey | AP47: Li Xinyan | AQ47: China | AY47: =AZ47*J47 -> 393829.8 | AZ47: 2730
A48: 45 | B48: H4A | C48: AS | D48: T3 | E48: 6 | F48: E/W | G48: 134.6 | H48: =7.6+24.6 -> 32.2 | J48: =G48+0.3*H48+0.3*I48 -> 144.26 | K48: CPCV | L48: 2 spots (side by side) | M48: -1 | N48: Yes | S48: 484800 | T48: =0.96*U48 -> 484800 | U48: 505000 | W48: =S48/U48-1 -> -0.04 | X48: =S48/J48 -> 3360.5989 | Y48: =T48/J48 -> 3360.5989 | Z48: =U48/J48 -> 3500.6239 | AC48: 45579 | AD48: =20%*S48+5000 -> 101960 | AI48: =80%*S48-5000 -> 382840 | AJ48: Chavenova | AP48: Antonio Jose Correia Simoes Rodrigues | AQ48: Portugal | AU48: to-1992@hotmail.com | AV48: 41775134596 | AY48: =AZ48*J48 -> 393829.8 | AZ48: 2730
A49: 46 | B49: H4A | C49: AT | D49: T3 | E49: 6 | F49: S/E | G49: 116.6 | H49: 16.5 | J49: =G49+0.3*H49+0.3*I49 -> 121.55 | K49: CPCV | L49: 2 spots (side by side) | M49: -2 | N49: Yes | S49: 441600 | T49: =0.96*U49 -> 441600 | U49: 460000 | W49: =S49/U49-1 -> -0.04 | X49: =S49/J49 -> 3633.0728 | Y49: =T49/J49 -> 3633.0728 | Z49: =U49/J49 -> 3784.4508 | AC49: 45631 | AD49: =20%*S49 -> 88320 | AI49: =80%*S49 -> 353280 | AJ49: Chavenova | AP49: Simao Carvalho | AQ49: Portugal | AU49: simaoascarvalho@gmail.com | AV49: 937058399 | AY49: =AZ49*J49 -> 331831.5 | AZ49: 2730
A50: 47 | B50: H4A | C50: AU | D50: T2 | E50: 6 | F50: N/W | G50: 85.8 | H50: 54.9 | J50: =G50+0.2*H50+0.3*I50 -> 96.78 | K50: CPCV | L50: 1 spot | M50: -1 | N50: Yes | S50: 362000 | T50: =0.96*U50 -> 360960 | U50: 376000 | V50: 355000 | W50: =S50/U50-1 -> -0.037234043 | X50: =S50/J50 -> 3740.4422 | Y50: =T50/J50 -> 3729.6962 | Z50: =U50/J50 -> 3885.1002 | AB50: 45742 | AC50: 45790 | AD50: =5000+67192 -> 72192 | AI50: 289600 | AJ50: Globalkey | AP50: Diogo André Costa Resende | AQ50: Portugal | AY50: =AZ50*J50 -> 264209.4 | AZ50: 2730
A51: 48 | B51: H4A | C51: AV | D51: T2 | E51: 6 | F51: W | G51: 84.8 | H51: 33.2 | J51: =G51+0.2*H51+0.3*I51 -> 91.44 | K51: CPCV | L51: 1 spot | M51: -2 | N51: Yes | S51: 355200 | T51: =0.96*U51 -> 355200 | U51: 370000 | V51: 345000 | W51: =S51/U51-1 -> -0.04 | X51: =S51/J51 -> 3884.5144 | Y51: =T51/J51 -> 3884.5144 | Z51: =U51/J51 -> 4046.3692 | AB51: 45821 | AC51: 45847 | AD51: =5000+66040 -> 71040 | AI51: 284160 | AJ51: Globalkey | AP51: Whalton Orlando Hippert | AQ51: Italy | AY51: =AZ51*J51 -> 249631.2 | AZ51: 2730
A52: 49 | B52: H4A | C52: AW | D52: T2 | E52: 6 | F52: W | G52: 84.8 | H52: 33.2 | J52: =G52+0.2*H52+0.3*I52 -> 91.44 | K52: CPCV | L52: 1 spot | M52: -1 | N52: Yes | S52: 365000 | T52: =0.96*U52 -> 350400 | U52: 365000 | W52: =S52/U52-1 -> 0 | X52: =S52/J52 -> 3991.6885 | Y52: =T52/J52 -> 3832.021 | Z52: =U52/J52 -> 3991.6885 | AC52: 45600 | AD52: =20%*S52 -> 73000 | AI52: =80%*S52 -> 292000 | AJ52: Globalkey | AP52: Flávia Soutelos Teixeira | AQ52: Portugal | AU52: flaviateixeira@hotmail.com | AV52: 967702834 | AY52: =AZ52*J52 -> 249631.2 | AZ52: 2730
