Workbook

Sheet Dashboard - Overview & Project
B2: KPIs | D2: Month | F2: January | H2: Accumulated - 1-01/2026 | L2: 2026 Forecast
D3: Actual | E3: Budget | F3: Gap | H3: Actual | I3: Budget | J3: Gap | L3: Forecast | M3: Budget | N3: Gap
B4: Sales
B5: Units | D5: =+VLOOKUP($B$5,'KPIs - Sales Goals'!$A$48:$AP$48,VLOOKUP('Dashboard - Overview & Project'!$F$2,'Dashboard - Overview & Project'!$B$44:$D$55,3,FALSE)) -> 0 | E5: =+VLOOKUP($B$5,'KPIs - Sales Goals'!$A$48:$AP$48,VLOOKUP('Dashboard - Overview & Project'!$F$2,'Dashboard - Overview & Project'!$B$44:$D$55,2,FALSE)) -> 0 | F5: =IF(AND(D5>0,E5>0),D5/E5,IF(AND(D5>0,E5=0),100%,IF(AND(D5=0,E5>0),0,IF(AND(D5=0,E5=0),"***",0)))) -> *** | H5: =+'KPIs - Sales Goals'!D48 -> 0 | I5: =+'KPIs - Sales Goals'!E48 -> 0 | J5: =IF(AND(H5>0,I5>0),H5/I5,IF(AND(H5>0,I5=0),100%,IF(AND(H5=0,I5>0),0,IF(AND(H5=0,I5=0),"***",0)))) -> *** | L5: =+'Goals & Budget 2026 - Updated'!AF48 -> 0 | M5: =+'Goals & Budget 2026'!AF48 -> 0 | N5: =IF(AND(L5>0,M5>0),L5/M5,IF(AND(L5>0,M5=0),100%,IF(AND(L5=0,M5>0),0,IF(AND(L5=0,M5=0),"***",0)))) -> ***
B6: Units (TU) | D6: =+VLOOKUP($B$5,'KPIs - Sales Goals'!$A$49:$AP$49,VLOOKUP('Dashboard - Overview & Project'!$F$2,'Dashboard - Overview & Project'!$B$44:$D$55,3,FALSE)) -> 0 | E6: =+VLOOKUP($B$5,'KPIs - Sales Goals'!$A$49:$AP$49,VLOOKUP('Dashboard - Overview & Project'!$F$2,'Dashboard - Overview & Project'!$B$44:$D$55,2,FALSE)) -> 0 | F6: =IF(AND(D6>0,E6>0),D6/E6,IF(AND(D6>0,E6=0),100%,IF(AND(D6=0,E6>0),0,IF(AND(D6=0,E6=0),"***",0)))) -> *** | H6: =+'KPIs - Sales Goals'!D49 -> 0 | I6: =+'KPIs - Sales Goals'!E49 -> 0 | J6: =IF(AND(H6>0,I6>0),H6/I6,IF(AND(H6>0,I6=0),100%,IF(AND(H6=0,I6>0),0,IF(AND(H6=0,I6=0),"***",0)))) -> *** | L6: =+'Goals & Budget 2026 - Updated'!AF49 -> 0 | M6: =+'Goals & Budget 2026'!AF49 -> 0 | N6: =IF(AND(L6>0,M6>0),L6/M6,IF(AND(L6>0,M6=0),100%,IF(AND(L6=0,M6>0),0,IF(AND(L6=0,M6=0),"***",0)))) -> ***
B7: Income
B8: Income | D8: =+VLOOKUP($B$5,'KPIs - Income'!$A$48:$AP$48,VLOOKUP('Dashboard - Overview & Project'!$F$2,'Dashboard - Overview & Project'!$B$44:$D$55,3,FALSE)) -> 0 | E8: =+VLOOKUP($B$5,'KPIs - Income'!$A$48:$AP$48,VLOOKUP('Dashboard - Overview & Project'!$F$2,'Dashboard - Overview & Project'!$B$44:$D$55,2,FALSE)) -> 0 | F8: =IF(AND(D8>0,E8>0),D8/E8,IF(AND(D8>0,E8=0),100%,IF(AND(D8=0,E8>0),0,IF(AND(D8=0,E8=0),"***",0)))) -> *** | H8: =+'KPIs - Income'!D48 -> 0 | I8: =+'KPIs - Income'!E48 -> 0 | J8: =IF(AND(H8>0,I8>0),H8/I8,IF(AND(H8>0,I8=0),100%,IF(AND(H8=0,I8>0),0,IF(AND(H8=0,I8=0),"***",0)))) -> *** | L8: =+'Goals & Budget 2026 - Updated'!BG48 -> 0 | M8: =+'Goals & Budget 2026'!BG48 -> 0 | N8: =IF(AND(L8>0,M8>0),L8/M8,IF(AND(L8>0,M8=0),100%,IF(AND(L8=0,M8>0),0,IF(AND(L8=0,M8=0),"***",0)))) -> ***
B9: Income (TU) | D9: =+VLOOKUP($B$5,'KPIs - Income'!$A$48:$AP$49,VLOOKUP('Dashboard - Overview & Project'!$F$2,'Dashboard - Overview & Project'!$B$44:$D$55,3,FALSE)) -> 0 | E9: =+VLOOKUP($B$5,'KPIs - Income'!$A$48:$AP$49,VLOOKUP('Dashboard - Overview & Project'!$F$2,'Dashboard - Overview & Project'!$B$44:$D$55,2,FALSE)) -> 0 | F9: =IF(AND(D9>0,E9>0),D9/E9,IF(AND(D9>0,E9=0),100%,IF(AND(D9=0,E9>0),0,IF(AND(D9=0,E9=0),"***",0)))) -> *** | H9: =+'KPIs - Income'!D49 -> 0 | I9: =+'KPIs - Income'!E49 -> 0 | J9: =IF(AND(H9>0,I9>0),H9/I9,IF(AND(H9>0,I9=0),100%,IF(AND(H9=0,I9>0),0,IF(AND(H9=0,I9=0),"***",0)))) -> *** | L9: =+'Goals & Budget 2026 - Updated'!BG49 -> 0 | M9: =+'Goals & Budget 2026'!BG49 -> 0 | N9: =IF(AND(L9>0,M9>0),L9/M9,IF(AND(L9>0,M9=0),100%,IF(AND(L9=0,M9>0),0,IF(AND(L9=0,M9=0),"***",0)))) -> ***
B10: € / Sq. M.
B11: € / Sq. M. | D11: =+VLOOKUP($B$5,'KPIs - €Sq.M.'!$A$48:$AP$48,VLOOKUP('Dashboard - Overview & Project'!$F$2,'Dashboard - Overview & Project'!$B$44:$D$55,3,FALSE)) -> 0 | E11: =+VLOOKUP($B$5,'KPIs - €Sq.M.'!$A$48:$AP$48,VLOOKUP('Dashboard - Overview & Project'!$F$2,'Dashboard - Overview & Project'!$B$44:$D$55,2,FALSE)) -> 0 | F11: =IF(AND(D11>0,E11>0),D11/E11,IF(AND(D11>0,E11=0),100%,IF(AND(D11=0,E11>0),0,IF(AND(D11=0,E11=0),"***",0)))) -> *** | H11: =+'KPIs - €Sq.M.'!D48 -> #DIV/0! | I11: =+'KPIs - €Sq.M.'!E48 -> #DIV/0! | J11: =IF(AND(H11>0,I11>0),H11/I11,IF(AND(H11>0,I11=0),100%,IF(AND(H11=0,I11>0),0,IF(AND(H11=0,I11=0),"***",0)))) -> #DIV/0! | L11: =+'Goals & Budget 2026'!AT48 -> 0 | M11: =+'Goals & Budget 2026 - Updated'!AT48 -> 0 | N11: =IF(AND(L11>0,M11>0),L11/M11,IF(AND(L11>0,M11=0),100%,IF(AND(L11=0,M11>0),0,IF(AND(L11=0,M11=0),"***",0)))) -> ***
B12: Key Performance Indicators
B13: Sales launch (units, 100%) | D13: =+VLOOKUP($B$5,'KPIs - Sales Launch'!$A$48:$AP$48,VLOOKUP('Dashboard - Overview & Project'!$F$2,'Dashboard - Overview & Project'!$B$44:$D$55,3,FALSE)) -> 0 | E13: =+VLOOKUP($B$5,'KPIs - Sales Launch'!$A$48:$AP$48,VLOOKUP('Dashboard - Overview & Project'!$F$2,'Dashboard - Overview & Project'!$B$44:$D$55,2,FALSE)) -> 0 | F13: =IF(AND(D13>0,E13>0),D13/E13,IF(AND(D13>0,E13=0),100%,IF(AND(D13=0,E13>0),0,IF(AND(D13=0,E13=0),"***",0)))) -> *** | H13: =+'KPIs - Sales Launch'!D48 -> 0 | I13: =+'KPIs - Sales Launch'!E48 -> 0 | J13: =IF(AND(H13>0,I13>0),H13/I13,IF(AND(H13>0,I13=0),100%,IF(AND(H13=0,I13>0),0,IF(AND(H13=0,I13=0),"***",0)))) -> *** | L13: =+'Goals & Budget 2026 - Updated'!P48 -> 0 | M13: =+'Goals & Budget 2026'!P48 -> 0 | N13: =IF(AND(L13>0,M13>0),L13/M13,IF(AND(L13>0,M13=0),100%,IF(AND(L13=0,M13>0),0,IF(AND(L13=0,M13=0),"***",0)))) -> ***
B14: Marketing (€, 100%) | D14: =+VLOOKUP($B$5,'KPIs - Marketing'!$A$48:$AP$48,VLOOKUP('Dashboard - Overview & Project'!$F$2,'Dashboard - Overview & Project'!$B$44:$D$55,3,FALSE)) -> 0 | E14: =+VLOOKUP($B$5,'KPIs - Marketing'!$A$48:$AP$48,VLOOKUP('Dashboard - Overview & Project'!$F$2,'Dashboard - Overview & Project'!$B$44:$D$55,2,FALSE)) -> 0 | F14: =IF(AND(D14>0,E14>0),D14/E14,IF(AND(D14>0,E14=0),100%,IF(AND(D14=0,E14>0),0,IF(AND(D14=0,E14=0),"***",0)))) -> *** | H14: =+'KPIs - Marketing'!D48 -> 0 | I14: =+'KPIs - Marketing'!E48 -> 0 | J14: =IF(AND(H14>0,I14>0),H14/I14,IF(AND(H14>0,I14=0),100%,IF(AND(H14=0,I14>0),0,IF(AND(H14=0,I14=0),"***",0)))) -> *** | L14: =+'Goals & Budget 2026 - Updated'!BV48 -> 0 | M14: =+'Goals & Budget 2026'!BV48 -> 0 | N14: =IF(AND(L14>0,M14>0),L14/M14,IF(AND(L14>0,M14=0),100%,IF(AND(L14=0,M14>0),0,IF(AND(L14=0,M14=0),"***",0)))) -> ***
B15: Schematics Approval (units, 100%) | D15: =+VLOOKUP($B$5,'KPIs - Schematics'!$A$48:$AP$48,VLOOKUP('Dashboard - Overview & Project'!$F$2,'Dashboard - Overview & Project'!$B$44:$D$55,3,FALSE)) -> 0 | E15: =+VLOOKUP($B$5,'KPIs - Schematics'!$A$48:$AP$48,VLOOKUP('Dashboard - Overview & Project'!$F$2,'Dashboard - Overview & Project'!$B$44:$D$55,2,FALSE)) -> 56 | F15: =IF(AND(D15>0,E15>0),D15/E15,IF(AND(D15>0,E15=0),100%,IF(AND(D15=0,E15>0),0,IF(AND(D15=0,E15=0),"***",0)))) -> 0 | H15: =+'KPIs - Schematics'!D48 -> 0 | I15: =+'KPIs - Schematics'!E48 -> 56 | J15: =IF(AND(H15>0,I15>0),H15/I15,IF(AND(H15>0,I15=0),100%,IF(AND(H15=0,I15>0),0,IF(AND(H15=0,I15=0),"***",0)))) -> 0 | L15: =+'Goals & Budget 2026 - Updated'!CK48 -> 0 | M15: =+'Goals & Budget 2026'!CK48 -> 760 | N15: =IF(AND(L15>0,M15>0),L15/M15,IF(AND(L15>0,M15=0),100%,IF(AND(L15=0,M15>0),0,IF(AND(L15=0,M15=0),"***",0)))) -> 0
B16: Tender (units, 100%) | D16: =+VLOOKUP($B$5,'KPIs - Tender'!$A$48:$AP$48,VLOOKUP('Dashboard - Overview & Project'!$F$2,'Dashboard - Overview & Project'!$B$44:$D$55,3,FALSE)) -> 0 | E16: =+VLOOKUP($B$5,'KPIs - Tender'!$A$48:$AP$48,VLOOKUP('Dashboard - Overview & Project'!$F$2,'Dashboard - Overview & Project'!$B$44:$D$55,2,FALSE)) -> 0 | F16: =IF(AND(D16>0,E16>0),D16/E16,IF(AND(D16>0,E16=0),100%,IF(AND(D16=0,E16>0),0,IF(AND(D16=0,E16=0),"***",0)))) -> *** | H16: =+'KPIs - Tender'!D48 -> 0 | I16: =+'KPIs - Tender'!E48 -> 0 | J16: =IF(AND(H16>0,I16>0),H16/I16,IF(AND(H16>0,I16=0),100%,IF(AND(H16=0,I16>0),0,IF(AND(H16=0,I16=0),"***",0)))) -> *** | L16: =+'Goals & Budget 2026 - Updated'!CX48 -> 0 | M16: =+'Goals & Budget 2026'!CX48 -> 625 | N16: =IF(AND(L16>0,M16>0),L16/M16,IF(AND(L16>0,M16=0),100%,IF(AND(L16=0,M16>0),0,IF(AND(L16=0,M16=0),"***",0)))) -> 0
B17: Construction - Start (units, 100%) | D17: =+VLOOKUP($B$5,'KPIs - Construction Start'!$A$48:$AP$48,VLOOKUP('Dashboard - Overview & Project'!$F$2,'Dashboard - Overview & Project'!$B$44:$D$55,3,FALSE)) -> 0 | E17: =+VLOOKUP($B$5,'KPIs - Construction Start'!$A$48:$AP$48,VLOOKUP('Dashboard - Overview & Project'!$F$2,'Dashboard - Overview & Project'!$B$44:$D$55,2,FALSE)) -> 58 | F17: =IF(AND(D17>0,E17>0),D17/E17,IF(AND(D17>0,E17=0),100%,IF(AND(D17=0,E17>0),0,IF(AND(D17=0,E17=0),"***",0)))) -> 0 | H17: =+'KPIs - Construction Start'!D48 -> 0 | I17: =+'KPIs - Construction Start'!E48 -> 58 | J17: =IF(AND(H17>0,I17>0),H17/I17,IF(AND(H17>0,I17=0),100%,IF(AND(H17=0,I17>0),0,IF(AND(H17=0,I17=0),"***",0)))) -> 0 | L17: =+'Goals & Budget 2026 - Updated'!DK48 -> 0 | M17: =+'Goals & Budget 2026'!DK48 -> 371 | N17: =IF(AND(L17>0,M17>0),L17/M17,IF(AND(L17>0,M17=0),100%,IF(AND(L17=0,M17>0),0,IF(AND(L17=0,M17=0),"***",0)))) -> 0
B18: Handover (units, 100%) | D18: =+VLOOKUP($B$5,'KPIs- Handover'!$A$48:$AP$48,VLOOKUP('Dashboard - Overview & Project'!$F$2,'Dashboard - Overview & Project'!$B$44:$D$55,3,FALSE)) -> 0 | E18: =+VLOOKUP($B$5,'KPIs- Handover'!$A$48:$AP$48,VLOOKUP('Dashboard - Overview & Project'!$F$2,'Dashboard - Overview & Project'!$B$44:$D$55,2,FALSE)) -> 0 | F18: =IF(AND(D19>0,E19>0),D19/E19,IF(AND(D19>0,E19=0),100%,IF(AND(D19=0,E19>0),0,IF(AND(D19=0,E19=0),"***",0)))) -> *** | H18: =+'KPIs- Handover'!D48 -> 0 | I18: =+'KPIs- Handover'!E48 -> 0 | J18: =IF(AND(H19>0,I19>0),H19/I19,IF(AND(H19>0,I19=0),100%,IF(AND(H19=0,I19>0),0,IF(AND(H19=0,I19=0),"***",0)))) -> *** | L18: =+'Goals & Budget 2026 - Updated'!EJ48 -> 0 | M18: =+'Goals & Budget 2026'!EJ48 -> 523 | N18: =IF(AND(L19>0,M19>0),L19/M19,IF(AND(L19>0,M19=0),100%,IF(AND(L19=0,M19>0),0,IF(AND(L19=0,M19=0),"***",0)))) -> 0
B19: Deeds (units, 100%) | D19: =+VLOOKUP($B$5,'KPIs- Deeds'!$A$48:$AP$48,VLOOKUP('Dashboard - Overview & Project'!$F$2,'Dashboard - Overview & Project'!$B$44:$D$55,3,FALSE)) -> 0 | E19: =+VLOOKUP($B$5,'KPIs- Deeds'!$A$48:$AP$48,VLOOKUP('Dashboard - Overview & Project'!$F$2,'Dashboard - Overview & Project'!$B$44:$D$55,2,FALSE)) -> 0 | F19: =IF(AND(D19>0,E19>0),D19/E19,IF(AND(D19>0,E19=0),100%,IF(AND(D19=0,E19>0),0,IF(AND(D19=0,E19=0),"***",0)))) -> *** | H19: =+'KPIs- Handover'!D48 -> 0 | I19: =+'KPIs- Handover'!E48 -> 0 | J19: =IF(AND(H19>0,I19>0),H19/I19,IF(AND(H19>0,I19=0),100%,IF(AND(H19=0,I19>0),0,IF(AND(H19=0,I19=0),"***",0)))) -> *** | L19: =+'Goals & Budget 2026 - Updated'!EJ48 -> 0 | M19: =+'Goals & Budget 2026'!EJ48 -> 523 | N19: =IF(AND(L19>0,M19>0),L19/M19,IF(AND(L19>0,M19=0),100%,IF(AND(L19=0,M19>0),0,IF(AND(L19=0,M19=0),"***",0)))) -> 0
B22: Project | C22: Saldouro - 10
B24: KPIs | D24: =+B43 -> January | H24: =+H2 -> Accumulated - 1-01/2026 | L24: 2026 Forecast
D25: Actual | E25: Budget | F25: Gap | H25: Actual | I25: Budget | J25: Gap | L25: Forecast | M25: Budget | N25: Gap
B26: Sales
B27: Units | D27: =+VLOOKUP($C$22,'KPIs - Sales Goals'!$A$3:$AP$49,$D$43,FALSE) -> 0 | E27: =+VLOOKUP($C$22,'KPIs - Sales Goals'!$A$3:$AP$49,$C$43,FALSE) -> 0 | F27: =IF(AND(D27>0,E27>0),D27/E27,IF(AND(D27>0,E27=0),100%,IF(AND(D27=0,E27>0),0,IF(AND(D27=0,E27=0),"***",0)))) -> *** | H27: =+VLOOKUP($C$22,'KPIs - Sales Goals'!$A$3:$AP$49,4,FALSE) -> 0 | I27: =+VLOOKUP($C$22,'KPIs - Sales Goals'!$A$3:$AP$49,5,FALSE) -> 0 | J27: =IF(AND(H27>0,I27>0),H27/I27,IF(AND(H27>0,I27=0),100%,IF(AND(H27=0,I27>0),0,IF(AND(H27=0,I27=0),"***",0)))) -> *** | L27: =+VLOOKUP($C$22,'Goals & Budget 2026 - Updated'!$A$2:$EJ$49,19,FALSE) -> 0 | M27: =+VLOOKUP($C$22,'Goals & Budget 2026'!$A$2:$EJ$49,19,FALSE) -> 0 | N27: =IF(AND(L27>0,M27>0),L27/M27,IF(AND(L27>0,M27=0),100%,IF(AND(L27=0,M27>0),0,IF(AND(L27=0,M27=0),"***",0)))) -> ***
B28: Income
B29: Income | D29: =+VLOOKUP($C$22,'KPIs - Income'!$A$3:$AP$49,$D$43,FALSE) -> 0 | E29: =+VLOOKUP($C$22,'KPIs - Income'!$A$3:$AP$49,$C$43,FALSE) -> 0 | F29: =IF(AND(D29>0,E29>0),D29/E29,IF(AND(D29>0,E29=0),100%,IF(AND(D29=0,E29>0),0,IF(AND(D29=0,E29=0),"***",0)))) -> *** | H29: =+VLOOKUP($C$22,'KPIs - Income'!$A$3:$AP$49,4,FALSE) -> 0 | I29: =+VLOOKUP($C$22,'KPIs - Income'!$A$3:$AP$49,5,FALSE) -> 0 | J29: =IF(AND(H29>0,I29>0),H29/I29,IF(AND(H29>0,I29=0),100%,IF(AND(H29=0,I29>0),0,IF(AND(H29=0,I29=0),"***",0)))) -> *** | L29: =+VLOOKUP($C$22,'Goals & Budget 2026 - Updated'!$A$2:$EJ$49,46,FALSE) -> 0 | M29: =+VLOOKUP($C$22,'Goals & Budget 2026'!$A$2:$EJ$49,46,FALSE) -> 0 | N29: =IF(AND(L29>0,M29>0),L29/M29,IF(AND(L29>0,M29=0),100%,IF(AND(L29=0,M29>0),0,IF(AND(L29=0,M29=0),"***",0)))) -> ***
B30: € / Sq. M.
B31: € / Sq. M. | D31: =+VLOOKUP($C$22,'KPIs - €Sq.M.'!$A$2:$AP$48,$D$43,FALSE) -> 0 | E31: =+VLOOKUP($C$22,'KPIs - €Sq.M.'!$A$2:$AP$48,$C$43,FALSE) -> 0 | F31: =IF(AND(D31>0,E31>0),D31/E31,IF(AND(D31>0,E31=0),100%,IF(AND(D31=0,E31>0),0,IF(AND(D31=0,E31=0),"***",0)))) -> *** | H31: =+VLOOKUP($C$22,'KPIs - €Sq.M.'!$A$2:$AP$48,4,FALSE) -> 0 | I31: =+VLOOKUP($C$22,'KPIs - €Sq.M.'!$A$2:$AP$48,5,FALSE) -> 0 | J31: =IF(AND(H31>0,I31>0),H31/I31,IF(AND(H31>0,I31=0),100%,IF(AND(H31=0,I31>0),0,IF(AND(H31=0,I31=0),"***",0)))) -> *** | L31: =+VLOOKUP($C$22,'Goals & Budget 2026 - Updated'!$A$2:$EJ$49,33,FALSE) -> 0 | M31: =+VLOOKUP($C$22,'Goals & Budget 2026'!$A$2:$EJ$49,33,FALSE) -> 0 | N31: =IF(AND(L31>0,M31>0),L31/M31,IF(AND(L31>0,M31=0),100%,IF(AND(L31=0,M31>0),0,IF(AND(L31=0,M31=0),"***",0)))) -> ***
B32: Key Performance Indicators
B33: Sales launch (units, 100%) | D33: =+VLOOKUP($C$22,'KPIs - Sales Launch'!$A$2:$AP$49,$D$43,FALSE) -> 0 | E33: =+VLOOKUP($C$22,'KPIs - Sales Launch'!$A$2:$AP$49,$C$43,FALSE) -> 0 | F33: =IF(AND(D33>0,E33>0),D33/E33,IF(AND(D33>0,E33=0),100%,IF(AND(D33=0,E33>0),0,IF(AND(D33=0,E33=0),"***",0)))) -> *** | H33: =+VLOOKUP($C$22,'KPIs - Sales Launch'!$A$2:$AP$49,4,FALSE) -> 0 | I33: =+VLOOKUP($C$22,'KPIs - Sales Launch'!$A$2:$AP$49,5,FALSE) -> 0 | J33: =IF(AND(H33>0,I33>0),H33/I33,IF(AND(H33>0,I33=0),100%,IF(AND(H33=0,I33>0),0,IF(AND(H33=0,I33=0),"***",0)))) -> *** | L33: =+VLOOKUP($C$22,'Goals & Budget 2026 - Updated'!$A$2:$EJ$49,59,FALSE) -> 0 | M33: =+VLOOKUP($C$22,'Goals & Budget 2026'!$A$2:$EJ$49,59,FALSE) -> 0 | N33: =IF(AND(L33>0,M33>0),L33/M33,IF(AND(L33>0,M33=0),100%,IF(AND(L33=0,M33>0),0,IF(AND(L33=0,M33=0),"***",0)))) -> ***
B34: Marketing (€, 100%) | D34: =+VLOOKUP($C$22,'KPIs - Marketing'!$A$2:$AP$49,$D$43,FALSE) -> 0 | E34: =+VLOOKUP($C$22,'KPIs - Marketing'!$A$2:$AP$49,$C$43,FALSE) -> 0 | F34: =IF(AND(D34>0,E34>0),D34/E34,IF(AND(D34>0,E34=0),100%,IF(AND(D34=0,E34>0),0,IF(AND(D34=0,E34=0),"***",0)))) -> *** | H34: =+VLOOKUP($C$22,'KPIs - Marketing'!$A$2:$AP$49,4,FALSE) -> 0 | I34: =+VLOOKUP($C$22,'KPIs - Marketing'!$A$2:$AP$49,5,FALSE) -> 0 | J34: =IF(AND(H34>0,I34>0),H34/I34,IF(AND(H34>0,I34=0),100%,IF(AND(H34=0,I34>0),0,IF(AND(H34=0,I34=0),"***",0)))) -> *** | L34: =+VLOOKUP($C$22,'Goals & Budget 2026 - Updated'!$A$2:$EJ$49,74,FALSE) -> 0 | M34: =+VLOOKUP($C$22,'Goals & Budget 2026'!$A$2:$EJ$49,74,FALSE) -> 0 | N34: =IF(AND(L34>0,M34>0),L34/M34,IF(AND(L34>0,M34=0),100%,IF(AND(L34=0,M34>0),0,IF(AND(L34=0,M34=0),"***",0)))) -> ***
B35: Schematics Approval (units, 100%) | D35: =+VLOOKUP($C$22,'KPIs - Schematics'!$A$2:$AP$49,$D$43,FALSE) -> 0 | E35: =+VLOOKUP($C$22,'KPIs - Schematics'!$A$2:$AP$49,$C$43,FALSE) -> 0 | F35: =IF(AND(D35>0,E35>0),D35/E35,IF(AND(D35>0,E35=0),100%,IF(AND(D35=0,E35>0),0,IF(AND(D35=0,E35=0),"***",0)))) -> *** | H35: =+VLOOKUP($C$22,'KPIs - Schematics'!$A$2:$AP$49,4,FALSE) -> 0 | I35: =+VLOOKUP($C$22,'KPIs - Schematics'!$A$2:$AP$49,5,FALSE) -> 0 | J35: =IF(AND(H35>0,I35>0),H35/I35,IF(AND(H35>0,I35=0),100%,IF(AND(H35=0,I35>0),0,IF(AND(H35=0,I35=0),"***",0)))) -> *** | L35: =+VLOOKUP($C$22,'Goals & Budget 2026 - Updated'!$A$2:$EJ$49,89,FALSE) -> 0 | M35: =+VLOOKUP($C$22,'Goals & Budget 2026'!$A$2:$EJ$49,89,FALSE) -> 0 | N35: =IF(AND(L35>0,M35>0),L35/M35,IF(AND(L35>0,M35=0),100%,IF(AND(L35=0,M35>0),0,IF(AND(L35=0,M35=0),"***",0)))) -> ***
B36: Tender (units, 100%) | D36: =+VLOOKUP($C$22,'KPIs - Tender'!$A$2:$AP$49,$D$43,FALSE) -> 0 | E36: =+VLOOKUP($C$22,'KPIs - Tender'!$A$2:$AP$49,$C$43,FALSE) -> 0 | F36: =IF(AND(D36>0,E36>0),D36/E36,IF(AND(D36>0,E36=0),100%,IF(AND(D36=0,E36>0),0,IF(AND(D36=0,E36=0),"***",0)))) -> *** | H36: =+VLOOKUP($C$22,'KPIs - Tender'!$A$2:$AP$49,4,FALSE) -> 0 | I36: =+VLOOKUP($C$22,'KPIs - Tender'!$A$2:$AP$49,5,FALSE) -> 0 | J36: =IF(AND(H36>0,I36>0),H36/I36,IF(AND(H36>0,I36=0),100%,IF(AND(H36=0,I36>0),0,IF(AND(H36=0,I36=0),"***",0)))) -> *** | L36: =+VLOOKUP($C$22,'Goals & Budget 2026 - Updated'!$A$2:$EJ$49,102,FALSE) -> 0 | M36: =+VLOOKUP($C$22,'Goals & Budget 2026'!$A$2:$EJ$49,102,FALSE) -> 0 | N36: =IF(AND(L36>0,M36>0),L36/M36,IF(AND(L36>0,M36=0),100%,IF(AND(L36=0,M36>0),0,IF(AND(L36=0,M36=0),"***",0)))) -> ***
B37: Construction - Start (units, 100%) | D37: =+VLOOKUP($C$22,'KPIs - Construction Start'!$A$2:$AP$49,$D$43,FALSE) -> 0 | E37: =+VLOOKUP($C$22,'KPIs - Construction Start'!$A$2:$AP$49,$C$43,FALSE) -> 0 | F37: =IF(AND(D37>0,E37>0),D37/E37,IF(AND(D37>0,E37=0),100%,IF(AND(D37=0,E37>0),0,IF(AND(D37=0,E37=0),"***",0)))) -> *** | H37: =+VLOOKUP($C$22,'KPIs - Construction Start'!$A$2:$AP$49,4,FALSE) -> 0 | I37: =+VLOOKUP($C$22,'KPIs - Construction Start'!$A$2:$AP$49,5,FALSE) -> 0 | J37: =IF(AND(H37>0,I37>0),H37/I37,IF(AND(H37>0,I37=0),100%,IF(AND(H37=0,I37>0),0,IF(AND(H37=0,I37=0),"***",0)))) -> *** | L37: =+VLOOKUP($C$22,'Goals & Budget 2026 - Updated'!$A$2:$EJ$49,115,FALSE) -> 0 | M37: =+VLOOKUP($C$22,'Goals & Budget 2026'!$A$2:$EJ$49,115,FALSE) -> 0 | N37: =IF(AND(L37>0,M37>0),L37/M37,IF(AND(L37>0,M37=0),100%,IF(AND(L37=0,M37>0),0,IF(AND(L37=0,M37=0),"***",0)))) -> ***
B38: Construction - % | D38: =+VLOOKUP($C$22,'KPIs - Construction %'!$A$2:$AP$47,$D$43,FALSE) -> 0 | E38: =+VLOOKUP($C$22,'KPIs - Construction %'!$A$2:$AP$47,$C$43,FALSE) -> 0.52 | F38: =IF(AND(D38>0,E38>0),D38/E38,IF(AND(D38>0,E38=0),100%,IF(AND(D38=0,E38>0),0,IF(AND(D38=0,E38=0),"***",0)))) -> 0 | L38: =+VLOOKUP($C$22,'Goals & Budget 2026 - Updated'!$A$2:$EJ$49,127,FALSE) -> 0 | M38: =+VLOOKUP($C$22,'Goals & Budget 2026'!$A$2:$EJ$49,127,FALSE) -> 0 | N38: =IF(AND(L38>0,M38>0),L38/M38,IF(AND(L38>0,M38=0),100%,IF(AND(L38=0,M38>0),0,IF(AND(L38=0,M38=0),"***",0)))) -> ***
B39: Handover (units, 100%) | D39: =+VLOOKUP($C$22,'KPIs- Handover'!$A$2:$AP$49,$D$43,FALSE) -> 0 | E39: =+VLOOKUP($C$22,'KPIs- Handover'!$A$2:$AP$49,$C$43,FALSE) -> 0 | F39: =IF(AND(D39>0,E39>0),D39/E39,IF(AND(D39>0,E39=0),100%,IF(AND(D39=0,E39>0),0,IF(AND(D39=0,E39=0),"***",0)))) -> *** | H39: =+VLOOKUP($C$22,'KPIs- Handover'!$A$2:$AP$49,4,FALSE) -> 0 | I39: =+VLOOKUP($C$22,'KPIs- Handover'!$A$2:$AP$49,5,FALSE) -> 0 | J39: =IF(AND(H39>0,I39>0),H39/I39,IF(AND(H39>0,I39=0),100%,IF(AND(H39=0,I39>0),0,IF(AND(H39=0,I39=0),"***",0)))) -> *** | L39: =+VLOOKUP($C$22,'Goals & Budget 2026 - Updated'!$A$2:$EJ$49,140,FALSE) -> 0 | M39: =+VLOOKUP($C$22,'Goals & Budget 2026'!$A$2:$EJ$49,140,FALSE) -> 62 | N39: =IF(AND(L39>0,M39>0),L39/M39,IF(AND(L39>0,M39=0),100%,IF(AND(L39=0,M39>0),0,IF(AND(L39=0,M39=0),"***",0)))) -> 0
B40: Deeds (units, 100%) | D40: =+VLOOKUP($C$22,'KPIs- Deeds'!$A$2:$AP$43,$D$43,FALSE) -> 0 | E40: =+VLOOKUP($C$22,'KPIs- Deeds'!$A$2:$AP$43,$C$43,FALSE) -> 0 | F40: =IF(AND(D40>0,E40>0),D40/E40,IF(AND(D40>0,E40=0),100%,IF(AND(D40=0,E40>0),0,IF(AND(D40=0,E40=0),"***",0)))) -> *** | H40: =+VLOOKUP($C$22,'KPIs- Deeds'!$A$2:$AP$43,4,FALSE) -> 0 | I40: =+VLOOKUP($C$22,'KPIs- Deeds'!$A$2:$AP$43,5,FALSE) -> 0 | J40: =IF(AND(H40>0,I40>0),H40/I40,IF(AND(H40>0,I40=0),100%,IF(AND(H40=0,I40>0),0,IF(AND(H40=0,I40=0),"***",0)))) -> *** | L40: =+VLOOKUP($C$22,'Goals & Budget 2026 - Updated'!$A$2:$EW$49,153,FALSE) -> 0 | M40: =+VLOOKUP($C$22,'Goals & Budget 2026'!$A$2:$EW$49,153,FALSE) -> 0 | N40: =IF(AND(L40>0,M40>0),L40/M40,IF(AND(L40>0,M40=0),100%,IF(AND(L40=0,M40>0),0,IF(AND(L40=0,M40=0),"***",0)))) -> ***
B42: Month of Analysis
B43: January | C43: =+VLOOKUP(B43,B44:C55,2,FALSE) -> 8 | D43: =+VLOOKUP(B43,B44:D55,3,FALSE) -> 7
B44: January | C44: 8 | D44: 7
B45: February | C45: 11 | D45: 10
B46: March | C46: 14 | D46: 13
B47: April | C47: =+C46+3 -> 17 | D47: 16
B48: May | C48: =+C47+3 -> 20 | D48: 19
B49: June | C49: =+C48+3 -> 23 | D49: 22
B50: July | C50: =+C49+3 -> 26 | D50: 25
B51: August | C51: =+C50+3 -> 29 | D51: 28
B52: September | C52: =+C51+3 -> 32 | D52: 31
B53: October | C53: =+C52+3 -> 35 | D53: 34
B54: November | C54: =+C53+3 -> 38 | D54: 37
B55: December | C55: =+C54+3 -> 41 | D55: 40

Sheet Goals & Budget 2026
A1: Project Info | D1: Sales Launch | Q1: Sales Goals | AH1: Sales Income (€/Sq. M.) | AU1: Sales Income (€) | BH1: Marketing Budget | BY1: Schematics Approval | CL1: Tender | CY1: Start Construction | DL1: Construction % | DX1: Handover | EK1: Deeds
A2: Project Name | B2: TU (%) | C2: Nr. Units | D2: 46023 | E2: 46054 | F2: 46082 | G2: 46113 | H2: 46143 | I2: 46174 | J2: 46204 | K2: 46235 | L2: 46266 | M2: 46296 | N2: 46327 | O2: 46357 | P2: Total | Q2: Inv. (1.2026) | R2: #NSellableUnits | S2: #SellableUnits | T2: 46023 | U2: 46054 | V2: 46082 | W2: 46113 | X2: 46143 | Y2: 46174 | Z2: 46204 | AA2: 46235 | AB2: 46266 | AC2: 46296 | AD2: 46327 | AE2: 46357 | AF2: Total Sales | AG2: Inv. (12.2026) | AH2: 46023 | AI2: 46054 | AJ2: 46082 | AK2: 46113 | AL2: 46143 | AM2: 46174 | AN2: 46204 | AO2: 46235 | AP2: 46266 | AQ2: 46296 | AR2: 46327 | AS2: 46357 | AT2: Avg. | AU2: 46023 | AV2: 46054 | AW2: 46082 | AX2: 46113 | AY2: 46143 | AZ2: 46174 | BA2: 46204 | BB2: 46235 | BC2: 46266 | BD2: 46296 | BE2: 46327 | BF2: 46357 | BG2: Total | BH2: Budget (Total) | BI2: Avg (Unit) | BJ2: 46023 | BK2: 46054 | BL2: 46082 | BM2: 46113 | BN2: 46143 | BO2: 46174 | BP2: 46204 | BQ2: 46235 | BR2: 46266 | BS2: 46296 | BT2: 46327 | BU2: 46357 | BV2: Total | BW2: Budget (Left) | BX2: Avg (Unit) | BY2: 46023 | BZ2: 46054 | CA2: 46082 | CB2: 46113 | CC2: 46143 | CD2: 46174 | CE2: 46204 | CF2: 46235 | CG2: 46266 | CH2: 46296 | CI2: 46327 | CJ2: 46357 | CK2: Total | CL2: 46023 | CM2: 46054 | CN2: 46082 | CO2: 46113 | CP2: 46143 | CQ2: 46174 | CR2: 46204 | CS2: 46235 | CT2: 46266 | CU2: 46296 | CV2: 46327 | CW2: 46357 | CX2: Total | CY2: 46023 | CZ2: 46054 | DA2: 46082 | DB2: 46113 | DC2: 46143 | DD2: 46174 | DE2: 46204 | DF2: 46235 | DG2: 46266 | DH2: 46296 | DI2: 46327 | DJ2: 46357 | DK2: Total | DL2: 46023 | DM2: 46054 | DN2: 46082 | DO2: 46113 | DP2: 46143 | DQ2: 46174 | DR2: 46204 | DS2: 46235 | DT2: 46266 | DU2: 46296 | DV2: 46327 | DW2: 46357 | DX2: 46023 | DY2: 46054 | DZ2: 46082 | EA2: 46113 | EB2: 46143 | EC2: 46174 | ED2: 46204 | EE2: 46235 | EF2: 46266 | EG2: 46296 | EH2: 46327 | EI2: 46357 | EJ2: Total | EK2: 46023 | EL2: 46054 | EM2: 46082 | EN2: 46113 | EO2: 46143 | EP2: 46174 | EQ2: 46204 | ER2: 46235 | ES2: 46266 | ET2: 46296 | EU2: 46327 | EV2: 46357 | EW2: Total
A3: Pinto Bessa | B3: 1 | C3: 30 | P3: =+SUM(D3:O3) -> 0 | AF3: =+SUM(T3:AE3) -> 0 | AG3: =+Q3-AF3 -> 0 | AT3: =+IFERROR(AVERAGE(AH3:AS3),0) -> 0 | BG3: =+SUM(AU3:BF3) -> 0 | BI3: =IFERROR(+BH3/C3,0) -> 0 | BV3: =+SUM(BJ3:BU3) -> 0 | BW3: =+BH3-BV3 -> 0 | BX3: =IFERROR(+BV3/C3,0) -> 0 | CA3: 30 | CK3: =+SUM(BY3:CJ3) -> 30 | CW3: 30 | CX3: =+SUM(CL3:CW3) -> 30 | DK3: =+SUM(CY3:DJ3) -> 0 | EJ3: =+SUM(DX3:EI3) -> 0 | EW3: =+SUM(EK3:EV3) -> 0
A4: Saldouro - 6 | B4: 1 | C4: 25 | P4: =+SUM(D4:O4) -> 0 | AF4: =+SUM(T4:AE4) -> 0 | AG4: =+Q4-AF4 -> 0 | AT4: =+IFERROR(AVERAGE(AH4:AS4),0) -> 0 | BG4: =+SUM(AU4:BF4) -> 0 | BI4: =IFERROR(+BH4/C4,0) -> 0 | BV4: =+SUM(BJ4:BU4) -> 0 | BW4: =+BH4-BV4 -> 0 | BX4: =IFERROR(+BV4/C4,0) -> 0 | CK4: =+SUM(BY4:CJ4) -> 0 | CX4: =+SUM(CL4:CW4) -> 0 | DK4: =+SUM(CY4:DJ4) -> 0 | DL4: 0.95 | DM4: 0.99 | DN4: 1 | DZ4: 25 | EJ4: =+SUM(DX4:EI4) -> 25 | EW4: =+SUM(EK4:EV4) -> 0
A5: Saldouro - 8 | B5: 1 | C5: 31 | P5: =+SUM(D5:O5) -> 0 | AF5: =+SUM(T5:AE5) -> 0 | AG5: =+Q5-AF5 -> 0 | AT5: =+IFERROR(AVERAGE(AH5:AS5),0) -> 0 | BG5: =+SUM(AU5:BF5) -> 0 | BI5: =IFERROR(+BH5/C5,0) -> 0 | BV5: =+SUM(BJ5:BU5) -> 0 | BW5: =+BH5-BV5 -> 0 | BX5: =IFERROR(+BV5/C5,0) -> 0 | CK5: =+SUM(BY5:CJ5) -> 0 | CX5: =+SUM(CL5:CW5) -> 0 | DK5: =+SUM(CY5:DJ5) -> 0 | EJ5: =+SUM(DX5:EI5) -> 0 | EW5: =+SUM(EK5:EV5) -> 0
A6: Saldouro - 9 | B6: 1 | C6: 46 | P6: =+SUM(D6:O6) -> 0 | AF6: =+SUM(T6:AE6) -> 0 | AG6: =+Q6-AF6 -> 0 | AT6: =+IFERROR(AVERAGE(AH6:AS6),0) -> 0 | BG6: =+SUM(AU6:BF6) -> 0 | BI6: =IFERROR(+BH6/C6,0) -> 0 | BV6: =+SUM(BJ6:BU6) -> 0 | BW6: =+BH6-BV6 -> 0 | BX6: =IFERROR(+BV6/C6,0) -> 0 | CK6: =+SUM(BY6:CJ6) -> 0 | CX6: =+SUM(CL6:CW6) -> 0 | DK6: =+SUM(CY6:DJ6) -> 0 | DL6: 0.42 | DM6: 0.47 | DN6: 0.52 | DO6: 0.57 | DP6: 0.63 | DQ6: 0.69 | DR6: 0.75 | DS6: 0.81 | DT6: 0.87 | DU6: 0.92 | DV6: 0.97 | DW6: 1 | EI6: 46 | EJ6: =+SUM(DX6:EI6) -> 46 | EW6: =+SUM(EK6:EV6) -> 0
A7: Saldouro - 10 | B7: 1 | C7: 62 | P7: =+SUM(D7:O7) -> 0 | AF7: =+SUM(T7:AE7) -> 0 | AG7: =+Q7-AF7 -> 0 | AT7: =+IFERROR(AVERAGE(AH7:AS7),0) -> 0 | BG7: =+SUM(AU7:BF7) -> 0 | BI7: =IFERROR(+BH7/C7,0) -> 0 | BV7: =+SUM(BJ7:BU7) -> 0 | BW7: =+BH7-BV7 -> 0 | BX7: =IFERROR(+BV7/C7,0) -> 0 | CK7: =+SUM(BY7:CJ7) -> 0 | CX7: =+SUM(CL7:CW7) -> 0 | DK7: =+SUM(CY7:DJ7) -> 0 | DL7: 0.52 | DM7: 0.57 | DN7: 0.62 | DO7: 0.67 | DP7: 0.72 | DQ7: 0.77 | DR7: 0.82 | DS7: 0.87 | DT7: 0.92 | DU7: 0.97 | DV7: 1 | EH7: 62 | EJ7: =+SUM(DX7:EI7) -> 62 | EW7: =+SUM(EK7:EV7) -> 0
A8: Saldouro - 12.2 | B8: 1 | C8: 37 | P8: =+SUM(D8:O8) -> 0 | AF8: =+SUM(T8:AE8) -> 0 | AG8: =+Q8-AF8 -> 0 | AT8: =+IFERROR(AVERAGE(AH8:AS8),0) -> 0 | BG8: =+SUM(AU8:BF8) -> 0 | BI8: =IFERROR(+BH8/C8,0) -> 0 | BV8: =+SUM(BJ8:BU8) -> 0 | BW8: =+BH8-BV8 -> 0 | BX8: =IFERROR(+BV8/C8,0) -> 0 | CK8: =+SUM(BY8:CJ8) -> 0 | CX8: =+SUM(CL8:CW8) -> 0 | DK8: =+SUM(CY8:DJ8) -> 0 | EJ8: =+SUM(DX8:EI8) -> 0 | EW8: =+SUM(EK8:EV8) -> 0
A9: Saldouro - 17.2 | B9: 1 | C9: 24 | P9: =+SUM(D9:O9) -> 0 | AF9: =+SUM(T9:AE9) -> 0 | AG9: =+Q9-AF9 -> 0 | AT9: =+IFERROR(AVERAGE(AH9:AS9),0) -> 0 | BG9: =+SUM(AU9:BF9) -> 0 | BI9: =IFERROR(+BH9/C9,0) -> 0 | BV9: =+SUM(BJ9:BU9) -> 0 | BW9: =+BH9-BV9 -> 0 | BX9: =IFERROR(+BV9/C9,0) -> 0 | CK9: =+SUM(BY9:CJ9) -> 0 | CX9: =+SUM(CL9:CW9) -> 0 | CZ9: 24 | DK9: =+SUM(CY9:DJ9) -> 24 | DM9: 0.006 | DN9: 0.035 | DO9: 0.064 | DP9: 0.094 | DQ9: 0.124 | DR9: 0.156 | DS9: 0.191 | DT9: 0.226 | DU9: 0.267 | DV9: 0.316 | DW9: 0.368 | EJ9: =+SUM(DX9:EI9) -> 0 | EW9: =+SUM(EK9:EV9) -> 0
A10: Panorama | B10: 1 | C10: 77 | P10: =+SUM(D10:O10) -> 0 | AF10: =+SUM(T10:AE10) -> 0 | AG10: =+Q10-AF10 -> 0 | AT10: =+IFERROR(AVERAGE(AH10:AS10),0) -> 0 | BG10: =+SUM(AU10:BF10) -> 0 | BI10: =IFERROR(+BH10/C10,0) -> 0 | BV10: =+SUM(BJ10:BU10) -> 0 | BW10: =+BH10-BV10 -> 0 | BX10: =IFERROR(+BV10/C10,0) -> 0 | CK10: =+SUM(BY10:CJ10) -> 0 | CX10: =+SUM(CL10:CW10) -> 0 | DK10: =+SUM(CY10:DJ10) -> 0 | EJ10: =+SUM(DX10:EI10) -> 0 | EW10: =+SUM(EK10:EV10) -> 0
A11: Verde Vale - H1 | B11: 1 | C11: 64 | P11: =+SUM(D11:O11) -> 0 | AF11: =+SUM(T11:AE11) -> 0 | AG11: =+Q11-AF11 -> 0 | AT11: =+IFERROR(AVERAGE(AH11:AS11),0) -> 0 | BG11: =+SUM(AU11:BF11) -> 0 | BI11: =IFERROR(+BH11/C11,0) -> 0 | BV11: =+SUM(BJ11:BU11) -> 0 | BW11: =+BH11-BV11 -> 0 | BX11: =IFERROR(+BV11/C11,0) -> 0 | CK11: =+SUM(BY11:CJ11) -> 0 | CX11: =+SUM(CL11:CW11) -> 0 | DK11: =+SUM(CY11:DJ11) -> 0 | DL11: 0.97 | DM11: 1 | DY11: 64 | EJ11: =+SUM(DX11:EI11) -> 64 | EW11: =+SUM(EK11:EV11) -> 0
A12: Verde Vale - H2 | B12: 1 | C12: 54 | P12: =+SUM(D12:O12) -> 0 | AF12: =+SUM(T12:AE12) -> 0 | AG12: =+Q12-AF12 -> 0 | AT12: =+IFERROR(AVERAGE(AH12:AS12),0) -> 0 | BG12: =+SUM(AU12:BF12) -> 0 | BI12: =IFERROR(+BH12/C12,0) -> 0 | BV12: =+SUM(BJ12:BU12) -> 0 | BW12: =+BH12-BV12 -> 0 | BX12: =IFERROR(+BV12/C12,0) -> 0 | CK12: =+SUM(BY12:CJ12) -> 0 | CX12: =+SUM(CL12:CW12) -> 0 | DK12: =+SUM(CY12:DJ12) -> 0 | DL12: 0.83 | DM12: 0.87 | DN12: 0.91 | DO12: 0.94 | DP12: 0.97 | DQ12: 1 | ED12: 54 | EJ12: =+SUM(DX12:EI12) -> 54 | EW12: =+SUM(EK12:EV12) -> 0
A13: Verde Vale - H3 | B13: 1 | C13: 56 | P13: =+SUM(D13:O13) -> 0 | AF13: =+SUM(T13:AE13) -> 0 | AG13: =+Q13-AF13 -> 0 | AT13: =+IFERROR(AVERAGE(AH13:AS13),0) -> 0 | BG13: =+SUM(AU13:BF13) -> 0 | BI13: =IFERROR(+BH13/C13,0) -> 0 | BV13: =+SUM(BJ13:BU13) -> 0 | BW13: =+BH13-BV13 -> 0 | BX13: =IFERROR(+BV13/C13,0) -> 0 | CK13: =+SUM(BY13:CJ13) -> 0 | CX13: =+SUM(CL13:CW13) -> 0 | DK13: =+SUM(CY13:DJ13) -> 0 | DL13: 0.91 | DM13: 0.95 | DN13: 0.97 | DO13: 1 | EB13: 56 | EJ13: =+SUM(DX13:EI13) -> 56 | EW13: =+SUM(EK13:EV13) -> 0
A14: Verde Vale - H4 | B14: 1 | C14: 80 | P14: =+SUM(D14:O14) -> 0 | AF14: =+SUM(T14:AE14) -> 0 | AG14: =+Q14-AF14 -> 0 | AT14: =+IFERROR(AVERAGE(AH14:AS14),0) -> 0 | BG14: =+SUM(AU14:BF14) -> 0 | BI14: =IFERROR(+BH14/C14,0) -> 0 | BV14: =+SUM(BJ14:BU14) -> 0 | BW14: =+BH14-BV14 -> 0 | BX14: =IFERROR(+BV14/C14,0) -> 0 | CK14: =+SUM(BY14:CJ14) -> 0 | CX14: =+SUM(CL14:CW14) -> 0 | DK14: =+SUM(CY14:DJ14) -> 0 | DL14: 0.62 | DM14: 0.67 | DN14: 0.72 | DO14: 0.77 | DP14: 0.81 | DQ14: 0.86 | DR14: 0.89 | DS14: 0.92 | DT14: 0.95 | DU14: 0.97 | DV14: 1 | EH14: 80 | EJ14: =+SUM(DX14:EI14) -> 80 | EW14: =+SUM(EK14:EV14) -> 0
A15: Verde Vale - S1 | B15: 1 | C15: 2 | P15: =+SUM(D15:O15) -> 0 | AF15: =+SUM(T15:AE15) -> 0 | AG15: =+Q15-AF15 -> 0 | AT15: =+IFERROR(AVERAGE(AH15:AS15),0) -> 0 | BG15: =+SUM(AU15:BF15) -> 0 | BI15: =IFERROR(+BH15/C15,0) -> 0 | BV15: =+SUM(BJ15:BU15) -> 0 | BW15: =+BH15-BV15 -> 0 | BX15: =IFERROR(+BV15/C15,0) -> 0 | CK15: =+SUM(BY15:CJ15) -> 0 | CX15: =+SUM(CL15:CW15) -> 0 | DK15: =+SUM(CY15:DJ15) -> 0 | DL15: 0.75 | DM15: 0.9 | DN15: 1 | DZ15: 2 | EJ15: =+SUM(DX15:EI15) -> 2 | EW15: =+SUM(EK15:EV15) -> 0
A16: Setúbal Sea View | B16: 1 | C16: 71 | P16: =+SUM(D16:O16) -> 0 | AF16: =+SUM(T16:AE16) -> 0 | AG16: =+Q16-AF16 -> 0 | AT16: =+IFERROR(AVERAGE(AH16:AS16),0) -> 0 | BG16: =+SUM(AU16:BF16) -> 0 | BI16: =IFERROR(+BH16/C16,0) -> 0 | BV16: =+SUM(BJ16:BU16) -> 0 | BW16: =+BH16-BV16 -> 0 | BX16: =IFERROR(+BV16/C16,0) -> 0 | CK16: =+SUM(BY16:CJ16) -> 0 | CX16: =+SUM(CL16:CW16) -> 0 | DK16: =+SUM(CY16:DJ16) -> 0 | EJ16: =+SUM(DX16:EI16) -> 0 | EW16: =+SUM(EK16:EV16) -> 0
A17: Coimbra Celas - 4 | B17: 1 | C17: 28 | P17: =+SUM(D17:O17) -> 0 | AF17: =+SUM(T17:AE17) -> 0 | AG17: =+Q17-AF17 -> 0 | AT17: =+IFERROR(AVERAGE(AH17:AS17),0) -> 0 | BG17: =+SUM(AU17:BF17) -> 0 | BI17: =IFERROR(+BH17/C17,0) -> 0 | BV17: =+SUM(BJ17:BU17) -> 0 | BW17: =+BH17-BV17 -> 0 | BX17: =IFERROR(+BV17/C17,0) -> 0 | CK17: =+SUM(BY17:CJ17) -> 0 | CX17: =+SUM(CL17:CW17) -> 0 | DH17: 28 | DK17: =+SUM(CY17:DJ17) -> 28 | DU17: 0.006 | DV17: 0.035 | DW17: 0.064 | EJ17: =+SUM(DX17:EI17) -> 0 | EW17: =+SUM(EK17:EV17) -> 0
A18: Coimbra Celas - 5 | B18: 1 | C18: 28 | P18: =+SUM(D18:O18) -> 0 | AF18: =+SUM(T18:AE18) -> 0 | AG18: =+Q18-AF18 -> 0 | AT18: =+IFERROR(AVERAGE(AH18:AS18),0) -> 0 | BG18: =+SUM(AU18:BF18) -> 0 | BI18: =IFERROR(+BH18/C18,0) -> 0 | BV18: =+SUM(BJ18:BU18) -> 0 | BW18: =+BH18-BV18 -> 0 | BX18: =IFERROR(+BV18/C18,0) -> 0 | BY18: 28 | CK18: =+SUM(BY18:CJ18) -> 28 | CP18: 28 | CX18: =+SUM(CL18:CW18) -> 28 | DG18: 28 | DK18: =+SUM(CY18:DJ18) -> 28 | DT18: 0.006 | DU18: 0.035 | DV18: 0.064 | DW18: 0.094 | EJ18: =+SUM(DX18:EI18) -> 0 | EW18: =+SUM(EK18:EV18) -> 0
A19: Coimbra Celas - 6 | B19: 1 | C19: 14 | P19: =+SUM(D19:O19) -> 0 | AF19: =+SUM(T19:AE19) -> 0 | AG19: =+Q19-AF19 -> 0 | AT19: =+IFERROR(AVERAGE(AH19:AS19),0) -> 0 | BG19: =+SUM(AU19:BF19) -> 0 | BI19: =IFERROR(+BH19/C19,0) -> 0 | BV19: =+SUM(BJ19:BU19) -> 0 | BW19: =+BH19-BV19 -> 0 | BX19: =IFERROR(+BV19/C19,0) -> 0 | BY19: 14 | CK19: =+SUM(BY19:CJ19) -> 14 | CP19: 14 | CX19: =+SUM(CL19:CW19) -> 14 | DF19: 14 | DK19: =+SUM(CY19:DJ19) -> 14 | DS19: 0.006 | DT19: 0.035 | DU19: 0.064 | DV19: 0.094 | DW19: 0.124 | EJ19: =+SUM(DX19:EI19) -> 0 | EW19: =+SUM(EK19:EV19) -> 0
A20: Coimbra Celas - 7 | B20: 1 | C20: 14 | P20: =+SUM(D20:O20) -> 0 | AF20: =+SUM(T20:AE20) -> 0 | AG20: =+Q20-AF20 -> 0 | AT20: =+IFERROR(AVERAGE(AH20:AS20),0) -> 0 | BG20: =+SUM(AU20:BF20) -> 0 | BI20: =IFERROR(+BH20/C20,0) -> 0 | BV20: =+SUM(BJ20:BU20) -> 0 | BW20: =+BH20-BV20 -> 0 | BX20: =IFERROR(+BV20/C20,0) -> 0 | BY20: 14 | CK20: =+SUM(BY20:CJ20) -> 14 | CP20: 14 | CX20: =+SUM(CL20:CW20) -> 14 | DF20: 14 | DK20: =+SUM(CY20:DJ20) -> 14 | DS20: 0.006 | DT20: 0.035 | DU20: 0.064 | DV20: 0.094 | DW20: 0.124 | EJ20: =+SUM(DX20:EI20) -> 0 | EW20: =+SUM(EK20:EV20) -> 0
A21: Coimbra Celas - 8 | B21: 1 | C21: 14 | P21: =+SUM(D21:O21) -> 0 | AF21: =+SUM(T21:AE21) -> 0 | AG21: =+Q21-AF21 -> 0 | AT21: =+IFERROR(AVERAGE(AH21:AS21),0) -> 0 | BG21: =+SUM(AU21:BF21) -> 0 | BI21: =IFERROR(+BH21/C21,0) -> 0 | BV21: =+SUM(BJ21:BU21) -> 0 | BW21: =+BH21-BV21 -> 0 | BX21: =IFERROR(+BV21/C21,0) -> 0 | CK21: =+SUM(BY21:CJ21) -> 0 | CX21: =+SUM(CL21:CW21) -> 0 | CY21: 14 | DK21: =+SUM(CY21:DJ21) -> 14 | DL21: 0.01 | DM21: 0.02 | DN21: 0.04 | DO21: 0.06 | DP21: 0.08 | DQ21: 0.1 | DR21: 0.12 | DS21: 0.14 | DT21: 0.16 | DU21: 0.2 | DV21: 0.22 | DW21: 0.24 | EJ21: =+SUM(DX21:EI21) -> 0 | EW21: =+SUM(EK21:EV21) -> 0
A22: Coimbra Celas - 9 | B22: 1 | C22: 14 | P22: =+SUM(D22:O22) -> 0 | AF22: =+SUM(T22:AE22) -> 0 | AG22: =+Q22-AF22 -> 0 | AT22: =+IFERROR(AVERAGE(AH22:AS22),0) -> 0 | BG22: =+SUM(AU22:BF22) -> 0 | BI22: =IFERROR(+BH22/C22,0) -> 0 | BV22: =+SUM(BJ22:BU22) -> 0 | BW22: =+BH22-BV22 -> 0 | BX22: =IFERROR(+BV22/C22,0) -> 0 | CK22: =+SUM(BY22:CJ22) -> 0 | CX22: =+SUM(CL22:CW22) -> 0 | CY22: 14 | DK22: =+SUM(CY22:DJ22) -> 14 | DL22: 0.01 | DM22: 0.02 | DN22: 0.04 | DO22: 0.06 | DP22: 0.08 | DQ22: 0.1 | DR22: 0.12 | DS22: 0.14 | DT22: 0.16 | DU22: 0.2 | DV22: 0.22 | DW22: 0.24 | EJ22: =+SUM(DX22:EI22) -> 0 | EW22: =+SUM(EK22:EV22) -> 0
A23: Red Clip | B23: 1 | C23: 30 | P23: =+SUM(D23:O23) -> 0 | AF23: =+SUM(T23:AE23) -> 0 | AG23: =+Q23-AF23 -> 0 | AT23: =+IFERROR(AVERAGE(AH23:AS23),0) -> 0 | BG23: =+SUM(AU23:BF23) -> 0 | BI23: =IFERROR(+BH23/C23,0) -> 0 | BV23: =+SUM(BJ23:BU23) -> 0 | BW23: =+BH23-BV23 -> 0 | BX23: =IFERROR(+BV23/C23,0) -> 0 | CK23: =+SUM(BY23:CJ23) -> 0 | CX23: =+SUM(CL23:CW23) -> 0 | CY23: 30 | DK23: =+SUM(CY23:DJ23) -> 30 | DL23: 0.006 | DM23: 0.035 | DN23: 0.064 | DO23: 0.094 | DP23: 0.124 | DQ23: 0.156 | DR23: 0.191 | DS23: 0.226 | DT23: 0.267 | DU23: 0.316 | DV23: 0.368 | DW23: 0.422 | EJ23: =+SUM(DX23:EI23) -> 0 | EW23: =+SUM(EK23:EV23) -> 0
A24: Bélgica - 1 | B24: 0.5 | C24: 58 | P24: =+SUM(D24:O24) -> 0 | AF24: =+SUM(T24:AE24) -> 0 | AG24: =+Q24-AF24 -> 0 | AT24: =+IFERROR(AVERAGE(AH24:AS24),0) -> 0 | BG24: =+SUM(AU24:BF24) -> 0 | BI24: =IFERROR(+BH24/C24,0) -> 0 | BV24: =+SUM(BJ24:BU24) -> 0 | BW24: =+BH24-BV24 -> 0 | BX24: =IFERROR(+BV24/C24,0) -> 0 | CC24: 58 | CK24: =+SUM(BY24:CJ24) -> 58 | CW24: 58 | CX24: =+SUM(CL24:CW24) -> 58 | DK24: =+SUM(CY24:DJ24) -> 0 | EJ24: =+SUM(DX24:EI24) -> 0 | EW24: =+SUM(EK24:EV24) -> 0
A25: Bélgica - 2 | B25: 0.5 | C25: 58 | P25: =+SUM(D25:O25) -> 0 | AF25: =+SUM(T25:AE25) -> 0 | AG25: =+Q25-AF25 -> 0 | AT25: =+IFERROR(AVERAGE(AH25:AS25),0) -> 0 | BG25: =+SUM(AU25:BF25) -> 0 | BI25: =IFERROR(+BH25/C25,0) -> 0 | BV25: =+SUM(BJ25:BU25) -> 0 | BW25: =+BH25-BV25 -> 0 | BX25: =IFERROR(+BV25/C25,0) -> 0 | CC25: 58 | CK25: =+SUM(BY25:CJ25) -> 58 | CW25: 58 | CX25: =+SUM(CL25:CW25) -> 58 | DK25: =+SUM(CY25:DJ25) -> 0 | EJ25: =+SUM(DX25:EI25) -> 0 | EW25: =+SUM(EK25:EV25) -> 0
A26: Bélgica - 3 | B26: 0.5 | C26: 58 | P26: =+SUM(D26:O26) -> 0 | AF26: =+SUM(T26:AE26) -> 0 | AG26: =+Q26-AF26 -> 0 | AT26: =+IFERROR(AVERAGE(AH26:AS26),0) -> 0 | BG26: =+SUM(AU26:BF26) -> 0 | BI26: =IFERROR(+BH26/C26,0) -> 0 | BV26: =+SUM(BJ26:BU26) -> 0 | BW26: =+BH26-BV26 -> 0 | BX26: =IFERROR(+BV26/C26,0) -> 0 | CC26: 58 | CK26: =+SUM(BY26:CJ26) -> 58 | CW26: 58 | CX26: =+SUM(CL26:CW26) -> 58 | DK26: =+SUM(CY26:DJ26) -> 0 | EJ26: =+SUM(DX26:EI26) -> 0 | EW26: =+SUM(EK26:EV26) -> 0
A27: Bélgica - 4 | B27: 0.5 | C27: 58 | P27: =+SUM(D27:O27) -> 0 | AF27: =+SUM(T27:AE27) -> 0 | AG27: =+Q27-AF27 -> 0 | AT27: =+IFERROR(AVERAGE(AH27:AS27),0) -> 0 | BG27: =+SUM(AU27:BF27) -> 0 | BI27: =IFERROR(+BH27/C27,0) -> 0 | BV27: =+SUM(BJ27:BU27) -> 0 | BW27: =+BH27-BV27 -> 0 | BX27: =IFERROR(+BV27/C27,0) -> 0 | CC27: 58 | CK27: =+SUM(BY27:CJ27) -> 58 | CW27: 58 | CX27: =+SUM(CL27:CW27) -> 58 | DK27: =+SUM(CY27:DJ27) -> 0 | EJ27: =+SUM(DX27:EI27) -> 0 | EW27: =+SUM(EK27:EV27) -> 0
A28: Antas South - S. Apts. | B28: 1 | C28: 164 | P28: =+SUM(D28:O28) -> 0 | AF28: =+SUM(T28:AE28) -> 0 | AG28: =+Q28-AF28 -> 0 | AT28: =+IFERROR(AVERAGE(AH28:AS28),0) -> 0 | BG28: =+SUM(AU28:BF28) -> 0 | BI28: =IFERROR(+BH28/C28,0) -> 0 | BV28: =+SUM(BJ28:BU28) -> 0 | BW28: =+BH28-BV28 -> 0 | BX28: =IFERROR(+BV28/C28,0) -> 0 | CK28: =+SUM(BY28:CJ28) -> 0 | CX28: =+SUM(CL28:CW28) -> 0 | DK28: =+SUM(CY28:DJ28) -> 0 | EJ28: =+SUM(DX28:EI28) -> 0 | EW28: =+SUM(EK28:EV28) -> 0
A29: Antas South - Resi | B29: 1 | C29: 57 | P29: =+SUM(D29:O29) -> 0 | AF29: =+SUM(T29:AE29) -> 0 | AG29: =+Q29-AF29 -> 0 | AT29: =+IFERROR(AVERAGE(AH29:AS29),0) -> 0 | BG29: =+SUM(AU29:BF29) -> 0 | BI29: =IFERROR(+BH29/C29,0) -> 0 | BV29: =+SUM(BJ29:BU29) -> 0 | BW29: =+BH29-BV29 -> 0 | BX29: =IFERROR(+BV29/C29,0) -> 0 | CK29: =+SUM(BY29:CJ29) -> 0 | CX29: =+SUM(CL29:CW29) -> 0 | DK29: =+SUM(CY29:DJ29) -> 0 | EJ29: =+SUM(DX29:EI29) -> 0 | EW29: =+SUM(EK29:EV29) -> 0
A30: Antas North | B30: 1 | C30: ? | P30: =+SUM(D30:O30) -> 0 | AF30: =+SUM(T30:AE30) -> 0 | AG30: =+Q30-AF30 -> 0 | AT30: =+IFERROR(AVERAGE(AH30:AS30),0) -> 0 | BG30: =+SUM(AU30:BF30) -> 0 | BI30: =IFERROR(+BH30/C30,0) -> 0 | BV30: =+SUM(BJ30:BU30) -> 0 | BW30: =+BH30-BV30 -> 0 | BX30: =IFERROR(+BV30/C30,0) -> 0 | CK30: =+SUM(BY30:CJ30) -> 0 | CX30: =+SUM(CL30:CW30) -> 0 | DK30: =+SUM(CY30:DJ30) -> 0 | EJ30: =+SUM(DX30:EI30) -> 0 | EW30: =+SUM(EK30:EV30) -> 0
A31: Villa do Conde - Allotment | B31: 1 | C31: 1 | CK31: =+SUM(BY31:CJ31) -> 0 | CX31: =+SUM(CL31:CW31) -> 0 | DK31: =+SUM(CY31:DJ31) -> 0 | EJ31: =+SUM(DX31:EI31) -> 0 | EW31: =+SUM(EK31:EV31) -> 0
A32: Vila do Conde - Phase 1 | B32: 1 | C32: 159 | P32: =+SUM(D32:O32) -> 0 | AF32: =+SUM(T32:AE32) -> 0 | AG32: =+Q32-AF32 -> 0 | AT32: =+IFERROR(AVERAGE(AH32:AS32),0) -> 0 | BG32: =+SUM(AU32:BF32) -> 0 | BI32: =IFERROR(+BH32/C32,0) -> 0 | BV32: =+SUM(BJ32:BU32) -> 0 | BW32: =+BH32-BV32 -> 0 | BX32: =IFERROR(+BV32/C32,0) -> 0 | CK32: =+SUM(BY32:CJ32) -> 0 | CM32: =99+60 -> 159 | CX32: =+SUM(CL32:CW32) -> 159 | DD32: 99 | DH32: 60 | DK32: =+SUM(CY32:DJ32) -> 159 | EJ32: =+SUM(DX32:EI32) -> 0 | EW32: =+SUM(EK32:EV32) -> 0
A33: Vila do Conde - Phase 2 | B33: 1 | C33: 39 | P33: =+SUM(D33:O33) -> 0 | AF33: =+SUM(T33:AE33) -> 0 | AG33: =+Q33-AF33 -> 0 | AT33: =+IFERROR(AVERAGE(AH33:AS33),0) -> 0 | BG33: =+SUM(AU33:BF33) -> 0 | BI33: =IFERROR(+BH33/C33,0) -> 0 | BV33: =+SUM(BJ33:BU33) -> 0 | BW33: =+BH33-BV33 -> 0 | BX33: =IFERROR(+BV33/C33,0) -> 0 | CE33: 39 | CK33: =+SUM(BY33:CJ33) -> 39 | CV33: 39 | CX33: =+SUM(CL33:CW33) -> 39 | DK33: =+SUM(CY33:DJ33) -> 0 | EJ33: =+SUM(DX33:EI33) -> 0 | EW33: =+SUM(EK33:EV33) -> 0
A34: Vila do Conde - Phase 3 | B34: 1 | C34: 76 | P34: =+SUM(D34:O34) -> 0 | AF34: =+SUM(T34:AE34) -> 0 | AG34: =+Q34-AF34 -> 0 | AT34: =+IFERROR(AVERAGE(AH34:AS34),0) -> 0 | BG34: =+SUM(AU34:BF34) -> 0 | BI34: =IFERROR(+BH34/C34,0) -> 0 | BV34: =+SUM(BJ34:BU34) -> 0 | BW34: =+BH34-BV34 -> 0 | BX34: =IFERROR(+BV34/C34,0) -> 0 | CB34: 63 | CK34: =+SUM(BY34:CJ34) -> 63 | CT34: 63 | CX34: =+SUM(CL34:CW34) -> 63 | DK34: =+SUM(CY34:DJ34) -> 0 | EJ34: =+SUM(DX34:EI34) -> 0 | EW34: =+SUM(EK34:EV34) -> 0
A35: Parkview | B35: 1 | C35: 39 | P35: =+SUM(D35:O35) -> 0 | AF35: =+SUM(T35:AE35) -> 0 | AG35: =+Q35-AF35 -> 0 | AT35: =+IFERROR(AVERAGE(AH35:AS35),0) -> 0 | BG35: =+SUM(AU35:BF35) -> 0 | BI35: =IFERROR(+BH35/C35,0) -> 0 | BV35: =+SUM(BJ35:BU35) -> 0 | BW35: =+BH35-BV35 -> 0 | BX35: =IFERROR(+BV35/C35,0) -> 0 | CK35: =+SUM(BY35:CJ35) -> 0 | CX35: =+SUM(CL35:CW35) -> 0 | DK35: =+SUM(CY35:DJ35) -> 0 | DL35: 0.92 | DM35: 0.96 | DN35: 0.98 | DO35: 1 | EB35: 39 | EJ35: =+SUM(DX35:EI35) -> 39 | EW35: =+SUM(EK35:EV35) -> 0
A36: Eleven | B36: 1 | C36: 95 | P36: =+SUM(D36:O36) -> 0 | AF36: =+SUM(T36:AE36) -> 0 | AG36: =+Q36-AF36 -> 0 | AT36: =+IFERROR(AVERAGE(AH36:AS36),0) -> 0 | BG36: =+SUM(AU36:BF36) -> 0 | BI36: =IFERROR(+BH36/C36,0) -> 0 | BV36: =+SUM(BJ36:BU36) -> 0 | BW36: =+BH36-BV36 -> 0 | BX36: =IFERROR(+BV36/C36,0) -> 0 | CK36: =+SUM(BY36:CJ36) -> 0 | CX36: =+SUM(CL36:CW36) -> 0 | DK36: =+SUM(CY36:DJ36) -> 0 | DL36: 0.99 | DM36: 0.99 | DN36: 1 | DZ36: 95 | EJ36: =+SUM(DX36:EI36) -> 95 | EW36: =+SUM(EK36:EV36) -> 0
A37: Clip Allotment | B37: 1 | C37: 1 | BI37: =IFERROR(+BH37/C37,0) -> 0 | CK37: =+SUM(BY37:CJ37) -> 0 | CX37: =+SUM(CL37:CW37) -> 0 | DK37: =+SUM(CY37:DJ37) -> 0 | EJ37: =+SUM(DX37:EI37) -> 0 | EW37: =+SUM(EK37:EV37) -> 0
A38: Clip Stage A | B38: 1 | C38: 83 | P38: =+SUM(D38:O38) -> 0 | AF38: =+SUM(T38:AE38) -> 0 | AG38: =+Q38-AF38 -> 0 | AT38: =+IFERROR(AVERAGE(AH38:AS38),0) -> 0 | BG38: =+SUM(AU38:BF38) -> 0 | BI38: =IFERROR(+BH38/C38,0) -> 0 | BV38: =+SUM(BJ38:BU38) -> 0 | BW38: =+BH38-BV38 -> 0 | BX38: =IFERROR(+BV38/C38,0) -> 0 | CK38: =+SUM(BY38:CJ38) -> 0 | CX38: =+SUM(CL38:CW38) -> 0 | DK38: =+SUM(CY38:DJ38) -> 0 | EJ38: =+SUM(DX38:EI38) -> 0 | EW38: =+SUM(EK38:EV38) -> 0
A39: Clip Stage B | B39: 1 | C39: 180 | P39: =+SUM(D39:O39) -> 0 | AF39: =+SUM(T39:AE39) -> 0 | AG39: =+Q39-AF39 -> 0 | AT39: =+IFERROR(AVERAGE(AH39:AS39),0) -> 0 | BG39: =+SUM(AU39:BF39) -> 0 | BI39: =IFERROR(+BH39/C39,0) -> 0 | BV39: =+SUM(BJ39:BU39) -> 0 | BW39: =+BH39-BV39 -> 0 | BX39: =IFERROR(+BV39/C39,0) -> 0 | CK39: =+SUM(BY39:CJ39) -> 0 | CX39: =+SUM(CL39:CW39) -> 0 | DK39: =+SUM(CY39:DJ39) -> 0 | EJ39: =+SUM(DX39:EI39) -> 0 | EW39: =+SUM(EK39:EV39) -> 0
A40: TUMAIA II - Allotment | B40: 1 | C40: 1 | BI40: =IFERROR(+BH40/C40,0) -> 0 | CK40: =+SUM(BY40:CJ40) -> 0 | CX40: =+SUM(CL40:CW40) -> 0 | DK40: =+SUM(CY40:DJ40) -> 0 | EJ40: =+SUM(DX40:EI40) -> 0 | EW40: =+SUM(EK40:EV40) -> 0
A41: TUMAIA II - A | B41: 1 | C41: 133 | P41: =+SUM(D41:O41) -> 0 | AF41: =+SUM(T41:AE41) -> 0 | AG41: =+Q41-AF41 -> 0 | AT41: =+IFERROR(AVERAGE(AH41:AS41),0) -> 0 | BG41: =+SUM(AU41:BF41) -> 0 | BI41: =IFERROR(+BH41/C41,0) -> 0 | BV41: =+SUM(BJ41:BU41) -> 0 | BW41: =+BH41-BV41 -> 0 | BX41: =IFERROR(+BV41/C41,0) -> 0 | CK41: =+SUM(BY41:CJ41) -> 0 | CX41: =+SUM(CL41:CW41) -> 0 | DK41: =+SUM(CY41:DJ41) -> 0 | EJ41: =+SUM(DX41:EI41) -> 0 | EW41: =+SUM(EK41:EV41) -> 0
A42: TUMAIA II - B | B42: 1 | C42: 132 | P42: =+SUM(D42:O42) -> 0 | AF42: =+SUM(T42:AE42) -> 0 | AG42: =+Q42-AF42 -> 0 | AT42: =+IFERROR(AVERAGE(AH42:AS42),0) -> 0 | BG42: =+SUM(AU42:BF42) -> 0 | BI42: =IFERROR(+BH42/C42,0) -> 0 | BV42: =+SUM(BJ42:BU42) -> 0 | BW42: =+BH42-BV42 -> 0 | BX42: =IFERROR(+BV42/C42,0) -> 0 | CK42: =+SUM(BY42:CJ42) -> 0 | CX42: =+SUM(CL42:CW42) -> 0 | DK42: =+SUM(CY42:DJ42) -> 0 | EJ42: =+SUM(DX42:EI42) -> 0 | EW42: =+SUM(EK42:EV42) -> 0
A43: TUMAIA II - C | B43: 1 | C43: 90 | P43: =+SUM(D43:O43) -> 0 | AF43: =+SUM(T43:AE43) -> 0 | AG43: =+Q43-AF43 -> 0 | AT43: =+IFERROR(AVERAGE(AH43:AS43),0) -> 0 | BG43: =+SUM(AU43:BF43) -> 0 | BI43: =IFERROR(+BH43/C43,0) -> 0 | BV43: =+SUM(BJ43:BU43) -> 0 | BW43: =+BH43-BV43 -> 0 | BX43: =IFERROR(+BV43/C43,0) -> 0 | CK43: =+SUM(BY43:CJ43) -> 0 | CX43: =+SUM(CL43:CW43) -> 0 | DK43: =+SUM(CY43:DJ43) -> 0 | EJ43: =+SUM(DX43:EI43) -> 0 | EW43: =+SUM(EK43:EV43) -> 0
A44: Coutinho 80 | B44: 1 | C44: 144 | P44: =+SUM(D44:O44) -> 0 | AF44: =+SUM(T44:AE44) -> 0 | AG44: =+Q44-AF44 -> 0 | AT44: =+IFERROR(AVERAGE(AH44:AS44),0) -> 0 | BG44: =+SUM(AU44:BF44) -> 0 | BI44: =IFERROR(+BH44/C44,0) -> 0 | BV44: =+SUM(BJ44:BU44) -> 0 | BW44: =+BH44-BV44 -> 0 | BX44: =IFERROR(+BV44/C44,0) -> 0 | CG44: 144 | CK44: =+SUM(BY44:CJ44) -> 144 | CX44: =+SUM(CL44:CW44) -> 0 | DK44: =+SUM(CY44:DJ44) -> 0 | EJ44: =+SUM(DX44:EI44) -> 0 | EW44: =+SUM(EK44:EV44) -> 0
A45: Benfica | B45: 1 | C45: 46 | P45: =+SUM(D45:O45) -> 0 | AF45: =+SUM(T45:AE45) -> 0 | AG45: =+Q45-AF45 -> 0 | AT45: =+IFERROR(AVERAGE(AH45:AS45),0) -> 0 | BG45: =+SUM(AU45:BF45) -> 0 | BI45: =IFERROR(+BH45/C45,0) -> 0 | BV45: =+SUM(BJ45:BU45) -> 0 | BW45: =+BH45-BV45 -> 0 | BX45: =IFERROR(+BV45/C45,0) -> 0 | CA45: 46 | CK45: =+SUM(BY45:CJ45) -> 46 | CQ45: 46 | CX45: =+SUM(CL45:CW45) -> 46 | DI45: 46 | DK45: =+SUM(CY45:DJ45) -> 46 | DV45: 0.01 | DW45: 0.04 | EJ45: =+SUM(DX45:EI45) -> 0 | EW45: =+SUM(EK45:EV45) -> 0
A46: Madalena | B46: 1 | C46: 144 | P46: =+SUM(D46:O46) -> 0 | AF46: =+SUM(T46:AE46) -> 0 | AG46: =+Q46-AF46 -> 0 | AT46: =+IFERROR(AVERAGE(AH46:AS46),0) -> 0 | BG46: =+SUM(AU46:BF46) -> 0 | BI46: =IFERROR(+BH46/C46,0) -> 0 | BV46: =+SUM(BJ46:BU46) -> 0 | BW46: =+BH46-BV46 -> 0 | BX46: =IFERROR(+BV46/C46,0) -> 0 | CE46: 150 | CK46: =+SUM(BY46:CJ46) -> 150 | CX46: =+SUM(CL46:CW46) -> 0 | DK46: =+SUM(CY46:DJ46) -> 0 | EJ46: =+SUM(DX46:EI46) -> 0 | EW46: =+SUM(EK46:EV46) -> 0
A47: Setúbal Alentejo | B47: 1 | C47: 378 | P47: =+SUM(D47:O47) -> 0 | AF47: =+SUM(T47:AE47) -> 0 | AG47: =+Q47-AF47 -> 0 | AT47: =+IFERROR(AVERAGE(AH47:AS47),0) -> 0 | BG47: =+SUM(AU47:BF47) -> 0 | BI47: =IFERROR(+BH47/C47,0) -> 0 | BV47: =+SUM(BJ47:BU47) -> 0 | BW47: =+BH47-BV47 -> 0 | BX47: =IFERROR(+BV47/C47,0) -> 0 | CK47: =+SUM(BY47:CJ47) -> 0 | CX47: =+SUM(CL47:CW47) -> 0 | DK47: =+SUM(CY47:DJ47) -> 0 | EJ47: =+SUM(DX47:EI47) -> 0 | EW47: =+SUM(EK47:EV47) -> 0
A48: Total | D48: =+SUM(D3:D47) -> 0 | E48: =+SUM(E3:E47) -> 0 | F48: =+SUM(F3:F47) -> 0 | G48: =+SUM(G3:G47) -> 0 | H48: =+SUM(H3:H47) -> 0 | I48: =+SUM(I3:I47) -> 0 | J48: =+SUM(J3:J47) -> 0 | K48: =+SUM(K3:K47) -> 0 | ... AG48: =+SUM(AG3:AG47) -> 0 | AH48: =+AVERAGE(AH3:AH47) -> #DIV/0! | AI48: =+AVERAGE(AI3:AI47) -> #DIV/0! | AJ48: =+AVERAGE(AJ3:AJ47) -> #DIV/0! | AK48: =+AVERAGE(AK3:AK47) -> #DIV/0! | AL48: =+AVERAGE(AL3:AL47) -> #DIV/0! | AM48: =+AVERAGE(AM3:AM47) -> #DIV/0! | AN48: =+AVERAGE(AN3:AN47) -> #DIV/0! | AO48: =+AVERAGE(AO3:AO47) -> #DIV/0! | ... AS48: =+AVERAGE(AS3:AS47) -> #DIV/0! | AT48: =IFERROR(AVERAGE(AH48:AS48),0) -> 0 | AU48: =+SUM(AU3:AU47) -> 0 | AV48: =+SUM(AV3:AV47) -> 0 | AW48: =+SUM(AW3:AW47) -> 0 | AX48: =+SUM(AX3:AX47) -> 0 | AY48: =+SUM(AY3:AY47) -> 0 | AZ48: =+SUM(AZ3:AZ47) -> 0 | BA48: =+SUM(BA3:BA47) -> 0 | BB48: =+SUM(BB3:BB47) -> 0 | ... BH48: =+SUM(BH3:BH47) -> 0 | BI48: =+IFERROR(AVERAGEIF(BI3:BI47,">0"),0) -> 0 | BJ48: =+SUM(BJ3:BJ47) -> 0 | BK48: =+SUM(BK3:BK47) -> 0 | BL48: =+SUM(BL3:BL47) -> 0 | BM48: =+SUM(BM3:BM47) -> 0 | BN48: =+SUM(BN3:BN47) -> 0 | BO48: =+SUM(BO3:BO47) -> 0 | BP48: =+SUM(BP3:BP47) -> 0 | BQ48: =+SUM(BQ3:BQ47) -> 0 | ... BW48: =+SUM(BW3:BW47) -> 0 | BX48: =+IFERROR(AVERAGEIF(BX3:BX47,">0"),0) -> 0 | BY48: =+SUM(BY3:BY47) -> 56 | BZ48: =+SUM(BZ3:BZ47) -> 0 | CA48: =+SUM(CA3:CA47) -> 76 | CB48: =+SUM(CB3:CB47) -> 63 | CC48: =+SUM(CC3:CC47) -> 232 | CD48: =+SUM(CD3:CD47) -> 0 | CE48: =+SUM(CE3:CE47) -> 189 | CF48: =+SUM(CF3:CF47) -> 0 | ... DK48: =+SUM(DK3:DK47) -> 371 | DX48: =+SUM(DX3:DX47) -> 0 | DY48: =+SUM(DY3:DY47) -> 64 | DZ48: =+SUM(DZ3:DZ47) -> 122 | EA48: =+SUM(EA3:EA47) -> 0 | EB48: =+SUM(EB3:EB47) -> 95 | EC48: =+SUM(EC3:EC47) -> 0 | ED48: =+SUM(ED3:ED47) -> 54 | EE48: =+SUM(EE3:EE47) -> 0 | ... EW48: =+SUM(EW3:EW47) -> 0
A49: Total (TU%) | D49: =+SUMPRODUCT(D3:D47,$B$3:$B$47) -> 0 | E49: =+SUMPRODUCT(E3:E47,$B$3:$B$47) -> 0 | F49: =+SUMPRODUCT(F3:F47,$B$3:$B$47) -> 0 | G49: =+SUMPRODUCT(G3:G47,$B$3:$B$47) -> 0 | H49: =+SUMPRODUCT(H3:H47,$B$3:$B$47) -> 0 | I49: =+SUMPRODUCT(I3:I47,$B$3:$B$47) -> 0 | J49: =+SUMPRODUCT(J3:J47,$B$3:$B$47) -> 0 | K49: =+SUMPRODUCT(K3:K47,$B$3:$B$47) -> 0 | ... P49: =+SUMPRODUCT(P3:P47,$B$3:$B$47) -> 0 | Q49: =+SUMPRODUCT(Q3:Q47,B3:B47) -> 0 | R49: =+SUMPRODUCT(R3:R47,B3:B47) -> 0 | S49: =+SUMPRODUCT(S3:S47,$B$3:$B$47) -> 0 | T49: =+SUMPRODUCT(T3:T47,$B$3:$B$47) -> 0 | U49: =+SUMPRODUCT(U3:U47,$B$3:$B$47) -> 0 | V49: =+SUMPRODUCT(V3:V47,$B$3:$B$47) -> 0 | W49: =+SUMPRODUCT(W3:W47,$B$3:$B$47) -> 0 | X49: =+SUMPRODUCT(X3:X47,$B$3:$B$47) -> 0 | Y49: =+SUMPRODUCT(Y3:Y47,$B$3:$B$47) -> 0 | Z49: =+SUMPRODUCT(Z3:Z47,$B$3:$B$47) -> 0 | ... AG49: =+SUMPRODUCT(AG3:AG47,$B$3:$B$47) -> 0 | AU49: =+SUMPRODUCT(AU3:AU47,$B$3:$B$47) -> 0 | AV49: =+SUMPRODUCT(AV3:AV47,$B$3:$B$47) -> 0 | AW49: =+SUMPRODUCT(AW3:AW47,$B$3:$B$47) -> 0 | AX49: =+SUMPRODUCT(AX3:AX47,$B$3:$B$47) -> 0 | AY49: =+SUMPRODUCT(AY3:AY47,$B$3:$B$47) -> 0 | AZ49: =+SUMPRODUCT(AZ3:AZ47,$B$3:$B$47) -> 0 | BA49: =+SUMPRODUCT(BA3:BA47,$B$3:$B$47) -> 0 | BB49: =+SUMPRODUCT(BB3:BB47,$B$3:$B$47) -> 0 | ... BH49: =+SUMPRODUCT(BH3:BH47,$B$3:$B$47) -> 0 | BJ49: =+SUMPRODUCT(BJ3:BJ47,$B$3:$B$47) -> 0 | BK49: =+SUMPRODUCT(BK3:BK47,$B$3:$B$47) -> 0 | BL49: =+SUMPRODUCT(BL3:BL47,$B$3:$B$47) -> 0 | BM49: =+SUMPRODUCT(BM3:BM47,$B$3:$B$47) -> 0 | BN49: =+SUMPRODUCT(BN3:BN47,$B$3:$B$47) -> 0 | BO49: =+SUMPRODUCT(BO3:BO47,$B$3:$B$47) -> 0 | BP49: =+SUMPRODUCT(BP3:BP47,$B$3:$B$47) -> 0 | BQ49: =+SUMPRODUCT(BQ3:BQ47,$B$3:$B$47) -> 0 | ... BW49: =+SUMPRODUCT(BW3:BW47,$B$3:$B$47) -> 0 | BY49: =+SUMPRODUCT(BY3:BY47,$B$3:$B$47) -> 56 | BZ49: =+SUMPRODUCT(BZ3:BZ47,$B$3:$B$47) -> 0 | CA49: =+SUMPRODUCT(CA3:CA47,$B$3:$B$47) -> 76 | CB49: =+SUMPRODUCT(CB3:CB47,$B$3:$B$47) -> 63 | CC49: =+SUMPRODUCT(CC3:CC47,$B$3:$B$47) -> 116 | CD49: =+SUMPRODUCT(CD3:CD47,$B$3:$B$47) -> 0 | CE49: =+SUMPRODUCT(CE3:CE47,$B$3:$B$47) -> 189 | CF49: =+SUMPRODUCT(CF3:CF47,$B$3:$B$47) -> 0 | ... DK49: =+SUMPRODUCT(DK3:DK47,$B$3:$B$47) -> 371 | DX49: =+SUMPRODUCT(DX3:DX47,$B$3:$B$47) -> 0 | DY49: =+SUMPRODUCT(DY3:DY47,$B$3:$B$47) -> 64 | DZ49: =+SUMPRODUCT(DZ3:DZ47,$B$3:$B$47) -> 122 | EA49: =+SUMPRODUCT(EA3:EA47,$B$3:$B$47) -> 0 | EB49: =+SUMPRODUCT(EB3:EB47,$B$3:$B$47) -> 95 | EC49: =+SUMPRODUCT(EC3:EC47,$B$3:$B$47) -> 0 | ED49: =+SUMPRODUCT(ED3:ED47,$B$3:$B$47) -> 54 | EE49: =+SUMPRODUCT(EE3:EE47,$B$3:$B$47) -> 0 | ... EW49: =+SUMPRODUCT(EW3:EW47,$B$3:$B$47) -> 0

Sheet Goals & Budget 2026 - Updated
A1: Project Info | D1: Sales Launch | Q1: Sales Goals (#Units) | AH1: Sales Income (€/Sq. M.) | AU1: Sales Income (€) | BH1: Marketing Budget | BY1: Schematics Approval | CL1: Tender | CY1: Start Construction | DL1: Construction % | DX1: Handover | EK1: Deeds
A2: Project Name | B2: TU (%) | C2: Nr. Units | D2: 46023 | E2: 46054 | F2: 46082 | G2: 46113 | H2: 46143 | I2: 46174 | J2: 46204 | K2: 46235 | L2: 46266 | M2: 46296 | N2: 46327 | O2: 46357 | P2: Total | Q2: Inventory (01.01.2026) | R2: # Non-Sellable Units | S2: # Sellable Units | T2: 46023 | U2: 46054 | V2: 46082 | W2: 46113 | X2: 46143 | Y2: 46174 | Z2: 46204 | AA2: 46235 | AB2: 46266 | AC2: 46296 | AD2: 46327 | AE2: 46357 | AF2: Total Sales | AG2: Inventory (12.2026) | AH2: 46023 | AI2: 46054 | AJ2: 46082 | AK2: 46113 | AL2: 46143 | AM2: 46174 | AN2: 46204 | AO2: 46235 | AP2: 46266 | AQ2: 46296 | AR2: 46327 | AS2: 46357 | AT2: Avg. | AU2: 46023 | AV2: 46054 | AW2: 46082 | AX2: 46113 | AY2: 46143 | AZ2: 46174 | BA2: 46204 | BB2: 46235 | BC2: 46266 | BD2: 46296 | BE2: 46327 | BF2: 46357 | BG2: Total | BH2: Budget (Total) | BI2: Avg (Unit) | BJ2: 46023 | BK2: 46054 | BL2: 46082 | BM2: 46113 | BN2: 46143 | BO2: 46174 | BP2: 46204 | BQ2: 46235 | BR2: 46266 | BS2: 46296 | BT2: 46327 | BU2: 46357 | BV2: Total | BW2: Budget (Left) | BX2: Avg (Unit) | BY2: 46023 | BZ2: 46054 | CA2: 46082 | CB2: 46113 | CC2: 46143 | CD2: 46174 | CE2: 46204 | CF2: 46235 | CG2: 46266 | CH2: 46296 | CI2: 46327 | CJ2: 46357 | CK2: Total | CL2: 46023 | CM2: 46054 | CN2: 46082 | CO2: 46113 | CP2: 46143 | CQ2: 46174 | CR2: 46204 | CS2: 46235 | CT2: 46266 | CU2: 46296 | CV2: 46327 | CW2: 46357 | CX2: Total | CY2: 46023 | CZ2: 46054 | DA2: 46082 | DB2: 46113 | DC2: 46143 | DD2: 46174 | DE2: 46204 | DF2: 46235 | DG2: 46266 | DH2: 46296 | DI2: 46327 | DJ2: 46357 | DK2: Total | DL2: 46023 | DM2: 46054 | DN2: 46082 | DO2: 46113 | DP2: 46143 | DQ2: 46174 | DR2: 46204 | DS2: 46235 | DT2: 46266 | DU2: 46296 | DV2: 46327 | DW2: 46357 | DX2: 46023 | DY2: 46054 | DZ2: 46082 | EA2: 46113 | EB2: 46143 | EC2: 46174 | ED2: 46204 | EE2: 46235 | EF2: 46266 | EG2: 46296 | EH2: 46327 | EI2: 46357 | EJ2: Total | EK2: 46023 | EL2: 46054 | EM2: 46082 | EN2: 46113 | EO2: 46143 | EP2: 46174 | EQ2: 46204 | ER2: 46235 | ES2: 46266 | ET2: 46296 | EU2: 46327 | EV2: 46357 | EW2: Total
A3: Pinto Bessa | B3: 1 | C3: 30 | P3: =+SUM(D3:O3) -> 0 | AF3: =+SUM(T3:AE3) -> 0 | AG3: =+S3-AF3 -> 0 | AT3: =IFERROR(AVERAGE(AH3:AS3),0) -> 0 | BG3: =+SUM(AU3:BF3) -> 0 | BI3: =+IFERROR(BH3/C3,0) -> 0 | BV3: =+SUM(BJ3:BU3) -> 0 | BW3: =+BH3-BV3 -> 0 | BX3: =+IFERROR(BV3/C3,0) -> 0 | CK3: =+SUM(BY3:CJ3) -> 0 | CX3: =+SUM(CL3:CW3) -> 0 | DK3: =+SUM(CY3:DJ3) -> 0 | EJ3: =+SUM(DX3:EI3) -> 0 | EW3: =+SUM(EK3:EV3) -> 0
A4: Saldouro - 6 | B4: 1 | C4: 25 | P4: =+SUM(D4:O4) -> 0 | AF4: =+SUM(T4:AE4) -> 0 | AG4: =+S4-AF4 -> 0 | AT4: =IFERROR(AVERAGE(AH4:AS4),0) -> 0 | BG4: =+SUM(AU4:BF4) -> 0 | BI4: =+IFERROR(BH4/C4,0) -> 0 | BV4: =+SUM(BJ4:BU4) -> 0 | BW4: =+BH4-BV4 -> 0 | BX4: =+IFERROR(BV4/C4,0) -> 0 | CK4: =+SUM(BY4:CJ4) -> 0 | CX4: =+SUM(CL4:CW4) -> 0 | DK4: =+SUM(CY4:DJ4) -> 0 | EJ4: =+SUM(DX4:EI4) -> 0 | EW4: =+SUM(EK4:EV4) -> 0
A5: Saldouro - 8 | B5: 1 | C5: 31 | P5: =+SUM(D5:O5) -> 0 | AF5: =+SUM(T5:AE5) -> 0 | AG5: =+S5-AF5 -> 0 | AT5: =IFERROR(AVERAGE(AH5:AS5),0) -> 0 | BG5: =+SUM(AU5:BF5) -> 0 | BI5: =+IFERROR(BH5/C5,0) -> 0 | BV5: =+SUM(BJ5:BU5) -> 0 | BW5: =+BH5-BV5 -> 0 | BX5: =+IFERROR(BV5/C5,0) -> 0 | CK5: =+SUM(BY5:CJ5) -> 0 | CX5: =+SUM(CL5:CW5) -> 0 | DK5: =+SUM(CY5:DJ5) -> 0 | EJ5: =+SUM(DX5:EI5) -> 0 | EW5: =+SUM(EK5:EV5) -> 0
A6: Saldouro - 9 | B6: 1 | C6: 46 | P6: =+SUM(D6:O6) -> 0 | AF6: =+SUM(T6:AE6) -> 0 | AG6: =+S6-AF6 -> 0 | AT6: =IFERROR(AVERAGE(AH6:AS6),0) -> 0 | BG6: =+SUM(AU6:BF6) -> 0 | BI6: =+IFERROR(BH6/C6,0) -> 0 | BV6: =+SUM(BJ6:BU6) -> 0 | BW6: =+BH6-BV6 -> 0 | BX6: =+IFERROR(BV6/C6,0) -> 0 | CK6: =+SUM(BY6:CJ6) -> 0 | CX6: =+SUM(CL6:CW6) -> 0 | DK6: =+SUM(CY6:DJ6) -> 0 | EJ6: =+SUM(DX6:EI6) -> 0 | EW6: =+SUM(EK6:EV6) -> 0
A7: Saldouro - 10 | B7: 1 | C7: 62 | P7: =+SUM(D7:O7) -> 0 | AF7: =+SUM(T7:AE7) -> 0 | AG7: =+S7-AF7 -> 0 | AT7: =IFERROR(AVERAGE(AH7:AS7),0) -> 0 | BG7: =+SUM(AU7:BF7) -> 0 | BI7: =+IFERROR(BH7/C7,0) -> 0 | BV7: =+SUM(BJ7:BU7) -> 0 | BW7: =+BH7-BV7 -> 0 | BX7: =+IFERROR(BV7/C7,0) -> 0 | CK7: =+SUM(BY7:CJ7) -> 0 | CX7: =+SUM(CL7:CW7) -> 0 | DK7: =+SUM(CY7:DJ7) -> 0 | EJ7: =+SUM(DX7:EI7) -> 0 | EW7: =+SUM(EK7:EV7) -> 0
A8: Saldouro - 12.2 | B8: 1 | C8: 37 | P8: =+SUM(D8:O8) -> 0 | AF8: =+SUM(T8:AE8) -> 0 | AG8: =+S8-AF8 -> 0 | AT8: =IFERROR(AVERAGE(AH8:AS8),0) -> 0 | BG8: =+SUM(AU8:BF8) -> 0 | BI8: =+IFERROR(BH8/C8,0) -> 0 | BV8: =+SUM(BJ8:BU8) -> 0 | BW8: =+BH8-BV8 -> 0 | BX8: =+IFERROR(BV8/C8,0) -> 0 | CK8: =+SUM(BY8:CJ8) -> 0 | CX8: =+SUM(CL8:CW8) -> 0 | DK8: =+SUM(CY8:DJ8) -> 0 | EJ8: =+SUM(DX8:EI8) -> 0 | EW8: =+SUM(EK8:EV8) -> 0
A9: Saldouro - 17.2 | B9: 1 | C9: 24 | P9: =+SUM(D9:O9) -> 0 | AF9: =+SUM(T9:AE9) -> 0 | AG9: =+S9-AF9 -> 0 | AT9: =IFERROR(AVERAGE(AH9:AS9),0) -> 0 | BG9: =+SUM(AU9:BF9) -> 0 | BI9: =+IFERROR(BH9/C9,0) -> 0 | BV9: =+SUM(BJ9:BU9) -> 0 | BW9: =+BH9-BV9 -> 0 | BX9: =+IFERROR(BV9/C9,0) -> 0 | CK9: =+SUM(BY9:CJ9) -> 0 | CX9: =+SUM(CL9:CW9) -> 0 | DK9: =+SUM(CY9:DJ9) -> 0 | EJ9: =+SUM(DX9:EI9) -> 0 | EW9: =+SUM(EK9:EV9) -> 0
A10: Panorama | B10: 1 | C10: 77 | P10: =+SUM(D10:O10) -> 0 | AF10: =+SUM(T10:AE10) -> 0 | AG10: =+S10-AF10 -> 0 | AT10: =IFERROR(AVERAGE(AH10:AS10),0) -> 0 | BG10: =+SUM(AU10:BF10) -> 0 | BI10: =+IFERROR(BH10/C10,0) -> 0 | BV10: =+SUM(BJ10:BU10) -> 0 | BW10: =+BH10-BV10 -> 0 | BX10: =+IFERROR(BV10/C10,0) -> 0 | CK10: =+SUM(BY10:CJ10) -> 0 | CX10: =+SUM(CL10:CW10) -> 0 | DK10: =+SUM(CY10:DJ10) -> 0 | EJ10: =+SUM(DX10:EI10) -> 0 | EW10: =+SUM(EK10:EV10) -> 0
A11: Verde Vale - H1 | B11: 1 | C11: 64 | P11: =+SUM(D11:O11) -> 0 | AF11: =+SUM(T11:AE11) -> 0 | AG11: =+S11-AF11 -> 0 | AT11: =IFERROR(AVERAGE(AH11:AS11),0) -> 0 | BG11: =+SUM(AU11:BF11) -> 0 | BI11: =+IFERROR(BH11/C11,0) -> 0 | BV11: =+SUM(BJ11:BU11) -> 0 | BW11: =+BH11-BV11 -> 0 | BX11: =+IFERROR(BV11/C11,0) -> 0 | CK11: =+SUM(BY11:CJ11) -> 0 | CX11: =+SUM(CL11:CW11) -> 0 | DK11: =+SUM(CY11:DJ11) -> 0 | EJ11: =+SUM(DX11:EI11) -> 0 | EW11: =+SUM(EK11:EV11) -> 0
A12: Verde Vale - H2 | B12: 1 | C12: 54 | P12: =+SUM(D12:O12) -> 0 | AF12: =+SUM(T12:AE12) -> 0 | AG12: =+S12-AF12 -> 0 | AT12: =IFERROR(AVERAGE(AH12:AS12),0) -> 0 | BG12: =+SUM(AU12:BF12) -> 0 | BI12: =+IFERROR(BH12/C12,0) -> 0 | BV12: =+SUM(BJ12:BU12) -> 0 | BW12: =+BH12-BV12 -> 0 | BX12: =+IFERROR(BV12/C12,0) -> 0 | CK12: =+SUM(BY12:CJ12) -> 0 | CX12: =+SUM(CL12:CW12) -> 0 | DK12: =+SUM(CY12:DJ12) -> 0 | EJ12: =+SUM(DX12:EI12) -> 0 | EW12: =+SUM(EK12:EV12) -> 0
A13: Verde Vale - H3 | B13: 1 | C13: 56 | P13: =+SUM(D13:O13) -> 0 | AF13: =+SUM(T13:AE13) -> 0 | AG13: =+S13-AF13 -> 0 | AT13: =IFERROR(AVERAGE(AH13:AS13),0) -> 0 | BG13: =+SUM(AU13:BF13) -> 0 | BI13: =+IFERROR(BH13/C13,0) -> 0 | BV13: =+SUM(BJ13:BU13) -> 0 | BW13: =+BH13-BV13 -> 0 | BX13: =+IFERROR(BV13/C13,0) -> 0 | CK13: =+SUM(BY13:CJ13) -> 0 | CX13: =+SUM(CL13:CW13) -> 0 | DK13: =+SUM(CY13:DJ13) -> 0 | EJ13: =+SUM(DX13:EI13) -> 0 | EW13: =+SUM(EK13:EV13) -> 0
A14: Verde Vale - H4 | B14: 1 | C14: 80 | P14: =+SUM(D14:O14) -> 0 | AF14: =+SUM(T14:AE14) -> 0 | AG14: =+S14-AF14 -> 0 | AT14: =IFERROR(AVERAGE(AH14:AS14),0) -> 0 | BG14: =+SUM(AU14:BF14) -> 0 | BI14: =+IFERROR(BH14/C14,0) -> 0 | BV14: =+SUM(BJ14:BU14) -> 0 | BW14: =+BH14-BV14 -> 0 | BX14: =+IFERROR(BV14/C14,0) -> 0 | CK14: =+SUM(BY14:CJ14) -> 0 | CX14: =+SUM(CL14:CW14) -> 0 | DK14: =+SUM(CY14:DJ14) -> 0 | EJ14: =+SUM(DX14:EI14) -> 0 | EW14: =+SUM(EK14:EV14) -> 0
... A29: Antas South - Resi | B29: 1 | C29: 57 | P29: =+SUM(D29:O29) -> 0 | AF29: =+SUM(T29:AE29) -> 0 | AG29: =+S29-AF29 -> 0 | AT29: =IFERROR(AVERAGE(AH29:AS29),0) -> 0 | BG29: =+SUM(AU29:BF29) -> 0 | BI29: =+IFERROR(BH29/C29,0) -> 0 | BV29: =+SUM(BJ29:BU29) -> 0 | BW29: =+BH29-BV29 -> 0 | BX29: =+IFERROR(BV29/C29,0) -> 0 | CK29: =+SUM(BY29:CJ29) -> 0 | CX29: =+SUM(CL29:CW29) -> 0 | DK29: =+SUM(CY29:DJ29) -> 0 | EJ29: =+SUM(DX29:EI29) -> 0 | EW29: =+SUM(EK29:EV29) -> 0
A30: Antas North | B30: 1 | C30: ? | P30: =+SUM(D30:O30) -> 0 | AF30: =+SUM(T30:AE30) -> 0 | AG30: =+S30-AF30 -> 0 | AT30: =IFERROR(AVERAGE(AH30:AS30),0) -> 0 | BG30: =+SUM(AU30:BF30) -> 0 | BI30: =+IFERROR(BH30/C30,0) -> 0 | BV30: =+SUM(BJ30:BU30) -> 0 | BW30: =+BH30-BV30 -> 0 | BX30: =+IFERROR(BV30/C30,0) -> 0 | CK30: =+SUM(BY30:CJ30) -> 0 | CX30: =+SUM(CL30:CW30) -> 0 | DK30: =+SUM(CY30:DJ30) -> 0 | EJ30: =+SUM(DX30:EI30) -> 0 | EW30: =+SUM(EK30:EV30) -> 0
A31: Vila do Conde - Allotment | B31: 1 | C31: 1
A32: Vila do Conde - Phase 1 | B32: 1 | C32: 165 | P32: =+SUM(D32:O32) -> 0 | AF32: =+SUM(T32:AE32) -> 0 | AG32: =+S32-AF32 -> 0 | AT32: =IFERROR(AVERAGE(AH32:AS32),0) -> 0 | BG32: =+SUM(AU32:BF32) -> 0 | BI32: =+IFERROR(BH32/C32,0) -> 0 | BV32: =+SUM(BJ32:BU32) -> 0 | BW32: =+BH32-BV32 -> 0 | BX32: =+IFERROR(BV32/C32,0) -> 0 | CK32: =+SUM(BY32:CJ32) -> 0 | CX32: =+SUM(CL32:CW32) -> 0 | DK32: =+SUM(CY32:DJ32) -> 0 | EJ32: =+SUM(DX32:EI32) -> 0 | EW32: =+SUM(EK32:EV32) -> 0
A33: Vila do Conde - Phase 2 | B33: 1 | C33: 39 | P33: =+SUM(D33:O33) -> 0 | AF33: =+SUM(T33:AE33) -> 0 | AG33: =+S33-AF33 -> 0 | AT33: =IFERROR(AVERAGE(AH33:AS33),0) -> 0 | BG33: =+SUM(AU33:BF33) -> 0 | BI33: =+IFERROR(BH33/C33,0) -> 0 | BV33: =+SUM(BJ33:BU33) -> 0 | BW33: =+BH33-BV33 -> 0 | BX33: =+IFERROR(BV33/C33,0) -> 0 | CK33: =+SUM(BY33:CJ33) -> 0 | CX33: =+SUM(CL33:CW33) -> 0 | DK33: =+SUM(CY33:DJ33) -> 0 | EJ33: =+SUM(DX33:EI33) -> 0 | EW33: =+SUM(EK33:EV33) -> 0
A34: Vila do Conde - Phase 3 | B34: 1 | C34: 76 | P34: =+SUM(D34:O34) -> 0 | AF34: =+SUM(T34:AE34) -> 0 | AG34: =+S34-AF34 -> 0 | AT34: =IFERROR(AVERAGE(AH34:AS34),0) -> 0 | BG34: =+SUM(AU34:BF34) -> 0 | BI34: =+IFERROR(BH34/C34,0) -> 0 | BV34: =+SUM(BJ34:BU34) -> 0 | BW34: =+BH34-BV34 -> 0 | BX34: =+IFERROR(BV34/C34,0) -> 0 | CK34: =+SUM(BY34:CJ34) -> 0 | CX34: =+SUM(CL34:CW34) -> 0 | DK34: =+SUM(CY34:DJ34) -> 0 | EJ34: =+SUM(DX34:EI34) -> 0 | EW34: =+SUM(EK34:EV34) -> 0
A35: Parkview | B35: 1 | C35: 39 | P35: =+SUM(D35:O35) -> 0 | AF35: =+SUM(T35:AE35) -> 0 | AG35: =+S35-AF35 -> 0 | AT35: =IFERROR(AVERAGE(AH35:AS35),0) -> 0 | BG35: =+SUM(AU35:BF35) -> 0 | BI35: =+IFERROR(BH35/C35,0) -> 0 | BV35: =+SUM(BJ35:BU35) -> 0 | BW35: =+BH35-BV35 -> 0 | BX35: =+IFERROR(BV35/C35,0) -> 0 | CK35: =+SUM(BY35:CJ35) -> 0 | CX35: =+SUM(CL35:CW35) -> 0 | DK35: =+SUM(CY35:DJ35) -> 0 | EJ35: =+SUM(DX35:EI35) -> 0 | EW35: =+SUM(EK35:EV35) -> 0
A36: Eleven | B36: 1 | C36: 95 | P36: =+SUM(D36:O36) -> 0 | AF36: =+SUM(T36:AE36) -> 0 | AG36: =+S36-AF36 -> 0 | AT36: =IFERROR(AVERAGE(AH36:AS36),0) -> 0 | BG36: =+SUM(AU36:BF36) -> 0 | BI36: =+IFERROR(BH36/C36,0) -> 0 | BV36: =+SUM(BJ36:BU36) -> 0 | BW36: =+BH36-BV36 -> 0 | BX36: =+IFERROR(BV36/C36,0) -> 0 | CK36: =+SUM(BY36:CJ36) -> 0 | CX36: =+SUM(CL36:CW36) -> 0 | DK36: =+SUM(CY36:DJ36) -> 0 | EJ36: =+SUM(DX36:EI36) -> 0 | EW36: =+SUM(EK36:EV36) -> 0
A37: Clip Allotment | B37: 1 | C37: 1 | BI37: =+IFERROR(BH37/C37,0) -> 0
A38: Clip Stage A | B38: 1 | C38: 83 | P38: =+SUM(D38:O38) -> 0 | AF38: =+SUM(T38:AE38) -> 0 | AG38: =+S38-AF38 -> 0 | AT38: =IFERROR(AVERAGE(AH38:AS38),0) -> 0 | BG38: =+SUM(AU38:BF38) -> 0 | BI38: =+IFERROR(BH38/C38,0) -> 0 | BV38: =+SUM(BJ38:BU38) -> 0 | BW38: =+BH38-BV38 -> 0 | BX38: =+IFERROR(BV38/C38,0) -> 0 | CK38: =+SUM(BY38:CJ38) -> 0 | CX38: =+SUM(CL38:CW38) -> 0 | DK38: =+SUM(CY38:DJ38) -> 0 | EJ38: =+SUM(DX38:EI38) -> 0 | EW38: =+SUM(EK38:EV38) -> 0
A39: Clip Stage B | B39: 1 | C39: 180 | P39: =+SUM(D39:O39) -> 0 | AF39: =+SUM(T39:AE39) -> 0 | AG39: =+S39-AF39 -> 0 | AT39: =IFERROR(AVERAGE(AH39:AS39),0) -> 0 | BG39: =+SUM(AU39:BF39) -> 0 | BI39: =+IFERROR(BH39/C39,0) -> 0 | BV39: =+SUM(BJ39:BU39) -> 0 | BW39: =+BH39-BV39 -> 0 | BX39: =+IFERROR(BV39/C39,0) -> 0 | CK39: =+SUM(BY39:CJ39) -> 0 | CX39: =+SUM(CL39:CW39) -> 0 | DK39: =+SUM(CY39:DJ39) -> 0 | EJ39: =+SUM(DX39:EI39) -> 0 | EW39: =+SUM(EK39:EV39) -> 0
A40: TUMAIA II - Allotment | B40: 1 | C40: 1 | BI40: =+IFERROR(BH40/C40,0) -> 0
A41: TUMAIA II - A | B41: 1 | C41: 133 | P41: =+SUM(D41:O41) -> 0 | AF41: =+SUM(T41:AE41) -> 0 | AG41: =+S41-AF41 -> 0 | AT41: =IFERROR(AVERAGE(AH41:AS41),0) -> 0 | BG41: =+SUM(AU41:BF41) -> 0 | BI41: =+IFERROR(BH41/C41,0) -> 0 | BV41: =+SUM(BJ41:BU41) -> 0 | BW41: =+BH41-BV41 -> 0 | BX41: =+IFERROR(BV41/C41,0) -> 0 | CK41: =+SUM(BY41:CJ41) -> 0 | CX41: =+SUM(CL41:CW41) -> 0 | DK41: =+SUM(CY41:DJ41) -> 0 | EJ41: =+SUM(DX41:EI41) -> 0 | EW41: =+SUM(EK41:EV41) -> 0
A42: TUMAIA II - B | B42: 1 | C42: 132 | P42: =+SUM(D42:O42) -> 0 | AF42: =+SUM(T42:AE42) -> 0 | AG42: =+S42-AF42 -> 0 | AT42: =IFERROR(AVERAGE(AH42:AS42),0) -> 0 | BG42: =+SUM(AU42:BF42) -> 0 | BI42: =+IFERROR(BH42/C42,0) -> 0 | BV42: =+SUM(BJ42:BU42) -> 0 | BW42: =+BH42-BV42 -> 0 | BX42: =+IFERROR(BV42/C42,0) -> 0 | CK42: =+SUM(BY42:CJ42) -> 0 | CX42: =+SUM(CL42:CW42) -> 0 | DK42: =+SUM(CY42:DJ42) -> 0 | EJ42: =+SUM(DX42:EI42) -> 0 | EW42: =+SUM(EK42:EV42) -> 0
A43: TUMAIA II - C | B43: 1 | C43: 90 | P43: =+SUM(D43:O43) -> 0 | AF43: =+SUM(T43:AE43) -> 0 | AG43: =+S43-AF43 -> 0 | AT43: =IFERROR(AVERAGE(AH43:AS43),0) -> 0 | BG43: =+SUM(AU43:BF43) -> 0 | BI43: =+IFERROR(BH43/C43,0) -> 0 | BV43: =+SUM(BJ43:BU43) -> 0 | BW43: =+BH43-BV43 -> 0 | BX43: =+IFERROR(BV43/C43,0) -> 0 | CK43: =+SUM(BY43:CJ43) -> 0 | CX43: =+SUM(CL43:CW43) -> 0 | DK43: =+SUM(CY43:DJ43) -> 0 | EJ43: =+SUM(DX43:EI43) -> 0 | EW43: =+SUM(EK43:EV43) -> 0
A44: Coutinho 80 | B44: 1 | C44: 144 | P44: =+SUM(D44:O44) -> 0 | AF44: =+SUM(T44:AE44) -> 0 | AG44: =+S44-AF44 -> 0 | AT44: =IFERROR(AVERAGE(AH44:AS44),0) -> 0 | BG44: =+SUM(AU44:BF44) -> 0 | BI44: =+IFERROR(BH44/C44,0) -> 0 | BV44: =+SUM(BJ44:BU44) -> 0 | BW44: =+BH44-BV44 -> 0 | BX44: =+IFERROR(BV44/C44,0) -> 0 | CK44: =+SUM(BY44:CJ44) -> 0 | CX44: =+SUM(CL44:CW44) -> 0 | DK44: =+SUM(CY44:DJ44) -> 0 | EJ44: =+SUM(DX44:EI44) -> 0 | EW44: =+SUM(EK44:EV44) -> 0
A45: Benfica | B45: 1 | C45: 46 | P45: =+SUM(D45:O45) -> 0 | AF45: =+SUM(T45:AE45) -> 0 | AG45: =+S45-AF45 -> 0 | AT45: =IFERROR(AVERAGE(AH45:AS45),0) -> 0 | BG45: =+SUM(AU45:BF45) -> 0 | BI45: =+IFERROR(BH45/C45,0) -> 0 | BV45: =+SUM(BJ45:BU45) -> 0 | BW45: =+BH45-BV45 -> 0 | BX45: =+IFERROR(BV45/C45,0) -> 0 | CK45: =+SUM(BY45:CJ45) -> 0 | CX45: =+SUM(CL45:CW45) -> 0 | DK45: =+SUM(CY45:DJ45) -> 0 | EJ45: =+SUM(DX45:EI45) -> 0 | EW45: =+SUM(EK45:EV45) -> 0
A46: Madalena | B46: 1 | C46: 144 | P46: =+SUM(D46:O46) -> 0 | AF46: =+SUM(T46:AE46) -> 0 | AG46: =+S46-AF46 -> 0 | AT46: =IFERROR(AVERAGE(AH46:AS46),0) -> 0 | BG46: =+SUM(AU46:BF46) -> 0 | BI46: =+IFERROR(BH46/C46,0) -> 0 | BV46: =+SUM(BJ46:BU46) -> 0 | BW46: =+BH46-BV46 -> 0 | BX46: =+IFERROR(BV46/C46,0) -> 0 | CK46: =+SUM(BY46:CJ46) -> 0 | CX46: =+SUM(CL46:CW46) -> 0 | DK46: =+SUM(CY46:DJ46) -> 0 | EJ46: =+SUM(DX46:EI46) -> 0 | EW46: =+SUM(EK46:EV46) -> 0
A47: Setúbal Alentejo | B47: 1 | C47: 378 | P47: =+SUM(D47:O47) -> 0 | AF47: =+SUM(T47:AE47) -> 0 | AG47: =+S47-AF47 -> 0 | AT47: =IFERROR(AVERAGE(AH47:AS47),0) -> 0 | BG47: =+SUM(AU47:BF47) -> 0 | BI47: =+IFERROR(BH47/C47,0) -> 0 | BV47: =+SUM(BJ47:BU47) -> 0 | BW47: =+BH47-BV47 -> 0 | BX47: =+IFERROR(BV47/C47,0) -> 0 | CK47: =+SUM(BY47:CJ47) -> 0 | CX47: =+SUM(CL47:CW47) -> 0 | DK47: =+SUM(CY47:DJ47) -> 0 | EJ47: =+SUM(DX47:EI47) -> 0 | EW47: =+SUM(EK47:EV47) -> 0
A48: Total | D48: =+SUM(D3:D47) -> 0 | E48: =+SUM(E3:E47) -> 0 | F48: =+SUM(F3:F47) -> 0 | G48: =+SUM(G3:G47) -> 0 | H48: =+SUM(H3:H47) -> 0 | I48: =+SUM(I3:I47) -> 0 | J48: =+SUM(J3:J47) -> 0 | K48: =+SUM(K3:K47) -> 0 | ... AG48: =+SUM(AG3:AG47) -> 0 | AH48: =+AVERAGEA(AH3:AH47) -> #DIV/0! | AI48: =+AVERAGEA(AI3:AI47) -> #DIV/0! | AJ48: =+AVERAGEA(AJ3:AJ47) -> #DIV/0! | AK48: =+AVERAGEA(AK3:AK47) -> #DIV/0! | AL48: =+AVERAGEA(AL3:AL47) -> #DIV/0! | AM48: =+AVERAGEA(AM3:AM47) -> #DIV/0! | AN48: =+AVERAGEA(AN3:AN47) -> #DIV/0! | AO48: =+AVERAGEA(AO3:AO47) -> #DIV/0! | ... AS48: =+AVERAGEA(AS3:AS47) -> #DIV/0! | AT48: =IFERROR(AVERAGE(AH48:AS48),0) -> 0 | AU48: =+SUM(AU3:AU47) -> 0 | AV48: =+SUM(AV3:AV47) -> 0 | AW48: =+SUM(AW3:AW47) -> 0 | AX48: =+SUM(AX3:AX47) -> 0 | AY48: =+SUM(AY3:AY47) -> 0 | AZ48: =+SUM(AZ3:AZ47) -> 0 | BA48: =+SUM(BA3:BA47) -> 0 | BB48: =+SUM(BB3:BB47) -> 0 | ... BH48: =+SUM(BH3:BH47) -> 0 | BI48: =+IFERROR(AVERAGE(BI3:BI47),0) -> 0 | BJ48: =+SUM(BJ3:BJ47) -> 0 | BK48: =+SUM(BK3:BK47) -> 0 | BL48: =+SUM(BL3:BL47) -> 0 | BM48: =+SUM(BM3:BM47) -> 0 | BN48: =+SUM(BN3:BN47) -> 0 | BO48: =+SUM(BO3:BO47) -> 0 | BP48: =+SUM(BP3:BP47) -> 0 | BQ48: =+SUM(BQ3:BQ47) -> 0 | ... BW48: =+SUM(BW3:BW47) -> 0 | BX48: =+AVERAGE(BX3:BX47) -> 0 | BY48: =+SUM(BY3:BY47) -> 0 | BZ48: =+SUM(BZ3:BZ47) -> 0 | CA48: =+SUM(CA3:CA47) -> 0 | CB48: =+SUM(CB3:CB47) -> 0 | CC48: =+SUM(CC3:CC47) -> 0 | CD48: =+SUM(CD3:CD47) -> 0 | CE48: =+SUM(CE3:CE47) -> 0 | CF48: =+SUM(CF3:CF47) -> 0 | ... DK48: =+SUM(DK3:DK47) -> 0 | DX48: =+SUM(DX3:DX47) -> 0 | DY48: =+SUM(DY3:DY47) -> 0 | DZ48: =+SUM(DZ3:DZ47) -> 0 | EA48: =+SUM(EA3:EA47) -> 0 | EB48: =+SUM(EB3:EB47) -> 0 | EC48: =+SUM(EC3:EC47) -> 0 | ED48: =+SUM(ED3:ED47) -> 0 | EE48: =+SUM(EE3:EE47) -> 0 | ... EW48: =+SUM(EW3:EW47) -> 0
A49: Total (TU%) | D49: =+SUMPRODUCT(D3:D47,$B$3:$B$47) -> 0 | E49: =+SUMPRODUCT(E3:E47,$B$3:$B$47) -> 0 | F49: =+SUMPRODUCT(F3:F47,$B$3:$B$47) -> 0 | G49: =+SUMPRODUCT(G3:G47,$B$3:$B$47) -> 0 | H49: =+SUMPRODUCT(H3:H47,$B$3:$B$47) -> 0 | I49: =+SUMPRODUCT(I3:I47,$B$3:$B$47) -> 0 | J49: =+SUMPRODUCT(J3:J47,$B$3:$B$47) -> 0 | K49: =+SUMPRODUCT(K3:K47,$B$3:$B$47) -> 0 | ... P49: =+SUMPRODUCT(P3:P47,$B$3:$B$47) -> 0 | Q49: =+SUMPRODUCT(Q3:Q47,B3:B47) -> 0 | R49: =+SUMPRODUCT(R3:R47,B3:B47) -> 0 | S49: =+SUMPRODUCT(S3:S47,$B$3:$B$47) -> 0 | T49: =+SUMPRODUCT(T3:T47,$B$3:$B$47) -> 0 | U49: =+SUMPRODUCT(U3:U47,$B$3:$B$47) -> 0 | V49: =+SUMPRODUCT(V3:V47,$B$3:$B$47) -> 0 | W49: =+SUMPRODUCT(W3:W47,$B$3:$B$47) -> 0 | X49: =+SUMPRODUCT(X3:X47,$B$3:$B$47) -> 0 | Y49: =+SUMPRODUCT(Y3:Y47,$B$3:$B$47) -> 0 | Z49: =+SUMPRODUCT(Z3:Z47,$B$3:$B$47) -> 0 | ... AG49: =+SUMPRODUCT(AG3:AG47,$B$3:$B$47) -> 0 | AU49: =+SUMPRODUCT(AU3:AU47,$B$3:$B$47) -> 0 | AV49: =+SUMPRODUCT(AV3:AV47,$B$3:$B$47) -> 0 | AW49: =+SUMPRODUCT(AW3:AW47,$B$3:$B$47) -> 0 | AX49: =+SUMPRODUCT(AX3:AX47,$B$3:$B$47) -> 0 | AY49: =+SUMPRODUCT(AY3:AY47,$B$3:$B$47) -> 0 | AZ49: =+SUMPRODUCT(AZ3:AZ47,$B$3:$B$47) -> 0 | BA49: =+SUMPRODUCT(BA3:BA47,$B$3:$B$47) -> 0 | BB49: =+SUMPRODUCT(BB3:BB47,$B$3:$B$47) -> 0 | ... BH49: =+SUMPRODUCT(BH3:BH47,$B$3:$B$47) -> 0 | BJ49: =+SUMPRODUCT(BJ3:BJ47,$B$3:$B$47) -> 0 | BK49: =+SUMPRODUCT(BK3:BK47,$B$3:$B$47) -> 0 | BL49: =+SUMPRODUCT(BL3:BL47,$B$3:$B$47) -> 0 | BM49: =+SUMPRODUCT(BM3:BM47,$B$3:$B$47) -> 0 | BN49: =+SUMPRODUCT(BN3:BN47,$B$3:$B$47) -> 0 | BO49: =+SUMPRODUCT(BO3:BO47,$B$3:$B$47) -> 0 | BP49: =+SUMPRODUCT(BP3:BP47,$B$3:$B$47) -> 0 | BQ49: =+SUMPRODUCT(BQ3:BQ47,$B$3:$B$47) -> 0 | ... BW49: =+SUMPRODUCT(BW3:BW47,$B$3:$B$47) -> 0 | BY49: =+SUMPRODUCT(BY3:BY47,$B$3:$B$47) -> 0 | BZ49: =+SUMPRODUCT(BZ3:BZ47,$B$3:$B$47) -> 0 | CA49: =+SUMPRODUCT(CA3:CA47,$B$3:$B$47) -> 0 | CB49: =+SUMPRODUCT(CB3:CB47,$B$3:$B$47) -> 0 | CC49: =+SUMPRODUCT(CC3:CC47,$B$3:$B$47) -> 0 | CD49: =+SUMPRODUCT(CD3:CD47,$B$3:$B$47) -> 0 | CE49: =+SUMPRODUCT(CE3:CE47,$B$3:$B$47) -> 0 | CF49: =+SUMPRODUCT(CF3:CF47,$B$3:$B$47) -> 0 | ... DK49: =+SUMPRODUCT(DK3:DK47,$B$3:$B$47) -> 0 | DX49: =+SUMPRODUCT(DX3:DX47,$B$3:$B$47) -> 0 | DY49: =+SUMPRODUCT(DY3:DY47,$B$3:$B$47) -> 0 | DZ49: =+SUMPRODUCT(DZ3:DZ47,$B$3:$B$47) -> 0 | EA49: =+SUMPRODUCT(EA3:EA47,$B$3:$B$47) -> 0 | EB49: =+SUMPRODUCT(EB3:EB47,$B$3:$B$47) -> 0 | EC49: =+SUMPRODUCT(EC3:EC47,$B$3:$B$47) -> 0 | ED49: =+SUMPRODUCT(ED3:ED47,$B$3:$B$47) -> 0 | EE49: =+SUMPRODUCT(EE3:EE47,$B$3:$B$47) -> 0 | ... EW49: =+SUMPRODUCT(EW3:EW47,$B$3:$B$47) -> 0

Sheet KPIs - Sales Launch
A1: KPIs | D1: =+'Dashboard - Overview & Project'!H2 -> Accumulated - 1-01/2026 | G1: 46023 | J1: 46054 | M1: 46082 | P1: 46113 | S1: 46143 | V1: 46174 | Y1: 46204 | AB1: 46235 | AE1: 46266 | AH1: 46296 | AK1: 46327 | AN1: 46357
A2: Project Name | B2: TU (%) | C2: Nr. Units | D2: Actual | E2: Budget | F2: Gap | G2: Actual | H2: Budget | I2: Gap | J2: Actual | K2: Budget | L2: Gap | M2: Actual | N2: Budget | O2: Gap | P2: Actual | Q2: Budget | R2: Gap | S2: Actual | T2: Budget | U2: Gap | V2: Actual | W2: Budget | X2: Gap | Y2: Actual | Z2: Budget | AA2: Gap | AB2: Actual | AC2: Budget | AD2: Gap | AE2: Actual | AF2: Budget | AG2: Gap | AH2: Actual | AI2: Budget | AJ2: Gap | AK2: Actual | AL2: Budget | AM2: Gap | AN2: Actual | AO2: Budget | AP2: Gap
A3: Pinto Bessa | B3: 1 | C3: 30 | D3: =+G3 -> 0 | E3: =+H3 -> 0 | F3: =IF(AND(D3>0,E3>0),D3/E3,IF(AND(D3>0,E3=0),100%,IF(AND(D3=0,E3>0),0,IF(AND(D3=0,E3=0),"***",0)))) -> *** | H3: =+IFERROR(VLOOKUP($A3,'Goals & Budget 2026'!$A$2:$EJ$49,4,FALSE),0) -> 0 | I3: =IF(AND(G3>0,H3>0),G3/H3,IF(AND(G3>0,H3=0),100%,IF(AND(G3=0,H3>0),0,IF(AND(G3=0,H3=0),"***",0)))) -> *** | K3: =+IFERROR(VLOOKUP($A3,'Goals & Budget 2026'!$A$2:$EJ$49,5,FALSE),0) -> 0 | L3: =IF(AND(J3>0,K3>0),J3/K3,IF(AND(J3>0,K3=0),100%,IF(AND(J3=0,K3>0),0,IF(AND(J3=0,K3=0),"***",0)))) -> *** | N3: =+IFERROR(VLOOKUP($A3,'Goals & Budget 2026'!$A$2:$EJ$49,6,FALSE),0) -> 0 | O3: =IF(AND(M3>0,N3>0),M3/N3,IF(AND(M3>0,N3=0),100%,IF(AND(M3=0,N3>0),0,IF(AND(M3=0,N3=0),"***",0)))) -> *** | Q3: =+IFERROR(VLOOKUP($A3,'Goals & Budget 2026'!$A$2:$EJ$49,7,FALSE),0) -> 0 | R3: =IF(AND(P3>0,Q3>0),P3/Q3,IF(AND(P3>0,Q3=0),100%,IF(AND(P3=0,Q3>0),0,IF(AND(P3=0,Q3=0),"***",0)))) -> *** | T3: =+IFERROR(VLOOKUP($A3,'Goals & Budget 2026'!$A$2:$EJ$49,8,FALSE),0) -> 0 | U3: =IF(AND(S3>0,T3>0),S3/T3,IF(AND(S3>0,T3=0),100%,IF(AND(S3=0,T3>0),0,IF(AND(S3=0,T3=0),"***",0)))) -> *** | W3: =+IFERROR(VLOOKUP($A3,'Goals & Budget 2026'!$A$2:$EJ$49,9,FALSE),0) -> 0 | X3: =IF(AND(V3>0,W3>0),V3/W3,IF(AND(V3>0,W3=0),100%,IF(AND(V3=0,W3>0),0,IF(AND(V3=0,W3=0),"***",0)))) -> *** | Z3: =+IFERROR(VLOOKUP($A3,'Goals & Budget 2026'!$A$2:$EJ$49,10,FALSE),0) -> 0 | AA3: =IF(AND(Y3>0,Z3>0),Y3/Z3,IF(AND(Y3>0,Z3=0),100%,IF(AND(Y3=0,Z3>0),0,IF(AND(Y3=0,Z3=0),"***",0)))) -> *** | AC3: =+IFERROR(VLOOKUP($A3,'Goals & Budget 2026'!$A$2:$EJ$49,11,FALSE),0) -> 0 | AD3: =IF(AND(AB3>0,AC3>0),AB3/AC3,IF(AND(AB3>0,AC3=0),100%,IF(AND(AB3=0,AC3>0),0,IF(AND(AB3=0,AC3=0),"***",0)))) -> *** | AF3: =+IFERROR(VLOOKUP($A3,'Goals & Budget 2026'!$A$2:$EJ$49,12,FALSE),0) -> 0 | AG3: =IF(AND(AE3>0,AF3>0),AE3/AF3,IF(AND(AE3>0,AF3=0),100%,IF(AND(AE3=0,AF3>0),0,IF(AND(AE3=0,AF3=0),"***",0)))) -> *** | AI3: =+IFERROR(VLOOKUP($A3,'Goals & Budget 2026'!$A$2:$EJ$49,13,FALSE),0) -> 0 | AJ3: =IF(AND(AH3>0,AI3>0),AH3/AI3,IF(AND(AH3>0,AI3=0),100%,IF(AND(AH3=0,AI3>0),0,IF(AND(AH3=0,AI3=0),"***",0)))) -> *** | AL3: =+IFERROR(VLOOKUP($A3,'Goals & Budget 2026'!$A$2:$EJ$49,14,FALSE),0) -> 0 | AM3: =IF(AND(AK3>0,AL3>0),AK3/AL3,IF(AND(AK3>0,AL3=0),100%,IF(AND(AK3=0,AL3>0),0,IF(AND(AK3=0,AL3=0),"***",0)))) -> *** | AO3: =+IFERROR(VLOOKUP($A3,'Goals & Budget 2026'!$A$2:$EJ$49,15,FALSE),0) -> 0 | AP3: =IF(AND(AN3>0,AO3>0),AN3/AO3,IF(AND(AN3>0,AO3=0),100%,IF(AND(AN3=0,AO3>0),0,IF(AND(AN3=0,AO3=0),"***",0)))) -> ***
A4: Saldouro - 6 | B4: 1 | C4: 25 | D4: =+G4 -> 0 | E4: =+H4 -> 0 | F4: =IF(AND(D4>0,E4>0),D4/E4,IF(AND(D4>0,E4=0),100%,IF(AND(D4=0,E4>0),0,IF(AND(D4=0,E4=0),"***",0)))) -> *** | H4: =+IFERROR(VLOOKUP($A4,'Goals & Budget 2026'!$A$2:$EJ$49,4,FALSE),0) -> 0 | I4: =IF(AND(G4>0,H4>0),G4/H4,IF(AND(G4>0,H4=0),100%,IF(AND(G4=0,H4>0),0,IF(AND(G4=0,H4=0),"***",0)))) -> *** | K4: =+IFERROR(VLOOKUP($A4,'Goals & Budget 2026'!$A$2:$EJ$49,5,FALSE),0) -> 0 | L4: =IF(AND(J4>0,K4>0),J4/K4,IF(AND(J4>0,K4=0),100%,IF(AND(J4=0,K4>0),0,IF(AND(J4=0,K4=0),"***",0)))) -> *** | N4: =+IFERROR(VLOOKUP($A4,'Goals & Budget 2026'!$A$2:$EJ$49,6,FALSE),0) -> 0 | O4: =IF(AND(M4>0,N4>0),M4/N4,IF(AND(M4>0,N4=0),100%,IF(AND(M4=0,N4>0),0,IF(AND(M4=0,N4=0),"***",0)))) -> *** | Q4: =+IFERROR(VLOOKUP($A4,'Goals & Budget 2026'!$A$2:$EJ$49,7,FALSE),0) -> 0 | R4: =IF(AND(P4>0,Q4>0),P4/Q4,IF(AND(P4>0,Q4=0),100%,IF(AND(P4=0,Q4>0),0,IF(AND(P4=0,Q4=0),"***",0)))) -> *** | T4: =+IFERROR(VLOOKUP($A4,'Goals & Budget 2026'!$A$2:$EJ$49,8,FALSE),0) -> 0 | U4: =IF(AND(S4>0,T4>0),S4/T4,IF(AND(S4>0,T4=0),100%,IF(AND(S4=0,T4>0),0,IF(AND(S4=0,T4=0),"***",0)))) -> *** | W4: =+IFERROR(VLOOKUP($A4,'Goals & Budget 2026'!$A$2:$EJ$49,9,FALSE),0) -> 0 | X4: =IF(AND(V4>0,W4>0),V4/W4,IF(AND(V4>0,W4=0),100%,IF(AND(V4=0,W4>0),0,IF(AND(V4=0,W4=0),"***",0)))) -> *** | Z4: =+IFERROR(VLOOKUP($A4,'Goals & Budget 2026'!$A$2:$EJ$49,10,FALSE),0) -> 0 | AA4: =IF(AND(Y4>0,Z4>0),Y4/Z4,IF(AND(Y4>0,Z4=0),100%,IF(AND(Y4=0,Z4>0),0,IF(AND(Y4=0,Z4=0),"***",0)))) -> *** | AC4: =+IFERROR(VLOOKUP($A4,'Goals & Budget 2026'!$A$2:$EJ$49,11,FALSE),0) -> 0 | AD4: =IF(AND(AB4>0,AC4>0),AB4/AC4,IF(AND(AB4>0,AC4=0),100%,IF(AND(AB4=0,AC4>0),0,IF(AND(AB4=0,AC4=0),"***",0)))) -> *** | AF4: =+IFERROR(VLOOKUP($A4,'Goals & Budget 2026'!$A$2:$EJ$49,12,FALSE),0) -> 0 | AG4: =IF(AND(AE4>0,AF4>0),AE4/AF4,IF(AND(AE4>0,AF4=0),100%,IF(AND(AE4=0,AF4>0),0,IF(AND(AE4=0,AF4=0),"***",0)))) -> *** | AI4: =+IFERROR(VLOOKUP($A4,'Goals & Budget 2026'!$A$2:$EJ$49,13,FALSE),0) -> 0 | AJ4: =IF(AND(AH4>0,AI4>0),AH4/AI4,IF(AND(AH4>0,AI4=0),100%,IF(AND(AH4=0,AI4>0),0,IF(AND(AH4=0,AI4=0),"***",0)))) -> *** | AL4: =+IFERROR(VLOOKUP($A4,'Goals & Budget 2026'!$A$2:$EJ$49,14,FALSE),0) -> 0 | AM4: =IF(AND(AK4>0,AL4>0),AK4/AL4,IF(AND(AK4>0,AL4=0),100%,IF(AND(AK4=0,AL4>0),0,IF(AND(AK4=0,AL4=0),"***",0)))) -> *** | AO4: =+IFERROR(VLOOKUP($A4,'Goals & Budget 2026'!$A$2:$EJ$49,15,FALSE),0) -> 0 | AP4: =IF(AND(AN4>0,AO4>0),AN4/AO4,IF(AND(AN4>0,AO4=0),100%,IF(AND(AN4=0,AO4>0),0,IF(AND(AN4=0,AO4=0),"***",0)))) -> ***
A5: Saldouro - 8 | B5: 1 | C5: 31 | D5: =+G5 -> 0 | E5: =+H5 -> 0 | F5: =IF(AND(D5>0,E5>0),D5/E5,IF(AND(D5>0,E5=0),100%,IF(AND(D5=0,E5>0),0,IF(AND(D5=0,E5=0),"***",0)))) -> *** | H5: =+IFERROR(VLOOKUP($A5,'Goals & Budget 2026'!$A$2:$EJ$49,4,FALSE),0) -> 0 | I5: =IF(AND(G5>0,H5>0),G5/H5,IF(AND(G5>0,H5=0),100%,IF(AND(G5=0,H5>0),0,IF(AND(G5=0,H5=0),"***",0)))) -> *** | K5: =+IFERROR(VLOOKUP($A5,'Goals & Budget 2026'!$A$2:$EJ$49,5,FALSE),0) -> 0 | L5: =IF(AND(J5>0,K5>0),J5/K5,IF(AND(J5>0,K5=0),100%,IF(AND(J5=0,K5>0),0,IF(AND(J5=0,K5=0),"***",0)))) -> *** | N5: =+IFERROR(VLOOKUP($A5,'Goals & Budget 2026'!$A$2:$EJ$49,6,FALSE),0) -> 0 | O5: =IF(AND(M5>0,N5>0),M5/N5,IF(AND(M5>0,N5=0),100%,IF(AND(M5=0,N5>0),0,IF(AND(M5=0,N5=0),"***",0)))) -> *** | Q5: =+IFERROR(VLOOKUP($A5,'Goals & Budget 2026'!$A$2:$EJ$49,7,FALSE),0) -> 0 | R5: =IF(AND(P5>0,Q5>0),P5/Q5,IF(AND(P5>0,Q5=0),100%,IF(AND(P5=0,Q5>0),0,IF(AND(P5=0,Q5=0),"***",0)))) -> *** | T5: =+IFERROR(VLOOKUP($A5,'Goals & Budget 2026'!$A$2:$EJ$49,8,FALSE),0) -> 0 | U5: =IF(AND(S5>0,T5>0),S5/T5,IF(AND(S5>0,T5=0),100%,IF(AND(S5=0,T5>0),0,IF(AND(S5=0,T5=0),"***",0)))) -> *** | W5: =+IFERROR(VLOOKUP($A5,'Goals & Budget 2026'!$A$2:$EJ$49,9,FALSE),0) -> 0 | X5: =IF(AND(V5>0,W5>0),V5/W5,IF(AND(V5>0,W5=0),100%,IF(AND(V5=0,W5>0),0,IF(AND(V5=0,W5=0),"***",0)))) -> *** | Z5: =+IFERROR(VLOOKUP($A5,'Goals & Budget 2026'!$A$2:$EJ$49,10,FALSE),0) -> 0 | AA5: =IF(AND(Y5>0,Z5>0),Y5/Z5,IF(AND(Y5>0,Z5=0),100%,IF(AND(Y5=0,Z5>0),0,IF(AND(Y5=0,Z5=0),"***",0)))) -> *** | AC5: =+IFERROR(VLOOKUP($A5,'Goals & Budget 2026'!$A$2:$EJ$49,11,FALSE),0) -> 0 | AD5: =IF(AND(AB5>0,AC5>0),AB5/AC5,IF(AND(AB5>0,AC5=0),100%,IF(AND(AB5=0,AC5>0),0,IF(AND(AB5=0,AC5=0),"***",0)))) -> *** | AF5: =+IFERROR(VLOOKUP($A5,'Goals & Budget 2026'!$A$2:$EJ$49,12,FALSE),0) -> 0 | AG5: =IF(AND(AE5>0,AF5>0),AE5/AF5,IF(AND(AE5>0,AF5=0),100%,IF(AND(AE5=0,AF5>0),0,IF(AND(AE5=0,AF5=0),"***",0)))) -> *** | AI5: =+IFERROR(VLOOKUP($A5,'Goals & Budget 2026'!$A$2:$EJ$49,13,FALSE),0) -> 0 | AJ5: =IF(AND(AH5>0,AI5>0),AH5/AI5,IF(AND(AH5>0,AI5=0),100%,IF(AND(AH5=0,AI5>0),0,IF(AND(AH5=0,AI5=0),"***",0)))) -> *** | AL5: =+IFERROR(VLOOKUP($A5,'Goals & Budget 2026'!$A$2:$EJ$49,14,FALSE),0) -> 0 | AM5: =IF(AND(AK5>0,AL5>0),AK5/AL5,IF(AND(AK5>0,AL5=0),100%,IF(AND(AK5=0,AL5>0),0,IF(AND(AK5=0,AL5=0),"***",0)))) -> *** | AO5: =+IFERROR(VLOOKUP($A5,'Goals & Budget 2026'!$A$2:$EJ$49,15,FALSE),0) -> 0 | AP5: =IF(AND(AN5>0,AO5>0),AN5/AO5,IF(AND(AN5>0,AO5=0),100%,IF(AND(AN5=0,AO5>0),0,IF(AND(AN5=0,AO5=0),"***",0)))) -> ***
A6: Saldouro - 9 | B6: 1 | C6: 46 | D6: =+G6 -> 0 | E6: =+H6 -> 0 | F6: =IF(AND(D6>0,E6>0),D6/E6,IF(AND(D6>0,E6=0),100%,IF(AND(D6=0,E6>0),0,IF(AND(D6=0,E6=0),"***",0)))) -> *** | H6: =+IFERROR(VLOOKUP($A6,'Goals & Budget 2026'!$A$2:$EJ$49,4,FALSE),0) -> 0 | I6: =IF(AND(G6>0,H6>0),G6/H6,IF(AND(G6>0,H6=0),100%,IF(AND(G6=0,H6>0),0,IF(AND(G6=0,H6=0),"***",0)))) -> *** | K6: =+IFERROR(VLOOKUP($A6,'Goals & Budget 2026'!$A$2:$EJ$49,5,FALSE),0) -> 0 | L6: =IF(AND(J6>0,K6>0),J6/K6,IF(AND(J6>0,K6=0),100%,IF(AND(J6=0,K6>0),0,IF(AND(J6=0,K6=0),"***",0)))) -> *** | N6: =+IFERROR(VLOOKUP($A6,'Goals & Budget 2026'!$A$2:$EJ$49,6,FALSE),0) -> 0 | O6: =IF(AND(M6>0,N6>0),M6/N6,IF(AND(M6>0,N6=0),100%,IF(AND(M6=0,N6>0),0,IF(AND(M6=0,N6=0),"***",0)))) -> *** | Q6: =+IFERROR(VLOOKUP($A6,'Goals & Budget 2026'!$A$2:$EJ$49,7,FALSE),0) -> 0 | R6: =IF(AND(P6>0,Q6>0),P6/Q6,IF(AND(P6>0,Q6=0),100%,IF(AND(P6=0,Q6>0),0,IF(AND(P6=0,Q6=0),"***",0)))) -> *** | T6: =+IFERROR(VLOOKUP($A6,'Goals & Budget 2026'!$A$2:$EJ$49,8,FALSE),0) -> 0 | U6: =IF(AND(S6>0,T6>0),S6/T6,IF(AND(S6>0,T6=0),100%,IF(AND(S6=0,T6>0),0,IF(AND(S6=0,T6=0),"***",0)))) -> *** | W6: =+IFERROR(VLOOKUP($A6,'Goals & Budget 2026'!$A$2:$EJ$49,9,FALSE),0) -> 0 | X6: =IF(AND(V6>0,W6>0),V6/W6,IF(AND(V6>0,W6=0),100%,IF(AND(V6=0,W6>0),0,IF(AND(V6=0,W6=0),"***",0)))) -> *** | Z6: =+IFERROR(VLOOKUP($A6,'Goals & Budget 2026'!$A$2:$EJ$49,10,FALSE),0) -> 0 | AA6: =IF(AND(Y6>0,Z6>0),Y6/Z6,IF(AND(Y6>0,Z6=0),100%,IF(AND(Y6=0,Z6>0),0,IF(AND(Y6=0,Z6=0),"***",0)))) -> *** | AC6: =+IFERROR(VLOOKUP($A6,'Goals & Budget 2026'!$A$2:$EJ$49,11,FALSE),0) -> 0 | AD6: =IF(AND(AB6>0,AC6>0),AB6/AC6,IF(AND(AB6>0,AC6=0),100%,IF(AND(AB6=0,AC6>0),0,IF(AND(AB6=0,AC6=0),"***",0)))) -> *** | AF6: =+IFERROR(VLOOKUP($A6,'Goals & Budget 2026'!$A$2:$EJ$49,12,FALSE),0) -> 0 | AG6: =IF(AND(AE6>0,AF6>0),AE6/AF6,IF(AND(AE6>0,AF6=0),100%,IF(AND(AE6=0,AF6>0),0,IF(AND(AE6=0,AF6=0),"***",0)))) -> *** | AI6: =+IFERROR(VLOOKUP($A6,'Goals & Budget 2026'!$A$2:$EJ$49,13,FALSE),0) -> 0 | AJ6: =IF(AND(AH6>0,AI6>0),AH6/AI6,IF(AND(AH6>0,AI6=0),100%,IF(AND(AH6=0,AI6>0),0,IF(AND(AH6=0,AI6=0),"***",0)))) -> *** | AL6: =+IFERROR(VLOOKUP($A6,'Goals & Budget 2026'!$A$2:$EJ$49,14,FALSE),0) -> 0 | AM6: =IF(AND(AK6>0,AL6>0),AK6/AL6,IF(AND(AK6>0,AL6=0),100%,IF(AND(AK6=0,AL6>0),0,IF(AND(AK6=0,AL6=0),"***",0)))) -> *** | AO6: =+IFERROR(VLOOKUP($A6,'Goals & Budget 2026'!$A$2:$EJ$49,15,FALSE),0) -> 0 | AP6: =IF(AND(AN6>0,AO6>0),AN6/AO6,IF(AND(AN6>0,AO6=0),100%,IF(AND(AN6=0,AO6>0),0,IF(AND(AN6=0,AO6=0),"***",0)))) -> ***
A7: Saldouro - 10 | B7: 1 | C7: 62 | D7: =+G7 -> 0 | E7: =+H7 -> 0 | F7: =IF(AND(D7>0,E7>0),D7/E7,IF(AND(D7>0,E7=0),100%,IF(AND(D7=0,E7>0),0,IF(AND(D7=0,E7=0),"***",0)))) -> *** | H7: =+IFERROR(VLOOKUP($A7,'Goals & Budget 2026'!$A$2:$EJ$49,4,FALSE),0) -> 0 | I7: =IF(AND(G7>0,H7>0),G7/H7,IF(AND(G7>0,H7=0),100%,IF(AND(G7=0,H7>0),0,IF(AND(G7=0,H7=0),"***",0)))) -> *** | K7: =+IFERROR(VLOOKUP($A7,'Goals & Budget 2026'!$A$2:$EJ$49,5,FALSE),0) -> 0 | L7: =IF(AND(J7>0,K7>0),J7/K7,IF(AND(J7>0,K7=0),100%,IF(AND(J7=0,K7>0),0,IF(AND(J7=0,K7=0),"***",0)))) -> *** | N7: =+IFERROR(VLOOKUP($A7,'Goals & Budget 2026'!$A$2:$EJ$49,6,FALSE),0) -> 0 | O7: =IF(AND(M7>0,N7>0),M7/N7,IF(AND(M7>0,N7=0),100%,IF(AND(M7=0,N7>0),0,IF(AND(M7=0,N7=0),"***",0)))) -> *** | Q7: =+IFERROR(VLOOKUP($A7,'Goals & Budget 2026'!$A$2:$EJ$49,7,FALSE),0) -> 0 | R7: =IF(AND(P7>0,Q7>0),P7/Q7,IF(AND(P7>0,Q7=0),100%,IF(AND(P7=0,Q7>0),0,IF(AND(P7=0,Q7=0),"***",0)))) -> *** | T7: =+IFERROR(VLOOKUP($A7,'Goals & Budget 2026'!$A$2:$EJ$49,8,FALSE),0) -> 0 | U7: =IF(AND(S7>0,T7>0),S7/T7,IF(AND(S7>0,T7=0),100%,IF(AND(S7=0,T7>0),0,IF(AND(S7=0,T7=0),"***",0)))) -> *** | W7: =+IFERROR(VLOOKUP($A7,'Goals & Budget 2026'!$A$2:$EJ$49,9,FALSE),0) -> 0 | X7: =IF(AND(V7>0,W7>0),V7/W7,IF(AND(V7>0,W7=0),100%,IF(AND(V7=0,W7>0),0,IF(AND(V7=0,W7=0),"***",0)))) -> *** | Z7: =+IFERROR(VLOOKUP($A7,'Goals & Budget 2026'!$A$2:$EJ$49,10,FALSE),0) -> 0 | AA7: =IF(AND(Y7>0,Z7>0),Y7/Z7,IF(AND(Y7>0,Z7=0),100%,IF(AND(Y7=0,Z7>0),0,IF(AND(Y7=0,Z7=0),"***",0)))) -> *** | AC7: =+IFERROR(VLOOKUP($A7,'Goals & Budget 2026'!$A$2:$EJ$49,11,FALSE),0) -> 0 | AD7: =IF(AND(AB7>0,AC7>0),AB7/AC7,IF(AND(AB7>0,AC7=0),100%,IF(AND(AB7=0,AC7>0),0,IF(AND(AB7=0,AC7=0),"***",0)))) -> *** | AF7: =+IFERROR(VLOOKUP($A7,'Goals & Budget 2026'!$A$2:$EJ$49,12,FALSE),0) -> 0 | AG7: =IF(AND(AE7>0,AF7>0),AE7/AF7,IF(AND(AE7>0,AF7=0),100%,IF(AND(AE7=0,AF7>0),0,IF(AND(AE7=0,AF7=0),"***",0)))) -> *** | AI7: =+IFERROR(VLOOKUP($A7,'Goals & Budget 2026'!$A$2:$EJ$49,13,FALSE),0) -> 0 | AJ7: =IF(AND(AH7>0,AI7>0),AH7/AI7,IF(AND(AH7>0,AI7=0),100%,IF(AND(AH7=0,AI7>0),0,IF(AND(AH7=0,AI7=0),"***",0)))) -> *** | AL7: =+IFERROR(VLOOKUP($A7,'Goals & Budget 2026'!$A$2:$EJ$49,14,FALSE),0) -> 0 | AM7: =IF(AND(AK7>0,AL7>0),AK7/AL7,IF(AND(AK7>0,AL7=0),100%,IF(AND(AK7=0,AL7>0),0,IF(AND(AK7=0,AL7=0),"***",0)))) -> *** | AO7: =+IFERROR(VLOOKUP($A7,'Goals & Budget 2026'!$A$2:$EJ$49,15,FALSE),0) -> 0 | AP7: =IF(AND(AN7>0,AO7>0),AN7/AO7,IF(AND(AN7>0,AO7=0),100%,IF(AND(AN7=0,AO7>0),0,IF(AND(AN7=0,AO7=0),"***",0)))) -> ***
A8: Saldouro - 12.2 | B8: 1 | C8: 37 | D8: =+G8 -> 0 | E8: =+H8 -> 0 | F8: =IF(AND(D8>0,E8>0),D8/E8,IF(AND(D8>0,E8=0),100%,IF(AND(D8=0,E8>0),0,IF(AND(D8=0,E8=0),"***",0)))) -> *** | H8: =+IFERROR(VLOOKUP($A8,'Goals & Budget 2026'!$A$2:$EJ$49,4,FALSE),0) -> 0 | I8: =IF(AND(G8>0,H8>0),G8/H8,IF(AND(G8>0,H8=0),100%,IF(AND(G8=0,H8>0),0,IF(AND(G8=0,H8=0),"***",0)))) -> *** | K8: =+IFERROR(VLOOKUP($A8,'Goals & Budget 2026'!$A$2:$EJ$49,5,FALSE),0) -> 0 | L8: =IF(AND(J8>0,K8>0),J8/K8,IF(AND(J8>0,K8=0),100%,IF(AND(J8=0,K8>0),0,IF(AND(J8=0,K8=0),"***",0)))) -> *** | N8: =+IFERROR(VLOOKUP($A8,'Goals & Budget 2026'!$A$2:$EJ$49,6,FALSE),0) -> 0 | O8: =IF(AND(M8>0,N8>0),M8/N8,IF(AND(M8>0,N8=0),100%,IF(AND(M8=0,N8>0),0,IF(AND(M8=0,N8=0),"***",0)))) -> *** | Q8: =+IFERROR(VLOOKUP($A8,'Goals & Budget 2026'!$A$2:$EJ$49,7,FALSE),0) -> 0 | R8: =IF(AND(P8>0,Q8>0),P8/Q8,IF(AND(P8>0,Q8=0),100%,IF(AND(P8=0,Q8>0),0,IF(AND(P8=0,Q8=0),"***",0)))) -> *** | T8: =+IFERROR(VLOOKUP($A8,'Goals & Budget 2026'!$A$2:$EJ$49,8,FALSE),0) -> 0 | U8: =IF(AND(S8>0,T8>0),S8/T8,IF(AND(S8>0,T8=0),100%,IF(AND(S8=0,T8>0),0,IF(AND(S8=0,T8=0),"***",0)))) -> *** | W8: =+IFERROR(VLOOKUP($A8,'Goals & Budget 2026'!$A$2:$EJ$49,9,FALSE),0) -> 0 | X8: =IF(AND(V8>0,W8>0),V8/W8,IF(AND(V8>0,W8=0),100%,IF(AND(V8=0,W8>0),0,IF(AND(V8=0,W8=0),"***",0)))) -> *** | Z8: =+IFERROR(VLOOKUP($A8,'Goals & Budget 2026'!$A$2:$EJ$49,10,FALSE),0) -> 0 | AA8: =IF(AND(Y8>0,Z8>0),Y8/Z8,IF(AND(Y8>0,Z8=0),100%,IF(AND(Y8=0,Z8>0),0,IF(AND(Y8=0,Z8=0),"***",0)))) -> *** | AC8: =+IFERROR(VLOOKUP($A8,'Goals & Budget 2026'!$A$2:$EJ$49,11,FALSE),0) -> 0 | AD8: =IF(AND(AB8>0,AC8>0),AB8/AC8,IF(AND(AB8>0,AC8=0),100%,IF(AND(AB8=0,AC8>0),0,IF(AND(AB8=0,AC8=0),"***",0)))) -> *** | AF8: =+IFERROR(VLOOKUP($A8,'Goals & Budget 2026'!$A$2:$EJ$49,12,FALSE),0) -> 0 | AG8: =IF(AND(AE8>0,AF8>0),AE8/AF8,IF(AND(AE8>0,AF8=0),100%,IF(AND(AE8=0,AF8>0),0,IF(AND(AE8=0,AF8=0),"***",0)))) -> *** | AI8: =+IFERROR(VLOOKUP($A8,'Goals & Budget 2026'!$A$2:$EJ$49,13,FALSE),0) -> 0 | AJ8: =IF(AND(AH8>0,AI8>0),AH8/AI8,IF(AND(AH8>0,AI8=0),100%,IF(AND(AH8=0,AI8>0),0,IF(AND(AH8=0,AI8=0),"***",0)))) -> *** | AL8: =+IFERROR(VLOOKUP($A8,'Goals & Budget 2026'!$A$2:$EJ$49,14,FALSE),0) -> 0 | AM8: =IF(AND(AK8>0,AL8>0),AK8/AL8,IF(AND(AK8>0,AL8=0),100%,IF(AND(AK8=0,AL8>0),0,IF(AND(AK8=0,AL8=0),"***",0)))) -> *** | AO8: =+IFERROR(VLOOKUP($A8,'Goals & Budget 2026'!$A$2:$EJ$49,15,FALSE),0) -> 0 | AP8: =IF(AND(AN8>0,AO8>0),AN8/AO8,IF(AND(AN8>0,AO8=0),100%,IF(AND(AN8=0,AO8>0),0,IF(AND(AN8=0,AO8=0),"***",0)))) -> ***
A9: Saldouro - 17.2 | B9: 1 | C9: 24 | D9: =+G9 -> 0 | E9: =+H9 -> 0 | F9: =IF(AND(D9>0,E9>0),D9/E9,IF(AND(D9>0,E9=0),100%,IF(AND(D9=0,E9>0),0,IF(AND(D9=0,E9=0),"***",0)))) -> *** | H9: =+IFERROR(VLOOKUP($A9,'Goals & Budget 2026'!$A$2:$EJ$49,4,FALSE),0) -> 0 | I9: =IF(AND(G9>0,H9>0),G9/H9,IF(AND(G9>0,H9=0),100%,IF(AND(G9=0,H9>0),0,IF(AND(G9=0,H9=0),"***",0)))) -> *** | K9: =+IFERROR(VLOOKUP($A9,'Goals & Budget 2026'!$A$2:$EJ$49,5,FALSE),0) -> 0 | L9: =IF(AND(J9>0,K9>0),J9/K9,IF(AND(J9>0,K9=0),100%,IF(AND(J9=0,K9>0),0,IF(AND(J9=0,K9=0),"***",0)))) -> *** | N9: =+IFERROR(VLOOKUP($A9,'Goals & Budget 2026'!$A$2:$EJ$49,6,FALSE),0) -> 0 | O9: =IF(AND(M9>0,N9>0),M9/N9,IF(AND(M9>0,N9=0),100%,IF(AND(M9=0,N9>0),0,IF(AND(M9=0,N9=0),"***",0)))) -> *** | Q9: =+IFERROR(VLOOKUP($A9,'Goals & Budget 2026'!$A$2:$EJ$49,7,FALSE),0) -> 0 | R9: =IF(AND(P9>0,Q9>0),P9/Q9,IF(AND(P9>0,Q9=0),100%,IF(AND(P9=0,Q9>0),0,IF(AND(P9=0,Q9=0),"***",0)))) -> *** | T9: =+IFERROR(VLOOKUP($A9,'Goals & Budget 2026'!$A$2:$EJ$49,8,FALSE),0) -> 0 | U9: =IF(AND(S9>0,T9>0),S9/T9,IF(AND(S9>0,T9=0),100%,IF(AND(S9=0,T9>0),0,IF(AND(S9=0,T9=0),"***",0)))) -> *** | W9: =+IFERROR(VLOOKUP($A9,'Goals & Budget 2026'!$A$2:$EJ$49,9,FALSE),0) -> 0 | X9: =IF(AND(V9>0,W9>0),V9/W9,IF(AND(V9>0,W9=0),100%,IF(AND(V9=0,W9>0),0,IF(AND(V9=0,W9=0),"***",0)))) -> *** | Z9: =+IFERROR(VLOOKUP($A9,'Goals & Budget 2026'!$A$2:$EJ$49,10,FALSE),0) -> 0 | AA9: =IF(AND(Y9>0,Z9>0),Y9/Z9,IF(AND(Y9>0,Z9=0),100%,IF(AND(Y9=0,Z9>0),0,IF(AND(Y9=0,Z9=0),"***",0)))) -> *** | AC9: =+IFERROR(VLOOKUP($A9,'Goals & Budget 2026'!$A$2:$EJ$49,11,FALSE),0) -> 0 | AD9: =IF(AND(AB9>0,AC9>0),AB9/AC9,IF(AND(AB9>0,AC9=0),100%,IF(AND(AB9=0,AC9>0),0,IF(AND(AB9=0,AC9=0),"***",0)))) -> *** | AF9: =+IFERROR(VLOOKUP($A9,'Goals & Budget 2026'!$A$2:$EJ$49,12,FALSE),0) -> 0 | AG9: =IF(AND(AE9>0,AF9>0),AE9/AF9,IF(AND(AE9>0,AF9=0),100%,IF(AND(AE9=0,AF9>0),0,IF(AND(AE9=0,AF9=0),"***",0)))) -> *** | AI9: =+IFERROR(VLOOKUP($A9,'Goals & Budget 2026'!$A$2:$EJ$49,13,FALSE),0) -> 0 | AJ9: =IF(AND(AH9>0,AI9>0),AH9/AI9,IF(AND(AH9>0,AI9=0),100%,IF(AND(AH9=0,AI9>0),0,IF(AND(AH9=0,AI9=0),"***",0)))) -> *** | AL9: =+IFERROR(VLOOKUP($A9,'Goals & Budget 2026'!$A$2:$EJ$49,14,FALSE),0) -> 0 | AM9: =IF(AND(AK9>0,AL9>0),AK9/AL9,IF(AND(AK9>0,AL9=0),100%,IF(AND(AK9=0,AL9>0),0,IF(AND(AK9=0,AL9=0),"***",0)))) -> *** | AO9: =+IFERROR(VLOOKUP($A9,'Goals & Budget 2026'!$A$2:$EJ$49,15,FALSE),0) -> 0 | AP9: =IF(AND(AN9>0,AO9>0),AN9/AO9,IF(AND(AN9>0,AO9=0),100%,IF(AND(AN9=0,AO9>0),0,IF(AND(AN9=0,AO9=0),"***",0)))) -> ***
A10: Panorama | B10: 1 | C10: 77 | D10: =+G10 -> 0 | E10: =+H10 -> 0 | F10: =IF(AND(D10>0,E10>0),D10/E10,IF(AND(D10>0,E10=0),100%,IF(AND(D10=0,E10>0),0,IF(AND(D10=0,E10=0),"***",0)))) -> *** | H10: =+IFERROR(VLOOKUP($A10,'Goals & Budget 2026'!$A$2:$EJ$49,4,FALSE),0) -> 0 | I10: =IF(AND(G10>0,H10>0),G10/H10,IF(AND(G10>0,H10=0),100%,IF(AND(G10=0,H10>0),0,IF(AND(G10=0,H10=0),"***",0)))) -> *** | K10: =+IFERROR(VLOOKUP($A10,'Goals & Budget 2026'!$A$2:$EJ$49,5,FALSE),0) -> 0 | L10: =IF(AND(J10>0,K10>0),J10/K10,IF(AND(J10>0,K10=0),100%,IF(AND(J10=0,K10>0),0,IF(AND(J10=0,K10=0),"***",0)))) -> *** | N10: =+IFERROR(VLOOKUP($A10,'Goals & Budget 2026'!$A$2:$EJ$49,6,FALSE),0) -> 0 | O10: =IF(AND(M10>0,N10>0),M10/N10,IF(AND(M10>0,N10=0),100%,IF(AND(M10=0,N10>0),0,IF(AND(M10=0,N10=0),"***",0)))) -> *** | Q10: =+IFERROR(VLOOKUP($A10,'Goals & Budget 2026'!$A$2:$EJ$49,7,FALSE),0) -> 0 | R10: =IF(AND(P10>0,Q10>0),P10/Q10,IF(AND(P10>0,Q10=0),100%,IF(AND(P10=0,Q10>0),0,IF(AND(P10=0,Q10=0),"***",0)))) -> *** | T10: =+IFERROR(VLOOKUP($A10,'Goals & Budget 2026'!$A$2:$EJ$49,8,FALSE),0) -> 0 | U10: =IF(AND(S10>0,T10>0),S10/T10,IF(AND(S10>0,T10=0),100%,IF(AND(S10=0,T10>0),0,IF(AND(S10=0,T10=0),"***",0)))) -> *** | W10: =+IFERROR(VLOOKUP($A10,'Goals & Budget 2026'!$A$2:$EJ$49,9,FALSE),0) -> 0 | X10: =IF(AND(V10>0,W10>0),V10/W10,IF(AND(V10>0,W10=0),100%,IF(AND(V10=0,W10>0),0,IF(AND(V10=0,W10=0),"***",0)))) -> *** | Z10: =+IFERROR(VLOOKUP($A10,'Goals & Budget 2026'!$A$2:$EJ$49,10,FALSE),0) -> 0 | AA10: =IF(AND(Y10>0,Z10>0),Y10/Z10,IF(AND(Y10>0,Z10=0),100%,IF(AND(Y10=0,Z10>0),0,IF(AND(Y10=0,Z10=0),"***",0)))) -> *** | AC10: =+IFERROR(VLOOKUP($A10,'Goals & Budget 2026'!$A$2:$EJ$49,11,FALSE),0) -> 0 | AD10: =IF(AND(AB10>0,AC10>0),AB10/AC10,IF(AND(AB10>0,AC10=0),100%,IF(AND(AB10=0,AC10>0),0,IF(AND(AB10=0,AC10=0),"***",0)))) -> *** | AF10: =+IFERROR(VLOOKUP($A10,'Goals & Budget 2026'!$A$2:$EJ$49,12,FALSE),0) -> 0 | AG10: =IF(AND(AE10>0,AF10>0),AE10/AF10,IF(AND(AE10>0,AF10=0),100%,IF(AND(AE10=0,AF10>0),0,IF(AND(AE10=0,AF10=0),"***",0)))) -> *** | AI10: =+IFERROR(VLOOKUP($A10,'Goals & Budget 2026'!$A$2:$EJ$49,13,FALSE),0) -> 0 | AJ10: =IF(AND(AH10>0,AI10>0),AH10/AI10,IF(AND(AH10>0,AI10=0),100%,IF(AND(AH10=0,AI10>0),0,IF(AND(AH10=0,AI10=0),"***",0)))) -> *** | AL10: =+IFERROR(VLOOKUP($A10,'Goals & Budget 2026'!$A$2:$EJ$49,14,FALSE),0) -> 0 | AM10: =IF(AND(AK10>0,AL10>0),AK10/AL10,IF(AND(AK10>0,AL10=0),100%,IF(AND(AK10=0,AL10>0),0,IF(AND(AK10=0,AL10=0),"***",0)))) -> *** | AO10: =+IFERROR(VLOOKUP($A10,'Goals & Budget 2026'!$A$2:$EJ$49,15,FALSE),0) -> 0 | AP10: =IF(AND(AN10>0,AO10>0),AN10/AO10,IF(AND(AN10>0,AO10=0),100%,IF(AND(AN10=0,AO10>0),0,IF(AND(AN10=0,AO10=0),"***",0)))) -> ***
A11: Verde Vale - H1 | B11: 1 | C11: 64 | D11: =+G11 -> 0 | E11: =+H11 -> 0 | F11: =IF(AND(D11>0,E11>0),D11/E11,IF(AND(D11>0,E11=0),100%,IF(AND(D11=0,E11>0),0,IF(AND(D11=0,E11=0),"***",0)))) -> *** | H11: =+IFERROR(VLOOKUP($A11,'Goals & Budget 2026'!$A$2:$EJ$49,4,FALSE),0) -> 0 | I11: =IF(AND(G11>0,H11>0),G11/H11,IF(AND(G11>0,H11=0),100%,IF(AND(G11=0,H11>0),0,IF(AND(G11=0,H11=0),"***",0)))) -> *** | K11: =+IFERROR(VLOOKUP($A11,'Goals & Budget 2026'!$A$2:$EJ$49,5,FALSE),0) -> 0 | L11: =IF(AND(J11>0,K11>0),J11/K11,IF(AND(J11>0,K11=0),100%,IF(AND(J11=0,K11>0),0,IF(AND(J11=0,K11=0),"***",0)))) -> *** | N11: =+IFERROR(VLOOKUP($A11,'Goals & Budget 2026'!$A$2:$EJ$49,6,FALSE),0) -> 0 | O11: =IF(AND(M11>0,N11>0),M11/N11,IF(AND(M11>0,N11=0),100%,IF(AND(M11=0,N11>0),0,IF(AND(M11=0,N11=0),"***",0)))) -> *** | Q11: =+IFERROR(VLOOKUP($A11,'Goals & Budget 2026'!$A$2:$EJ$49,7,FALSE),0) -> 0 | R11: =IF(AND(P11>0,Q11>0),P11/Q11,IF(AND(P11>0,Q11=0),100%,IF(AND(P11=0,Q11>0),0,IF(AND(P11=0,Q11=0),"***",0)))) -> *** | T11: =+IFERROR(VLOOKUP($A11,'Goals & Budget 2026'!$A$2:$EJ$49,8,FALSE),0) -> 0 | U11: =IF(AND(S11>0,T11>0),S11/T11,IF(AND(S11>0,T11=0),100%,IF(AND(S11=0,T11>0),0,IF(AND(S11=0,T11=0),"***",0)))) -> *** | W11: =+IFERROR(VLOOKUP($A11,'Goals & Budget 2026'!$A$2:$EJ$49,9,FALSE),0) -> 0 | X11: =IF(AND(V11>0,W11>0),V11/W11,IF(AND(V11>0,W11=0),100%,IF(AND(V11=0,W11>0),0,IF(AND(V11=0,W11=0),"***",0)))) -> *** | Z11: =+IFERROR(VLOOKUP($A11,'Goals & Budget 2026'!$A$2:$EJ$49,10,FALSE),0) -> 0 | AA11: =IF(AND(Y11>0,Z11>0),Y11/Z11,IF(AND(Y11>0,Z11=0),100%,IF(AND(Y11=0,Z11>0),0,IF(AND(Y11=0,Z11=0),"***",0)))) -> *** | AC11: =+IFERROR(VLOOKUP($A11,'Goals & Budget 2026'!$A$2:$EJ$49,11,FALSE),0) -> 0 | AD11: =IF(AND(AB11>0,AC11>0),AB11/AC11,IF(AND(AB11>0,AC11=0),100%,IF(AND(AB11=0,AC11>0),0,IF(AND(AB11=0,AC11=0),"***",0)))) -> *** | AF11: =+IFERROR(VLOOKUP($A11,'Goals & Budget 2026'!$A$2:$EJ$49,12,FALSE),0) -> 0 | AG11: =IF(AND(AE11>0,AF11>0),AE11/AF11,IF(AND(AE11>0,AF11=0),100%,IF(AND(AE11=0,AF11>0),0,IF(AND(AE11=0,AF11=0),"***",0)))) -> *** | AI11: =+IFERROR(VLOOKUP($A11,'Goals & Budget 2026'!$A$2:$EJ$49,13,FALSE),0) -> 0 | AJ11: =IF(AND(AH11>0,AI11>0),AH11/AI11,IF(AND(AH11>0,AI11=0),100%,IF(AND(AH11=0,AI11>0),0,IF(AND(AH11=0,AI11=0),"***",0)))) -> *** | AL11: =+IFERROR(VLOOKUP($A11,'Goals & Budget 2026'!$A$2:$EJ$49,14,FALSE),0) -> 0 | AM11: =IF(AND(AK11>0,AL11>0),AK11/AL11,IF(AND(AK11>0,AL11=0),100%,IF(AND(AK11=0,AL11>0),0,IF(AND(AK11=0,AL11=0),"***",0)))) -> *** | AO11: =+IFERROR(VLOOKUP($A11,'Goals & Budget 2026'!$A$2:$EJ$49,15,FALSE),0) -> 0 | AP11: =IF(AND(AN11>0,AO11>0),AN11/AO11,IF(AND(AN11>0,AO11=0),100%,IF(AND(AN11=0,AO11>0),0,IF(AND(AN11=0,AO11=0),"***",0)))) -> ***
A12: Verde Vale - H2 | B12: 1 | C12: 54 | D12: =+G12 -> 0 | E12: =+H12 -> 0 | F12: =IF(AND(D12>0,E12>0),D12/E12,IF(AND(D12>0,E12=0),100%,IF(AND(D12=0,E12>0),0,IF(AND(D12=0,E12=0),"***",0)))) -> *** | H12: =+IFERROR(VLOOKUP($A12,'Goals & Budget 2026'!$A$2:$EJ$49,4,FALSE),0) -> 0 | I12: =IF(AND(G12>0,H12>0),G12/H12,IF(AND(G12>0,H12=0),100%,IF(AND(G12=0,H12>0),0,IF(AND(G12=0,H12=0),"***",0)))) -> *** | K12: =+IFERROR(VLOOKUP($A12,'Goals & Budget 2026'!$A$2:$EJ$49,5,FALSE),0) -> 0 | L12: =IF(AND(J12>0,K12>0),J12/K12,IF(AND(J12>0,K12=0),100%,IF(AND(J12=0,K12>0),0,IF(AND(J12=0,K12=0),"***",0)))) -> *** | N12: =+IFERROR(VLOOKUP($A12,'Goals & Budget 2026'!$A$2:$EJ$49,6,FALSE),0) -> 0 | O12: =IF(AND(M12>0,N12>0),M12/N12,IF(AND(M12>0,N12=0),100%,IF(AND(M12=0,N12>0),0,IF(AND(M12=0,N12=0),"***",0)))) -> *** | Q12: =+IFERROR(VLOOKUP($A12,'Goals & Budget 2026'!$A$2:$EJ$49,7,FALSE),0) -> 0 | R12: =IF(AND(P12>0,Q12>0),P12/Q12,IF(AND(P12>0,Q12=0),100%,IF(AND(P12=0,Q12>0),0,IF(AND(P12=0,Q12=0),"***",0)))) -> *** | T12: =+IFERROR(VLOOKUP($A12,'Goals & Budget 2026'!$A$2:$EJ$49,8,FALSE),0) -> 0 | U12: =IF(AND(S12>0,T12>0),S12/T12,IF(AND(S12>0,T12=0),100%,IF(AND(S12=0,T12>0),0,IF(AND(S12=0,T12=0),"***",0)))) -> *** | W12: =+IFERROR(VLOOKUP($A12,'Goals & Budget 2026'!$A$2:$EJ$49,9,FALSE),0) -> 0 | X12: =IF(AND(V12>0,W12>0),V12/W12,IF(AND(V12>0,W12=0),100%,IF(AND(V12=0,W12>0),0,IF(AND(V12=0,W12=0),"***",0)))) -> *** | Z12: =+IFERROR(VLOOKUP($A12,'Goals & Budget 2026'!$A$2:$EJ$49,10,FALSE),0) -> 0 | AA12: =IF(AND(Y12>0,Z12>0),Y12/Z12,IF(AND(Y12>0,Z12=0),100%,IF(AND(Y12=0,Z12>0),0,IF(AND(Y12=0,Z12=0),"***",0)))) -> *** | AC12: =+IFERROR(VLOOKUP($A12,'Goals & Budget 2026'!$A$2:$EJ$49,11,FALSE),0) -> 0 | AD12: =IF(AND(AB12>0,AC12>0),AB12/AC12,IF(AND(AB12>0,AC12=0),100%,IF(AND(AB12=0,AC12>0),0,IF(AND(AB12=0,AC12=0),"***",0)))) -> *** | AF12: =+IFERROR(VLOOKUP($A12,'Goals & Budget 2026'!$A$2:$EJ$49,12,FALSE),0) -> 0 | AG12: =IF(AND(AE12>0,AF12>0),AE12/AF12,IF(AND(AE12>0,AF12=0),100%,IF(AND(AE12=0,AF12>0),0,IF(AND(AE12=0,AF12=0),"***",0)))) -> *** | AI12: =+IFERROR(VLOOKUP($A12,'Goals & Budget 2026'!$A$2:$EJ$49,13,FALSE),0) -> 0 | AJ12: =IF(AND(AH12>0,AI12>0),AH12/AI12,IF(AND(AH12>0,AI12=0),100%,IF(AND(AH12=0,AI12>0),0,IF(AND(AH12=0,AI12=0),"***",0)))) -> *** | AL12: =+IFERROR(VLOOKUP($A12,'Goals & Budget 2026'!$A$2:$EJ$49,14,FALSE),0) -> 0 | AM12: =IF(AND(AK12>0,AL12>0),AK12/AL12,IF(AND(AK12>0,AL12=0),100%,IF(AND(AK12=0,AL12>0),0,IF(AND(AK12=0,AL12=0),"***",0)))) -> *** | AO12: =+IFERROR(VLOOKUP($A12,'Goals & Budget 2026'!$A$2:$EJ$49,15,FALSE),0) -> 0 | AP12: =IF(AND(AN12>0,AO12>0),AN12/AO12,IF(AND(AN12>0,AO12=0),100%,IF(AND(AN12=0,AO12>0),0,IF(AND(AN12=0,AO12=0),"***",0)))) -> ***
A13: Verde Vale - H3 | B13: 1 | C13: 56 | D13: =+G13 -> 0 | E13: =+H13 -> 0 | F13: =IF(AND(D13>0,E13>0),D13/E13,IF(AND(D13>0,E13=0),100%,IF(AND(D13=0,E13>0),0,IF(AND(D13=0,E13=0),"***",0)))) -> *** | H13: =+IFERROR(VLOOKUP($A13,'Goals & Budget 2026'!$A$2:$EJ$49,4,FALSE),0) -> 0 | I13: =IF(AND(G13>0,H13>0),G13/H13,IF(AND(G13>0,H13=0),100%,IF(AND(G13=0,H13>0),0,IF(AND(G13=0,H13=0),"***",0)))) -> *** | K13: =+IFERROR(VLOOKUP($A13,'Goals & Budget 2026'!$A$2:$EJ$49,5,FALSE),0) -> 0 | L13: =IF(AND(J13>0,K13>0),J13/K13,IF(AND(J13>0,K13=0),100%,IF(AND(J13=0,K13>0),0,IF(AND(J13=0,K13=0),"***",0)))) -> *** | N13: =+IFERROR(VLOOKUP($A13,'Goals & Budget 2026'!$A$2:$EJ$49,6,FALSE),0) -> 0 | O13: =IF(AND(M13>0,N13>0),M13/N13,IF(AND(M13>0,N13=0),100%,IF(AND(M13=0,N13>0),0,IF(AND(M13=0,N13=0),"***",0)))) -> *** | Q13: =+IFERROR(VLOOKUP($A13,'Goals & Budget 2026'!$A$2:$EJ$49,7,FALSE),0) -> 0 | R13: =IF(AND(P13>0,Q13>0),P13/Q13,IF(AND(P13>0,Q13=0),100%,IF(AND(P13=0,Q13>0),0,IF(AND(P13=0,Q13=0),"***",0)))) -> *** | T13: =+IFERROR(VLOOKUP($A13,'Goals & Budget 2026'!$A$2:$EJ$49,8,FALSE),0) -> 0 | U13: =IF(AND(S13>0,T13>0),S13/T13,IF(AND(S13>0,T13=0),100%,IF(AND(S13=0,T13>0),0,IF(AND(S13=0,T13=0),"***",0)))) -> *** | W13: =+IFERROR(VLOOKUP($A13,'Goals & Budget 2026'!$A$2:$EJ$49,9,FALSE),0) -> 0 | X13: =IF(AND(V13>0,W13>0),V13/W13,IF(AND(V13>0,W13=0),100%,IF(AND(V13=0,W13>0),0,IF(AND(V13=0,W13=0),"***",0)))) -> *** | Z13: =+IFERROR(VLOOKUP($A13,'Goals & Budget 2026'!$A$2:$EJ$49,10,FALSE),0) -> 0 | AA13: =IF(AND(Y13>0,Z13>0),Y13/Z13,IF(AND(Y13>0,Z13=0),100%,IF(AND(Y13=0,Z13>0),0,IF(AND(Y13=0,Z13=0),"***",0)))) -> *** | AC13: =+IFERROR(VLOOKUP($A13,'Goals & Budget 2026'!$A$2:$EJ$49,11,FALSE),0) -> 0 | AD13: =IF(AND(AB13>0,AC13>0),AB13/AC13,IF(AND(AB13>0,AC13=0),100%,IF(AND(AB13=0,AC13>0),0,IF(AND(AB13=0,AC13=0),"***",0)))) -> *** | AF13: =+IFERROR(VLOOKUP($A13,'Goals & Budget 2026'!$A$2:$EJ$49,12,FALSE),0) -> 0 | AG13: =IF(AND(AE13>0,AF13>0),AE13/AF13,IF(AND(AE13>0,AF13=0),100%,IF(AND(AE13=0,AF13>0),0,IF(AND(AE13=0,AF13=0),"***",0)))) -> *** | AI13: =+IFERROR(VLOOKUP($A13,'Goals & Budget 2026'!$A$2:$EJ$49,13,FALSE),0) -> 0 | AJ13: =IF(AND(AH13>0,AI13>0),AH13/AI13,IF(AND(AH13>0,AI13=0),100%,IF(AND(AH13=0,AI13>0),0,IF(AND(AH13=0,AI13=0),"***",0)))) -> *** | AL13: =+IFERROR(VLOOKUP($A13,'Goals & Budget 2026'!$A$2:$EJ$49,14,FALSE),0) -> 0 | AM13: =IF(AND(AK13>0,AL13>0),AK13/AL13,IF(AND(AK13>0,AL13=0),100%,IF(AND(AK13=0,AL13>0),0,IF(AND(AK13=0,AL13=0),"***",0)))) -> *** | AO13: =+IFERROR(VLOOKUP($A13,'Goals & Budget 2026'!$A$2:$EJ$49,15,FALSE),0) -> 0 | AP13: =IF(AND(AN13>0,AO13>0),AN13/AO13,IF(AND(AN13>0,AO13=0),100%,IF(AND(AN13=0,AO13>0),0,IF(AND(AN13=0,AO13=0),"***",0)))) -> ***
A14: Verde Vale - H4 | B14: 1 | C14: 80 | D14: =+G14 -> 0 | E14: =+H14 -> 0 | F14: =IF(AND(D14>0,E14>0),D14/E14,IF(AND(D14>0,E14=0),100%,IF(AND(D14=0,E14>0),0,IF(AND(D14=0,E14=0),"***",0)))) -> *** | H14: =+IFERROR(VLOOKUP($A14,'Goals & Budget 2026'!$A$2:$EJ$49,4,FALSE),0) -> 0 | I14: =IF(AND(G14>0,H14>0),G14/H14,IF(AND(G14>0,H14=0),100%,IF(AND(G14=0,H14>0),0,IF(AND(G14=0,H14=0),"***",0)))) -> *** | K14: =+IFERROR(VLOOKUP($A14,'Goals & Budget 2026'!$A$2:$EJ$49,5,FALSE),0) -> 0 | L14: =IF(AND(J14>0,K14>0),J14/K14,IF(AND(J14>0,K14=0),100%,IF(AND(J14=0,K14>0),0,IF(AND(J14=0,K14=0),"***",0)))) -> *** | N14: =+IFERROR(VLOOKUP($A14,'Goals & Budget 2026'!$A$2:$EJ$49,6,FALSE),0) -> 0 | O14: =IF(AND(M14>0,N14>0),M14/N14,IF(AND(M14>0,N14=0),100%,IF(AND(M14=0,N14>0),0,IF(AND(M14=0,N14=0),"***",0)))) -> *** | Q14: =+IFERROR(VLOOKUP($A14,'Goals & Budget 2026'!$A$2:$EJ$49,7,FALSE),0) -> 0 | R14: =IF(AND(P14>0,Q14>0),P14/Q14,IF(AND(P14>0,Q14=0),100%,IF(AND(P14=0,Q14>0),0,IF(AND(P14=0,Q14=0),"***",0)))) -> *** | T14: =+IFERROR(VLOOKUP($A14,'Goals & Budget 2026'!$A$2:$EJ$49,8,FALSE),0) -> 0 | U14: =IF(AND(S14>0,T14>0),S14/T14,IF(AND(S14>0,T14=0),100%,IF(AND(S14=0,T14>0),0,IF(AND(S14=0,T14=0),"***",0)))) -> *** | W14: =+IFERROR(VLOOKUP($A14,'Goals & Budget 2026'!$A$2:$EJ$49,9,FALSE),0) -> 0 | X14: =IF(AND(V14>0,W14>0),V14/W14,IF(AND(V14>0,W14=0),100%,IF(AND(V14=0,W14>0),0,IF(AND(V14=0,W14=0),"***",0)))) -> *** | Z14: =+IFERROR(VLOOKUP($A14,'Goals & Budget 2026'!$A$2:$EJ$49,10,FALSE),0) -> 0 | AA14: =IF(AND(Y14>0,Z14>0),Y14/Z14,IF(AND(Y14>0,Z14=0),100%,IF(AND(Y14=0,Z14>0),0,IF(AND(Y14=0,Z14=0),"***",0)))) -> *** | AC14: =+IFERROR(VLOOKUP($A14,'Goals & Budget 2026'!$A$2:$EJ$49,11,FALSE),0) -> 0 | AD14: =IF(AND(AB14>0,AC14>0),AB14/AC14,IF(AND(AB14>0,AC14=0),100%,IF(AND(AB14=0,AC14>0),0,IF(AND(AB14=0,AC14=0),"***",0)))) -> *** | AF14: =+IFERROR(VLOOKUP($A14,'Goals & Budget 2026'!$A$2:$EJ$49,12,FALSE),0) -> 0 | AG14: =IF(AND(AE14>0,AF14>0),AE14/AF14,IF(AND(AE14>0,AF14=0),100%,IF(AND(AE14=0,AF14>0),0,IF(AND(AE14=0,AF14=0),"***",0)))) -> *** | AI14: =+IFERROR(VLOOKUP($A14,'Goals & Budget 2026'!$A$2:$EJ$49,13,FALSE),0) -> 0 | AJ14: =IF(AND(AH14>0,AI14>0),AH14/AI14,IF(AND(AH14>0,AI14=0),100%,IF(AND(AH14=0,AI14>0),0,IF(AND(AH14=0,AI14=0),"***",0)))) -> *** | AL14: =+IFERROR(VLOOKUP($A14,'Goals & Budget 2026'!$A$2:$EJ$49,14,FALSE),0) -> 0 | AM14: =IF(AND(AK14>0,AL14>0),AK14/AL14,IF(AND(AK14>0,AL14=0),100%,IF(AND(AK14=0,AL14>0),0,IF(AND(AK14=0,AL14=0),"***",0)))) -> *** | AO14: =+IFERROR(VLOOKUP($A14,'Goals & Budget 2026'!$A$2:$EJ$49,15,FALSE),0) -> 0 | AP14: =IF(AND(AN14>0,AO14>0),AN14/AO14,IF(AND(AN14>0,AO14=0),100%,IF(AND(AN14=0,AO14>0),0,IF(AND(AN14=0,AO14=0),"***",0)))) -> ***
... A29: Antas South - Resi | B29: 1 | C29: 57 | D29: =+G29 -> 0 | E29: =+H29 -> 0 | F29: =IF(AND(D29>0,E29>0),D29/E29,IF(AND(D29>0,E29=0),100%,IF(AND(D29=0,E29>0),0,IF(AND(D29=0,E29=0),"***",0)))) -> *** | H29: =+IFERROR(VLOOKUP($A29,'Goals & Budget 2026'!$A$2:$EJ$49,4,FALSE),0) -> 0 | I29: =IF(AND(G29>0,H29>0),G29/H29,IF(AND(G29>0,H29=0),100%,IF(AND(G29=0,H29>0),0,IF(AND(G29=0,H29=0),"***",0)))) -> *** | K29: =+IFERROR(VLOOKUP($A29,'Goals & Budget 2026'!$A$2:$EJ$49,5,FALSE),0) -> 0 | L29: =IF(AND(J29>0,K29>0),J29/K29,IF(AND(J29>0,K29=0),100%,IF(AND(J29=0,K29>0),0,IF(AND(J29=0,K29=0),"***",0)))) -> *** | N29: =+IFERROR(VLOOKUP($A29,'Goals & Budget 2026'!$A$2:$EJ$49,6,FALSE),0) -> 0 | O29: =IF(AND(M29>0,N29>0),M29/N29,IF(AND(M29>0,N29=0),100%,IF(AND(M29=0,N29>0),0,IF(AND(M29=0,N29=0),"***",0)))) -> *** | Q29: =+IFERROR(VLOOKUP($A29,'Goals & Budget 2026'!$A$2:$EJ$49,7,FALSE),0) -> 0 | R29: =IF(AND(P29>0,Q29>0),P29/Q29,IF(AND(P29>0,Q29=0),100%,IF(AND(P29=0,Q29>0),0,IF(AND(P29=0,Q29=0),"***",0)))) -> *** | T29: =+IFERROR(VLOOKUP($A29,'Goals & Budget 2026'!$A$2:$EJ$49,8,FALSE),0) -> 0 | U29: =IF(AND(S29>0,T29>0),S29/T29,IF(AND(S29>0,T29=0),100%,IF(AND(S29=0,T29>0),0,IF(AND(S29=0,T29=0),"***",0)))) -> *** | W29: =+IFERROR(VLOOKUP($A29,'Goals & Budget 2026'!$A$2:$EJ$49,9,FALSE),0) -> 0 | X29: =IF(AND(V29>0,W29>0),V29/W29,IF(AND(V29>0,W29=0),100%,IF(AND(V29=0,W29>0),0,IF(AND(V29=0,W29=0),"***",0)))) -> *** | Z29: =+IFERROR(VLOOKUP($A29,'Goals & Budget 2026'!$A$2:$EJ$49,10,FALSE),0) -> 0 | AA29: =IF(AND(Y29>0,Z29>0),Y29/Z29,IF(AND(Y29>0,Z29=0),100%,IF(AND(Y29=0,Z29>0),0,IF(AND(Y29=0,Z29=0),"***",0)))) -> *** | AC29: =+IFERROR(VLOOKUP($A29,'Goals & Budget 2026'!$A$2:$EJ$49,11,FALSE),0) -> 0 | AD29: =IF(AND(AB29>0,AC29>0),AB29/AC29,IF(AND(AB29>0,AC29=0),100%,IF(AND(AB29=0,AC29>0),0,IF(AND(AB29=0,AC29=0),"***",0)))) -> *** | AF29: =+IFERROR(VLOOKUP($A29,'Goals & Budget 2026'!$A$2:$EJ$49,12,FALSE),0) -> 0 | AG29: =IF(AND(AE29>0,AF29>0),AE29/AF29,IF(AND(AE29>0,AF29=0),100%,IF(AND(AE29=0,AF29>0),0,IF(AND(AE29=0,AF29=0),"***",0)))) -> *** | AI29: =+IFERROR(VLOOKUP($A29,'Goals & Budget 2026'!$A$2:$EJ$49,13,FALSE),0) -> 0 | AJ29: =IF(AND(AH29>0,AI29>0),AH29/AI29,IF(AND(AH29>0,AI29=0),100%,IF(AND(AH29=0,AI29>0),0,IF(AND(AH29=0,AI29=0),"***",0)))) -> *** | AL29: =+IFERROR(VLOOKUP($A29,'Goals & Budget 2026'!$A$2:$EJ$49,14,FALSE),0) -> 0 | AM29: =IF(AND(AK29>0,AL29>0),AK29/AL29,IF(AND(AK29>0,AL29=0),100%,IF(AND(AK29=0,AL29>0),0,IF(AND(AK29=0,AL29=0),"***",0)))) -> *** | AO29: =+IFERROR(VLOOKUP($A29,'Goals & Budget 2026'!$A$2:$EJ$49,15,FALSE),0) -> 0 | AP29: =IF(AND(AN29>0,AO29>0),AN29/AO29,IF(AND(AN29>0,AO29=0),100%,IF(AND(AN29=0,AO29>0),0,IF(AND(AN29=0,AO29=0),"***",0)))) -> ***
A30: Antas North | B30: 1 | C30: ? | D30: =+G30 -> 0 | E30: =+H30 -> 0 | F30: =IF(AND(D30>0,E30>0),D30/E30,IF(AND(D30>0,E30=0),100%,IF(AND(D30=0,E30>0),0,IF(AND(D30=0,E30=0),"***",0)))) -> *** | H30: =+IFERROR(VLOOKUP($A30,'Goals & Budget 2026'!$A$2:$EJ$49,4,FALSE),0) -> 0 | I30: =IF(AND(G30>0,H30>0),G30/H30,IF(AND(G30>0,H30=0),100%,IF(AND(G30=0,H30>0),0,IF(AND(G30=0,H30=0),"***",0)))) -> *** | K30: =+IFERROR(VLOOKUP($A30,'Goals & Budget 2026'!$A$2:$EJ$49,5,FALSE),0) -> 0 | L30: =IF(AND(J30>0,K30>0),J30/K30,IF(AND(J30>0,K30=0),100%,IF(AND(J30=0,K30>0),0,IF(AND(J30=0,K30=0),"***",0)))) -> *** | N30: =+IFERROR(VLOOKUP($A30,'Goals & Budget 2026'!$A$2:$EJ$49,6,FALSE),0) -> 0 | O30: =IF(AND(M30>0,N30>0),M30/N30,IF(AND(M30>0,N30=0),100%,IF(AND(M30=0,N30>0),0,IF(AND(M30=0,N30=0),"***",0)))) -> *** | Q30: =+IFERROR(VLOOKUP($A30,'Goals & Budget 2026'!$A$2:$EJ$49,7,FALSE),0) -> 0 | R30: =IF(AND(P30>0,Q30>0),P30/Q30,IF(AND(P30>0,Q30=0),100%,IF(AND(P30=0,Q30>0),0,IF(AND(P30=0,Q30=0),"***",0)))) -> *** | T30: =+IFERROR(VLOOKUP($A30,'Goals & Budget 2026'!$A$2:$EJ$49,8,FALSE),0) -> 0 | U30: =IF(AND(S30>0,T30>0),S30/T30,IF(AND(S30>0,T30=0),100%,IF(AND(S30=0,T30>0),0,IF(AND(S30=0,T30=0),"***",0)))) -> *** | W30: =+IFERROR(VLOOKUP($A30,'Goals & Budget 2026'!$A$2:$EJ$49,9,FALSE),0) -> 0 | X30: =IF(AND(V30>0,W30>0),V30/W30,IF(AND(V30>0,W30=0),100%,IF(AND(V30=0,W30>0),0,IF(AND(V30=0,W30=0),"***",0)))) -> *** | Z30: =+IFERROR(VLOOKUP($A30,'Goals & Budget 2026'!$A$2:$EJ$49,10,FALSE),0) -> 0 | AA30: =IF(AND(Y30>0,Z30>0),Y30/Z30,IF(AND(Y30>0,Z30=0),100%,IF(AND(Y30=0,Z30>0),0,IF(AND(Y30=0,Z30=0),"***",0)))) -> *** | AC30: =+IFERROR(VLOOKUP($A30,'Goals & Budget 2026'!$A$2:$EJ$49,11,FALSE),0) -> 0 | AD30: =IF(AND(AB30>0,AC30>0),AB30/AC30,IF(AND(AB30>0,AC30=0),100%,IF(AND(AB30=0,AC30>0),0,IF(AND(AB30=0,AC30=0),"***",0)))) -> *** | AF30: =+IFERROR(VLOOKUP($A30,'Goals & Budget 2026'!$A$2:$EJ$49,12,FALSE),0) -> 0 | AG30: =IF(AND(AE30>0,AF30>0),AE30/AF30,IF(AND(AE30>0,AF30=0),100%,IF(AND(AE30=0,AF30>0),0,IF(AND(AE30=0,AF30=0),"***",0)))) -> *** | AI30: =+IFERROR(VLOOKUP($A30,'Goals & Budget 2026'!$A$2:$EJ$49,13,FALSE),0) -> 0 | AJ30: =IF(AND(AH30>0,AI30>0),AH30/AI30,IF(AND(AH30>0,AI30=0),100%,IF(AND(AH30=0,AI30>0),0,IF(AND(AH30=0,AI30=0),"***",0)))) -> *** | AL30: =+IFERROR(VLOOKUP($A30,'Goals & Budget 2026'!$A$2:$EJ$49,14,FALSE),0) -> 0 | AM30: =IF(AND(AK30>0,AL30>0),AK30/AL30,IF(AND(AK30>0,AL30=0),100%,IF(AND(AK30=0,AL30>0),0,IF(AND(AK30=0,AL30=0),"***",0)))) -> *** | AO30: =+IFERROR(VLOOKUP($A30,'Goals & Budget 2026'!$A$2:$EJ$49,15,FALSE),0) -> 0 | AP30: =IF(AND(AN30>0,AO30>0),AN30/AO30,IF(AND(AN30>0,AO30=0),100%,IF(AND(AN30=0,AO30>0),0,IF(AND(AN30=0,AO30=0),"***",0)))) -> ***
A31: Vila do Conde - Allotment | B31: 1 | C31: 1 | D31: =+G31 -> 0 | E31: =+H31 -> 0 | F31: =IF(AND(D31>0,E31>0),D31/E31,IF(AND(D31>0,E31=0),100%,IF(AND(D31=0,E31>0),0,IF(AND(D31=0,E31=0),"***",0)))) -> *** | H31: =+IFERROR(VLOOKUP($A31,'Goals & Budget 2026'!$A$2:$EJ$49,4,FALSE),0) -> 0 | I31: =IF(AND(G31>0,H31>0),G31/H31,IF(AND(G31>0,H31=0),100%,IF(AND(G31=0,H31>0),0,IF(AND(G31=0,H31=0),"***",0)))) -> *** | K31: =+IFERROR(VLOOKUP($A31,'Goals & Budget 2026'!$A$2:$EJ$49,5,FALSE),0) -> 0 | L31: =IF(AND(J31>0,K31>0),J31/K31,IF(AND(J31>0,K31=0),100%,IF(AND(J31=0,K31>0),0,IF(AND(J31=0,K31=0),"***",0)))) -> *** | N31: =+IFERROR(VLOOKUP($A31,'Goals & Budget 2026'!$A$2:$EJ$49,6,FALSE),0) -> 0 | O31: =IF(AND(M31>0,N31>0),M31/N31,IF(AND(M31>0,N31=0),100%,IF(AND(M31=0,N31>0),0,IF(AND(M31=0,N31=0),"***",0)))) -> *** | Q31: =+IFERROR(VLOOKUP($A31,'Goals & Budget 2026'!$A$2:$EJ$49,7,FALSE),0) -> 0 | R31: =IF(AND(P31>0,Q31>0),P31/Q31,IF(AND(P31>0,Q31=0),100%,IF(AND(P31=0,Q31>0),0,IF(AND(P31=0,Q31=0),"***",0)))) -> *** | T31: =+IFERROR(VLOOKUP($A31,'Goals & Budget 2026'!$A$2:$EJ$49,8,FALSE),0) -> 0 | U31: =IF(AND(S31>0,T31>0),S31/T31,IF(AND(S31>0,T31=0),100%,IF(AND(S31=0,T31>0),0,IF(AND(S31=0,T31=0),"***",0)))) -> *** | W31: =+IFERROR(VLOOKUP($A31,'Goals & Budget 2026'!$A$2:$EJ$49,9,FALSE),0) -> 0 | X31: =IF(AND(V31>0,W31>0),V31/W31,IF(AND(V31>0,W31=0),100%,IF(AND(V31=0,W31>0),0,IF(AND(V31=0,W31=0),"***",0)))) -> *** | Z31: =+IFERROR(VLOOKUP($A31,'Goals & Budget 2026'!$A$2:$EJ$49,10,FALSE),0) -> 0 | AA31: =IF(AND(Y31>0,Z31>0),Y31/Z31,IF(AND(Y31>0,Z31=0),100%,IF(AND(Y31=0,Z31>0),0,IF(AND(Y31=0,Z31=0),"***",0)))) -> *** | AC31: =+IFERROR(VLOOKUP($A31,'Goals & Budget 2026'!$A$2:$EJ$49,11,FALSE),0) -> 0 | AD31: =IF(AND(AB31>0,AC31>0),AB31/AC31,IF(AND(AB31>0,AC31=0),100%,IF(AND(AB31=0,AC31>0),0,IF(AND(AB31=0,AC31=0),"***",0)))) -> *** | AF31: =+IFERROR(VLOOKUP($A31,'Goals & Budget 2026'!$A$2:$EJ$49,12,FALSE),0) -> 0 | AG31: =IF(AND(AE31>0,AF31>0),AE31/AF31,IF(AND(AE31>0,AF31=0),100%,IF(AND(AE31=0,AF31>0),0,IF(AND(AE31=0,AF31=0),"***",0)))) -> *** | AI31: =+IFERROR(VLOOKUP($A31,'Goals & Budget 2026'!$A$2:$EJ$49,13,FALSE),0) -> 0 | AJ31: =IF(AND(AH31>0,AI31>0),AH31/AI31,IF(AND(AH31>0,AI31=0),100%,IF(AND(AH31=0,AI31>0),0,IF(AND(AH31=0,AI31=0),"***",0)))) -> *** | AL31: =+IFERROR(VLOOKUP($A31,'Goals & Budget 2026'!$A$2:$EJ$49,14,FALSE),0) -> 0 | AM31: =IF(AND(AK31>0,AL31>0),AK31/AL31,IF(AND(AK31>0,AL31=0),100%,IF(AND(AK31=0,AL31>0),0,IF(AND(AK31=0,AL31=0),"***",0)))) -> *** | AO31: =+IFERROR(VLOOKUP($A31,'Goals & Budget 2026'!$A$2:$EJ$49,15,FALSE),0) -> 0 | AP31: =IF(AND(AN31>0,AO31>0),AN31/AO31,IF(AND(AN31>0,AO31=0),100%,IF(AND(AN31=0,AO31>0),0,IF(AND(AN31=0,AO31=0),"***",0)))) -> ***
A32: Vila do Conde - Phase 1 | B32: 1 | C32: 165 | D32: =+G32 -> 0 | E32: =+H32 -> 0 | F32: =IF(AND(D32>0,E32>0),D32/E32,IF(AND(D32>0,E32=0),100%,IF(AND(D32=0,E32>0),0,IF(AND(D32=0,E32=0),"***",0)))) -> *** | H32: =+IFERROR(VLOOKUP($A32,'Goals & Budget 2026'!$A$2:$EJ$49,4,FALSE),0) -> 0 | I32: =IF(AND(G32>0,H32>0),G32/H32,IF(AND(G32>0,H32=0),100%,IF(AND(G32=0,H32>0),0,IF(AND(G32=0,H32=0),"***",0)))) -> *** | K32: =+IFERROR(VLOOKUP($A32,'Goals & Budget 2026'!$A$2:$EJ$49,5,FALSE),0) -> 0 | L32: =IF(AND(J32>0,K32>0),J32/K32,IF(AND(J32>0,K32=0),100%,IF(AND(J32=0,K32>0),0,IF(AND(J32=0,K32=0),"***",0)))) -> *** | N32: =+IFERROR(VLOOKUP($A32,'Goals & Budget 2026'!$A$2:$EJ$49,6,FALSE),0) -> 0 | O32: =IF(AND(M32>0,N32>0),M32/N32,IF(AND(M32>0,N32=0),100%,IF(AND(M32=0,N32>0),0,IF(AND(M32=0,N32=0),"***",0)))) -> *** | Q32: =+IFERROR(VLOOKUP($A32,'Goals & Budget 2026'!$A$2:$EJ$49,7,FALSE),0) -> 0 | R32: =IF(AND(P32>0,Q32>0),P32/Q32,IF(AND(P32>0,Q32=0),100%,IF(AND(P32=0,Q32>0),0,IF(AND(P32=0,Q32=0),"***",0)))) -> *** | T32: =+IFERROR(VLOOKUP($A32,'Goals & Budget 2026'!$A$2:$EJ$49,8,FALSE),0) -> 0 | U32: =IF(AND(S32>0,T32>0),S32/T32,IF(AND(S32>0,T32=0),100%,IF(AND(S32=0,T32>0),0,IF(AND(S32=0,T32=0),"***",0)))) -> *** | W32: =+IFERROR(VLOOKUP($A32,'Goals & Budget 2026'!$A$2:$EJ$49,9,FALSE),0) -> 0 | X32: =IF(AND(V32>0,W32>0),V32/W32,IF(AND(V32>0,W32=0),100%,IF(AND(V32=0,W32>0),0,IF(AND(V32=0,W32=0),"***",0)))) -> *** | Z32: =+IFERROR(VLOOKUP($A32,'Goals & Budget 2026'!$A$2:$EJ$49,10,FALSE),0) -> 0 | AA32: =IF(AND(Y32>0,Z32>0),Y32/Z32,IF(AND(Y32>0,Z32=0),100%,IF(AND(Y32=0,Z32>0),0,IF(AND(Y32=0,Z32=0),"***",0)))) -> *** | AC32: =+IFERROR(VLOOKUP($A32,'Goals & Budget 2026'!$A$2:$EJ$49,11,FALSE),0) -> 0 | AD32: =IF(AND(AB32>0,AC32>0),AB32/AC32,IF(AND(AB32>0,AC32=0),100%,IF(AND(AB32=0,AC32>0),0,IF(AND(AB32=0,AC32=0),"***",0)))) -> *** | AF32: =+IFERROR(VLOOKUP($A32,'Goals & Budget 2026'!$A$2:$EJ$49,12,FALSE),0) -> 0 | AG32: =IF(AND(AE32>0,AF32>0),AE32/AF32,IF(AND(AE32>0,AF32=0),100%,IF(AND(AE32=0,AF32>0),0,IF(AND(AE32=0,AF32=0),"***",0)))) -> *** | AI32: =+IFERROR(VLOOKUP($A32,'Goals & Budget 2026'!$A$2:$EJ$49,13,FALSE),0) -> 0 | AJ32: =IF(AND(AH32>0,AI32>0),AH32/AI32,IF(AND(AH32>0,AI32=0),100%,IF(AND(AH32=0,AI32>0),0,IF(AND(AH32=0,AI32=0),"***",0)))) -> *** | AL32: =+IFERROR(VLOOKUP($A32,'Goals & Budget 2026'!$A$2:$EJ$49,14,FALSE),0) -> 0 | AM32: =IF(AND(AK32>0,AL32>0),AK32/AL32,IF(AND(AK32>0,AL32=0),100%,IF(AND(AK32=0,AL32>0),0,IF(AND(AK32=0,AL32=0),"***",0)))) -> *** | AO32: =+IFERROR(VLOOKUP($A32,'Goals & Budget 2026'!$A$2:$EJ$49,15,FALSE),0) -> 0 | AP32: =IF(AND(AN32>0,AO32>0),AN32/AO32,IF(AND(AN32>0,AO32=0),100%,IF(AND(AN32=0,AO32>0),0,IF(AND(AN32=0,AO32=0),"***",0)))) -> ***
A33: Vila do Conde - Phase 2 | B33: 1 | C33: 39 | D33: =+G33 -> 0 | E33: =+H33 -> 0 | F33: =IF(AND(D33>0,E33>0),D33/E33,IF(AND(D33>0,E33=0),100%,IF(AND(D33=0,E33>0),0,IF(AND(D33=0,E33=0),"***",0)))) -> *** | H33: =+IFERROR(VLOOKUP($A33,'Goals & Budget 2026'!$A$2:$EJ$49,4,FALSE),0) -> 0 | I33: =IF(AND(G33>0,H33>0),G33/H33,IF(AND(G33>0,H33=0),100%,IF(AND(G33=0,H33>0),0,IF(AND(G33=0,H33=0),"***",0)))) -> *** | K33: =+IFERROR(VLOOKUP($A33,'Goals & Budget 2026'!$A$2:$EJ$49,5,FALSE),0) -> 0 | L33: =IF(AND(J33>0,K33>0),J33/K33,IF(AND(J33>0,K33=0),100%,IF(AND(J33=0,K33>0),0,IF(AND(J33=0,K33=0),"***",0)))) -> *** | N33: =+IFERROR(VLOOKUP($A33,'Goals & Budget 2026'!$A$2:$EJ$49,6,FALSE),0) -> 0 | O33: =IF(AND(M33>0,N33>0),M33/N33,IF(AND(M33>0,N33=0),100%,IF(AND(M33=0,N33>0),0,IF(AND(M33=0,N33=0),"***",0)))) -> *** | Q33: =+IFERROR(VLOOKUP($A33,'Goals & Budget 2026'!$A$2:$EJ$49,7,FALSE),0) -> 0 | R33: =IF(AND(P33>0,Q33>0),P33/Q33,IF(AND(P33>0,Q33=0),100%,IF(AND(P33=0,Q33>0),0,IF(AND(P33=0,Q33=0),"***",0)))) -> *** | T33: =+IFERROR(VLOOKUP($A33,'Goals & Budget 2026'!$A$2:$EJ$49,8,FALSE),0) -> 0 | U33: =IF(AND(S33>0,T33>0),S33/T33,IF(AND(S33>0,T33=0),100%,IF(AND(S33=0,T33>0),0,IF(AND(S33=0,T33=0),"***",0)))) -> *** | W33: =+IFERROR(VLOOKUP($A33,'Goals & Budget 2026'!$A$2:$EJ$49,9,FALSE),0) -> 0 | X33: =IF(AND(V33>0,W33>0),V33/W33,IF(AND(V33>0,W33=0),100%,IF(AND(V33=0,W33>0),0,IF(AND(V33=0,W33=0),"***",0)))) -> *** | Z33: =+IFERROR(VLOOKUP($A33,'Goals & Budget 2026'!$A$2:$EJ$49,10,FALSE),0) -> 0 | AA33: =IF(AND(Y33>0,Z33>0),Y33/Z33,IF(AND(Y33>0,Z33=0),100%,IF(AND(Y33=0,Z33>0),0,IF(AND(Y33=0,Z33=0),"***",0)))) -> *** | AC33: =+IFERROR(VLOOKUP($A33,'Goals & Budget 2026'!$A$2:$EJ$49,11,FALSE),0) -> 0 | AD33: =IF(AND(AB33>0,AC33>0),AB33/AC33,IF(AND(AB33>0,AC33=0),100%,IF(AND(AB33=0,AC33>0),0,IF(AND(AB33=0,AC33=0),"***",0)))) -> *** | AF33: =+IFERROR(VLOOKUP($A33,'Goals & Budget 2026'!$A$2:$EJ$49,12,FALSE),0) -> 0 | AG33: =IF(AND(AE33>0,AF33>0),AE33/AF33,IF(AND(AE33>0,AF33=0),100%,IF(AND(AE33=0,AF33>0),0,IF(AND(AE33=0,AF33=0),"***",0)))) -> *** | AI33: =+IFERROR(VLOOKUP($A33,'Goals & Budget 2026'!$A$2:$EJ$49,13,FALSE),0) -> 0 | AJ33: =IF(AND(AH33>0,AI33>0),AH33/AI33,IF(AND(AH33>0,AI33=0),100%,IF(AND(AH33=0,AI33>0),0,IF(AND(AH33=0,AI33=0),"***",0)))) -> *** | AL33: =+IFERROR(VLOOKUP($A33,'Goals & Budget 2026'!$A$2:$EJ$49,14,FALSE),0) -> 0 | AM33: =IF(AND(AK33>0,AL33>0),AK33/AL33,IF(AND(AK33>0,AL33=0),100%,IF(AND(AK33=0,AL33>0),0,IF(AND(AK33=0,AL33=0),"***",0)))) -> *** | AO33: =+IFERROR(VLOOKUP($A33,'Goals & Budget 2026'!$A$2:$EJ$49,15,FALSE),0) -> 0 | AP33: =IF(AND(AN33>0,AO33>0),AN33/AO33,IF(AND(AN33>0,AO33=0),100%,IF(AND(AN33=0,AO33>0),0,IF(AND(AN33=0,AO33=0),"***",0)))) -> ***
A34: Vila do Conde - Phase 3 | B34: 1 | C34: 76 | D34: =+G34 -> 0 | E34: =+H34 -> 0 | F34: =IF(AND(D34>0,E34>0),D34/E34,IF(AND(D34>0,E34=0),100%,IF(AND(D34=0,E34>0),0,IF(AND(D34=0,E34=0),"***",0)))) -> *** | H34: =+IFERROR(VLOOKUP($A34,'Goals & Budget 2026'!$A$2:$EJ$49,4,FALSE),0) -> 0 | I34: =IF(AND(G34>0,H34>0),G34/H34,IF(AND(G34>0,H34=0),100%,IF(AND(G34=0,H34>0),0,IF(AND(G34=0,H34=0),"***",0)))) -> *** | K34: =+IFERROR(VLOOKUP($A34,'Goals & Budget 2026'!$A$2:$EJ$49,5,FALSE),0) -> 0 | L34: =IF(AND(J34>0,K34>0),J34/K34,IF(AND(J34>0,K34=0),100%,IF(AND(J34=0,K34>0),0,IF(AND(J34=0,K34=0),"***",0)))) -> *** | N34: =+IFERROR(VLOOKUP($A34,'Goals & Budget 2026'!$A$2:$EJ$49,6,FALSE),0) -> 0 | O34: =IF(AND(M34>0,N34>0),M34/N34,IF(AND(M34>0,N34=0),100%,IF(AND(M34=0,N34>0),0,IF(AND(M34=0,N34=0),"***",0)))) -> *** | Q34: =+IFERROR(VLOOKUP($A34,'Goals & Budget 2026'!$A$2:$EJ$49,7,FALSE),0) -> 0 | R34: =IF(AND(P34>0,Q34>0),P34/Q34,IF(AND(P34>0,Q34=0),100%,IF(AND(P34=0,Q34>0),0,IF(AND(P34=0,Q34=0),"***",0)))) -> *** | T34: =+IFERROR(VLOOKUP($A34,'Goals & Budget 2026'!$A$2:$EJ$49,8,FALSE),0) -> 0 | U34: =IF(AND(S34>0,T34>0),S34/T34,IF(AND(S34>0,T34=0),100%,IF(AND(S34=0,T34>0),0,IF(AND(S34=0,T34=0),"***",0)))) -> *** | W34: =+IFERROR(VLOOKUP($A34,'Goals & Budget 2026'!$A$2:$EJ$49,9,FALSE),0) -> 0 | X34: =IF(AND(V34>0,W34>0),V34/W34,IF(AND(V34>0,W34=0),100%,IF(AND(V34=0,W34>0),0,IF(AND(V34=0,W34=0),"***",0)))) -> *** | Z34: =+IFERROR(VLOOKUP($A34,'Goals & Budget 2026'!$A$2:$EJ$49,10,FALSE),0) -> 0 | AA34: =IF(AND(Y34>0,Z34>0),Y34/Z34,IF(AND(Y34>0,Z34=0),100%,IF(AND(Y34=0,Z34>0),0,IF(AND(Y34=0,Z34=0),"***",0)))) -> *** | AC34: =+IFERROR(VLOOKUP($A34,'Goals & Budget 2026'!$A$2:$EJ$49,11,FALSE),0) -> 0 | AD34: =IF(AND(AB34>0,AC34>0),AB34/AC34,IF(AND(AB34>0,AC34=0),100%,IF(AND(AB34=0,AC34>0),0,IF(AND(AB34=0,AC34=0),"***",0)))) -> *** | AF34: =+IFERROR(VLOOKUP($A34,'Goals & Budget 2026'!$A$2:$EJ$49,12,FALSE),0) -> 0 | AG34: =IF(AND(AE34>0,AF34>0),AE34/AF34,IF(AND(AE34>0,AF34=0),100%,IF(AND(AE34=0,AF34>0),0,IF(AND(AE34=0,AF34=0),"***",0)))) -> *** | AI34: =+IFERROR(VLOOKUP($A34,'Goals & Budget 2026'!$A$2:$EJ$49,13,FALSE),0) -> 0 | AJ34: =IF(AND(AH34>0,AI34>0),AH34/AI34,IF(AND(AH34>0,AI34=0),100%,IF(AND(AH34=0,AI34>0),0,IF(AND(AH34=0,AI34=0),"***",0)))) -> *** | AL34: =+IFERROR(VLOOKUP($A34,'Goals & Budget 2026'!$A$2:$EJ$49,14,FALSE),0) -> 0 | AM34: =IF(AND(AK34>0,AL34>0),AK34/AL34,IF(AND(AK34>0,AL34=0),100%,IF(AND(AK34=0,AL34>0),0,IF(AND(AK34=0,AL34=0),"***",0)))) -> *** | AO34: =+IFERROR(VLOOKUP($A34,'Goals & Budget 2026'!$A$2:$EJ$49,15,FALSE),0) -> 0 | AP34: =IF(AND(AN34>0,AO34>0),AN34/AO34,IF(AND(AN34>0,AO34=0),100%,IF(AND(AN34=0,AO34>0),0,IF(AND(AN34=0,AO34=0),"***",0)))) -> ***
A35: Parkview | B35: 1 | C35: 39 | D35: =+G35 -> 0 | E35: =+H35 -> 0 | F35: =IF(AND(D35>0,E35>0),D35/E35,IF(AND(D35>0,E35=0),100%,IF(AND(D35=0,E35>0),0,IF(AND(D35=0,E35=0),"***",0)))) -> *** | H35: =+IFERROR(VLOOKUP($A35,'Goals & Budget 2026'!$A$2:$EJ$49,4,FALSE),0) -> 0 | I35: =IF(AND(G35>0,H35>0),G35/H35,IF(AND(G35>0,H35=0),100%,IF(AND(G35=0,H35>0),0,IF(AND(G35=0,H35=0),"***",0)))) -> *** | K35: =+IFERROR(VLOOKUP($A35,'Goals & Budget 2026'!$A$2:$EJ$49,5,FALSE),0) -> 0 | L35: =IF(AND(J35>0,K35>0),J35/K35,IF(AND(J35>0,K35=0),100%,IF(AND(J35=0,K35>0),0,IF(AND(J35=0,K35=0),"***",0)))) -> *** | N35: =+IFERROR(VLOOKUP($A35,'Goals & Budget 2026'!$A$2:$EJ$49,6,FALSE),0) -> 0 | O35: =IF(AND(M35>0,N35>0),M35/N35,IF(AND(M35>0,N35=0),100%,IF(AND(M35=0,N35>0),0,IF(AND(M35=0,N35=0),"***",0)))) -> *** | Q35: =+IFERROR(VLOOKUP($A35,'Goals & Budget 2026'!$A$2:$EJ$49,7,FALSE),0) -> 0 | R35: =IF(AND(P35>0,Q35>0),P35/Q35,IF(AND(P35>0,Q35=0),100%,IF(AND(P35=0,Q35>0),0,IF(AND(P35=0,Q35=0),"***",0)))) -> *** | T35: =+IFERROR(VLOOKUP($A35,'Goals & Budget 2026'!$A$2:$EJ$49,8,FALSE),0) -> 0 | U35: =IF(AND(S35>0,T35>0),S35/T35,IF(AND(S35>0,T35=0),100%,IF(AND(S35=0,T35>0),0,IF(AND(S35=0,T35=0),"***",0)))) -> *** | W35: =+IFERROR(VLOOKUP($A35,'Goals & Budget 2026'!$A$2:$EJ$49,9,FALSE),0) -> 0 | X35: =IF(AND(V35>0,W35>0),V35/W35,IF(AND(V35>0,W35=0),100%,IF(AND(V35=0,W35>0),0,IF(AND(V35=0,W35=0),"***",0)))) -> *** | Z35: =+IFERROR(VLOOKUP($A35,'Goals & Budget 2026'!$A$2:$EJ$49,10,FALSE),0) -> 0 | AA35: =IF(AND(Y35>0,Z35>0),Y35/Z35,IF(AND(Y35>0,Z35=0),100%,IF(AND(Y35=0,Z35>0),0,IF(AND(Y35=0,Z35=0),"***",0)))) -> *** | AC35: =+IFERROR(VLOOKUP($A35,'Goals & Budget 2026'!$A$2:$EJ$49,11,FALSE),0) -> 0 | AD35: =IF(AND(AB35>0,AC35>0),AB35/AC35,IF(AND(AB35>0,AC35=0),100%,IF(AND(AB35=0,AC35>0),0,IF(AND(AB35=0,AC35=0),"***",0)))) -> *** | AF35: =+IFERROR(VLOOKUP($A35,'Goals & Budget 2026'!$A$2:$EJ$49,12,FALSE),0) -> 0 | AG35: =IF(AND(AE35>0,AF35>0),AE35/AF35,IF(AND(AE35>0,AF35=0),100%,IF(AND(AE35=0,AF35>0),0,IF(AND(AE35=0,AF35=0),"***",0)))) -> *** | AI35: =+IFERROR(VLOOKUP($A35,'Goals & Budget 2026'!$A$2:$EJ$49,13,FALSE),0) -> 0 | AJ35: =IF(AND(AH35>0,AI35>0),AH35/AI35,IF(AND(AH35>0,AI35=0),100%,IF(AND(AH35=0,AI35>0),0,IF(AND(AH35=0,AI35=0),"***",0)))) -> *** | AL35: =+IFERROR(VLOOKUP($A35,'Goals & Budget 2026'!$A$2:$EJ$49,14,FALSE),0) -> 0 | AM35: =IF(AND(AK35>0,AL35>0),AK35/AL35,IF(AND(AK35>0,AL35=0),100%,IF(AND(AK35=0,AL35>0),0,IF(AND(AK35=0,AL35=0),"***",0)))) -> *** | AO35: =+IFERROR(VLOOKUP($A35,'Goals & Budget 2026'!$A$2:$EJ$49,15,FALSE),0) -> 0 | AP35: =IF(AND(AN35>0,AO35>0),AN35/AO35,IF(AND(AN35>0,AO35=0),100%,IF(AND(AN35=0,AO35>0),0,IF(AND(AN35=0,AO35=0),"***",0)))) -> ***
A36: Eleven | B36: 1 | C36: 95 | D36: =+G36 -> 0 | E36: =+H36 -> 0 | F36: =IF(AND(D36>0,E36>0),D36/E36,IF(AND(D36>0,E36=0),100%,IF(AND(D36=0,E36>0),0,IF(AND(D36=0,E36=0),"***",0)))) -> *** | H36: =+IFERROR(VLOOKUP($A36,'Goals & Budget 2026'!$A$2:$EJ$49,4,FALSE),0) -> 0 | I36: =IF(AND(G36>0,H36>0),G36/H36,IF(AND(G36>0,H36=0),100%,IF(AND(G36=0,H36>0),0,IF(AND(G36=0,H36=0),"***",0)))) -> *** | K36: =+IFERROR(VLOOKUP($A36,'Goals & Budget 2026'!$A$2:$EJ$49,5,FALSE),0) -> 0 | L36: =IF(AND(J36>0,K36>0),J36/K36,IF(AND(J36>0,K36=0),100%,IF(AND(J36=0,K36>0),0,IF(AND(J36=0,K36=0),"***",0)))) -> *** | N36: =+IFERROR(VLOOKUP($A36,'Goals & Budget 2026'!$A$2:$EJ$49,6,FALSE),0) -> 0 | O36: =IF(AND(M36>0,N36>0),M36/N36,IF(AND(M36>0,N36=0),100%,IF(AND(M36=0,N36>0),0,IF(AND(M36=0,N36=0),"***",0)))) -> *** | Q36: =+IFERROR(VLOOKUP($A36,'Goals & Budget 2026'!$A$2:$EJ$49,7,FALSE),0) -> 0 | R36: =IF(AND(P36>0,Q36>0),P36/Q36,IF(AND(P36>0,Q36=0),100%,IF(AND(P36=0,Q36>0),0,IF(AND(P36=0,Q36=0),"***",0)))) -> *** | T36: =+IFERROR(VLOOKUP($A36,'Goals & Budget 2026'!$A$2:$EJ$49,8,FALSE),0) -> 0 | U36: =IF(AND(S36>0,T36>0),S36/T36,IF(AND(S36>0,T36=0),100%,IF(AND(S36=0,T36>0),0,IF(AND(S36=0,T36=0),"***",0)))) -> *** | W36: =+IFERROR(VLOOKUP($A36,'Goals & Budget 2026'!$A$2:$EJ$49,9,FALSE),0) -> 0 | X36: =IF(AND(V36>0,W36>0),V36/W36,IF(AND(V36>0,W36=0),100%,IF(AND(V36=0,W36>0),0,IF(AND(V36=0,W36=0),"***",0)))) -> *** | Z36: =+IFERROR(VLOOKUP($A36,'Goals & Budget 2026'!$A$2:$EJ$49,10,FALSE),0) -> 0 | AA36: =IF(AND(Y36>0,Z36>0),Y36/Z36,IF(AND(Y36>0,Z36=0),100%,IF(AND(Y36=0,Z36>0),0,IF(AND(Y36=0,Z36=0),"***",0)))) -> *** | AC36: =+IFERROR(VLOOKUP($A36,'Goals & Budget 2026'!$A$2:$EJ$49,11,FALSE),0) -> 0 | AD36: =IF(AND(AB36>0,AC36>0),AB36/AC36,IF(AND(AB36>0,AC36=0),100%,IF(AND(AB36=0,AC36>0),0,IF(AND(AB36=0,AC36=0),"***",0)))) -> *** | AF36: =+IFERROR(VLOOKUP($A36,'Goals & Budget 2026'!$A$2:$EJ$49,12,FALSE),0) -> 0 | AG36: =IF(AND(AE36>0,AF36>0),AE36/AF36,IF(AND(AE36>0,AF36=0),100%,IF(AND(AE36=0,AF36>0),0,IF(AND(AE36=0,AF36=0),"***",0)))) -> *** | AI36: =+IFERROR(VLOOKUP($A36,'Goals & Budget 2026'!$A$2:$EJ$49,13,FALSE),0) -> 0 | AJ36: =IF(AND(AH36>0,AI36>0),AH36/AI36,IF(AND(AH36>0,AI36=0),100%,IF(AND(AH36=0,AI36>0),0,IF(AND(AH36=0,AI36=0),"***",0)))) -> *** | AL36: =+IFERROR(VLOOKUP($A36,'Goals & Budget 2026'!$A$2:$EJ$49,14,FALSE),0) -> 0 | AM36: =IF(AND(AK36>0,AL36>0),AK36/AL36,IF(AND(AK36>0,AL36=0),100%,IF(AND(AK36=0,AL36>0),0,IF(AND(AK36=0,AL36=0),"***",0)))) -> *** | AO36: =+IFERROR(VLOOKUP($A36,'Goals & Budget 2026'!$A$2:$EJ$49,15,FALSE),0) -> 0 | AP36: =IF(AND(AN36>0,AO36>0),AN36/AO36,IF(AND(AN36>0,AO36=0),100%,IF(AND(AN36=0,AO36>0),0,IF(AND(AN36=0,AO36=0),"***",0)))) -> ***
A37: Clip Allotment | B37: 1 | C37: 1 | D37: =+G37 -> 0 | E37: =+H37 -> 0 | F37: =IF(AND(D37>0,E37>0),D37/E37,IF(AND(D37>0,E37=0),100%,IF(AND(D37=0,E37>0),0,IF(AND(D37=0,E37=0),"***",0)))) -> *** | H37: =+IFERROR(VLOOKUP($A37,'Goals & Budget 2026'!$A$2:$EJ$49,4,FALSE),0) -> 0 | I37: =IF(AND(G37>0,H37>0),G37/H37,IF(AND(G37>0,H37=0),100%,IF(AND(G37=0,H37>0),0,IF(AND(G37=0,H37=0),"***",0)))) -> *** | K37: =+IFERROR(VLOOKUP($A37,'Goals & Budget 2026'!$A$2:$EJ$49,5,FALSE),0) -> 0 | L37: =IF(AND(J37>0,K37>0),J37/K37,IF(AND(J37>0,K37=0),100%,IF(AND(J37=0,K37>0),0,IF(AND(J37=0,K37=0),"***",0)))) -> *** | N37: =+IFERROR(VLOOKUP($A37,'Goals & Budget 2026'!$A$2:$EJ$49,6,FALSE),0) -> 0 | O37: =IF(AND(M37>0,N37>0),M37/N37,IF(AND(M37>0,N37=0),100%,IF(AND(M37=0,N37>0),0,IF(AND(M37=0,N37=0),"***",0)))) -> *** | Q37: =+IFERROR(VLOOKUP($A37,'Goals & Budget 2026'!$A$2:$EJ$49,7,FALSE),0) -> 0 | R37: =IF(AND(P37>0,Q37>0),P37/Q37,IF(AND(P37>0,Q37=0),100%,IF(AND(P37=0,Q37>0),0,IF(AND(P37=0,Q37=0),"***",0)))) -> *** | T37: =+IFERROR(VLOOKUP($A37,'Goals & Budget 2026'!$A$2:$EJ$49,8,FALSE),0) -> 0 | U37: =IF(AND(S37>0,T37>0),S37/T37,IF(AND(S37>0,T37=0),100%,IF(AND(S37=0,T37>0),0,IF(AND(S37=0,T37=0),"***",0)))) -> *** | W37: =+IFERROR(VLOOKUP($A37,'Goals & Budget 2026'!$A$2:$EJ$49,9,FALSE),0) -> 0 | X37: =IF(AND(V37>0,W37>0),V37/W37,IF(AND(V37>0,W37=0),100%,IF(AND(V37=0,W37>0),0,IF(AND(V37=0,W37=0),"***",0)))) -> *** | Z37: =+IFERROR(VLOOKUP($A37,'Goals & Budget 2026'!$A$2:$EJ$49,10,FALSE),0) -> 0 | AA37: =IF(AND(Y37>0,Z37>0),Y37/Z37,IF(AND(Y37>0,Z37=0),100%,IF(AND(Y37=0,Z37>0),0,IF(AND(Y37=0,Z37=0),"***",0)))) -> *** | AC37: =+IFERROR(VLOOKUP($A37,'Goals & Budget 2026'!$A$2:$EJ$49,11,FALSE),0) -> 0 | AD37: =IF(AND(AB37>0,AC37>0),AB37/AC37,IF(AND(AB37>0,AC37=0),100%,IF(AND(AB37=0,AC37>0),0,IF(AND(AB37=0,AC37=0),"***",0)))) -> *** | AF37: =+IFERROR(VLOOKUP($A37,'Goals & Budget 2026'!$A$2:$EJ$49,12,FALSE),0) -> 0 | AG37: =IF(AND(AE37>0,AF37>0),AE37/AF37,IF(AND(AE37>0,AF37=0),100%,IF(AND(AE37=0,AF37>0),0,IF(AND(AE37=0,AF37=0),"***",0)))) -> *** | AI37: =+IFERROR(VLOOKUP($A37,'Goals & Budget 2026'!$A$2:$EJ$49,13,FALSE),0) -> 0 | AJ37: =IF(AND(AH37>0,AI37>0),AH37/AI37,IF(AND(AH37>0,AI37=0),100%,IF(AND(AH37=0,AI37>0),0,IF(AND(AH37=0,AI37=0),"***",0)))) -> *** | AL37: =+IFERROR(VLOOKUP($A37,'Goals & Budget 2026'!$A$2:$EJ$49,14,FALSE),0) -> 0 | AM37: =IF(AND(AK37>0,AL37>0),AK37/AL37,IF(AND(AK37>0,AL37=0),100%,IF(AND(AK37=0,AL37>0),0,IF(AND(AK37=0,AL37=0),"***",0)))) -> *** | AO37: =+IFERROR(VLOOKUP($A37,'Goals & Budget 2026'!$A$2:$EJ$49,15,FALSE),0) -> 0 | AP37: =IF(AND(AN37>0,AO37>0),AN37/AO37,IF(AND(AN37>0,AO37=0),100%,IF(AND(AN37=0,AO37>0),0,IF(AND(AN37=0,AO37=0),"***",0)))) -> ***
A38: Clip Stage A | B38: 1 | C38: 83 | D38: =+G38 -> 0 | E38: =+H38 -> 0 | F38: =IF(AND(D38>0,E38>0),D38/E38,IF(AND(D38>0,E38=0),100%,IF(AND(D38=0,E38>0),0,IF(AND(D38=0,E38=0),"***",0)))) -> *** | H38: =+IFERROR(VLOOKUP($A38,'Goals & Budget 2026'!$A$2:$EJ$49,4,FALSE),0) -> 0 | I38: =IF(AND(G38>0,H38>0),G38/H38,IF(AND(G38>0,H38=0),100%,IF(AND(G38=0,H38>0),0,IF(AND(G38=0,H38=0),"***",0)))) -> *** | K38: =+IFERROR(VLOOKUP($A38,'Goals & Budget 2026'!$A$2:$EJ$49,5,FALSE),0) -> 0 | L38: =IF(AND(J38>0,K38>0),J38/K38,IF(AND(J38>0,K38=0),100%,IF(AND(J38=0,K38>0),0,IF(AND(J38=0,K38=0),"***",0)))) -> *** | N38: =+IFERROR(VLOOKUP($A38,'Goals & Budget 2026'!$A$2:$EJ$49,6,FALSE),0) -> 0 | O38: =IF(AND(M38>0,N38>0),M38/N38,IF(AND(M38>0,N38=0),100%,IF(AND(M38=0,N38>0),0,IF(AND(M38=0,N38=0),"***",0)))) -> *** | Q38: =+IFERROR(VLOOKUP($A38,'Goals & Budget 2026'!$A$2:$EJ$49,7,FALSE),0) -> 0 | R38: =IF(AND(P38>0,Q38>0),P38/Q38,IF(AND(P38>0,Q38=0),100%,IF(AND(P38=0,Q38>0),0,IF(AND(P38=0,Q38=0),"***",0)))) -> *** | T38: =+IFERROR(VLOOKUP($A38,'Goals & Budget 2026'!$A$2:$EJ$49,8,FALSE),0) -> 0 | U38: =IF(AND(S38>0,T38>0),S38/T38,IF(AND(S38>0,T38=0),100%,IF(AND(S38=0,T38>0),0,IF(AND(S38=0,T38=0),"***",0)))) -> *** | W38: =+IFERROR(VLOOKUP($A38,'Goals & Budget 2026'!$A$2:$EJ$49,9,FALSE),0) -> 0 | X38: =IF(AND(V38>0,W38>0),V38/W38,IF(AND(V38>0,W38=0),100%,IF(AND(V38=0,W38>0),0,IF(AND(V38=0,W38=0),"***",0)))) -> *** | Z38: =+IFERROR(VLOOKUP($A38,'Goals & Budget 2026'!$A$2:$EJ$49,10,FALSE),0) -> 0 | AA38: =IF(AND(Y38>0,Z38>0),Y38/Z38,IF(AND(Y38>0,Z38=0),100%,IF(AND(Y38=0,Z38>0),0,IF(AND(Y38=0,Z38=0),"***",0)))) -> *** | AC38: =+IFERROR(VLOOKUP($A38,'Goals & Budget 2026'!$A$2:$EJ$49,11,FALSE),0) -> 0 | AD38: =IF(AND(AB38>0,AC38>0),AB38/AC38,IF(AND(AB38>0,AC38=0),100%,IF(AND(AB38=0,AC38>0),0,IF(AND(AB38=0,AC38=0),"***",0)))) -> *** | AF38: =+IFERROR(VLOOKUP($A38,'Goals & Budget 2026'!$A$2:$EJ$49,12,FALSE),0) -> 0 | AG38: =IF(AND(AE38>0,AF38>0),AE38/AF38,IF(AND(AE38>0,AF38=0),100%,IF(AND(AE38=0,AF38>0),0,IF(AND(AE38=0,AF38=0),"***",0)))) -> *** | AI38: =+IFERROR(VLOOKUP($A38,'Goals & Budget 2026'!$A$2:$EJ$49,13,FALSE),0) -> 0 | AJ38: =IF(AND(AH38>0,AI38>0),AH38/AI38,IF(AND(AH38>0,AI38=0),100%,IF(AND(AH38=0,AI38>0),0,IF(AND(AH38=0,AI38=0),"***",0)))) -> *** | AL38: =+IFERROR(VLOOKUP($A38,'Goals & Budget 2026'!$A$2:$EJ$49,14,FALSE),0) -> 0 | AM38: =IF(AND(AK38>0,AL38>0),AK38/AL38,IF(AND(AK38>0,AL38=0),100%,IF(AND(AK38=0,AL38>0),0,IF(AND(AK38=0,AL38=0),"***",0)))) -> *** | AO38: =+IFERROR(VLOOKUP($A38,'Goals & Budget 2026'!$A$2:$EJ$49,15,FALSE),0) -> 0 | AP38: =IF(AND(AN38>0,AO38>0),AN38/AO38,IF(AND(AN38>0,AO38=0),100%,IF(AND(AN38=0,AO38>0),0,IF(AND(AN38=0,AO38=0),"***",0)))) -> ***
A39: Clip Stage B | B39: 1 | C39: 180 | D39: =+G39 -> 0 | E39: =+H39 -> 0 | F39: =IF(AND(D39>0,E39>0),D39/E39,IF(AND(D39>0,E39=0),100%,IF(AND(D39=0,E39>0),0,IF(AND(D39=0,E39=0),"***",0)))) -> *** | H39: =+IFERROR(VLOOKUP($A39,'Goals & Budget 2026'!$A$2:$EJ$49,4,FALSE),0) -> 0 | I39: =IF(AND(G39>0,H39>0),G39/H39,IF(AND(G39>0,H39=0),100%,IF(AND(G39=0,H39>0),0,IF(AND(G39=0,H39=0),"***",0)))) -> *** | K39: =+IFERROR(VLOOKUP($A39,'Goals & Budget 2026'!$A$2:$EJ$49,5,FALSE),0) -> 0 | L39: =IF(AND(J39>0,K39>0),J39/K39,IF(AND(J39>0,K39=0),100%,IF(AND(J39=0,K39>0),0,IF(AND(J39=0,K39=0),"***",0)))) -> *** | N39: =+IFERROR(VLOOKUP($A39,'Goals & Budget 2026'!$A$2:$EJ$49,6,FALSE),0) -> 0 | O39: =IF(AND(M39>0,N39>0),M39/N39,IF(AND(M39>0,N39=0),100%,IF(AND(M39=0,N39>0),0,IF(AND(M39=0,N39=0),"***",0)))) -> *** | Q39: =+IFERROR(VLOOKUP($A39,'Goals & Budget 2026'!$A$2:$EJ$49,7,FALSE),0) -> 0 | R39: =IF(AND(P39>0,Q39>0),P39/Q39,IF(AND(P39>0,Q39=0),100%,IF(AND(P39=0,Q39>0),0,IF(AND(P39=0,Q39=0),"***",0)))) -> *** | T39: =+IFERROR(VLOOKUP($A39,'Goals & Budget 2026'!$A$2:$EJ$49,8,FALSE),0) -> 0 | U39: =IF(AND(S39>0,T39>0),S39/T39,IF(AND(S39>0,T39=0),100%,IF(AND(S39=0,T39>0),0,IF(AND(S39=0,T39=0),"***",0)))) -> *** | W39: =+IFERROR(VLOOKUP($A39,'Goals & Budget 2026'!$A$2:$EJ$49,9,FALSE),0) -> 0 | X39: =IF(AND(V39>0,W39>0),V39/W39,IF(AND(V39>0,W39=0),100%,IF(AND(V39=0,W39>0),0,IF(AND(V39=0,W39=0),"***",0)))) -> *** | Z39: =+IFERROR(VLOOKUP($A39,'Goals & Budget 2026'!$A$2:$EJ$49,10,FALSE),0) -> 0 | AA39: =IF(AND(Y39>0,Z39>0),Y39/Z39,IF(AND(Y39>0,Z39=0),100%,IF(AND(Y39=0,Z39>0),0,IF(AND(Y39=0,Z39=0),"***",0)))) -> *** | AC39: =+IFERROR(VLOOKUP($A39,'Goals & Budget 2026'!$A$2:$EJ$49,11,FALSE),0) -> 0 | AD39: =IF(AND(AB39>0,AC39>0),AB39/AC39,IF(AND(AB39>0,AC39=0),100%,IF(AND(AB39=0,AC39>0),0,IF(AND(AB39=0,AC39=0),"***",0)))) -> *** | AF39: =+IFERROR(VLOOKUP($A39,'Goals & Budget 2026'!$A$2:$EJ$49,12,FALSE),0) -> 0 | AG39: =IF(AND(AE39>0,AF39>0),AE39/AF39,IF(AND(AE39>0,AF39=0),100%,IF(AND(AE39=0,AF39>0),0,IF(AND(AE39=0,AF39=0),"***",0)))) -> *** | AI39: =+IFERROR(VLOOKUP($A39,'Goals & Budget 2026'!$A$2:$EJ$49,13,FALSE),0) -> 0 | AJ39: =IF(AND(AH39>0,AI39>0),AH39/AI39,IF(AND(AH39>0,AI39=0),100%,IF(AND(AH39=0,AI39>0),0,IF(AND(AH39=0,AI39=0),"***",0)))) -> *** | AL39: =+IFERROR(VLOOKUP($A39,'Goals & Budget 2026'!$A$2:$EJ$49,14,FALSE),0) -> 0 | AM39: =IF(AND(AK39>0,AL39>0),AK39/AL39,IF(AND(AK39>0,AL39=0),100%,IF(AND(AK39=0,AL39>0),0,IF(AND(AK39=0,AL39=0),"***",0)))) -> *** | AO39: =+IFERROR(VLOOKUP($A39,'Goals & Budget 2026'!$A$2:$EJ$49,15,FALSE),0) -> 0 | AP39: =IF(AND(AN39>0,AO39>0),AN39/AO39,IF(AND(AN39>0,AO39=0),100%,IF(AND(AN39=0,AO39>0),0,IF(AND(AN39=0,AO39=0),"***",0)))) -> ***
A40: TUMAIA II - Allotment | B40: 1 | C40: 1 | D40: =+G40 -> 0 | E40: =+H40 -> 0 | F40: =IF(AND(D40>0,E40>0),D40/E40,IF(AND(D40>0,E40=0),100%,IF(AND(D40=0,E40>0),0,IF(AND(D40=0,E40=0),"***",0)))) -> *** | H40: =+IFERROR(VLOOKUP($A40,'Goals & Budget 2026'!$A$2:$EJ$49,4,FALSE),0) -> 0 | I40: =IF(AND(G40>0,H40>0),G40/H40,IF(AND(G40>0,H40=0),100%,IF(AND(G40=0,H40>0),0,IF(AND(G40=0,H40=0),"***",0)))) -> *** | K40: =+IFERROR(VLOOKUP($A40,'Goals & Budget 2026'!$A$2:$EJ$49,5,FALSE),0) -> 0 | L40: =IF(AND(J40>0,K40>0),J40/K40,IF(AND(J40>0,K40=0),100%,IF(AND(J40=0,K40>0),0,IF(AND(J40=0,K40=0),"***",0)))) -> *** | N40: =+IFERROR(VLOOKUP($A40,'Goals & Budget 2026'!$A$2:$EJ$49,6,FALSE),0) -> 0 | O40: =IF(AND(M40>0,N40>0),M40/N40,IF(AND(M40>0,N40=0),100%,IF(AND(M40=0,N40>0),0,IF(AND(M40=0,N40=0),"***",0)))) -> *** | Q40: =+IFERROR(VLOOKUP($A40,'Goals & Budget 2026'!$A$2:$EJ$49,7,FALSE),0) -> 0 | R40: =IF(AND(P40>0,Q40>0),P40/Q40,IF(AND(P40>0,Q40=0),100%,IF(AND(P40=0,Q40>0),0,IF(AND(P40=0,Q40=0),"***",0)))) -> *** | T40: =+IFERROR(VLOOKUP($A40,'Goals & Budget 2026'!$A$2:$EJ$49,8,FALSE),0) -> 0 | U40: =IF(AND(S40>0,T40>0),S40/T40,IF(AND(S40>0,T40=0),100%,IF(AND(S40=0,T40>0),0,IF(AND(S40=0,T40=0),"***",0)))) -> *** | W40: =+IFERROR(VLOOKUP($A40,'Goals & Budget 2026'!$A$2:$EJ$49,9,FALSE),0) -> 0 | X40: =IF(AND(V40>0,W40>0),V40/W40,IF(AND(V40>0,W40=0),100%,IF(AND(V40=0,W40>0),0,IF(AND(V40=0,W40=0),"***",0)))) -> *** | Z40: =+IFERROR(VLOOKUP($A40,'Goals & Budget 2026'!$A$2:$EJ$49,10,FALSE),0) -> 0 | AA40: =IF(AND(Y40>0,Z40>0),Y40/Z40,IF(AND(Y40>0,Z40=0),100%,IF(AND(Y40=0,Z40>0),0,IF(AND(Y40=0,Z40=0),"***",0)))) -> *** | AC40: =+IFERROR(VLOOKUP($A40,'Goals & Budget 2026'!$A$2:$EJ$49,11,FALSE),0) -> 0 | AD40: =IF(AND(AB40>0,AC40>0),AB40/AC40,IF(AND(AB40>0,AC40=0),100%,IF(AND(AB40=0,AC40>0),0,IF(AND(AB40=0,AC40=0),"***",0)))) -> *** | AF40: =+IFERROR(VLOOKUP($A40,'Goals & Budget 2026'!$A$2:$EJ$49,12,FALSE),0) -> 0 | AG40: =IF(AND(AE40>0,AF40>0),AE40/AF40,IF(AND(AE40>0,AF40=0),100%,IF(AND(AE40=0,AF40>0),0,IF(AND(AE40=0,AF40=0),"***",0)))) -> *** | AI40: =+IFERROR(VLOOKUP($A40,'Goals & Budget 2026'!$A$2:$EJ$49,13,FALSE),0) -> 0 | AJ40: =IF(AND(AH40>0,AI40>0),AH40/AI40,IF(AND(AH40>0,AI40=0),100%,IF(AND(AH40=0,AI40>0),0,IF(AND(AH40=0,AI40=0),"***",0)))) -> *** | AL40: =+IFERROR(VLOOKUP($A40,'Goals & Budget 2026'!$A$2:$EJ$49,14,FALSE),0) -> 0 | AM40: =IF(AND(AK40>0,AL40>0),AK40/AL40,IF(AND(AK40>0,AL40=0),100%,IF(AND(AK40=0,AL40>0),0,IF(AND(AK40=0,AL40=0),"***",0)))) -> *** | AO40: =+IFERROR(VLOOKUP($A40,'Goals & Budget 2026'!$A$2:$EJ$49,15,FALSE),0) -> 0 | AP40: =IF(AND(AN40>0,AO40>0),AN40/AO40,IF(AND(AN40>0,AO40=0),100%,IF(AND(AN40=0,AO40>0),0,IF(AND(AN40=0,AO40=0),"***",0)))) -> ***
A41: TUMAIA II - A | B41: 1 | C41: 133 | D41: =+G41 -> 0 | E41: =+H41 -> 0 | F41: =IF(AND(D41>0,E41>0),D41/E41,IF(AND(D41>0,E41=0),100%,IF(AND(D41=0,E41>0),0,IF(AND(D41=0,E41=0),"***",0)))) -> *** | H41: =+IFERROR(VLOOKUP($A41,'Goals & Budget 2026'!$A$2:$EJ$49,4,FALSE),0) -> 0 | I41: =IF(AND(G41>0,H41>0),G41/H41,IF(AND(G41>0,H41=0),100%,IF(AND(G41=0,H41>0),0,IF(AND(G41=0,H41=0),"***",0)))) -> *** | K41: =+IFERROR(VLOOKUP($A41,'Goals & Budget 2026'!$A$2:$EJ$49,5,FALSE),0) -> 0 | L41: =IF(AND(J41>0,K41>0),J41/K41,IF(AND(J41>0,K41=0),100%,IF(AND(J41=0,K41>0),0,IF(AND(J41=0,K41=0),"***",0)))) -> *** | N41: =+IFERROR(VLOOKUP($A41,'Goals & Budget 2026'!$A$2:$EJ$49,6,FALSE),0) -> 0 | O41: =IF(AND(M41>0,N41>0),M41/N41,IF(AND(M41>0,N41=0),100%,IF(AND(M41=0,N41>0),0,IF(AND(M41=0,N41=0),"***",0)))) -> *** | Q41: =+IFERROR(VLOOKUP($A41,'Goals & Budget 2026'!$A$2:$EJ$49,7,FALSE),0) -> 0 | R41: =IF(AND(P41>0,Q41>0),P41/Q41,IF(AND(P41>0,Q41=0),100%,IF(AND(P41=0,Q41>0),0,IF(AND(P41=0,Q41=0),"***",0)))) -> *** | T41: =+IFERROR(VLOOKUP($A41,'Goals & Budget 2026'!$A$2:$EJ$49,8,FALSE),0) -> 0 | U41: =IF(AND(S41>0,T41>0),S41/T41,IF(AND(S41>0,T41=0),100%,IF(AND(S41=0,T41>0),0,IF(AND(S41=0,T41=0),"***",0)))) -> *** | W41: =+IFERROR(VLOOKUP($A41,'Goals & Budget 2026'!$A$2:$EJ$49,9,FALSE),0) -> 0 | X41: =IF(AND(V41>0,W41>0),V41/W41,IF(AND(V41>0,W41=0),100%,IF(AND(V41=0,W41>0),0,IF(AND(V41=0,W41=0),"***",0)))) -> *** | Z41: =+IFERROR(VLOOKUP($A41,'Goals & Budget 2026'!$A$2:$EJ$49,10,FALSE),0) -> 0 | AA41: =IF(AND(Y41>0,Z41>0),Y41/Z41,IF(AND(Y41>0,Z41=0),100%,IF(AND(Y41=0,Z41>0),0,IF(AND(Y41=0,Z41=0),"***",0)))) -> *** | AC41: =+IFERROR(VLOOKUP($A41,'Goals & Budget 2026'!$A$2:$EJ$49,11,FALSE),0) -> 0 | AD41: =IF(AND(AB41>0,AC41>0),AB41/AC41,IF(AND(AB41>0,AC41=0),100%,IF(AND(AB41=0,AC41>0),0,IF(AND(AB41=0,AC41=0),"***",0)))) -> *** | AF41: =+IFERROR(VLOOKUP($A41,'Goals & Budget 2026'!$A$2:$EJ$49,12,FALSE),0) -> 0 | AG41: =IF(AND(AE41>0,AF41>0),AE41/AF41,IF(AND(AE41>0,AF41=0),100%,IF(AND(AE41=0,AF41>0),0,IF(AND(AE41=0,AF41=0),"***",0)))) -> *** | AI41: =+IFERROR(VLOOKUP($A41,'Goals & Budget 2026'!$A$2:$EJ$49,13,FALSE),0) -> 0 | AJ41: =IF(AND(AH41>0,AI41>0),AH41/AI41,IF(AND(AH41>0,AI41=0),100%,IF(AND(AH41=0,AI41>0),0,IF(AND(AH41=0,AI41=0),"***",0)))) -> *** | AL41: =+IFERROR(VLOOKUP($A41,'Goals & Budget 2026'!$A$2:$EJ$49,14,FALSE),0) -> 0 | AM41: =IF(AND(AK41>0,AL41>0),AK41/AL41,IF(AND(AK41>0,AL41=0),100%,IF(AND(AK41=0,AL41>0),0,IF(AND(AK41=0,AL41=0),"***",0)))) -> *** | AO41: =+IFERROR(VLOOKUP($A41,'Goals & Budget 2026'!$A$2:$EJ$49,15,FALSE),0) -> 0 | AP41: =IF(AND(AN41>0,AO41>0),AN41/AO41,IF(AND(AN41>0,AO41=0),100%,IF(AND(AN41=0,AO41>0),0,IF(AND(AN41=0,AO41=0),"***",0)))) -> ***
A42: TUMAIA II - B | B42: 1 | C42: 132 | D42: =+G42 -> 0 | E42: =+H42 -> 0 | F42: =IF(AND(D42>0,E42>0),D42/E42,IF(AND(D42>0,E42=0),100%,IF(AND(D42=0,E42>0),0,IF(AND(D42=0,E42=0),"***",0)))) -> *** | H42: =+IFERROR(VLOOKUP($A42,'Goals & Budget 2026'!$A$2:$EJ$49,4,FALSE),0) -> 0 | I42: =IF(AND(G42>0,H42>0),G42/H42,IF(AND(G42>0,H42=0),100%,IF(AND(G42=0,H42>0),0,IF(AND(G42=0,H42=0),"***",0)))) -> *** | K42: =+IFERROR(VLOOKUP($A42,'Goals & Budget 2026'!$A$2:$EJ$49,5,FALSE),0) -> 0 | L42: =IF(AND(J42>0,K42>0),J42/K42,IF(AND(J42>0,K42=0),100%,IF(AND(J42=0,K42>0),0,IF(AND(J42=0,K42=0),"***",0)))) -> *** | N42: =+IFERROR(VLOOKUP($A42,'Goals & Budget 2026'!$A$2:$EJ$49,6,FALSE),0) -> 0 | O42: =IF(AND(M42>0,N42>0),M42/N42,IF(AND(M42>0,N42=0),100%,IF(AND(M42=0,N42>0),0,IF(AND(M42=0,N42=0),"***",0)))) -> *** | Q42: =+IFERROR(VLOOKUP($A42,'Goals & Budget 2026'!$A$2:$EJ$49,7,FALSE),0) -> 0 | R42: =IF(AND(P42>0,Q42>0),P42/Q42,IF(AND(P42>0,Q42=0),100%,IF(AND(P42=0,Q42>0),0,IF(AND(P42=0,Q42=0),"***",0)))) -> *** | T42: =+IFERROR(VLOOKUP($A42,'Goals & Budget 2026'!$A$2:$EJ$49,8,FALSE),0) -> 0 | U42: =IF(AND(S42>0,T42>0),S42/T42,IF(AND(S42>0,T42=0),100%,IF(AND(S42=0,T42>0),0,IF(AND(S42=0,T42=0),"***",0)))) -> *** | W42: =+IFERROR(VLOOKUP($A42,'Goals & Budget 2026'!$A$2:$EJ$49,9,FALSE),0) -> 0 | X42: =IF(AND(V42>0,W42>0),V42/W42,IF(AND(V42>0,W42=0),100%,IF(AND(V42=0,W42>0),0,IF(AND(V42=0,W42=0),"***",0)))) -> *** | Z42: =+IFERROR(VLOOKUP($A42,'Goals & Budget 2026'!$A$2:$EJ$49,10,FALSE),0) -> 0 | AA42: =IF(AND(Y42>0,Z42>0),Y42/Z42,IF(AND(Y42>0,Z42=0),100%,IF(AND(Y42=0,Z42>0),0,IF(AND(Y42=0,Z42=0),"***",0)))) -> *** | AC42: =+IFERROR(VLOOKUP($A42,'Goals & Budget 2026'!$A$2:$EJ$49,11,FALSE),0) -> 0 | AD42: =IF(AND(AB42>0,AC42>0),AB42/AC42,IF(AND(AB42>0,AC42=0),100%,IF(AND(AB42=0,AC42>0),0,IF(AND(AB42=0,AC42=0),"***",0)))) -> *** | AF42: =+IFERROR(VLOOKUP($A42,'Goals & Budget 2026'!$A$2:$EJ$49,12,FALSE),0) -> 0 | AG42: =IF(AND(AE42>0,AF42>0),AE42/AF42,IF(AND(AE42>0,AF42=0),100%,IF(AND(AE42=0,AF42>0),0,IF(AND(AE42=0,AF42=0),"***",0)))) -> *** | AI42: =+IFERROR(VLOOKUP($A42,'Goals & Budget 2026'!$A$2:$EJ$49,13,FALSE),0) -> 0 | AJ42: =IF(AND(AH42>0,AI42>0),AH42/AI42,IF(AND(AH42>0,AI42=0),100%,IF(AND(AH42=0,AI42>0),0,IF(AND(AH42=0,AI42=0),"***",0)))) -> *** | AL42: =+IFERROR(VLOOKUP($A42,'Goals & Budget 2026'!$A$2:$EJ$49,14,FALSE),0) -> 0 | AM42: =IF(AND(AK42>0,AL42>0),AK42/AL42,IF(AND(AK42>0,AL42=0),100%,IF(AND(AK42=0,AL42>0),0,IF(AND(AK42=0,AL42=0),"***",0)))) -> *** | AO42: =+IFERROR(VLOOKUP($A42,'Goals & Budget 2026'!$A$2:$EJ$49,15,FALSE),0) -> 0 | AP42: =IF(AND(AN42>0,AO42>0),AN42/AO42,IF(AND(AN42>0,AO42=0),100%,IF(AND(AN42=0,AO42>0),0,IF(AND(AN42=0,AO42=0),"***",0)))) -> ***
... A47: Setúbal Alentejo | B47: 1 | C47: 378 | D47: =+G47 -> 0 | E47: =+H47 -> 0 | F47: =IF(AND(D47>0,E47>0),D47/E47,IF(AND(D47>0,E47=0),100%,IF(AND(D47=0,E47>0),0,IF(AND(D47=0,E47=0),"***",0)))) -> *** | H47: =+IFERROR(VLOOKUP($A47,'Goals & Budget 2026'!$A$2:$EJ$49,4,FALSE),0) -> 0 | I47: =IF(AND(G47>0,H47>0),G47/H47,IF(AND(G47>0,H47=0),100%,IF(AND(G47=0,H47>0),0,IF(AND(G47=0,H47=0),"***",0)))) -> *** | K47: =+IFERROR(VLOOKUP($A47,'Goals & Budget 2026'!$A$2:$EJ$49,5,FALSE),0) -> 0 | L47: =IF(AND(J47>0,K47>0),J47/K47,IF(AND(J47>0,K47=0),100%,IF(AND(J47=0,K47>0),0,IF(AND(J47=0,K47=0),"***",0)))) -> *** | N47: =+IFERROR(VLOOKUP($A47,'Goals & Budget 2026'!$A$2:$EJ$49,6,FALSE),0) -> 0 | O47: =IF(AND(M47>0,N47>0),M47/N47,IF(AND(M47>0,N47=0),100%,IF(AND(M47=0,N47>0),0,IF(AND(M47=0,N47=0),"***",0)))) -> *** | Q47: =+IFERROR(VLOOKUP($A47,'Goals & Budget 2026'!$A$2:$EJ$49,7,FALSE),0) -> 0 | R47: =IF(AND(P47>0,Q47>0),P47/Q47,IF(AND(P47>0,Q47=0),100%,IF(AND(P47=0,Q47>0),0,IF(AND(P47=0,Q47=0),"***",0)))) -> *** | T47: =+IFERROR(VLOOKUP($A47,'Goals & Budget 2026'!$A$2:$EJ$49,8,FALSE),0) -> 0 | U47: =IF(AND(S47>0,T47>0),S47/T47,IF(AND(S47>0,T47=0),100%,IF(AND(S47=0,T47>0),0,IF(AND(S47=0,T47=0),"***",0)))) -> *** | W47: =+IFERROR(VLOOKUP($A47,'Goals & Budget 2026'!$A$2:$EJ$49,9,FALSE),0) -> 0 | X47: =IF(AND(V47>0,W47>0),V47/W47,IF(AND(V47>0,W47=0),100%,IF(AND(V47=0,W47>0),0,IF(AND(V47=0,W47=0),"***",0)))) -> *** | Z47: =+IFERROR(VLOOKUP($A47,'Goals & Budget 2026'!$A$2:$EJ$49,10,FALSE),0) -> 0 | AA47: =IF(AND(Y47>0,Z47>0),Y47/Z47,IF(AND(Y47>0,Z47=0),100%,IF(AND(Y47=0,Z47>0),0,IF(AND(Y47=0,Z47=0),"***",0)))) -> *** | AC47: =+IFERROR(VLOOKUP($A47,'Goals & Budget 2026'!$A$2:$EJ$49,11,FALSE),0) -> 0 | AD47: =IF(AND(AB47>0,AC47>0),AB47/AC47,IF(AND(AB47>0,AC47=0),100%,IF(AND(AB47=0,AC47>0),0,IF(AND(AB47=0,AC47=0),"***",0)))) -> *** | AF47: =+IFERROR(VLOOKUP($A47,'Goals & Budget 2026'!$A$2:$EJ$49,12,FALSE),0) -> 0 | AG47: =IF(AND(AE47>0,AF47>0),AE47/AF47,IF(AND(AE47>0,AF47=0),100%,IF(AND(AE47=0,AF47>0),0,IF(AND(AE47=0,AF47=0),"***",0)))) -> *** | AI47: =+IFERROR(VLOOKUP($A47,'Goals & Budget 2026'!$A$2:$EJ$49,13,FALSE),0) -> 0 | AJ47: =IF(AND(AH47>0,AI47>0),AH47/AI47,IF(AND(AH47>0,AI47=0),100%,IF(AND(AH47=0,AI47>0),0,IF(AND(AH47=0,AI47=0),"***",0)))) -> *** | AL47: =+IFERROR(VLOOKUP($A47,'Goals & Budget 2026'!$A$2:$EJ$49,14,FALSE),0) -> 0 | AM47: =IF(AND(AK47>0,AL47>0),AK47/AL47,IF(AND(AK47>0,AL47=0),100%,IF(AND(AK47=0,AL47>0),0,IF(AND(AK47=0,AL47=0),"***",0)))) -> *** | AO47: =+IFERROR(VLOOKUP($A47,'Goals & Budget 2026'!$A$2:$EJ$49,15,FALSE),0) -> 0 | AP47: =IF(AND(AN47>0,AO47>0),AN47/AO47,IF(AND(AN47>0,AO47=0),100%,IF(AND(AN47=0,AO47>0),0,IF(AND(AN47=0,AO47=0),"***",0)))) -> ***
A48: Total | D48: =+SUM(D3:D47) -> 0 | E48: =+SUM(E3:E47) -> 0 | F48: =IF(AND(D48>0,E48>0),D48/E48,IF(AND(D48>0,E48=0),100%,IF(AND(D48=0,E48>0),0,IF(AND(D48=0,E48=0),"***",0)))) -> *** | G48: =+SUM(G3:G47) -> 0 | H48: =+SUM(H3:H47) -> 0 | I48: =IF(AND(G48>0,H48>0),G48/H48,IF(AND(G48>0,H48=0),100%,IF(AND(G48=0,H48>0),0,IF(AND(G48=0,H48=0),"***",0)))) -> *** | J48: =+SUM(J3:J47) -> 0 | K48: =+SUM(K3:K47) -> 0 | L48: =IF(AND(J48>0,K48>0),J48/K48,IF(AND(J48>0,K48=0),100%,IF(AND(J48=0,K48>0),0,IF(AND(J48=0,K48=0),"***",0)))) -> *** | M48: =+SUM(M3:M47) -> 0 | N48: =+SUM(N3:N47) -> 0 | O48: =IF(AND(M48>0,N48>0),M48/N48,IF(AND(M48>0,N48=0),100%,IF(AND(M48=0,N48>0),0,IF(AND(M48=0,N48=0),"***",0)))) -> *** | P48: =+SUM(P3:P47) -> 0 | Q48: =+SUM(Q3:Q47) -> 0 | R48: =IF(AND(P48>0,Q48>0),P48/Q48,IF(AND(P48>0,Q48=0),100%,IF(AND(P48=0,Q48>0),0,IF(AND(P48=0,Q48=0),"***",0)))) -> *** | S48: =+SUM(S3:S47) -> 0 | T48: =+SUM(T3:T47) -> 0 | U48: =IF(AND(S48>0,T48>0),S48/T48,IF(AND(S48>0,T48=0),100%,IF(AND(S48=0,T48>0),0,IF(AND(S48=0,T48=0),"***",0)))) -> *** | V48: =+SUM(V3:V47) -> 0 | W48: =+SUM(W3:W47) -> 0 | X48: =IF(AND(V48>0,W48>0),V48/W48,IF(AND(V48>0,W48=0),100%,IF(AND(V48=0,W48>0),0,IF(AND(V48=0,W48=0),"***",0)))) -> *** | Y48: =+SUM(Y3:Y47) -> 0 | Z48: =+SUM(Z3:Z47) -> 0 | AA48: =IF(AND(Y48>0,Z48>0),Y48/Z48,IF(AND(Y48>0,Z48=0),100%,IF(AND(Y48=0,Z48>0),0,IF(AND(Y48=0,Z48=0),"***",0)))) -> *** | AB48: =+SUM(AB3:AB47) -> 0 | AC48: =+SUM(AC3:AC47) -> 0 | AD48: =IF(AND(AB48>0,AC48>0),AB48/AC48,IF(AND(AB48>0,AC48=0),100%,IF(AND(AB48=0,AC48>0),0,IF(AND(AB48=0,AC48=0),"***",0)))) -> *** | AE48: =+SUM(AE3:AE47) -> 0 | AF48: =+SUM(AF3:AF47) -> 0 | AG48: =IF(AND(AE48>0,AF48>0),AE48/AF48,IF(AND(AE48>0,AF48=0),100%,IF(AND(AE48=0,AF48>0),0,IF(AND(AE48=0,AF48=0),"***",0)))) -> *** | AH48: =+SUM(AH3:AH47) -> 0 | AI48: =+SUM(AI3:AI47) -> 0 | AJ48: =IF(AND(AH48>0,AI48>0),AH48/AI48,IF(AND(AH48>0,AI48=0),100%,IF(AND(AH48=0,AI48>0),0,IF(AND(AH48=0,AI48=0),"***",0)))) -> *** | AK48: =+SUM(AK3:AK47) -> 0 | AL48: =+SUM(AL3:AL47) -> 0 | AM48: =IF(AND(AK48>0,AL48>0),AK48/AL48,IF(AND(AK48>0,AL48=0),100%,IF(AND(AK48=0,AL48>0),0,IF(AND(AK48=0,AL48=0),"***",0)))) -> *** | AN48: =+SUM(AN3:AN47) -> 0 | AO48: =+SUM(AO3:AO47) -> 0 | AP48: =IF(AND(AN48>0,AO48>0),AN48/AO48,IF(AND(AN48>0,AO48=0),100%,IF(AND(AN48=0,AO48>0),0,IF(AND(AN48=0,AO48=0),"***",0)))) -> ***
A49: Total (TU%) | D49: =+SUMPRODUCT(D3:D47,$B$3:$B$47) -> 0 | E49: =+SUMPRODUCT(E3:E47,$B$3:$B$47) -> 0 | F49: =IF(AND(D49>0,E49>0),D49/E49,IF(AND(D49>0,E49=0),100%,IF(AND(D49=0,E49>0),0,IF(AND(D49=0,E49=0),"***",0)))) -> *** | G49: =+SUMPRODUCT(G3:G47,$B$3:$B$47) -> 0 | H49: =+SUMPRODUCT(H3:H47,$B$3:$B$47) -> 0 | I49: =IF(AND(G49>0,H49>0),G49/H49,IF(AND(G49>0,H49=0),100%,IF(AND(G49=0,H49>0),0,IF(AND(G49=0,H49=0),"***",0)))) -> *** | J49: =+SUMPRODUCT(J3:J47,$B$3:$B$47) -> 0 | K49: =+SUMPRODUCT(K3:K47,$B$3:$B$47) -> 0 | L49: =IF(AND(J49>0,K49>0),J49/K49,IF(AND(J49>0,K49=0),100%,IF(AND(J49=0,K49>0),0,IF(AND(J49=0,K49=0),"***",0)))) -> *** | M49: =+SUMPRODUCT(M3:M47,$B$3:$B$47) -> 0 | N49: =+SUMPRODUCT(N3:N47,$B$3:$B$47) -> 0 | O49: =IF(AND(M49>0,N49>0),M49/N49,IF(AND(M49>0,N49=0),100%,IF(AND(M49=0,N49>0),0,IF(AND(M49=0,N49=0),"***",0)))) -> *** | P49: =+SUMPRODUCT(P3:P47,$B$3:$B$47) -> 0 | Q49: =+SUMPRODUCT(Q3:Q47,$B$3:$B$47) -> 0 | R49: =IF(AND(P49>0,Q49>0),P49/Q49,IF(AND(P49>0,Q49=0),100%,IF(AND(P49=0,Q49>0),0,IF(AND(P49=0,Q49=0),"***",0)))) -> *** | S49: =+SUMPRODUCT(S3:S47,$B$3:$B$47) -> 0 | T49: =+SUMPRODUCT(T3:T47,$B$3:$B$47) -> 0 | U49: =IF(AND(S49>0,T49>0),S49/T49,IF(AND(S49>0,T49=0),100%,IF(AND(S49=0,T49>0),0,IF(AND(S49=0,T49=0),"***",0)))) -> *** | V49: =+SUMPRODUCT(V3:V47,$B$3:$B$47) -> 0 | W49: =+SUMPRODUCT(W3:W47,$B$3:$B$47) -> 0 | X49: =IF(AND(V49>0,W49>0),V49/W49,IF(AND(V49>0,W49=0),100%,IF(AND(V49=0,W49>0),0,IF(AND(V49=0,W49=0),"***",0)))) -> *** | Y49: =+SUMPRODUCT(Y3:Y47,$B$3:$B$47) -> 0 | Z49: =+SUMPRODUCT(Z3:Z47,$B$3:$B$47) -> 0 | AA49: =IF(AND(Y49>0,Z49>0),Y49/Z49,IF(AND(Y49>0,Z49=0),100%,IF(AND(Y49=0,Z49>0),0,IF(AND(Y49=0,Z49=0),"***",0)))) -> *** | AB49: =+SUMPRODUCT(AB3:AB47,$B$3:$B$47) -> 0 | AC49: =+SUMPRODUCT(AC3:AC47,$B$3:$B$47) -> 0 | AD49: =IF(AND(AB49>0,AC49>0),AB49/AC49,IF(AND(AB49>0,AC49=0),100%,IF(AND(AB49=0,AC49>0),0,IF(AND(AB49=0,AC49=0),"***",0)))) -> *** | AE49: =+SUMPRODUCT(AE3:AE47,$B$3:$B$47) -> 0 | AF49: =+SUMPRODUCT(AF3:AF47,$B$3:$B$47) -> 0 | AG49: =IF(AND(AE49>0,AF49>0),AE49/AF49,IF(AND(AE49>0,AF49=0),100%,IF(AND(AE49=0,AF49>0),0,IF(AND(AE49=0,AF49=0),"***",0)))) -> *** | AH49: =+SUMPRODUCT(AH3:AH47,$B$3:$B$47) -> 0 | AI49: =+SUMPRODUCT(AI3:AI47,$B$3:$B$47) -> 0 | AJ49: =IF(AND(AH49>0,AI49>0),AH49/AI49,IF(AND(AH49>0,AI49=0),100%,IF(AND(AH49=0,AI49>0),0,IF(AND(AH49=0,AI49=0),"***",0)))) -> *** | AK49: =+SUMPRODUCT(AK3:AK47,$B$3:$B$47) -> 0 | AL49: =+SUMPRODUCT(AL3:AL47,$B$3:$B$47) -> 0 | AM49: =IF(AND(AK49>0,AL49>0),AK49/AL49,IF(AND(AK49>0,AL49=0),100%,IF(AND(AK49=0,AL49>0),0,IF(AND(AK49=0,AL49=0),"***",0)))) -> *** | AN49: =+SUMPRODUCT(AN3:AN47,$B$3:$B$47) -> 0 | AO49: =+SUMPRODUCT(AO3:AO47,$B$3:$B$47) -> 0 | AP49: =IF(AND(AN49>0,AO49>0),AN49/AO49,IF(AND(AN49>0,AO49=0),100%,IF(AND(AN49=0,AO49>0),0,IF(AND(AN49=0,AO49=0),"***",0)))) -> ***

Sheet KPIs - Sales Goals
A1: KPIs | D1: =+'Dashboard - Overview & Project'!H2 -> Accumulated - 1-01/2026 | G1: =+'KPIs - Sales Launch'!G1 -> 46023 | J1: =+'KPIs - Sales Launch'!J1 -> 46054 | M1: =+'KPIs - Sales Launch'!M1 -> 46082 | P1: =+'KPIs - Sales Launch'!P1 -> 46113 | S1: =+'KPIs - Sales Launch'!S1 -> 46143 | V1: =+'KPIs - Sales Launch'!V1 -> 46174 | Y1: =+'KPIs - Sales Launch'!Y1 -> 46204 | AB1: =+'KPIs - Sales Launch'!AB1 -> 46235 | AE1: =+'KPIs - Sales Launch'!AE1 -> 46266 | AH1: =+'KPIs - Sales Launch'!AH1 -> 46296 | AK1: =+'KPIs - Sales Launch'!AK1 -> 46327 | AN1: =+'KPIs - Sales Launch'!AN1 -> 46357
A2: Project Name | B2: TU (%) | C2: Nr. Units | D2: Actual | E2: Budget | F2: Gap | G2: Actual | H2: Budget | I2: Gap | J2: Actual | K2: Budget | L2: Gap | M2: Actual | N2: Budget | O2: Gap | P2: Actual | Q2: Budget | R2: Gap | S2: Actual | T2: Budget | U2: Gap | V2: Actual | W2: Budget | X2: Gap | Y2: Actual | Z2: Budget | AA2: Gap | AB2: Actual | AC2: Budget | AD2: Gap | AE2: Actual | AF2: Budget | AG2: Gap | AH2: Actual | AI2: Budget | AJ2: Gap | AK2: Actual | AL2: Budget | AM2: Gap | AN2: Actual | AO2: Budget | AP2: Gap
A3: Pinto Bessa | B3: 1 | C3: 30 | D3: =+G3 -> 0 | E3: =+H3 -> 0 | F3: =IF(AND(D3>0,E3>0),D3/E3,IF(AND(D3>0,E3=0),100%,IF(AND(D3=0,E3>0),0,IF(AND(D3=0,E3=0),"***",0)))) -> *** | H3: =+IFERROR(VLOOKUP($A3,'Goals & Budget 2026'!$A$2:$EJ$49,20,FALSE),0) -> 0 | I3: =IF(AND(G3>0,H3>0),G3/H3,IF(AND(G3>0,H3=0),100%,IF(AND(G3=0,H3>0),0,IF(AND(G3=0,H3=0),"***",0)))) -> *** | K3: =+IFERROR(VLOOKUP($A3,'Goals & Budget 2026'!$A$2:$EJ$49,21,FALSE),0) -> 0 | L3: =IF(AND(J3>0,K3>0),J3/K3,IF(AND(J3>0,K3=0),100%,IF(AND(J3=0,K3>0),0,IF(AND(J3=0,K3=0),"***",0)))) -> *** | N3: =+IFERROR(VLOOKUP($A3,'Goals & Budget 2026'!$A$2:$EJ$49,22,FALSE),0) -> 0 | O3: =IF(AND(M3>0,N3>0),M3/N3,IF(AND(M3>0,N3=0),100%,IF(AND(M3=0,N3>0),0,IF(AND(M3=0,N3=0),"***",0)))) -> *** | Q3: =+IFERROR(VLOOKUP($A3,'Goals & Budget 2026'!$A$2:$EJ$49,23,FALSE),0) -> 0 | R3: =IF(AND(P3>0,Q3>0),P3/Q3,IF(AND(P3>0,Q3=0),100%,IF(AND(P3=0,Q3>0),0,IF(AND(P3=0,Q3=0),"***",0)))) -> *** | T3: =+IFERROR(VLOOKUP($A3,'Goals & Budget 2026'!$A$2:$EJ$49,24,FALSE),0) -> 0 | U3: =IF(AND(S3>0,T3>0),S3/T3,IF(AND(S3>0,T3=0),100%,IF(AND(S3=0,T3>0),0,IF(AND(S3=0,T3=0),"***",0)))) -> *** | W3: =+IFERROR(VLOOKUP($A3,'Goals & Budget 2026'!$A$2:$EJ$49,25,FALSE),0) -> 0 | X3: =IF(AND(V3>0,W3>0),V3/W3,IF(AND(V3>0,W3=0),100%,IF(AND(V3=0,W3>0),0,IF(AND(V3=0,W3=0),"***",0)))) -> *** | Z3: =+IFERROR(VLOOKUP($A3,'Goals & Budget 2026'!$A$2:$EJ$49,26,FALSE),0) -> 0 | AA3: =IF(AND(Y3>0,Z3>0),Y3/Z3,IF(AND(Y3>0,Z3=0),100%,IF(AND(Y3=0,Z3>0),0,IF(AND(Y3=0,Z3=0),"***",0)))) -> *** | AC3: =+IFERROR(VLOOKUP($A3,'Goals & Budget 2026'!$A$2:$EJ$49,27,FALSE),0) -> 0 | AD3: =IF(AND(AB3>0,AC3>0),AB3/AC3,IF(AND(AB3>0,AC3=0),100%,IF(AND(AB3=0,AC3>0),0,IF(AND(AB3=0,AC3=0),"***",0)))) -> *** | AF3: =+IFERROR(VLOOKUP($A3,'Goals & Budget 2026'!$A$2:$EJ$49,28,FALSE),0) -> 0 | AG3: =IF(AND(AE3>0,AF3>0),AE3/AF3,IF(AND(AE3>0,AF3=0),100%,IF(AND(AE3=0,AF3>0),0,IF(AND(AE3=0,AF3=0),"***",0)))) -> *** | AI3: =+IFERROR(VLOOKUP($A3,'Goals & Budget 2026'!$A$2:$EJ$49,29,FALSE),0) -> 0 | AJ3: =IF(AND(AH3>0,AI3>0),AH3/AI3,IF(AND(AH3>0,AI3=0),100%,IF(AND(AH3=0,AI3>0),0,IF(AND(AH3=0,AI3=0),"***",0)))) -> *** | AL3: =+IFERROR(VLOOKUP($A3,'Goals & Budget 2026'!$A$2:$EJ$49,30,FALSE),0) -> 0 | AM3: =IF(AND(AK3>0,AL3>0),AK3/AL3,IF(AND(AK3>0,AL3=0),100%,IF(AND(AK3=0,AL3>0),0,IF(AND(AK3=0,AL3=0),"***",0)))) -> *** | AO3: =+IFERROR(VLOOKUP($A3,'Goals & Budget 2026'!$A$2:$EJ$49,31,FALSE),0) -> 0 | AP3: =IF(AND(AN3>0,AO3>0),AN3/AO3,IF(AND(AN3>0,AO3=0),100%,IF(AND(AN3=0,AO3>0),0,IF(AND(AN3=0,AO3=0),"***",0)))) -> ***
A4: Saldouro - 6 | B4: 1 | C4: 25 | D4: =+G4 -> 0 | E4: =+H4 -> 0 | F4: =IF(AND(D4>0,E4>0),D4/E4,IF(AND(D4>0,E4=0),100%,IF(AND(D4=0,E4>0),0,IF(AND(D4=0,E4=0),"***",0)))) -> *** | H4: =+IFERROR(VLOOKUP($A4,'Goals & Budget 2026'!$A$2:$EJ$49,20,FALSE),0) -> 0 | I4: =IF(AND(G4>0,H4>0),G4/H4,IF(AND(G4>0,H4=0),100%,IF(AND(G4=0,H4>0),0,IF(AND(G4=0,H4=0),"***",0)))) -> *** | K4: =+IFERROR(VLOOKUP($A4,'Goals & Budget 2026'!$A$2:$EJ$49,21,FALSE),0) -> 0 | L4: =IF(AND(J4>0,K4>0),J4/K4,IF(AND(J4>0,K4=0),100%,IF(AND(J4=0,K4>0),0,IF(AND(J4=0,K4=0),"***",0)))) -> *** | N4: =+IFERROR(VLOOKUP($A4,'Goals & Budget 2026'!$A$2:$EJ$49,22,FALSE),0) -> 0 | O4: =IF(AND(M4>0,N4>0),M4/N4,IF(AND(M4>0,N4=0),100%,IF(AND(M4=0,N4>0),0,IF(AND(M4=0,N4=0),"***",0)))) -> *** | Q4: =+IFERROR(VLOOKUP($A4,'Goals & Budget 2026'!$A$2:$EJ$49,23,FALSE),0) -> 0 | R4: =IF(AND(P4>0,Q4>0),P4/Q4,IF(AND(P4>0,Q4=0),100%,IF(AND(P4=0,Q4>0),0,IF(AND(P4=0,Q4=0),"***",0)))) -> *** | T4: =+IFERROR(VLOOKUP($A4,'Goals & Budget 2026'!$A$2:$EJ$49,24,FALSE),0) -> 0 | U4: =IF(AND(S4>0,T4>0),S4/T4,IF(AND(S4>0,T4=0),100%,IF(AND(S4=0,T4>0),0,IF(AND(S4=0,T4=0),"***",0)))) -> *** | W4: =+IFERROR(VLOOKUP($A4,'Goals & Budget 2026'!$A$2:$EJ$49,25,FALSE),0) -> 0 | X4: =IF(AND(V4>0,W4>0),V4/W4,IF(AND(V4>0,W4=0),100%,IF(AND(V4=0,W4>0),0,IF(AND(V4=0,W4=0),"***",0)))) -> *** | Z4: =+IFERROR(VLOOKUP($A4,'Goals & Budget 2026'!$A$2:$EJ$49,26,FALSE),0) -> 0 | AA4: =IF(AND(Y4>0,Z4>0),Y4/Z4,IF(AND(Y4>0,Z4=0),100%,IF(AND(Y4=0,Z4>0),0,IF(AND(Y4=0,Z4=0),"***",0)))) -> *** | AC4: =+IFERROR(VLOOKUP($A4,'Goals & Budget 2026'!$A$2:$EJ$49,27,FALSE),0) -> 0 | AD4: =IF(AND(AB4>0,AC4>0),AB4/AC4,IF(AND(AB4>0,AC4=0),100%,IF(AND(AB4=0,AC4>0),0,IF(AND(AB4=0,AC4=0),"***",0)))) -> *** | AF4: =+IFERROR(VLOOKUP($A4,'Goals & Budget 2026'!$A$2:$EJ$49,28,FALSE),0) -> 0 | AG4: =IF(AND(AE4>0,AF4>0),AE4/AF4,IF(AND(AE4>0,AF4=0),100%,IF(AND(AE4=0,AF4>0),0,IF(AND(AE4=0,AF4=0),"***",0)))) -> *** | AI4: =+IFERROR(VLOOKUP($A4,'Goals & Budget 2026'!$A$2:$EJ$49,29,FALSE),0) -> 0 | AJ4: =IF(AND(AH4>0,AI4>0),AH4/AI4,IF(AND(AH4>0,AI4=0),100%,IF(AND(AH4=0,AI4>0),0,IF(AND(AH4=0,AI4=0),"***",0)))) -> *** | AL4: =+IFERROR(VLOOKUP($A4,'Goals & Budget 2026'!$A$2:$EJ$49,30,FALSE),0) -> 0 | AM4: =IF(AND(AK4>0,AL4>0),AK4/AL4,IF(AND(AK4>0,AL4=0),100%,IF(AND(AK4=0,AL4>0),0,IF(AND(AK4=0,AL4=0),"***",0)))) -> *** | AO4: =+IFERROR(VLOOKUP($A4,'Goals & Budget 2026'!$A$2:$EJ$49,31,FALSE),0) -> 0 | AP4: =IF(AND(AN4>0,AO4>0),AN4/AO4,IF(AND(AN4>0,AO4=0),100%,IF(AND(AN4=0,AO4>0),0,IF(AND(AN4=0,AO4=0),"***",0)))) -> ***
A5: Saldouro - 8 | B5: 1 | C5: 31 | D5: =+G5 -> 0 | E5: =+H5 -> 0 | F5: =IF(AND(D5>0,E5>0),D5/E5,IF(AND(D5>0,E5=0),100%,IF(AND(D5=0,E5>0),0,IF(AND(D5=0,E5=0),"***",0)))) -> *** | H5: =+IFERROR(VLOOKUP($A5,'Goals & Budget 2026'!$A$2:$EJ$49,20,FALSE),0) -> 0 | I5: =IF(AND(G5>0,H5>0),G5/H5,IF(AND(G5>0,H5=0),100%,IF(AND(G5=0,H5>0),0,IF(AND(G5=0,H5=0),"***",0)))) -> *** | K5: =+IFERROR(VLOOKUP($A5,'Goals & Budget 2026'!$A$2:$EJ$49,21,FALSE),0) -> 0 | L5: =IF(AND(J5>0,K5>0),J5/K5,IF(AND(J5>0,K5=0),100%,IF(AND(J5=0,K5>0),0,IF(AND(J5=0,K5=0),"***",0)))) -> *** | N5: =+IFERROR(VLOOKUP($A5,'Goals & Budget 2026'!$A$2:$EJ$49,22,FALSE),0) -> 0 | O5: =IF(AND(M5>0,N5>0),M5/N5,IF(AND(M5>0,N5=0),100%,IF(AND(M5=0,N5>0),0,IF(AND(M5=0,N5=0),"***",0)))) -> *** | Q5: =+IFERROR(VLOOKUP($A5,'Goals & Budget 2026'!$A$2:$EJ$49,23,FALSE),0) -> 0 | R5: =IF(AND(P5>0,Q5>0),P5/Q5,IF(AND(P5>0,Q5=0),100%,IF(AND(P5=0,Q5>0),0,IF(AND(P5=0,Q5=0),"***",0)))) -> *** | T5: =+IFERROR(VLOOKUP($A5,'Goals & Budget 2026'!$A$2:$EJ$49,24,FALSE),0) -> 0 | U5: =IF(AND(S5>0,T5>0),S5/T5,IF(AND(S5>0,T5=0),100%,IF(AND(S5=0,T5>0),0,IF(AND(S5=0,T5=0),"***",0)))) -> *** | W5: =+IFERROR(VLOOKUP($A5,'Goals & Budget 2026'!$A$2:$EJ$49,25,FALSE),0) -> 0 | X5: =IF(AND(V5>0,W5>0),V5/W5,IF(AND(V5>0,W5=0),100%,IF(AND(V5=0,W5>0),0,IF(AND(V5=0,W5=0),"***",0)))) -> *** | Z5: =+IFERROR(VLOOKUP($A5,'Goals & Budget 2026'!$A$2:$EJ$49,26,FALSE),0) -> 0 | AA5: =IF(AND(Y5>0,Z5>0),Y5/Z5,IF(AND(Y5>0,Z5=0),100%,IF(AND(Y5=0,Z5>0),0,IF(AND(Y5=0,Z5=0),"***",0)))) -> *** | AC5: =+IFERROR(VLOOKUP($A5,'Goals & Budget 2026'!$A$2:$EJ$49,27,FALSE),0) -> 0 | AD5: =IF(AND(AB5>0,AC5>0),AB5/AC5,IF(AND(AB5>0,AC5=0),100%,IF(AND(AB5=0,AC5>0),0,IF(AND(AB5=0,AC5=0),"***",0)))) -> *** | AF5: =+IFERROR(VLOOKUP($A5,'Goals & Budget 2026'!$A$2:$EJ$49,28,FALSE),0) -> 0 | AG5: =IF(AND(AE5>0,AF5>0),AE5/AF5,IF(AND(AE5>0,AF5=0),100%,IF(AND(AE5=0,AF5>0),0,IF(AND(AE5=0,AF5=0),"***",0)))) -> *** | AI5: =+IFERROR(VLOOKUP($A5,'Goals & Budget 2026'!$A$2:$EJ$49,29,FALSE),0) -> 0 | AJ5: =IF(AND(AH5>0,AI5>0),AH5/AI5,IF(AND(AH5>0,AI5=0),100%,IF(AND(AH5=0,AI5>0),0,IF(AND(AH5=0,AI5=0),"***",0)))) -> *** | AL5: =+IFERROR(VLOOKUP($A5,'Goals & Budget 2026'!$A$2:$EJ$49,30,FALSE),0) -> 0 | AM5: =IF(AND(AK5>0,AL5>0),AK5/AL5,IF(AND(AK5>0,AL5=0),100%,IF(AND(AK5=0,AL5>0),0,IF(AND(AK5=0,AL5=0),"***",0)))) -> *** | AO5: =+IFERROR(VLOOKUP($A5,'Goals & Budget 2026'!$A$2:$EJ$49,31,FALSE),0) -> 0 | AP5: =IF(AND(AN5>0,AO5>0),AN5/AO5,IF(AND(AN5>0,AO5=0),100%,IF(AND(AN5=0,AO5>0),0,IF(AND(AN5=0,AO5=0),"***",0)))) -> ***
A6: Saldouro - 9 | B6: 1 | C6: 46 | D6: =+G6 -> 0 | E6: =+H6 -> 0 | F6: =IF(AND(D6>0,E6>0),D6/E6,IF(AND(D6>0,E6=0),100%,IF(AND(D6=0,E6>0),0,IF(AND(D6=0,E6=0),"***",0)))) -> *** | H6: =+IFERROR(VLOOKUP($A6,'Goals & Budget 2026'!$A$2:$EJ$49,20,FALSE),0) -> 0 | I6: =IF(AND(G6>0,H6>0),G6/H6,IF(AND(G6>0,H6=0),100%,IF(AND(G6=0,H6>0),0,IF(AND(G6=0,H6=0),"***",0)))) -> *** | K6: =+IFERROR(VLOOKUP($A6,'Goals & Budget 2026'!$A$2:$EJ$49,21,FALSE),0) -> 0 | L6: =IF(AND(J6>0,K6>0),J6/K6,IF(AND(J6>0,K6=0),100%,IF(AND(J6=0,K6>0),0,IF(AND(J6=0,K6=0),"***",0)))) -> *** | N6: =+IFERROR(VLOOKUP($A6,'Goals & Budget 2026'!$A$2:$EJ$49,22,FALSE),0) -> 0 | O6: =IF(AND(M6>0,N6>0),M6/N6,IF(AND(M6>0,N6=0),100%,IF(AND(M6=0,N6>0),0,IF(AND(M6=0,N6=0),"***",0)))) -> *** | Q6: =+IFERROR(VLOOKUP($A6,'Goals & Budget 2026'!$A$2:$EJ$49,23,FALSE),0) -> 0 | R6: =IF(AND(P6>0,Q6>0),P6/Q6,IF(AND(P6>0,Q6=0),100%,IF(AND(P6=0,Q6>0),0,IF(AND(P6=0,Q6=0),"***",0)))) -> *** | T6: =+IFERROR(VLOOKUP($A6,'Goals & Budget 2026'!$A$2:$EJ$49,24,FALSE),0) -> 0 | U6: =IF(AND(S6>0,T6>0),S6/T6,IF(AND(S6>0,T6=0),100%,IF(AND(S6=0,T6>0),0,IF(AND(S6=0,T6=0),"***",0)))) -> *** | W6: =+IFERROR(VLOOKUP($A6,'Goals & Budget 2026'!$A$2:$EJ$49,25,FALSE),0) -> 0 | X6: =IF(AND(V6>0,W6>0),V6/W6,IF(AND(V6>0,W6=0),100%,IF(AND(V6=0,W6>0),0,IF(AND(V6=0,W6=0),"***",0)))) -> *** | Z6: =+IFERROR(VLOOKUP($A6,'Goals & Budget 2026'!$A$2:$EJ$49,26,FALSE),0) -> 0 | AA6: =IF(AND(Y6>0,Z6>0),Y6/Z6,IF(AND(Y6>0,Z6=0),100%,IF(AND(Y6=0,Z6>0),0,IF(AND(Y6=0,Z6=0),"***",0)))) -> *** | AC6: =+IFERROR(VLOOKUP($A6,'Goals & Budget 2026'!$A$2:$EJ$49,27,FALSE),0) -> 0 | AD6: =IF(AND(AB6>0,AC6>0),AB6/AC6,IF(AND(AB6>0,AC6=0),100%,IF(AND(AB6=0,AC6>0),0,IF(AND(AB6=0,AC6=0),"***",0)))) -> *** | AF6: =+IFERROR(VLOOKUP($A6,'Goals & Budget 2026'!$A$2:$EJ$49,28,FALSE),0) -> 0 | AG6: =IF(AND(AE6>0,AF6>0),AE6/AF6,IF(AND(AE6>0,AF6=0),100%,IF(AND(AE6=0,AF6>0),0,IF(AND(AE6=0,AF6=0),"***",0)))) -> *** | AI6: =+IFERROR(VLOOKUP($A6,'Goals & Budget 2026'!$A$2:$EJ$49,29,FALSE),0) -> 0 | AJ6: =IF(AND(AH6>0,AI6>0),AH6/AI6,IF(AND(AH6>0,AI6=0),100%,IF(AND(AH6=0,AI6>0),0,IF(AND(AH6=0,AI6=0),"***",0)))) -> *** | AL6: =+IFERROR(VLOOKUP($A6,'Goals & Budget 2026'!$A$2:$EJ$49,30,FALSE),0) -> 0 | AM6: =IF(AND(AK6>0,AL6>0),AK6/AL6,IF(AND(AK6>0,AL6=0),100%,IF(AND(AK6=0,AL6>0),0,IF(AND(AK6=0,AL6=0),"***",0)))) -> *** | AO6: =+IFERROR(VLOOKUP($A6,'Goals & Budget 2026'!$A$2:$EJ$49,31,FALSE),0) -> 0 | AP6: =IF(AND(AN6>0,AO6>0),AN6/AO6,IF(AND(AN6>0,AO6=0),100%,IF(AND(AN6=0,AO6>0),0,IF(AND(AN6=0,AO6=0),"***",0)))) -> ***
A7: Saldouro - 10 | B7: 1 | C7: 62 | D7: =+G7 -> 0 | E7: =+H7 -> 0 | F7: =IF(AND(D7>0,E7>0),D7/E7,IF(AND(D7>0,E7=0),100%,IF(AND(D7=0,E7>0),0,IF(AND(D7=0,E7=0),"***",0)))) -> *** | H7: =+IFERROR(VLOOKUP($A7,'Goals & Budget 2026'!$A$2:$EJ$49,20,FALSE),0) -> 0 | I7: =IF(AND(G7>0,H7>0),G7/H7,IF(AND(G7>0,H7=0),100%,IF(AND(G7=0,H7>0),0,IF(AND(G7=0,H7=0),"***",0)))) -> *** | K7: =+IFERROR(VLOOKUP($A7,'Goals & Budget 2026'!$A$2:$EJ$49,21,FALSE),0) -> 0 | L7: =IF(AND(J7>0,K7>0),J7/K7,IF(AND(J7>0,K7=0),100%,IF(AND(J7=0,K7>0),0,IF(AND(J7=0,K7=0),"***",0)))) -> *** | N7: =+IFERROR(VLOOKUP($A7,'Goals & Budget 2026'!$A$2:$EJ$49,22,FALSE),0) -> 0 | O7: =IF(AND(M7>0,N7>0),M7/N7,IF(AND(M7>0,N7=0),100%,IF(AND(M7=0,N7>0),0,IF(AND(M7=0,N7=0),"***",0)))) -> *** | Q7: =+IFERROR(VLOOKUP($A7,'Goals & Budget 2026'!$A$2:$EJ$49,23,FALSE),0) -> 0 | R7: =IF(AND(P7>0,Q7>0),P7/Q7,IF(AND(P7>0,Q7=0),100%,IF(AND(P7=0,Q7>0),0,IF(AND(P7=0,Q7=0),"***",0)))) -> *** | T7: =+IFERROR(VLOOKUP($A7,'Goals & Budget 2026'!$A$2:$EJ$49,24,FALSE),0) -> 0 | U7: =IF(AND(S7>0,T7>0),S7/T7,IF(AND(S7>0,T7=0),100%,IF(AND(S7=0,T7>0),0,IF(AND(S7=0,T7=0),"***",0)))) -> *** | W7: =+IFERROR(VLOOKUP($A7,'Goals & Budget 2026'!$A$2:$EJ$49,25,FALSE),0) -> 0 | X7: =IF(AND(V7>0,W7>0),V7/W7,IF(AND(V7>0,W7=0),100%,IF(AND(V7=0,W7>0),0,IF(AND(V7=0,W7=0),"***",0)))) -> *** | Z7: =+IFERROR(VLOOKUP($A7,'Goals & Budget 2026'!$A$2:$EJ$49,26,FALSE),0) -> 0 | AA7: =IF(AND(Y7>0,Z7>0),Y7/Z7,IF(AND(Y7>0,Z7=0),100%,IF(AND(Y7=0,Z7>0),0,IF(AND(Y7=0,Z7=0),"***",0)))) -> *** | AC7: =+IFERROR(VLOOKUP($A7,'Goals & Budget 2026'!$A$2:$EJ$49,27,FALSE),0) -> 0 | AD7: =IF(AND(AB7>0,AC7>0),AB7/AC7,IF(AND(AB7>0,AC7=0),100%,IF(AND(AB7=0,AC7>0),0,IF(AND(AB7=0,AC7=0),"***",0)))) -> *** | AF7: =+IFERROR(VLOOKUP($A7,'Goals & Budget 2026'!$A$2:$EJ$49,28,FALSE),0) -> 0 | AG7: =IF(AND(AE7>0,AF7>0),AE7/AF7,IF(AND(AE7>0,AF7=0),100%,IF(AND(AE7=0,AF7>0),0,IF(AND(AE7=0,AF7=0),"***",0)))) -> *** | AI7: =+IFERROR(VLOOKUP($A7,'Goals & Budget 2026'!$A$2:$EJ$49,29,FALSE),0) -> 0 | AJ7: =IF(AND(AH7>0,AI7>0),AH7/AI7,IF(AND(AH7>0,AI7=0),100%,IF(AND(AH7=0,AI7>0),0,IF(AND(AH7=0,AI7=0),"***",0)))) -> *** | AL7: =+IFERROR(VLOOKUP($A7,'Goals & Budget 2026'!$A$2:$EJ$49,30,FALSE),0) -> 0 | AM7: =IF(AND(AK7>0,AL7>0),AK7/AL7,IF(AND(AK7>0,AL7=0),100%,IF(AND(AK7=0,AL7>0),0,IF(AND(AK7=0,AL7=0),"***",0)))) -> *** | AO7: =+IFERROR(VLOOKUP($A7,'Goals & Budget 2026'!$A$2:$EJ$49,31,FALSE),0) -> 0 | AP7: =IF(AND(AN7>0,AO7>0),AN7/AO7,IF(AND(AN7>0,AO7=0),100%,IF(AND(AN7=0,AO7>0),0,IF(AND(AN7=0,AO7=0),"***",0)))) -> ***
A8: Saldouro - 12.2 | B8: 1 | C8: 37 | D8: =+G8 -> 0 | E8: =+H8 -> 0 | F8: =IF(AND(D8>0,E8>0),D8/E8,IF(AND(D8>0,E8=0),100%,IF(AND(D8=0,E8>0),0,IF(AND(D8=0,E8=0),"***",0)))) -> *** | H8: =+IFERROR(VLOOKUP($A8,'Goals & Budget 2026'!$A$2:$EJ$49,20,FALSE),0) -> 0 | I8: =IF(AND(G8>0,H8>0),G8/H8,IF(AND(G8>0,H8=0),100%,IF(AND(G8=0,H8>0),0,IF(AND(G8=0,H8=0),"***",0)))) -> *** | K8: =+IFERROR(VLOOKUP($A8,'Goals & Budget 2026'!$A$2:$EJ$49,21,FALSE),0) -> 0 | L8: =IF(AND(J8>0,K8>0),J8/K8,IF(AND(J8>0,K8=0),100%,IF(AND(J8=0,K8>0),0,IF(AND(J8=0,K8=0),"***",0)))) -> *** | N8: =+IFERROR(VLOOKUP($A8,'Goals & Budget 2026'!$A$2:$EJ$49,22,FALSE),0) -> 0 | O8: =IF(AND(M8>0,N8>0),M8/N8,IF(AND(M8>0,N8=0),100%,IF(AND(M8=0,N8>0),0,IF(AND(M8=0,N8=0),"***",0)))) -> *** | Q8: =+IFERROR(VLOOKUP($A8,'Goals & Budget 2026'!$A$2:$EJ$49,23,FALSE),0) -> 0 | R8: =IF(AND(P8>0,Q8>0),P8/Q8,IF(AND(P8>0,Q8=0),100%,IF(AND(P8=0,Q8>0),0,IF(AND(P8=0,Q8=0),"***",0)))) -> *** | T8: =+IFERROR(VLOOKUP($A8,'Goals & Budget 2026'!$A$2:$EJ$49,24,FALSE),0) -> 0 | U8: =IF(AND(S8>0,T8>0),S8/T8,IF(AND(S8>0,T8=0),100%,IF(AND(S8=0,T8>0),0,IF(AND(S8=0,T8=0),"***",0)))) -> *** | W8: =+IFERROR(VLOOKUP($A8,'Goals & Budget 2026'!$A$2:$EJ$49,25,FALSE),0) -> 0 | X8: =IF(AND(V8>0,W8>0),V8/W8,IF(AND(V8>0,W8=0),100%,IF(AND(V8=0,W8>0),0,IF(AND(V8=0,W8=0),"***",0)))) -> *** | Z8: =+IFERROR(VLOOKUP($A8,'Goals & Budget 2026'!$A$2:$EJ$49,26,FALSE),0) -> 0 | AA8: =IF(AND(Y8>0,Z8>0),Y8/Z8,IF(AND(Y8>0,Z8=0),100%,IF(AND(Y8=0,Z8>0),0,IF(AND(Y8=0,Z8=0),"***",0)))) -> *** | AC8: =+IFERROR(VLOOKUP($A8,'Goals & Budget 2026'!$A$2:$EJ$49,27,FALSE),0) -> 0 | AD8: =IF(AND(AB8>0,AC8>0),AB8/AC8,IF(AND(AB8>0,AC8=0),100%,IF(AND(AB8=0,AC8>0),0,IF(AND(AB8=0,AC8=0),"***",0)))) -> *** | AF8: =+IFERROR(VLOOKUP($A8,'Goals & Budget 2026'!$A$2:$EJ$49,28,FALSE),0) -> 0 | AG8: =IF(AND(AE8>0,AF8>0),AE8/AF8,IF(AND(AE8>0,AF8=0),100%,IF(AND(AE8=0,AF8>0),0,IF(AND(AE8=0,AF8=0),"***",0)))) -> *** | AI8: =+IFERROR(VLOOKUP($A8,'Goals & Budget 2026'!$A$2:$EJ$49,29,FALSE),0) -> 0 | AJ8: =IF(AND(AH8>0,AI8>0),AH8/AI8,IF(AND(AH8>0,AI8=0),100%,IF(AND(AH8=0,AI8>0),0,IF(AND(AH8=0,AI8=0),"***",0)))) -> *** | AL8: =+IFERROR(VLOOKUP($A8,'Goals & Budget 2026'!$A$2:$EJ$49,30,FALSE),0) -> 0 | AM8: =IF(AND(AK8>0,AL8>0),AK8/AL8,IF(AND(AK8>0,AL8=0),100%,IF(AND(AK8=0,AL8>0),0,IF(AND(AK8=0,AL8=0),"***",0)))) -> *** | AO8: =+IFERROR(VLOOKUP($A8,'Goals & Budget 2026'!$A$2:$EJ$49,31,FALSE),0) -> 0 | AP8: =IF(AND(AN8>0,AO8>0),AN8/AO8,IF(AND(AN8>0,AO8=0),100%,IF(AND(AN8=0,AO8>0),0,IF(AND(AN8=0,AO8=0),"***",0)))) -> ***
A9: Saldouro - 17.2 | B9: 1 | C9: 24 | D9: =+G9 -> 0 | E9: =+H9 -> 0 | F9: =IF(AND(D9>0,E9>0),D9/E9,IF(AND(D9>0,E9=0),100%,IF(AND(D9=0,E9>0),0,IF(AND(D9=0,E9=0),"***",0)))) -> *** | H9: =+IFERROR(VLOOKUP($A9,'Goals & Budget 2026'!$A$2:$EJ$49,20,FALSE),0) -> 0 | I9: =IF(AND(G9>0,H9>0),G9/H9,IF(AND(G9>0,H9=0),100%,IF(AND(G9=0,H9>0),0,IF(AND(G9=0,H9=0),"***",0)))) -> *** | K9: =+IFERROR(VLOOKUP($A9,'Goals & Budget 2026'!$A$2:$EJ$49,21,FALSE),0) -> 0 | L9: =IF(AND(J9>0,K9>0),J9/K9,IF(AND(J9>0,K9=0),100%,IF(AND(J9=0,K9>0),0,IF(AND(J9=0,K9=0),"***",0)))) -> *** | N9: =+IFERROR(VLOOKUP($A9,'Goals & Budget 2026'!$A$2:$EJ$49,22,FALSE),0) -> 0 | O9: =IF(AND(M9>0,N9>0),M9/N9,IF(AND(M9>0,N9=0),100%,IF(AND(M9=0,N9>0),0,IF(AND(M9=0,N9=0),"***",0)))) -> *** | Q9: =+IFERROR(VLOOKUP($A9,'Goals & Budget 2026'!$A$2:$EJ$49,23,FALSE),0) -> 0 | R9: =IF(AND(P9>0,Q9>0),P9/Q9,IF(AND(P9>0,Q9=0),100%,IF(AND(P9=0,Q9>0),0,IF(AND(P9=0,Q9=0),"***",0)))) -> *** | T9: =+IFERROR(VLOOKUP($A9,'Goals & Budget 2026'!$A$2:$EJ$49,24,FALSE),0) -> 0 | U9: =IF(AND(S9>0,T9>0),S9/T9,IF(AND(S9>0,T9=0),100%,IF(AND(S9=0,T9>0),0,IF(AND(S9=0,T9=0),"***",0)))) -> *** | W9: =+IFERROR(VLOOKUP($A9,'Goals & Budget 2026'!$A$2:$EJ$49,25,FALSE),0) -> 0 | X9: =IF(AND(V9>0,W9>0),V9/W9,IF(AND(V9>0,W9=0),100%,IF(AND(V9=0,W9>0),0,IF(AND(V9=0,W9=0),"***",0)))) -> *** | Z9: =+IFERROR(VLOOKUP($A9,'Goals & Budget 2026'!$A$2:$EJ$49,26,FALSE),0) -> 0 | AA9: =IF(AND(Y9>0,Z9>0),Y9/Z9,IF(AND(Y9>0,Z9=0),100%,IF(AND(Y9=0,Z9>0),0,IF(AND(Y9=0,Z9=0),"***",0)))) -> *** | AC9: =+IFERROR(VLOOKUP($A9,'Goals & Budget 2026'!$A$2:$EJ$49,27,FALSE),0) -> 0 | AD9: =IF(AND(AB9>0,AC9>0),AB9/AC9,IF(AND(AB9>0,AC9=0),100%,IF(AND(AB9=0,AC9>0),0,IF(AND(AB9=0,AC9=0),"***",0)))) -> *** | AF9: =+IFERROR(VLOOKUP($A9,'Goals & Budget 2026'!$A$2:$EJ$49,28,FALSE),0) -> 0 | AG9: =IF(AND(AE9>0,AF9>0),AE9/AF9,IF(AND(AE9>0,AF9=0),100%,IF(AND(AE9=0,AF9>0),0,IF(AND(AE9=0,AF9=0),"***",0)))) -> *** | AI9: =+IFERROR(VLOOKUP($A9,'Goals & Budget 2026'!$A$2:$EJ$49,29,FALSE),0) -> 0 | AJ9: =IF(AND(AH9>0,AI9>0),AH9/AI9,IF(AND(AH9>0,AI9=0),100%,IF(AND(AH9=0,AI9>0),0,IF(AND(AH9=0,AI9=0),"***",0)))) -> *** | AL9: =+IFERROR(VLOOKUP($A9,'Goals & Budget 2026'!$A$2:$EJ$49,30,FALSE),0) -> 0 | AM9: =IF(AND(AK9>0,AL9>0),AK9/AL9,IF(AND(AK9>0,AL9=0),100%,IF(AND(AK9=0,AL9>0),0,IF(AND(AK9=0,AL9=0),"***",0)))) -> *** | AO9: =+IFERROR(VLOOKUP($A9,'Goals & Budget 2026'!$A$2:$EJ$49,31,FALSE),0) -> 0 | AP9: =IF(AND(AN9>0,AO9>0),AN9/AO9,IF(AND(AN9>0,AO9=0),100%,IF(AND(AN9=0,AO9>0),0,IF(AND(AN9=0,AO9=0),"***",0)))) -> ***
A10: Panorama | B10: 1 | C10: 77 | D10: =+G10 -> 0 | E10: =+H10 -> 0 | F10: =IF(AND(D10>0,E10>0),D10/E10,IF(AND(D10>0,E10=0),100%,IF(AND(D10=0,E10>0),0,IF(AND(D10=0,E10=0),"***",0)))) -> *** | H10: =+IFERROR(VLOOKUP($A10,'Goals & Budget 2026'!$A$2:$EJ$49,20,FALSE),0) -> 0 | I10: =IF(AND(G10>0,H10>0),G10/H10,IF(AND(G10>0,H10=0),100%,IF(AND(G10=0,H10>0),0,IF(AND(G10=0,H10=0),"***",0)))) -> *** | K10: =+IFERROR(VLOOKUP($A10,'Goals & Budget 2026'!$A$2:$EJ$49,21,FALSE),0) -> 0 | L10: =IF(AND(J10>0,K10>0),J10/K10,IF(AND(J10>0,K10=0),100%,IF(AND(J10=0,K10>0),0,IF(AND(J10=0,K10=0),"***",0)))) -> *** | N10: =+IFERROR(VLOOKUP($A10,'Goals & Budget 2026'!$A$2:$EJ$49,22,FALSE),0) -> 0 | O10: =IF(AND(M10>0,N10>0),M10/N10,IF(AND(M10>0,N10=0),100%,IF(AND(M10=0,N10>0),0,IF(AND(M10=0,N10=0),"***",0)))) -> *** | Q10: =+IFERROR(VLOOKUP($A10,'Goals & Budget 2026'!$A$2:$EJ$49,23,FALSE),0) -> 0 | R10: =IF(AND(P10>0,Q10>0),P10/Q10,IF(AND(P10>0,Q10=0),100%,IF(AND(P10=0,Q10>0),0,IF(AND(P10=0,Q10=0),"***",0)))) -> *** | T10: =+IFERROR(VLOOKUP($A10,'Goals & Budget 2026'!$A$2:$EJ$49,24,FALSE),0) -> 0 | U10: =IF(AND(S10>0,T10>0),S10/T10,IF(AND(S10>0,T10=0),100%,IF(AND(S10=0,T10>0),0,IF(AND(S10=0,T10=0),"***",0)))) -> *** | W10: =+IFERROR(VLOOKUP($A10,'Goals & Budget 2026'!$A$2:$EJ$49,25,FALSE),0) -> 0 | X10: =IF(AND(V10>0,W10>0),V10/W10,IF(AND(V10>0,W10=0),100%,IF(AND(V10=0,W10>0),0,IF(AND(V10=0,W10=0),"***",0)))) -> *** | Z10: =+IFERROR(VLOOKUP($A10,'Goals & Budget 2026'!$A$2:$EJ$49,26,FALSE),0) -> 0 | AA10: =IF(AND(Y10>0,Z10>0),Y10/Z10,IF(AND(Y10>0,Z10=0),100%,IF(AND(Y10=0,Z10>0),0,IF(AND(Y10=0,Z10=0),"***",0)))) -> *** | AC10: =+IFERROR(VLOOKUP($A10,'Goals & Budget 2026'!$A$2:$EJ$49,27,FALSE),0) -> 0 | AD10: =IF(AND(AB10>0,AC10>0),AB10/AC10,IF(AND(AB10>0,AC10=0),100%,IF(AND(AB10=0,AC10>0),0,IF(AND(AB10=0,AC10=0),"***",0)))) -> *** | AF10: =+IFERROR(VLOOKUP($A10,'Goals & Budget 2026'!$A$2:$EJ$49,28,FALSE),0) -> 0 | AG10: =IF(AND(AE10>0,AF10>0),AE10/AF10,IF(AND(AE10>0,AF10=0),100%,IF(AND(AE10=0,AF10>0),0,IF(AND(AE10=0,AF10=0),"***",0)))) -> *** | AI10: =+IFERROR(VLOOKUP($A10,'Goals & Budget 2026'!$A$2:$EJ$49,29,FALSE),0) -> 0 | AJ10: =IF(AND(AH10>0,AI10>0),AH10/AI10,IF(AND(AH10>0,AI10=0),100%,IF(AND(AH10=0,AI10>0),0,IF(AND(AH10=0,AI10=0),"***",0)))) -> *** | AL10: =+IFERROR(VLOOKUP($A10,'Goals & Budget 2026'!$A$2:$EJ$49,30,FALSE),0) -> 0 | AM10: =IF(AND(AK10>0,AL10>0),AK10/AL10,IF(AND(AK10>0,AL10=0),100%,IF(AND(AK10=0,AL10>0),0,IF(AND(AK10=0,AL10=0),"***",0)))) -> *** | AO10: =+IFERROR(VLOOKUP($A10,'Goals & Budget 2026'!$A$2:$EJ$49,31,FALSE),0) -> 0 | AP10: =IF(AND(AN10>0,AO10>0),AN10/AO10,IF(AND(AN10>0,AO10=0),100%,IF(AND(AN10=0,AO10>0),0,IF(AND(AN10=0,AO10=0),"***",0)))) -> ***
A11: Verde Vale - H1 | B11: 1 | C11: 64 | D11: =+G11 -> 0 | E11: =+H11 -> 0 | F11: =IF(AND(D11>0,E11>0),D11/E11,IF(AND(D11>0,E11=0),100%,IF(AND(D11=0,E11>0),0,IF(AND(D11=0,E11=0),"***",0)))) -> *** | H11: =+IFERROR(VLOOKUP($A11,'Goals & Budget 2026'!$A$2:$EJ$49,20,FALSE),0) -> 0 | I11: =IF(AND(G11>0,H11>0),G11/H11,IF(AND(G11>0,H11=0),100%,IF(AND(G11=0,H11>0),0,IF(AND(G11=0,H11=0),"***",0)))) -> *** | K11: =+IFERROR(VLOOKUP($A11,'Goals & Budget 2026'!$A$2:$EJ$49,21,FALSE),0) -> 0 | L11: =IF(AND(J11>0,K11>0),J11/K11,IF(AND(J11>0,K11=0),100%,IF(AND(J11=0,K11>0),0,IF(AND(J11=0,K11=0),"***",0)))) -> *** | N11: =+IFERROR(VLOOKUP($A11,'Goals & Budget 2026'!$A$2:$EJ$49,22,FALSE),0) -> 0 | O11: =IF(AND(M11>0,N11>0),M11/N11,IF(AND(M11>0,N11=0),100%,IF(AND(M11=0,N11>0),0,IF(AND(M11=0,N11=0),"***",0)))) -> *** | Q11: =+IFERROR(VLOOKUP($A11,'Goals & Budget 2026'!$A$2:$EJ$49,23,FALSE),0) -> 0 | R11: =IF(AND(P11>0,Q11>0),P11/Q11,IF(AND(P11>0,Q11=0),100%,IF(AND(P11=0,Q11>0),0,IF(AND(P11=0,Q11=0),"***",0)))) -> *** | T11: =+IFERROR(VLOOKUP($A11,'Goals & Budget 2026'!$A$2:$EJ$49,24,FALSE),0) -> 0 | U11: =IF(AND(S11>0,T11>0),S11/T11,IF(AND(S11>0,T11=0),100%,IF(AND(S11=0,T11>0),0,IF(AND(S11=0,T11=0),"***",0)))) -> *** | W11: =+IFERROR(VLOOKUP($A11,'Goals & Budget 2026'!$A$2:$EJ$49,25,FALSE),0) -> 0 | X11: =IF(AND(V11>0,W11>0),V11/W11,IF(AND(V11>0,W11=0),100%,IF(AND(V11=0,W11>0),0,IF(AND(V11=0,W11=0),"***",0)))) -> *** | Z11: =+IFERROR(VLOOKUP($A11,'Goals & Budget 2026'!$A$2:$EJ$49,26,FALSE),0) -> 0 | AA11: =IF(AND(Y11>0,Z11>0),Y11/Z11,IF(AND(Y11>0,Z11=0),100%,IF(AND(Y11=0,Z11>0),0,IF(AND(Y11=0,Z11=0),"***",0)))) -> *** | AC11: =+IFERROR(VLOOKUP($A11,'Goals & Budget 2026'!$A$2:$EJ$49,27,FALSE),0) -> 0 | AD11: =IF(AND(AB11>0,AC11>0),AB11/AC11,IF(AND(AB11>0,AC11=0),100%,IF(AND(AB11=0,AC11>0),0,IF(AND(AB11=0,AC11=0),"***",0)))) -> *** | AF11: =+IFERROR(VLOOKUP($A11,'Goals & Budget 2026'!$A$2:$EJ$49,28,FALSE),0) -> 0 | AG11: =IF(AND(AE11>0,AF11>0),AE11/AF11,IF(AND(AE11>0,AF11=0),100%,IF(AND(AE11=0,AF11>0),0,IF(AND(AE11=0,AF11=0),"***",0)))) -> *** | AI11: =+IFERROR(VLOOKUP($A11,'Goals & Budget 2026'!$A$2:$EJ$49,29,FALSE),0) -> 0 | AJ11: =IF(AND(AH11>0,AI11>0),AH11/AI11,IF(AND(AH11>0,AI11=0),100%,IF(AND(AH11=0,AI11>0),0,IF(AND(AH11=0,AI11=0),"***",0)))) -> *** | AL11: =+IFERROR(VLOOKUP($A11,'Goals & Budget 2026'!$A$2:$EJ$49,30,FALSE),0) -> 0 | AM11: =IF(AND(AK11>0,AL11>0),AK11/AL11,IF(AND(AK11>0,AL11=0),100%,IF(AND(AK11=0,AL11>0),0,IF(AND(AK11=0,AL11=0),"***",0)))) -> *** | AO11: =+IFERROR(VLOOKUP($A11,'Goals & Budget 2026'!$A$2:$EJ$49,31,FALSE),0) -> 0 | AP11: =IF(AND(AN11>0,AO11>0),AN11/AO11,IF(AND(AN11>0,AO11=0),100%,IF(AND(AN11=0,AO11>0),0,IF(AND(AN11=0,AO11=0),"***",0)))) -> ***
A12: Verde Vale - H2 | B12: 1 | C12: 54 | D12: =+G12 -> 0 | E12: =+H12 -> 0 | F12: =IF(AND(D12>0,E12>0),D12/E12,IF(AND(D12>0,E12=0),100%,IF(AND(D12=0,E12>0),0,IF(AND(D12=0,E12=0),"***",0)))) -> *** | H12: =+IFERROR(VLOOKUP($A12,'Goals & Budget 2026'!$A$2:$EJ$49,20,FALSE),0) -> 0 | I12: =IF(AND(G12>0,H12>0),G12/H12,IF(AND(G12>0,H12=0),100%,IF(AND(G12=0,H12>0),0,IF(AND(G12=0,H12=0),"***",0)))) -> *** | K12: =+IFERROR(VLOOKUP($A12,'Goals & Budget 2026'!$A$2:$EJ$49,21,FALSE),0) -> 0 | L12: =IF(AND(J12>0,K12>0),J12/K12,IF(AND(J12>0,K12=0),100%,IF(AND(J12=0,K12>0),0,IF(AND(J12=0,K12=0),"***",0)))) -> *** | N12: =+IFERROR(VLOOKUP($A12,'Goals & Budget 2026'!$A$2:$EJ$49,22,FALSE),0) -> 0 | O12: =IF(AND(M12>0,N12>0),M12/N12,IF(AND(M12>0,N12=0),100%,IF(AND(M12=0,N12>0),0,IF(AND(M12=0,N12=0),"***",0)))) -> *** | Q12: =+IFERROR(VLOOKUP($A12,'Goals & Budget 2026'!$A$2:$EJ$49,23,FALSE),0) -> 0 | R12: =IF(AND(P12>0,Q12>0),P12/Q12,IF(AND(P12>0,Q12=0),100%,IF(AND(P12=0,Q12>0),0,IF(AND(P12=0,Q12=0),"***",0)))) -> *** | T12: =+IFERROR(VLOOKUP($A12,'Goals & Budget 2026'!$A$2:$EJ$49,24,FALSE),0) -> 0 | U12: =IF(AND(S12>0,T12>0),S12/T12,IF(AND(S12>0,T12=0),100%,IF(AND(S12=0,T12>0),0,IF(AND(S12=0,T12=0),"***",0)))) -> *** | W12: =+IFERROR(VLOOKUP($A12,'Goals & Budget 2026'!$A$2:$EJ$49,25,FALSE),0) -> 0 | X12: =IF(AND(V12>0,W12>0),V12/W12,IF(AND(V12>0,W12=0),100%,IF(AND(V12=0,W12>0),0,IF(AND(V12=0,W12=0),"***",0)))) -> *** | Z12: =+IFERROR(VLOOKUP($A12,'Goals & Budget 2026'!$A$2:$EJ$49,26,FALSE),0) -> 0 | AA12: =IF(AND(Y12>0,Z12>0),Y12/Z12,IF(AND(Y12>0,Z12=0),100%,IF(AND(Y12=0,Z12>0),0,IF(AND(Y12=0,Z12=0),"***",0)))) -> *** | AC12: =+IFERROR(VLOOKUP($A12,'Goals & Budget 2026'!$A$2:$EJ$49,27,FALSE),0) -> 0 | AD12: =IF(AND(AB12>0,AC12>0),AB12/AC12,IF(AND(AB12>0,AC12=0),100%,IF(AND(AB12=0,AC12>0),0,IF(AND(AB12=0,AC12=0),"***",0)))) -> *** | AF12: =+IFERROR(VLOOKUP($A12,'Goals & Budget 2026'!$A$2:$EJ$49,28,FALSE),0) -> 0 | AG12: =IF(AND(AE12>0,AF12>0),AE12/AF12,IF(AND(AE12>0,AF12=0),100%,IF(AND(AE12=0,AF12>0),0,IF(AND(AE12=0,AF12=0),"***",0)))) -> *** | AI12: =+IFERROR(VLOOKUP($A12,'Goals & Budget 2026'!$A$2:$EJ$49,29,FALSE),0) -> 0 | AJ12: =IF(AND(AH12>0,AI12>0),AH12/AI12,IF(AND(AH12>0,AI12=0),100%,IF(AND(AH12=0,AI12>0),0,IF(AND(AH12=0,AI12=0),"***",0)))) -> *** | AL12: =+IFERROR(VLOOKUP($A12,'Goals & Budget 2026'!$A$2:$EJ$49,30,FALSE),0) -> 0 | AM12: =IF(AND(AK12>0,AL12>0),AK12/AL12,IF(AND(AK12>0,AL12=0),100%,IF(AND(AK12=0,AL12>0),0,IF(AND(AK12=0,AL12=0),"***",0)))) -> *** | AO12: =+IFERROR(VLOOKUP($A12,'Goals & Budget 2026'!$A$2:$EJ$49,31,FALSE),0) -> 0 | AP12: =IF(AND(AN12>0,AO12>0),AN12/AO12,IF(AND(AN12>0,AO12=0),100%,IF(AND(AN12=0,AO12>0),0,IF(AND(AN12=0,AO12=0),"***",0)))) -> ***
A13: Verde Vale - H3 | B13: 1 | C13: 56 | D13: =+G13 -> 0 | E13: =+H13 -> 0 | F13: =IF(AND(D13>0,E13>0),D13/E13,IF(AND(D13>0,E13=0),100%,IF(AND(D13=0,E13>0),0,IF(AND(D13=0,E13=0),"***",0)))) -> *** | H13: =+IFERROR(VLOOKUP($A13,'Goals & Budget 2026'!$A$2:$EJ$49,20,FALSE),0) -> 0 | I13: =IF(AND(G13>0,H13>0),G13/H13,IF(AND(G13>0,H13=0),100%,IF(AND(G13=0,H13>0),0,IF(AND(G13=0,H13=0),"***",0)))) -> *** | K13: =+IFERROR(VLOOKUP($A13,'Goals & Budget 2026'!$A$2:$EJ$49,21,FALSE),0) -> 0 | L13: =IF(AND(J13>0,K13>0),J13/K13,IF(AND(J13>0,K13=0),100%,IF(AND(J13=0,K13>0),0,IF(AND(J13=0,K13=0),"***",0)))) -> *** | N13: =+IFERROR(VLOOKUP($A13,'Goals & Budget 2026'!$A$2:$EJ$49,22,FALSE),0) -> 0 | O13: =IF(AND(M13>0,N13>0),M13/N13,IF(AND(M13>0,N13=0),100%,IF(AND(M13=0,N13>0),0,IF(AND(M13=0,N13=0),"***",0)))) -> *** | Q13: =+IFERROR(VLOOKUP($A13,'Goals & Budget 2026'!$A$2:$EJ$49,23,FALSE),0) -> 0 | R13: =IF(AND(P13>0,Q13>0),P13/Q13,IF(AND(P13>0,Q13=0),100%,IF(AND(P13=0,Q13>0),0,IF(AND(P13=0,Q13=0),"***",0)))) -> *** | T13: =+IFERROR(VLOOKUP($A13,'Goals & Budget 2026'!$A$2:$EJ$49,24,FALSE),0) -> 0 | U13: =IF(AND(S13>0,T13>0),S13/T13,IF(AND(S13>0,T13=0),100%,IF(AND(S13=0,T13>0),0,IF(AND(S13=0,T13=0),"***",0)))) -> *** | W13: =+IFERROR(VLOOKUP($A13,'Goals & Budget 2026'!$A$2:$EJ$49,25,FALSE),0) -> 0 | X13: =IF(AND(V13>0,W13>0),V13/W13,IF(AND(V13>0,W13=0),100%,IF(AND(V13=0,W13>0),0,IF(AND(V13=0,W13=0),"***",0)))) -> *** | Z13: =+IFERROR(VLOOKUP($A13,'Goals & Budget 2026'!$A$2:$EJ$49,26,FALSE),0) -> 0 | AA13: =IF(AND(Y13>0,Z13>0),Y13/Z13,IF(AND(Y13>0,Z13=0),100%,IF(AND(Y13=0,Z13>0),0,IF(AND(Y13=0,Z13=0),"***",0)))) -> *** | AC13: =+IFERROR(VLOOKUP($A13,'Goals & Budget 2026'!$A$2:$EJ$49,27,FALSE),0) -> 0 | AD13: =IF(AND(AB13>0,AC13>0),AB13/AC13,IF(AND(AB13>0,AC13=0),100%,IF(AND(AB13=0,AC13>0),0,IF(AND(AB13=0,AC13=0),"***",0)))) -> *** | AF13: =+IFERROR(VLOOKUP($A13,'Goals & Budget 2026'!$A$2:$EJ$49,28,FALSE),0) -> 0 | AG13: =IF(AND(AE13>0,AF13>0),AE13/AF13,IF(AND(AE13>0,AF13=0),100%,IF(AND(AE13=0,AF13>0),0,IF(AND(AE13=0,AF13=0),"***",0)))) -> *** | AI13: =+IFERROR(VLOOKUP($A13,'Goals & Budget 2026'!$A$2:$EJ$49,29,FALSE),0) -> 0 | AJ13: =IF(AND(AH13>0,AI13>0),AH13/AI13,IF(AND(AH13>0,AI13=0),100%,IF(AND(AH13=0,AI13>0),0,IF(AND(AH13=0,AI13=0),"***",0)))) -> *** | AL13: =+IFERROR(VLOOKUP($A13,'Goals & Budget 2026'!$A$2:$EJ$49,30,FALSE),0) -> 0 | AM13: =IF(AND(AK13>0,AL13>0),AK13/AL13,IF(AND(AK13>0,AL13=0),100%,IF(AND(AK13=0,AL13>0),0,IF(AND(AK13=0,AL13=0),"***",0)))) -> *** | AO13: =+IFERROR(VLOOKUP($A13,'Goals & Budget 2026'!$A$2:$EJ$49,31,FALSE),0) -> 0 | AP13: =IF(AND(AN13>0,AO13>0),AN13/AO13,IF(AND(AN13>0,AO13=0),100%,IF(AND(AN13=0,AO13>0),0,IF(AND(AN13=0,AO13=0),"***",0)))) -> ***
A14: Verde Vale - H4 | B14: 1 | C14: 80 | D14: =+G14 -> 0 | E14: =+H14 -> 0 | F14: =IF(AND(D14>0,E14>0),D14/E14,IF(AND(D14>0,E14=0),100%,IF(AND(D14=0,E14>0),0,IF(AND(D14=0,E14=0),"***",0)))) -> *** | H14: =+IFERROR(VLOOKUP($A14,'Goals & Budget 2026'!$A$2:$EJ$49,20,FALSE),0) -> 0 | I14: =IF(AND(G14>0,H14>0),G14/H14,IF(AND(G14>0,H14=0),100%,IF(AND(G14=0,H14>0),0,IF(AND(G14=0,H14=0),"***",0)))) -> *** | K14: =+IFERROR(VLOOKUP($A14,'Goals & Budget 2026'!$A$2:$EJ$49,21,FALSE),0) -> 0 | L14: =IF(AND(J14>0,K14>0),J14/K14,IF(AND(J14>0,K14=0),100%,IF(AND(J14=0,K14>0),0,IF(AND(J14=0,K14=0),"***",0)))) -> *** | N14: =+IFERROR(VLOOKUP($A14,'Goals & Budget 2026'!$A$2:$EJ$49,22,FALSE),0) -> 0 | O14: =IF(AND(M14>0,N14>0),M14/N14,IF(AND(M14>0,N14=0),100%,IF(AND(M14=0,N14>0),0,IF(AND(M14=0,N14=0),"***",0)))) -> *** | Q14: =+IFERROR(VLOOKUP($A14,'Goals & Budget 2026'!$A$2:$EJ$49,23,FALSE),0) -> 0 | R14: =IF(AND(P14>0,Q14>0),P14/Q14,IF(AND(P14>0,Q14=0),100%,IF(AND(P14=0,Q14>0),0,IF(AND(P14=0,Q14=0),"***",0)))) -> *** | T14: =+IFERROR(VLOOKUP($A14,'Goals & Budget 2026'!$A$2:$EJ$49,24,FALSE),0) -> 0 | U14: =IF(AND(S14>0,T14>0),S14/T14,IF(AND(S14>0,T14=0),100%,IF(AND(S14=0,T14>0),0,IF(AND(S14=0,T14=0),"***",0)))) -> *** | W14: =+IFERROR(VLOOKUP($A14,'Goals & Budget 2026'!$A$2:$EJ$49,25,FALSE),0) -> 0 | X14: =IF(AND(V14>0,W14>0),V14/W14,IF(AND(V14>0,W14=0),100%,IF(AND(V14=0,W14>0),0,IF(AND(V14=0,W14=0),"***",0)))) -> *** | Z14: =+IFERROR(VLOOKUP($A14,'Goals & Budget 2026'!$A$2:$EJ$49,26,FALSE),0) -> 0 | AA14: =IF(AND(Y14>0,Z14>0),Y14/Z14,IF(AND(Y14>0,Z14=0),100%,IF(AND(Y14=0,Z14>0),0,IF(AND(Y14=0,Z14=0),"***",0)))) -> *** | AC14: =+IFERROR(VLOOKUP($A14,'Goals & Budget 2026'!$A$2:$EJ$49,27,FALSE),0) -> 0 | AD14: =IF(AND(AB14>0,AC14>0),AB14/AC14,IF(AND(AB14>0,AC14=0),100%,IF(AND(AB14=0,AC14>0),0,IF(AND(AB14=0,AC14=0),"***",0)))) -> *** | AF14: =+IFERROR(VLOOKUP($A14,'Goals & Budget 2026'!$A$2:$EJ$49,28,FALSE),0) -> 0 | AG14: =IF(AND(AE14>0,AF14>0),AE14/AF14,IF(AND(AE14>0,AF14=0),100%,IF(AND(AE14=0,AF14>0),0,IF(AND(AE14=0,AF14=0),"***",0)))) -> *** | AI14: =+IFERROR(VLOOKUP($A14,'Goals & Budget 2026'!$A$2:$EJ$49,29,FALSE),0) -> 0 | AJ14: =IF(AND(AH14>0,AI14>0),AH14/AI14,IF(AND(AH14>0,AI14=0),100%,IF(AND(AH14=0,AI14>0),0,IF(AND(AH14=0,AI14=0),"***",0)))) -> *** | AL14: =+IFERROR(VLOOKUP($A14,'Goals & Budget 2026'!$A$2:$EJ$49,30,FALSE),0) -> 0 | AM14: =IF(AND(AK14>0,AL14>0),AK14/AL14,IF(AND(AK14>0,AL14=0),100%,IF(AND(AK14=0,AL14>0),0,IF(AND(AK14=0,AL14=0),"***",0)))) -> *** | AO14: =+IFERROR(VLOOKUP($A14,'Goals & Budget 2026'!$A$2:$EJ$49,31,FALSE),0) -> 0 | AP14: =IF(AND(AN14>0,AO14>0),AN14/AO14,IF(AND(AN14>0,AO14=0),100%,IF(AND(AN14=0,AO14>0),0,IF(AND(AN14=0,AO14=0),"***",0)))) -> ***
... A29: Antas South - Resi | B29: 1 | C29: 57 | D29: =+G29 -> 0 | E29: =+H29 -> 0 | F29: =IF(AND(D29>0,E29>0),D29/E29,IF(AND(D29>0,E29=0),100%,IF(AND(D29=0,E29>0),0,IF(AND(D29=0,E29=0),"***",0)))) -> *** | H29: =+IFERROR(VLOOKUP($A29,'Goals & Budget 2026'!$A$2:$EJ$49,20,FALSE),0) -> 0 | I29: =IF(AND(G29>0,H29>0),G29/H29,IF(AND(G29>0,H29=0),100%,IF(AND(G29=0,H29>0),0,IF(AND(G29=0,H29=0),"***",0)))) -> *** | K29: =+IFERROR(VLOOKUP($A29,'Goals & Budget 2026'!$A$2:$EJ$49,21,FALSE),0) -> 0 | L29: =IF(AND(J29>0,K29>0),J29/K29,IF(AND(J29>0,K29=0),100%,IF(AND(J29=0,K29>0),0,IF(AND(J29=0,K29=0),"***",0)))) -> *** | N29: =+IFERROR(VLOOKUP($A29,'Goals & Budget 2026'!$A$2:$EJ$49,22,FALSE),0) -> 0 | O29: =IF(AND(M29>0,N29>0),M29/N29,IF(AND(M29>0,N29=0),100%,IF(AND(M29=0,N29>0),0,IF(AND(M29=0,N29=0),"***",0)))) -> *** | Q29: =+IFERROR(VLOOKUP($A29,'Goals & Budget 2026'!$A$2:$EJ$49,23,FALSE),0) -> 0 | R29: =IF(AND(P29>0,Q29>0),P29/Q29,IF(AND(P29>0,Q29=0),100%,IF(AND(P29=0,Q29>0),0,IF(AND(P29=0,Q29=0),"***",0)))) -> *** | T29: =+IFERROR(VLOOKUP($A29,'Goals & Budget 2026'!$A$2:$EJ$49,24,FALSE),0) -> 0 | U29: =IF(AND(S29>0,T29>0),S29/T29,IF(AND(S29>0,T29=0),100%,IF(AND(S29=0,T29>0),0,IF(AND(S29=0,T29=0),"***",0)))) -> *** | W29: =+IFERROR(VLOOKUP($A29,'Goals & Budget 2026'!$A$2:$EJ$49,25,FALSE),0) -> 0 | X29: =IF(AND(V29>0,W29>0),V29/W29,IF(AND(V29>0,W29=0),100%,IF(AND(V29=0,W29>0),0,IF(AND(V29=0,W29=0),"***",0)))) -> *** | Z29: =+IFERROR(VLOOKUP($A29,'Goals & Budget 2026'!$A$2:$EJ$49,26,FALSE),0) -> 0 | AA29: =IF(AND(Y29>0,Z29>0),Y29/Z29,IF(AND(Y29>0,Z29=0),100%,IF(AND(Y29=0,Z29>0),0,IF(AND(Y29=0,Z29=0),"***",0)))) -> *** | AC29: =+IFERROR(VLOOKUP($A29,'Goals & Budget 2026'!$A$2:$EJ$49,27,FALSE),0) -> 0 | AD29: =IF(AND(AB29>0,AC29>0),AB29/AC29,IF(AND(AB29>0,AC29=0),100%,IF(AND(AB29=0,AC29>0),0,IF(AND(AB29=0,AC29=0),"***",0)))) -> *** | AF29: =+IFERROR(VLOOKUP($A29,'Goals & Budget 2026'!$A$2:$EJ$49,28,FALSE),0) -> 0 | AG29: =IF(AND(AE29>0,AF29>0),AE29/AF29,IF(AND(AE29>0,AF29=0),100%,IF(AND(AE29=0,AF29>0),0,IF(AND(AE29=0,AF29=0),"***",0)))) -> *** | AI29: =+IFERROR(VLOOKUP($A29,'Goals & Budget 2026'!$A$2:$EJ$49,29,FALSE),0) -> 0 | AJ29: =IF(AND(AH29>0,AI29>0),AH29/AI29,IF(AND(AH29>0,AI29=0),100%,IF(AND(AH29=0,AI29>0),0,IF(AND(AH29=0,AI29=0),"***",0)))) -> *** | AL29: =+IFERROR(VLOOKUP($A29,'Goals & Budget 2026'!$A$2:$EJ$49,30,FALSE),0) -> 0 | AM29: =IF(AND(AK29>0,AL29>0),AK29/AL29,IF(AND(AK29>0,AL29=0),100%,IF(AND(AK29=0,AL29>0),0,IF(AND(AK29=0,AL29=0),"***",0)))) -> *** | AO29: =+IFERROR(VLOOKUP($A29,'Goals & Budget 2026'!$A$2:$EJ$49,31,FALSE),0) -> 0 | AP29: =IF(AND(AN29>0,AO29>0),AN29/AO29,IF(AND(AN29>0,AO29=0),100%,IF(AND(AN29=0,AO29>0),0,IF(AND(AN29=0,AO29=0),"***",0)))) -> ***
A30: Antas North | B30: 1 | C30: ? | D30: =+G30 -> 0 | E30: =+H30 -> 0 | F30: =IF(AND(D30>0,E30>0),D30/E30,IF(AND(D30>0,E30=0),100%,IF(AND(D30=0,E30>0),0,IF(AND(D30=0,E30=0),"***",0)))) -> *** | H30: =+IFERROR(VLOOKUP($A30,'Goals & Budget 2026'!$A$2:$EJ$49,20,FALSE),0) -> 0 | I30: =IF(AND(G30>0,H30>0),G30/H30,IF(AND(G30>0,H30=0),100%,IF(AND(G30=0,H30>0),0,IF(AND(G30=0,H30=0),"***",0)))) -> *** | K30: =+IFERROR(VLOOKUP($A30,'Goals & Budget 2026'!$A$2:$EJ$49,21,FALSE),0) -> 0 | L30: =IF(AND(J30>0,K30>0),J30/K30,IF(AND(J30>0,K30=0),100%,IF(AND(J30=0,K30>0),0,IF(AND(J30=0,K30=0),"***",0)))) -> *** | N30: =+IFERROR(VLOOKUP($A30,'Goals & Budget 2026'!$A$2:$EJ$49,22,FALSE),0) -> 0 | O30: =IF(AND(M30>0,N30>0),M30/N30,IF(AND(M30>0,N30=0),100%,IF(AND(M30=0,N30>0),0,IF(AND(M30=0,N30=0),"***",0)))) -> *** | Q30: =+IFERROR(VLOOKUP($A30,'Goals & Budget 2026'!$A$2:$EJ$49,23,FALSE),0) -> 0 | R30: =IF(AND(P30>0,Q30>0),P30/Q30,IF(AND(P30>0,Q30=0),100%,IF(AND(P30=0,Q30>0),0,IF(AND(P30=0,Q30=0),"***",0)))) -> *** | T30: =+IFERROR(VLOOKUP($A30,'Goals & Budget 2026'!$A$2:$EJ$49,24,FALSE),0) -> 0 | U30: =IF(AND(S30>0,T30>0),S30/T30,IF(AND(S30>0,T30=0),100%,IF(AND(S30=0,T30>0),0,IF(AND(S30=0,T30=0),"***",0)))) -> *** | W30: =+IFERROR(VLOOKUP($A30,'Goals & Budget 2026'!$A$2:$EJ$49,25,FALSE),0) -> 0 | X30: =IF(AND(V30>0,W30>0),V30/W30,IF(AND(V30>0,W30=0),100%,IF(AND(V30=0,W30>0),0,IF(AND(V30=0,W30=0),"***",0)))) -> *** | Z30: =+IFERROR(VLOOKUP($A30,'Goals & Budget 2026'!$A$2:$EJ$49,26,FALSE),0) -> 0 | AA30: =IF(AND(Y30>0,Z30>0),Y30/Z30,IF(AND(Y30>0,Z30=0),100%,IF(AND(Y30=0,Z30>0),0,IF(AND(Y30=0,Z30=0),"***",0)))) -> *** | AC30: =+IFERROR(VLOOKUP($A30,'Goals & Budget 2026'!$A$2:$EJ$49,27,FALSE),0) -> 0 | AD30: =IF(AND(AB30>0,AC30>0),AB30/AC30,IF(AND(AB30>0,AC30=0),100%,IF(AND(AB30=0,AC30>0),0,IF(AND(AB30=0,AC30=0),"***",0)))) -> *** | AF30: =+IFERROR(VLOOKUP($A30,'Goals & Budget 2026'!$A$2:$EJ$49,28,FALSE),0) -> 0 | AG30: =IF(AND(AE30>0,AF30>0),AE30/AF30,IF(AND(AE30>0,AF30=0),100%,IF(AND(AE30=0,AF30>0),0,IF(AND(AE30=0,AF30=0),"***",0)))) -> *** | AI30: =+IFERROR(VLOOKUP($A30,'Goals & Budget 2026'!$A$2:$EJ$49,29,FALSE),0) -> 0 | AJ30: =IF(AND(AH30>0,AI30>0),AH30/AI30,IF(AND(AH30>0,AI30=0),100%,IF(AND(AH30=0,AI30>0),0,IF(AND(AH30=0,AI30=0),"***",0)))) -> *** | AL30: =+IFERROR(VLOOKUP($A30,'Goals & Budget 2026'!$A$2:$EJ$49,30,FALSE),0) -> 0 | AM30: =IF(AND(AK30>0,AL30>0),AK30/AL30,IF(AND(AK30>0,AL30=0),100%,IF(AND(AK30=0,AL30>0),0,IF(AND(AK30=0,AL30=0),"***",0)))) -> *** | AO30: =+IFERROR(VLOOKUP($A30,'Goals & Budget 2026'!$A$2:$EJ$49,31,FALSE),0) -> 0 | AP30: =IF(AND(AN30>0,AO30>0),AN30/AO30,IF(AND(AN30>0,AO30=0),100%,IF(AND(AN30=0,AO30>0),0,IF(AND(AN30=0,AO30=0),"***",0)))) -> ***
A31: Vila do Conde - Allotment | B31: 1 | C31: 1 | D31: =+G31 -> 0 | E31: =+H31 -> 0 | F31: =IF(AND(D31>0,E31>0),D31/E31,IF(AND(D31>0,E31=0),100%,IF(AND(D31=0,E31>0),0,IF(AND(D31=0,E31=0),"***",0)))) -> *** | H31: =+IFERROR(VLOOKUP($A31,'Goals & Budget 2026'!$A$2:$EJ$49,20,FALSE),0) -> 0 | I31: =IF(AND(G31>0,H31>0),G31/H31,IF(AND(G31>0,H31=0),100%,IF(AND(G31=0,H31>0),0,IF(AND(G31=0,H31=0),"***",0)))) -> *** | K31: =+IFERROR(VLOOKUP($A31,'Goals & Budget 2026'!$A$2:$EJ$49,21,FALSE),0) -> 0 | L31: =IF(AND(J31>0,K31>0),J31/K31,IF(AND(J31>0,K31=0),100%,IF(AND(J31=0,K31>0),0,IF(AND(J31=0,K31=0),"***",0)))) -> *** | N31: =+IFERROR(VLOOKUP($A31,'Goals & Budget 2026'!$A$2:$EJ$49,22,FALSE),0) -> 0 | O31: =IF(AND(M31>0,N31>0),M31/N31,IF(AND(M31>0,N31=0),100%,IF(AND(M31=0,N31>0),0,IF(AND(M31=0,N31=0),"***",0)))) -> *** | Q31: =+IFERROR(VLOOKUP($A31,'Goals & Budget 2026'!$A$2:$EJ$49,23,FALSE),0) -> 0 | R31: =IF(AND(P31>0,Q31>0),P31/Q31,IF(AND(P31>0,Q31=0),100%,IF(AND(P31=0,Q31>0),0,IF(AND(P31=0,Q31=0),"***",0)))) -> *** | T31: =+IFERROR(VLOOKUP($A31,'Goals & Budget 2026'!$A$2:$EJ$49,24,FALSE),0) -> 0 | U31: =IF(AND(S31>0,T31>0),S31/T31,IF(AND(S31>0,T31=0),100%,IF(AND(S31=0,T31>0),0,IF(AND(S31=0,T31=0),"***",0)))) -> *** | W31: =+IFERROR(VLOOKUP($A31,'Goals & Budget 2026'!$A$2:$EJ$49,25,FALSE),0) -> 0 | X31: =IF(AND(V31>0,W31>0),V31/W31,IF(AND(V31>0,W31=0),100%,IF(AND(V31=0,W31>0),0,IF(AND(V31=0,W31=0),"***",0)))) -> *** | Z31: =+IFERROR(VLOOKUP($A31,'Goals & Budget 2026'!$A$2:$EJ$49,26,FALSE),0) -> 0 | AA31: =IF(AND(Y31>0,Z31>0),Y31/Z31,IF(AND(Y31>0,Z31=0),100%,IF(AND(Y31=0,Z31>0),0,IF(AND(Y31=0,Z31=0),"***",0)))) -> *** | AC31: =+IFERROR(VLOOKUP($A31,'Goals & Budget 2026'!$A$2:$EJ$49,27,FALSE),0) -> 0 | AD31: =IF(AND(AB31>0,AC31>0),AB31/AC31,IF(AND(AB31>0,AC31=0),100%,IF(AND(AB31=0,AC31>0),0,IF(AND(AB31=0,AC31=0),"***",0)))) -> *** | AF31: =+IFERROR(VLOOKUP($A31,'Goals & Budget 2026'!$A$2:$EJ$49,28,FALSE),0) -> 0 | AG31: =IF(AND(AE31>0,AF31>0),AE31/AF31,IF(AND(AE31>0,AF31=0),100%,IF(AND(AE31=0,AF31>0),0,IF(AND(AE31=0,AF31=0),"***",0)))) -> *** | AI31: =+IFERROR(VLOOKUP($A31,'Goals & Budget 2026'!$A$2:$EJ$49,29,FALSE),0) -> 0 | AJ31: =IF(AND(AH31>0,AI31>0),AH31/AI31,IF(AND(AH31>0,AI31=0),100%,IF(AND(AH31=0,AI31>0),0,IF(AND(AH31=0,AI31=0),"***",0)))) -> *** | AL31: =+IFERROR(VLOOKUP($A31,'Goals & Budget 2026'!$A$2:$EJ$49,30,FALSE),0) -> 0 | AM31: =IF(AND(AK31>0,AL31>0),AK31/AL31,IF(AND(AK31>0,AL31=0),100%,IF(AND(AK31=0,AL31>0),0,IF(AND(AK31=0,AL31=0),"***",0)))) -> *** | AO31: =+IFERROR(VLOOKUP($A31,'Goals & Budget 2026'!$A$2:$EJ$49,31,FALSE),0) -> 0 | AP31: =IF(AND(AN31>0,AO31>0),AN31/AO31,IF(AND(AN31>0,AO31=0),100%,IF(AND(AN31=0,AO31>0),0,IF(AND(AN31=0,AO31=0),"***",0)))) -> ***
A32: Vila do Conde - Phase 1 | B32: 1 | C32: 165 | D32: =+G32 -> 0 | E32: =+H32 -> 0 | F32: =IF(AND(D32>0,E32>0),D32/E32,IF(AND(D32>0,E32=0),100%,IF(AND(D32=0,E32>0),0,IF(AND(D32=0,E32=0),"***",0)))) -> *** | H32: =+IFERROR(VLOOKUP($A32,'Goals & Budget 2026'!$A$2:$EJ$49,20,FALSE),0) -> 0 | I32: =IF(AND(G32>0,H32>0),G32/H32,IF(AND(G32>0,H32=0),100%,IF(AND(G32=0,H32>0),0,IF(AND(G32=0,H32=0),"***",0)))) -> *** | K32: =+IFERROR(VLOOKUP($A32,'Goals & Budget 2026'!$A$2:$EJ$49,21,FALSE),0) -> 0 | L32: =IF(AND(J32>0,K32>0),J32/K32,IF(AND(J32>0,K32=0),100%,IF(AND(J32=0,K32>0),0,IF(AND(J32=0,K32=0),"***",0)))) -> *** | N32: =+IFERROR(VLOOKUP($A32,'Goals & Budget 2026'!$A$2:$EJ$49,22,FALSE),0) -> 0 | O32: =IF(AND(M32>0,N32>0),M32/N32,IF(AND(M32>0,N32=0),100%,IF(AND(M32=0,N32>0),0,IF(AND(M32=0,N32=0),"***",0)))) -> *** | Q32: =+IFERROR(VLOOKUP($A32,'Goals & Budget 2026'!$A$2:$EJ$49,23,FALSE),0) -> 0 | R32: =IF(AND(P32>0,Q32>0),P32/Q32,IF(AND(P32>0,Q32=0),100%,IF(AND(P32=0,Q32>0),0,IF(AND(P32=0,Q32=0),"***",0)))) -> *** | T32: =+IFERROR(VLOOKUP($A32,'Goals & Budget 2026'!$A$2:$EJ$49,24,FALSE),0) -> 0 | U32: =IF(AND(S32>0,T32>0),S32/T32,IF(AND(S32>0,T32=0),100%,IF(AND(S32=0,T32>0),0,IF(AND(S32=0,T32=0),"***",0)))) -> *** | W32: =+IFERROR(VLOOKUP($A32,'Goals & Budget 2026'!$A$2:$EJ$49,25,FALSE),0) -> 0 | X32: =IF(AND(V32>0,W32>0),V32/W32,IF(AND(V32>0,W32=0),100%,IF(AND(V32=0,W32>0),0,IF(AND(V32=0,W32=0),"***",0)))) -> *** | Z32: =+IFERROR(VLOOKUP($A32,'Goals & Budget 2026'!$A$2:$EJ$49,26,FALSE),0) -> 0 | AA32: =IF(AND(Y32>0,Z32>0),Y32/Z32,IF(AND(Y32>0,Z32=0),100%,IF(AND(Y32=0,Z32>0),0,IF(AND(Y32=0,Z32=0),"***",0)))) -> *** | AC32: =+IFERROR(VLOOKUP($A32,'Goals & Budget 2026'!$A$2:$EJ$49,27,FALSE),0) -> 0 | AD32: =IF(AND(AB32>0,AC32>0),AB32/AC32,IF(AND(AB32>0,AC32=0),100%,IF(AND(AB32=0,AC32>0),0,IF(AND(AB32=0,AC32=0),"***",0)))) -> *** | AF32: =+IFERROR(VLOOKUP($A32,'Goals & Budget 2026'!$A$2:$EJ$49,28,FALSE),0) -> 0 | AG32: =IF(AND(AE32>0,AF32>0),AE32/AF32,IF(AND(AE32>0,AF32=0),100%,IF(AND(AE32=0,AF32>0),0,IF(AND(AE32=0,AF32=0),"***",0)))) -> *** | AI32: =+IFERROR(VLOOKUP($A32,'Goals & Budget 2026'!$A$2:$EJ$49,29,FALSE),0) -> 0 | AJ32: =IF(AND(AH32>0,AI32>0),AH32/AI32,IF(AND(AH32>0,AI32=0),100%,IF(AND(AH32=0,AI32>0),0,IF(AND(AH32=0,AI32=0),"***",0)))) -> *** | AL32: =+IFERROR(VLOOKUP($A32,'Goals & Budget 2026'!$A$2:$EJ$49,30,FALSE),0) -> 0 | AM32: =IF(AND(AK32>0,AL32>0),AK32/AL32,IF(AND(AK32>0,AL32=0),100%,IF(AND(AK32=0,AL32>0),0,IF(AND(AK32=0,AL32=0),"***",0)))) -> *** | AO32: =+IFERROR(VLOOKUP($A32,'Goals & Budget 2026'!$A$2:$EJ$49,31,FALSE),0) -> 0 | AP32: =IF(AND(AN32>0,AO32>0),AN32/AO32,IF(AND(AN32>0,AO32=0),100%,IF(AND(AN32=0,AO32>0),0,IF(AND(AN32=0,AO32=0),"***",0)))) -> ***
A33: Vila do Conde - Phase 2 | B33: 1 | C33: 39 | D33: =+G33 -> 0 | E33: =+H33 -> 0 | F33: =IF(AND(D33>0,E33>0),D33/E33,IF(AND(D33>0,E33=0),100%,IF(AND(D33=0,E33>0),0,IF(AND(D33=0,E33=0),"***",0)))) -> *** | H33: =+IFERROR(VLOOKUP($A33,'Goals & Budget 2026'!$A$2:$EJ$49,20,FALSE),0) -> 0 | I33: =IF(AND(G33>0,H33>0),G33/H33,IF(AND(G33>0,H33=0),100%,IF(AND(G33=0,H33>0),0,IF(AND(G33=0,H33=0),"***",0)))) -> *** | K33: =+IFERROR(VLOOKUP($A33,'Goals & Budget 2026'!$A$2:$EJ$49,21,FALSE),0) -> 0 | L33: =IF(AND(J33>0,K33>0),J33/K33,IF(AND(J33>0,K33=0),100%,IF(AND(J33=0,K33>0),0,IF(AND(J33=0,K33=0),"***",0)))) -> *** | N33: =+IFERROR(VLOOKUP($A33,'Goals & Budget 2026'!$A$2:$EJ$49,22,FALSE),0) -> 0 | O33: =IF(AND(M33>0,N33>0),M33/N33,IF(AND(M33>0,N33=0),100%,IF(AND(M33=0,N33>0),0,IF(AND(M33=0,N33=0),"***",0)))) -> *** | Q33: =+IFERROR(VLOOKUP($A33,'Goals & Budget 2026'!$A$2:$EJ$49,23,FALSE),0) -> 0 | R33: =IF(AND(P33>0,Q33>0),P33/Q33,IF(AND(P33>0,Q33=0),100%,IF(AND(P33=0,Q33>0),0,IF(AND(P33=0,Q33=0),"***",0)))) -> *** | T33: =+IFERROR(VLOOKUP($A33,'Goals & Budget 2026'!$A$2:$EJ$49,24,FALSE),0) -> 0 | U33: =IF(AND(S33>0,T33>0),S33/T33,IF(AND(S33>0,T33=0),100%,IF(AND(S33=0,T33>0),0,IF(AND(S33=0,T33=0),"***",0)))) -> *** | W33: =+IFERROR(VLOOKUP($A33,'Goals & Budget 2026'!$A$2:$EJ$49,25,FALSE),0) -> 0 | X33: =IF(AND(V33>0,W33>0),V33/W33,IF(AND(V33>0,W33=0),100%,IF(AND(V33=0,W33>0),0,IF(AND(V33=0,W33=0),"***",0)))) -> *** | Z33: =+IFERROR(VLOOKUP($A33,'Goals & Budget 2026'!$A$2:$EJ$49,26,FALSE),0) -> 0 | AA33: =IF(AND(Y33>0,Z33>0),Y33/Z33,IF(AND(Y33>0,Z33=0),100%,IF(AND(Y33=0,Z33>0),0,IF(AND(Y33=0,Z33=0),"***",0)))) -> *** | AC33: =+IFERROR(VLOOKUP($A33,'Goals & Budget 2026'!$A$2:$EJ$49,27,FALSE),0) -> 0 | AD33: =IF(AND(AB33>0,AC33>0),AB33/AC33,IF(AND(AB33>0,AC33=0),100%,IF(AND(AB33=0,AC33>0),0,IF(AND(AB33=0,AC33=0),"***",0)))) -> *** | AF33: =+IFERROR(VLOOKUP($A33,'Goals & Budget 2026'!$A$2:$EJ$49,28,FALSE),0) -> 0 | AG33: =IF(AND(AE33>0,AF33>0),AE33/AF33,IF(AND(AE33>0,AF33=0),100%,IF(AND(AE33=0,AF33>0),0,IF(AND(AE33=0,AF33=0),"***",0)))) -> *** | AI33: =+IFERROR(VLOOKUP($A33,'Goals & Budget 2026'!$A$2:$EJ$49,29,FALSE),0) -> 0 | AJ33: =IF(AND(AH33>0,AI33>0),AH33/AI33,IF(AND(AH33>0,AI33=0),100%,IF(AND(AH33=0,AI33>0),0,IF(AND(AH33=0,AI33=0),"***",0)))) -> *** | AL33: =+IFERROR(VLOOKUP($A33,'Goals & Budget 2026'!$A$2:$EJ$49,30,FALSE),0) -> 0 | AM33: =IF(AND(AK33>0,AL33>0),AK33/AL33,IF(AND(AK33>0,AL33=0),100%,IF(AND(AK33=0,AL33>0),0,IF(AND(AK33=0,AL33=0),"***",0)))) -> *** | AO33: =+IFERROR(VLOOKUP($A33,'Goals & Budget 2026'!$A$2:$EJ$49,31,FALSE),0) -> 0 | AP33: =IF(AND(AN33>0,AO33>0),AN33/AO33,IF(AND(AN33>0,AO33=0),100%,IF(AND(AN33=0,AO33>0),0,IF(AND(AN33=0,AO33=0),"***",0)))) -> ***
A34: Vila do Conde - Phase 3 | B34: 1 | C34: 76 | D34: =+G34 -> 0 | E34: =+H34 -> 0 | F34: =IF(AND(D34>0,E34>0),D34/E34,IF(AND(D34>0,E34=0),100%,IF(AND(D34=0,E34>0),0,IF(AND(D34=0,E34=0),"***",0)))) -> *** | H34: =+IFERROR(VLOOKUP($A34,'Goals & Budget 2026'!$A$2:$EJ$49,20,FALSE),0) -> 0 | I34: =IF(AND(G34>0,H34>0),G34/H34,IF(AND(G34>0,H34=0),100%,IF(AND(G34=0,H34>0),0,IF(AND(G34=0,H34=0),"***",0)))) -> *** | K34: =+IFERROR(VLOOKUP($A34,'Goals & Budget 2026'!$A$2:$EJ$49,21,FALSE),0) -> 0 | L34: =IF(AND(J34>0,K34>0),J34/K34,IF(AND(J34>0,K34=0),100%,IF(AND(J34=0,K34>0),0,IF(AND(J34=0,K34=0),"***",0)))) -> *** | N34: =+IFERROR(VLOOKUP($A34,'Goals & Budget 2026'!$A$2:$EJ$49,22,FALSE),0) -> 0 | O34: =IF(AND(M34>0,N34>0),M34/N34,IF(AND(M34>0,N34=0),100%,IF(AND(M34=0,N34>0),0,IF(AND(M34=0,N34=0),"***",0)))) -> *** | Q34: =+IFERROR(VLOOKUP($A34,'Goals & Budget 2026'!$A$2:$EJ$49,23,FALSE),0) -> 0 | R34: =IF(AND(P34>0,Q34>0),P34/Q34,IF(AND(P34>0,Q34=0),100%,IF(AND(P34=0,Q34>0),0,IF(AND(P34=0,Q34=0),"***",0)))) -> *** | T34: =+IFERROR(VLOOKUP($A34,'Goals & Budget 2026'!$A$2:$EJ$49,24,FALSE),0) -> 0 | U34: =IF(AND(S34>0,T34>0),S34/T34,IF(AND(S34>0,T34=0),100%,IF(AND(S34=0,T34>0),0,IF(AND(S34=0,T34=0),"***",0)))) -> *** | W34: =+IFERROR(VLOOKUP($A34,'Goals & Budget 2026'!$A$2:$EJ$49,25,FALSE),0) -> 0 | X34: =IF(AND(V34>0,W34>0),V34/W34,IF(AND(V34>0,W34=0),100%,IF(AND(V34=0,W34>0),0,IF(AND(V34=0,W34=0),"***",0)))) -> *** | Z34: =+IFERROR(VLOOKUP($A34,'Goals & Budget 2026'!$A$2:$EJ$49,26,FALSE),0) -> 0 | AA34: =IF(AND(Y34>0,Z34>0),Y34/Z34,IF(AND(Y34>0,Z34=0),100%,IF(AND(Y34=0,Z34>0),0,IF(AND(Y34=0,Z34=0),"***",0)))) -> *** | AC34: =+IFERROR(VLOOKUP($A34,'Goals & Budget 2026'!$A$2:$EJ$49,27,FALSE),0) -> 0 | AD34: =IF(AND(AB34>0,AC34>0),AB34/AC34,IF(AND(AB34>0,AC34=0),100%,IF(AND(AB34=0,AC34>0),0,IF(AND(AB34=0,AC34=0),"***",0)))) -> *** | AF34: =+IFERROR(VLOOKUP($A34,'Goals & Budget 2026'!$A$2:$EJ$49,28,FALSE),0) -> 0 | AG34: =IF(AND(AE34>0,AF34>0),AE34/AF34,IF(AND(AE34>0,AF34=0),100%,IF(AND(AE34=0,AF34>0),0,IF(AND(AE34=0,AF34=0),"***",0)))) -> *** | AI34: =+IFERROR(VLOOKUP($A34,'Goals & Budget 2026'!$A$2:$EJ$49,29,FALSE),0) -> 0 | AJ34: =IF(AND(AH34>0,AI34>0),AH34/AI34,IF(AND(AH34>0,AI34=0),100%,IF(AND(AH34=0,AI34>0),0,IF(AND(AH34=0,AI34=0),"***",0)))) -> *** | AL34: =+IFERROR(VLOOKUP($A34,'Goals & Budget 2026'!$A$2:$EJ$49,30,FALSE),0) -> 0 | AM34: =IF(AND(AK34>0,AL34>0),AK34/AL34,IF(AND(AK34>0,AL34=0),100%,IF(AND(AK34=0,AL34>0),0,IF(AND(AK34=0,AL34=0),"***",0)))) -> *** | AO34: =+IFERROR(VLOOKUP($A34,'Goals & Budget 2026'!$A$2:$EJ$49,31,FALSE),0) -> 0 | AP34: =IF(AND(AN34>0,AO34>0),AN34/AO34,IF(AND(AN34>0,AO34=0),100%,IF(AND(AN34=0,AO34>0),0,IF(AND(AN34=0,AO34=0),"***",0)))) -> ***
A35: Parkview | B35: 1 | C35: 39 | D35: =+G35 -> 0 | E35: =+H35 -> 0 | F35: =IF(AND(D35>0,E35>0),D35/E35,IF(AND(D35>0,E35=0),100%,IF(AND(D35=0,E35>0),0,IF(AND(D35=0,E35=0),"***",0)))) -> *** | H35: =+IFERROR(VLOOKUP($A35,'Goals & Budget 2026'!$A$2:$EJ$49,20,FALSE),0) -> 0 | I35: =IF(AND(G35>0,H35>0),G35/H35,IF(AND(G35>0,H35=0),100%,IF(AND(G35=0,H35>0),0,IF(AND(G35=0,H35=0),"***",0)))) -> *** | K35: =+IFERROR(VLOOKUP($A35,'Goals & Budget 2026'!$A$2:$EJ$49,21,FALSE),0) -> 0 | L35: =IF(AND(J35>0,K35>0),J35/K35,IF(AND(J35>0,K35=0),100%,IF(AND(J35=0,K35>0),0,IF(AND(J35=0,K35=0),"***",0)))) -> *** | N35: =+IFERROR(VLOOKUP($A35,'Goals & Budget 2026'!$A$2:$EJ$49,22,FALSE),0) -> 0 | O35: =IF(AND(M35>0,N35>0),M35/N35,IF(AND(M35>0,N35=0),100%,IF(AND(M35=0,N35>0),0,IF(AND(M35=0,N35=0),"***",0)))) -> *** | Q35: =+IFERROR(VLOOKUP($A35,'Goals & Budget 2026'!$A$2:$EJ$49,23,FALSE),0) -> 0 | R35: =IF(AND(P35>0,Q35>0),P35/Q35,IF(AND(P35>0,Q35=0),100%,IF(AND(P35=0,Q35>0),0,IF(AND(P35=0,Q35=0),"***",0)))) -> *** | T35: =+IFERROR(VLOOKUP($A35,'Goals & Budget 2026'!$A$2:$EJ$49,24,FALSE),0) -> 0 | U35: =IF(AND(S35>0,T35>0),S35/T35,IF(AND(S35>0,T35=0),100%,IF(AND(S35=0,T35>0),0,IF(AND(S35=0,T35=0),"***",0)))) -> *** | W35: =+IFERROR(VLOOKUP($A35,'Goals & Budget 2026'!$A$2:$EJ$49,25,FALSE),0) -> 0 | X35: =IF(AND(V35>0,W35>0),V35/W35,IF(AND(V35>0,W35=0),100%,IF(AND(V35=0,W35>0),0,IF(AND(V35=0,W35=0),"***",0)))) -> *** | Z35: =+IFERROR(VLOOKUP($A35,'Goals & Budget 2026'!$A$2:$EJ$49,26,FALSE),0) -> 0 | AA35: =IF(AND(Y35>0,Z35>0),Y35/Z35,IF(AND(Y35>0,Z35=0),100%,IF(AND(Y35=0,Z35>0),0,IF(AND(Y35=0,Z35=0),"***",0)))) -> *** | AC35: =+IFERROR(VLOOKUP($A35,'Goals & Budget 2026'!$A$2:$EJ$49,27,FALSE),0) -> 0 | AD35: =IF(AND(AB35>0,AC35>0),AB35/AC35,IF(AND(AB35>0,AC35=0),100%,IF(AND(AB35=0,AC35>0),0,IF(AND(AB35=0,AC35=0),"***",0)))) -> *** | AF35: =+IFERROR(VLOOKUP($A35,'Goals & Budget 2026'!$A$2:$EJ$49,28,FALSE),0) -> 0 | AG35: =IF(AND(AE35>0,AF35>0),AE35/AF35,IF(AND(AE35>0,AF35=0),100%,IF(AND(AE35=0,AF35>0),0,IF(AND(AE35=0,AF35=0),"***",0)))) -> *** | AI35: =+IFERROR(VLOOKUP($A35,'Goals & Budget 2026'!$A$2:$EJ$49,29,FALSE),0) -> 0 | AJ35: =IF(AND(AH35>0,AI35>0),AH35/AI35,IF(AND(AH35>0,AI35=0),100%,IF(AND(AH35=0,AI35>0),0,IF(AND(AH35=0,AI35=0),"***",0)))) -> *** | AL35: =+IFERROR(VLOOKUP($A35,'Goals & Budget 2026'!$A$2:$EJ$49,30,FALSE),0) -> 0 | AM35: =IF(AND(AK35>0,AL35>0),AK35/AL35,IF(AND(AK35>0,AL35=0),100%,IF(AND(AK35=0,AL35>0),0,IF(AND(AK35=0,AL35=0),"***",0)))) -> *** | AO35: =+IFERROR(VLOOKUP($A35,'Goals & Budget 2026'!$A$2:$EJ$49,31,FALSE),0) -> 0 | AP35: =IF(AND(AN35>0,AO35>0),AN35/AO35,IF(AND(AN35>0,AO35=0),100%,IF(AND(AN35=0,AO35>0),0,IF(AND(AN35=0,AO35=0),"***",0)))) -> ***
